Workbook
Name BaseYear: 'Cover Page'!$C$63
Name CompanyName: 'Cover Page'!$B$2
Name CurrentPrice: 'DCF & Sensitivity'!$D$55
Name ExitMultiple: Assumptions!$D$89
Name FirstForecastYear: 'Cover Page'!$C$64
Name NetDebt: 'DCF & Sensitivity'!$D$48
Name ScenarioRange: Assumptions!$E$9:$G$9
Name SharesOut: 'DCF & Sensitivity'!$D$51
Name TaxRate: 'DCF & Sensitivity'!$D$16
Name TerminalGrowth: Assumptions!$D$88
Name Ticker: 'Cover Page'!$B$3
Name WACC: Assumptions!$D$87

Sheet Cover Page
B2: BRINKER INTERNATIONAL, INC.
B3: NYSE: EAT
B4: Casual Dining — Chili's Grill & Bar, Maggiano's Little Italy
B6: Company Overview
B7: Sector | C7: Consumer Discretionary: Casual Dining Restaurants
B8: Brands | C8: Chili's Grill & Bar (1,576 restaurants), Maggiano's Little Italy (52 restaurants)
B9: Footprint | C9: 1,628 system-wide units; 1,162 Co-owned + 466 franchised; US + 27 intl countries
B10: Revenue Model | C10: ~99% Company sales (food/beverage/banquet); ~1% franchise royalties & fees
B11: Capital Structure | C11: $426M LT debt ($350M 8.25% sr notes due 2030 + finance leases); $1.0B revolver undrawn; $507M buyback authority
B13: Valuation Snapshot
B14: Current Share Price | C14: ='DCF & Sensitivity'!D55 -> 168
B15: Base Case (Perpetuity Growth) | C15: ='DCF & Sensitivity'!D53 -> 103.57659
B16: Base Case (Exit Multiple, 11x) | C16: ='DCF & Sensitivity'!D54 -> 157.48607
B17: Upside/(Downside) vs Market (Blended) | C17: =AVERAGE(C15:C16)/C14-1 -> -0.22302781
B19: Key Assumptions
B20: WACC | C20: =Assumptions!D87 -> 0.10509837
B21: Terminal Growth Rate | C21: =Assumptions!D88 -> 0.025
B22: Exit EV/EBITDA Multiple | C22: =Assumptions!D89 -> 11
B23: Terminal Rest. Op. Margin | C23: =Assumptions!M39 -> 0.165
B24: Net Debt ($M) | C24: ='DCF & Sensitivity'!D48 -> 407.1
B25: Diluted Shares Outstanding (M) | C25: ='DCF & Sensitivity'!D51 -> 45.5
B27: Table of Contents
B28: › Summary
B29: Scenario Summary
B30: SWOT
B31: › Valuation
B32: Assumptions
B33: Revenue Build
B34: Income Statement
B35: Balance Sheet
B36: Cash Flow
B37: DCF & Sensitivity
B38: Comps
... B45: › Color Coding
B46: Blue text | C46: Hardcoded inputs and assumptions. Scenario drivers, historical data, WACC components.
B47: Black text | C47: Formulas and calculations that reference cells within the same sheet.
B48: Green text | C48: Cross-sheet links. Formulas pulling values from other tabs.
B49: › Number Conventions
B50: Amounts | C50: All $ values in millions ($M) unless labeled per-share ($/sh). Units column on each sheet confirms.
B51: Percentages | C51: Stored as decimals (0.125 = 12.5%) and displayed with 0.0% format
B52: Fiscal year | C52: Brinker fiscal year ends late June. FY25 = July 2024 through June 2025.
B53: Negatives | C53: Shown as (123) in parentheses via number format, not as -123.
B54: › Scenario Toggle
B55: Selector cells | C55: "Assumptions" tab with dropdown of "Bear" / "Base" / "Bull" options. Each row's selector independently drives one scenario dimension.
B56: Interpolation | C56: Revenue and Margin drivers interpolate YoY from the FY26E anchor to the scenario-selected FY30E terminal value.
B57: › How to Run the Model
B58: 1. Set Scenario | C58: Use dropdowns on top of "Assumptions" tab to select Bear/Base/Bull per driver.
B59: 2. Flex DCF Inputs | C59: Flex any of the DCF inputs including WACC or Terminal Value in the DCF section on the bottom of the "Assumptions" tab
B60: 3. Update Market Data | C60: Update current share price on "DCF & SensitivityD55". Flows through to upside calcs on DCF tab and Cover Page.
B62: Fiscal Year Inputs
B63: Base Year (first historical) | C63: 2021
B64: First Forecast Year | C64: 2026
Z100: =WACC -> 0.10509837
Z101: =CompanyName & " (" & Ticker & ")" -> BRINKER INTERNATIONAL, INC. (NYSE: EAT)

Sheet Scenario Summary
B2: Scenario Summary
B3: Brinker International (EAT)
B4: Bear / Base / Bull scenarios side-by-side. Valuation from Shadow DCF tab (simplified model, scenario-specific drivers). Current market: $168/sh.
B5: The valuation outputs (share price & FY30E) values are simplified views of bear, base, and bull that reconcile within a material percentage of main model
B7: Valuation Summary | C7: Units | D7: Bear | E7: Base | F7: Bull | G7: Range (Bull − Bear)
B8: Implied Price — Perpetuity | C8: $/sh | D8: ='Shadow DCF'!D126 -> 49.300117 | E8: ='Shadow DCF'!E126 -> 99.477411 | F8: ='Shadow DCF'!F126 -> 169.69318 | G8: =F8-D8 -> 120.39306
B9: Implied Price — Exit Multiple | C9: $/sh | D9: ='Shadow DCF'!D127 -> 89.857388 | E9: ='Shadow DCF'!E127 -> 152.74057 | F9: ='Shadow DCF'!F127 -> 244.45682 | G9: =F9-D9 -> 154.59943
B10: Blended (avg of two methods) | C10: $/sh | D10: ='Shadow DCF'!D128 -> 69.578753 | E10: ='Shadow DCF'!E128 -> 126.10899 | F10: ='Shadow DCF'!F128 -> 207.075 | G10: =F10-D10 -> 137.49625
B11: Current Share Price | C11: $/sh | D11: ='DCF & Sensitivity'!$D$55 -> 168 | E11: ='DCF & Sensitivity'!$D$55 -> 168 | F11: ='DCF & Sensitivity'!$D$55 -> 168 | G11: —
B12: Upside / (Downside) vs. market | C12: % | D12: =D10/D11-1 -> -0.58584076 | E12: =E10/E11-1 -> -0.24935123 | F12: =F10/F11-1 -> 0.23258929 | G12: =F12-D12 -> 0.81843005
B14: Scenario Drivers | C14: Units | D14: Bear | E14: Base | F14: Bull | G14: ="FY"&TEXT(MOD('Cover Page'!$C$64-1,100),"00")&"A" -> FY25A
B15: Chili's Same-Store Sales | C15: % | D15: =Assumptions!E11 -> 0.01 | E15: =Assumptions!F11 -> 0.025 | F15: =Assumptions!G11 -> 0.04 | G15: ='Revenue Build'!H22 -> 0.17
B16: Maggiano's Same-Store Sales | C16: % | D16: =Assumptions!E12 -> -0.03 | E16: =Assumptions!F12 -> 0.01 | F16: =Assumptions!G12 -> 0.03 | G16: ='Revenue Build'!H29 -> 0.008
B17: F&B % of Co Sales (terminal FY30E) | C17: % | D17: =Assumptions!E15 -> 0.27 | E17: =Assumptions!F15 -> 0.26 | F17: =Assumptions!G15 -> 0.245 | G17: =Assumptions!H36 -> 0.25314415
B18: Labor % (terminal FY30E) | C18: % | D18: =Assumptions!E16 -> 0.335 | E18: =Assumptions!F16 -> 0.325 | F18: =Assumptions!G16 -> 0.315 | G18: =Assumptions!H37 -> 0.32187506
B19: Rest. Expenses % (terminal FY30E) | C19: % | D19: =Assumptions!E17 -> 0.26 | E19: =Assumptions!F17 -> 0.25 | F19: =Assumptions!G17 -> 0.235 | G19: =Assumptions!H38 -> 0.25001406
B20: G&A % of revenue (terminal FY30E) | C20: % | D20: =Assumptions!E18 -> 0.045 | E20: =Assumptions!F18 -> 0.04 | F20: =Assumptions!G18 -> 0.038 | G20: =Assumptions!H41 -> 0.041231752
B21: Implied Terminal EBITDA Margin | C21: % | D21: =1-D17-D18-D19-D20 -> 0.09 | E21: =1-E17-E18-E19-E20 -> 0.125 | F21: =1-F17-F18-F19-F20 -> 0.167 | G21: =1-G17-G18-G19-G20 -> 0.13373498
B22: Capex % of revenue (terminal FY30E) | C22: % | D22: =Assumptions!E19 -> 0.045 | E22: =Assumptions!F19 -> 0.04 | F22: =Assumptions!G19 -> 0.035 | G22: =Assumptions!H63 -> 0.049273801
B23: Terminal Growth Rate | C23: % | D23: =Assumptions!E23 -> 0.02 | E23: =Assumptions!F23 -> 0.025 | F23: =Assumptions!G23 -> 0.03 | G23: —
B24: Exit EV/EBITDA Multiple | C24: x | D24: =Assumptions!E24 -> 9 | E24: =Assumptions!F24 -> 11 | F24: =Assumptions!G24 -> 13 | G24: —
J25: Note: Perpetuity and Exit Multiple can diverge in tail scenarios because FCF and EBITDA don't scale in lockstep — in Bull, margin expansion and operating leverage make EBITDA grow faster than FCF; in Bear, the opposite. Since perpetuity anchors on FCF and exit multiple anchors on EBITDA, the two methods are valuing different-sized underlying numbers.
B26: FY30E Model Outputs | C26: Units | D26: Bear | E26: Base | F26: Bull
B27: Revenue FY30E | C27: $M | D27: ='Shadow DCF'!D120 -> 6030.3002 | E27: ='Shadow DCF'!E120 -> 6396.5957 | F27: ='Shadow DCF'!F120 -> 6779.3304
B28: EBITDA FY30E | C28: $M | D28: ='Shadow DCF'!D121 -> 610.39569 | E28: ='Shadow DCF'!E121 -> 868.86404 | F28: ='Shadow DCF'!F121 -> 1202.0658
B29: EBITDA Margin FY30E | C29: % | D29: ='Shadow DCF'!D122 -> 0.10122144 | E29: ='Shadow DCF'!E122 -> 0.13583226 | F29: ='Shadow DCF'!F122 -> 0.17731335
B30: FCF FY30E | C30: $M | D30: ='Shadow DCF'!D123 -> 204.57667 | E30: ='Shadow DCF'!E123 -> 434.73353 | F30: ='Shadow DCF'!F123 -> 730.58063
B31: Enterprise Value — Perpetuity | C31: $M | D31: ='Shadow DCF'!D124 -> 2650.2553 | E31: ='Shadow DCF'!E124 -> 4933.3222 | F31: ='Shadow DCF'!F124 -> 8128.1396
B32: Enterprise Value — Exit Multiple | C32: $M | D32: ='Shadow DCF'!D125 -> 4495.6112 | E32: ='Shadow DCF'!E125 -> 7356.7961 | F32: ='Shadow DCF'!F125 -> 11529.885
B34: Takeaways
B35: i) ~70% of enterprise value sits in terminal value across all three scenarios and both exit multiple and perpetuity methods. Valuation is driven by go-forward steady-state assumptions, not the 5-year forecast. ii) Restaurant operating margin is not the crux. Casual dining margins mean-revert within a narrow band as operators flex pricing and labor against commodity cycles. Even our Bear-to-Bull margin range of 9-17% overstates the realistic spread. iii) The real debate is where Chili's SSS stabilizes. FY25A printed +17% on new-CEO momentum (Hochman), '3 for Me' value messaging, and viral social media moments (Triple Dipper). Essentially, a hype cycle that can't compound forever. Bear/Base/Bull assume 1% / 2.5% / 4% in steady state. A 150bps swing in terminal SSS compounds through 50 years of terminal value and drives the full ~$137/sh Bear-to-Bull dispersion. iv) Maggiano's is 9% of revenue in FY25A, still not totally negliable compared to Chili's company-owned 90% of revenue.
B43: Check: Rec to Three Statement DCF | C43: Units | D43: Bear | E43: Base | F43: Bull
B44: Blended Share Price - Scenario Summary | C44: $/sh | D44: ='Shadow DCF'!D128 -> 69.578753 | E44: ='Shadow DCF'!E128 -> 126.10899 | F44: ='Shadow DCF'!F128 -> 207.075
B45: Blended Share Price - Main Model | C45: $/sh | D45: ='Shadow DCF Rec'!D24 -> 76.59 | E45: ='Shadow DCF Rec'!E24 -> 130.535 | F45: ='Shadow DCF Rec'!F24 -> 203.885
B46: Variance (Shadow − Main) | C46: % | D46: =IFERROR(D44/D45-1,"") -> -0.091542596 | E46: =IFERROR(E44/E45-1,"") -> -0.033906671 | F46: =IFERROR(F44/F45-1,"") -> 0.015646076

Sheet SWOT
B2: SWOT Analysis
B3: Brinker International, Inc. (EAT)
C5: Helpful (to achieving objectives) | H5: Harmful (to achieving objectives)
B6: INTERNAL | C6: STRENGTHS | H6: WEAKNESSES
C7: • Chili's: 6 consecutive quarters of double-digit sales + positive traffic growth through Q1 FY26 | H7: • Maggiano's is a drag: Q2 FY26 SSS -2.4%, ROM down -6.7%; turnaround plan is early-stage
C8: • Chili's AUV jumped from $3.2M (FY22) to $4.5M (FY25), +41% over 3 years | H8: • Single-brand concentration — Chili's is >90% of revenue; limited geographic diversification
C9: • Restaurant operating margin expanded from 11% (FY22) to 17.5% (FY25); Q2 FY26 consolidated ROM 18.8% | H9: • 21% / 8.6% SSS growth in Q1/Q2 FY26; guidance implies mid-single-digit for remainder. Where does run-rate SSS land?
C10: • Value positioning — strong gains among <$60K household income segments despite macro weakness
C11: • $507M buyback authority (Aug 2025 top-up); $679M CFO FY25 covers capex + buybacks + debt paydown
C12: • Paid down $360M of revolver in FY25; debt reduced from $786M to $426M; revolver undrawn at 6/25/25
B15: EXTERNAL | C15: OPPORTUNITIES | H15: THREATS
C16: • International franchise expansion — 26-32 franchise openings planned FY26 (mostly international); 18 active dev agreements | H16: • Economic downturn impact on casual dining; consumer discretionary spending risk
C17: • Maggiano's 'North Star' turnaround plan — apply Chili's playbook to underperforming segment | H17: • Consumer shift toward healthier / fast-casual options (CMG, SG, CAVA) could compress casual dining TAM
C18: • Operating leverage on G&A and fixed costs as Chili's AUV continues to scale (target $6M+ 'North of Six' units) | H18: • Wage inflation — low to mid-single digits expected FY26; labor is 32%+ of company sales
C19: • 100% bonus depreciation restored (OBBBA, July 2025) — improves near-term FCF on capex-heavy new units | H19: • $350M 8.25% notes mature July 2030 — refinancing risk at current rates
H20: • Chili's turnaround centered on hype cycle — potential regression to weak SSS performance

Sheet Valuation >>>
B18: Valuation >>>

Sheet Assumptions
B2: Assumptions
B3: Brinker International, Inc. (NYSE: EAT)
B4: All $ in millions unless noted. Fiscal year ends last Wednesday in June.
B7: SCENARIO SELECTOR
B8: FY26E anchored to mgmt's raised guidance (post-Q2). FY27-FY30 interpolate linearly between FY26 start and scenario terminal values. Each driver toggles independently via column H dropdown.
B9: Metric | C9: Units | D9: FY26E Start | E9: Bear | F9: Base | G9: Bull | H9: Scenario
B10: REVENUE
B11: Chili's Same Store Sales Growth | C11: % | D11: 0.086 | E11: 0.01 | F11: 0.025 | G11: 0.04 | H11: Base
B12: Maggiano's Same Store Sales Growth | C12: % | D12: -0.024 | E12: -0.03 | F12: 0.01 | G12: 0.03 | H12: Base
B13: Franchise Royalty Rate (blended) | C13: % | D13: 0.045 | E13: 0.045 | F13: 0.046 | G13: 0.047 | H13: Base
B14: COST
B15: F&B % of Co sales | C15: % | D15: 0.255 | E15: 0.27 | F15: 0.26 | G15: 0.245 | H15: Base
B16: Labor % of Co sales | C16: % | D16: 0.322 | E16: 0.335 | F16: 0.325 | G16: 0.315 | H16: Base
B17: Restaurant expenses % | C17: % | D17: 0.245 | E17: 0.26 | F17: 0.25 | G17: 0.235 | H17: Base
B18: G&A % of revenue | C18: % | D18: 0.041 | E18: 0.045 | F18: 0.04 | G18: 0.038 | H18: Base
B19: Capex % of revenue | C19: % | D19: 0.045 | E19: 0.045 | F19: 0.04 | G19: 0.035 | H19: Base
B20: CAPITAL ALLOCATION
B21: Buybacks % of FCF | C21: % | D21: 0.6 | E21: 0.3 | F21: 0.5 | G21: 0.7 | H21: Base
B22: VALUATION
B23: Terminal Growth Rate | C23: % | D23: 0.025 | E23: 0.02 | F23: 0.025 | G23: 0.03 | H23: Base
B24: Exit EV / EBITDA Multiple | C24: x | D24: 11 | E24: 9 | F24: 11 | G24: 13 | H24: Base
B27: Revenue Drivers | C27: Units | D27: =IF('Cover Page'!$C$63+0<'Cover Page'!$C$64,"FY"&TEXT(MOD('Cover Page'!$C$63+0,100),"00")&"A","FY"&TEXT(MOD('Cover Page'!$C$63+0,100),"00")&"E") -> FY21A | E27: =IF('Cover Page'!$C$63+1<'Cover Page'!$C$64,"FY"&TEXT(MOD('Cover Page'!$C$63+1,100),"00")&"A","FY"&TEXT(MOD('Cover Page'!$C$63+1,100),"00")&"E") -> FY22A | F27: =IF('Cover Page'!$C$63+2<'Cover Page'!$C$64,"FY"&TEXT(MOD('Cover Page'!$C$63+2,100),"00")&"A","FY"&TEXT(MOD('Cover Page'!$C$63+2,100),"00")&"E") -> FY23A | G27: =IF('Cover Page'!$C$63+3<'Cover Page'!$C$64,"FY"&TEXT(MOD('Cover Page'!$C$63+3,100),"00")&"A","FY"&TEXT(MOD('Cover Page'!$C$63+3,100),"00")&"E") -> FY24A | H27: =IF('Cover Page'!$C$63+4<'Cover Page'!$C$64,"FY"&TEXT(MOD('Cover Page'!$C$63+4,100),"00")&"A","FY"&TEXT(MOD('Cover Page'!$C$63+4,100),"00")&"E") -> FY25A | I27: =IF('Cover Page'!$C$63+5<'Cover Page'!$C$64,"FY"&TEXT(MOD('Cover Page'!$C$63+5,100),"00")&"A","FY"&TEXT(MOD('Cover Page'!$C$63+5,100),"00")&"E") -> FY26E | J27: =IF('Cover Page'!$C$63+6<'Cover Page'!$C$64,"FY"&TEXT(MOD('Cover Page'!$C$63+6,100),"00")&"A","FY"&TEXT(MOD('Cover Page'!$C$63+6,100),"00")&"E") -> FY27E | K27: =IF('Cover Page'!$C$63+7<'Cover Page'!$C$64,"FY"&TEXT(MOD('Cover Page'!$C$63+7,100),"00")&"A","FY"&TEXT(MOD('Cover Page'!$C$63+7,100),"00")&"E") -> FY28E | L27: =IF('Cover Page'!$C$63+8<'Cover Page'!$C$64,"FY"&TEXT(MOD('Cover Page'!$C$63+8,100),"00")&"A","FY"&TEXT(MOD('Cover Page'!$C$63+8,100),"00")&"E") -> FY29E | M27: =IF('Cover Page'!$C$63+9<'Cover Page'!$C$64,"FY"&TEXT(MOD('Cover Page'!$C$63+9,100),"00")&"A","FY"&TEXT(MOD('Cover Page'!$C$63+9,100),"00")&"E") -> FY30E | O27: Notes
B28: Chili's Same-Store Sales | C28: % | D28: ='Revenue Build'!D22 -> 0.215 | E28: ='Revenue Build'!E22 -> 0.03 | F28: ='Revenue Build'!F22 -> 0.074 | G28: ='Revenue Build'!G22 -> 0.038 | H28: ='Revenue Build'!H22 -> 0.17 | I28: ='Revenue Build'!I22 -> 0.086 | J28: ='Revenue Build'!J22 -> 0.0473 | K28: ='Revenue Build'!K22 -> 0.0301 | ... M28: ='Revenue Build'!M22 -> 0.025 | O28: Our revenue proforma uses same-store sales (SSS) growth applied to FY25 reported revenue which is not a bottoms-up unit build. This captures comp growth at existing restaurants but implicitly ignores: Net new stores, Closed stores , and New store ramp This is acceptable for Brinker because net unit change is immaterial (<0.5% of revenue). For a high-growth restaurant concept (e.g., TXRH, WING), a proper unit economic build would be essential. Revenue Build unit economics shown in HP in the Revenue Build Tab reflect how that analytical framework would work but does not flow into the forecast.
B29: Chili's Company Sales | C29: $M | D29: ='Income Statement'!D11-'Revenue Build'!D31 -> 3008.7 | E29: ='Income Statement'!E11-'Revenue Build'!E31 -> 3290.9 | F29: ='Income Statement'!F11-'Revenue Build'!F31 -> 3487.9 | G29: ='Income Statement'!G11-'Revenue Build'!G31 -> 3881.1 | H29: ='Income Statement'!H11-'Revenue Build'!H31 -> 4850.2 | I29: ='Income Statement'!H9*(1+I28) -> 5250.5928 | J29: =I29*(1+J28) -> 5498.9458 | K29: =J29*(1+K28) -> 5664.4641 | L29: =K29*(1+L28) -> 5783.9843 | M29: =L29*(1+M28) -> 5928.5839
B30: Maggiano's Same-Store Sales | C30: % | D30: ='Revenue Build'!D29 -> 0.15 | E30: ='Revenue Build'!E29 -> 0.08 | F30: ='Revenue Build'!F29 -> 0.069 | G30: ='Revenue Build'!G29 -> 0.024 | H30: ='Revenue Build'!H29 -> 0.008 | I30: ='Revenue Build'!I29 -> -0.024 | J30: ='Revenue Build'!J29 -> -0.007 | K30: ='Revenue Build'!K29 -> 0.01 | ... M30: ='Revenue Build'!M29 -> 0.01
B31: Maggiano's Company Sales | C31: $M | D31: ='Revenue Build'!D31 -> 270.3 | E31: ='Revenue Build'!E31 -> 421.2 | F31: ='Revenue Build'!F31 -> 475 | G31: ='Revenue Build'!G31 -> 490 | H31: ='Revenue Build'!H31 -> 485.1 | I31: ='Income Statement'!H10*(1+I30) -> 488.488 | J31: =I31*(1+J30) -> 485.06858 | K31: =J31*(1+K30) -> 489.91927 | L31: =K31*(1+L30) -> 494.81846 | M31: =L31*(1+M30) -> 499.76665
B32: Franchise & Other Revenue | C32: $M | D32: ='Revenue Build'!D39 -> 58.8 | E32: ='Revenue Build'!E39 -> 92 | F32: ='Revenue Build'!F39 -> 91.2 | G32: ='Revenue Build'!G39 -> 44 | H32: ='Revenue Build'!H39 -> 48.9 | I32: ='Revenue Build'!I39 -> 65.43327 | J32: ='Revenue Build'!J39 -> 71.325917 | K32: ='Revenue Build'!K39 -> 76.605997 | ... M32: ='Revenue Build'!M39 -> 84.489546
B33: Total Revenue | C33: $M | D33: =D29+D31+D32 -> 3337.8 | E33: =E29+E31+E32 -> 3804.1 | F33: =F29+F31+F32 -> 4054.1 | G33: =G29+G31+G32 -> 4415.1 | H33: =H29+H31+H32 -> 5384.2 | I33: =I29+I31+I32 -> 5804.5141 | J33: =J29+J31+J32 -> 6055.3403 | K33: =K29+K31+K32 -> 6230.9894 | ... M33: =M29+M31+M32 -> 6512.8401
B35: Margin Drivers
B36: Food & Beverage (F&B) costs % co. sales | C36: % | D36: ='Income Statement'!D18 -> 0.26465386 | E36: ='Income Statement'!E18 -> 0.28245468 | F36: ='Income Statement'!F18 -> 0.2752025 | G36: ='Income Statement'!G18 -> 0.25339159 | H36: ='Income Statement'!H18 -> 0.25314415 | I36: =D15 -> 0.255 | J36: =I36+(INDEX($E$15:$G$15,MATCH($H$15,$E$9:$G$9,0))-I36)*1/4 -> 0.25625 | K36: =I36+(INDEX($E$15:$G$15,MATCH($H$15,$E$9:$G$9,0))-I36)*2/4 -> 0.2575 | L36: =I36+(INDEX($E$15:$G$15,MATCH($H$15,$E$9:$G$9,0))-I36)*3/4 -> 0.25875 | M36: =INDEX($E$15:$G$15,MATCH($H$15,$E$9:$G$9,0)) -> 0.26 | O36: Food (Proteins, Dairy, Bakery), Alcholoic and Non-Alchoholic Beverages (Scales w/ Traffic)
B37: Labor % of co. sales | C37: % | D37: ='Income Statement'!D20 -> 0.33796889 | E37: ='Income Statement'!E20 -> 0.34700035 | F37: ='Income Statement'!F20 -> 0.3434606 | G37: ='Income Statement'!G20 -> 0.33568209 | H37: ='Income Statement'!H20 -> 0.32187506 | I37: =D16 -> 0.322 | J37: =I37+(INDEX($E$16:$G$16,MATCH($H$16,$E$9:$G$9,0))-I37)*1/4 -> 0.32275 | K37: =I37+(INDEX($E$16:$G$16,MATCH($H$16,$E$9:$G$9,0))-I37)*2/4 -> 0.3235 | L37: =I37+(INDEX($E$16:$G$16,MATCH($H$16,$E$9:$G$9,0))-I37)*3/4 -> 0.32425 | M37: =INDEX($E$16:$G$16,MATCH($H$16,$E$9:$G$9,0)) -> 0.325 | O37: Personell wages - Hourly workers and restaurant management (Semi-variable)
B38: Restaurant expenses % of co. sales | C38: % | D38: ='Income Statement'!D22 -> 0.26181763 | E38: ='Income Statement'!E22 -> 0.26084965 | F38: ='Income Statement'!F22 -> 0.26657246 | G38: ='Income Statement'!G22 -> 0.27748164 | H38: ='Income Statement'!H22 -> 0.25001406 | I38: =D17 -> 0.245 | J38: =I38+(INDEX($E$17:$G$17,MATCH($H$17,$E$9:$G$9,0))-I38)*1/4 -> 0.24625 | K38: =I38+(INDEX($E$17:$G$17,MATCH($H$17,$E$9:$G$9,0))-I38)*2/4 -> 0.2475 | L38: =I38+(INDEX($E$17:$G$17,MATCH($H$17,$E$9:$G$9,0))-I38)*3/4 -> 0.24875 | M38: =INDEX($E$17:$G$17,MATCH($H$17,$E$9:$G$9,0)) -> 0.25 | O38: Occupancy costs, utilities, repairs & maintenance, marketing and promos, payment processing fees (Most Fixed Op. Margin Cost)
B39: Restaurant operating margin | C39: % | D39: =1-D36-D37-D38 -> 0.13555962 | E39: =1-E36-E37-E38 -> 0.10969532 | F39: =1-F36-F37-F38 -> 0.11476444 | G39: =1-G36-G37-G38 -> 0.13344467 | H39: =1-H36-H37-H38 -> 0.17496673 | I39: =1-I36-I37-I38 -> 0.178 | J39: =1-J36-J37-J38 -> 0.17475 | K39: =1-K36-K37-K38 -> 0.1715 | ... M39: =1-M36-M37-M38 -> 0.165
B40: D&A % of revenue | C40: % | D40: ='Income Statement'!D26/'Income Statement'!D13 -> 0.0449997 | E40: ='Income Statement'!E26/'Income Statement'!E13 -> 0.04321653 | F40: ='Income Statement'!F26/'Income Statement'!F13 -> 0.041562862 | G40: ='Income Statement'!G26/'Income Statement'!G13 -> 0.03868542 | H40: ='Income Statement'!H26/'Income Statement'!H13 -> 0.038371532 | I40: 0.039 | J40: 0.04 | K40: 0.04 | L40: 0.041 | M40: 0.041 | O40: Driven by Chili's remodel program and Maggiano's reinvestment & OBBBA depreciation accelerating near-term expense recognition on new builds and equipment
B41: G&A % of revenue | C41: % | D41: ='Income Statement'!D27/'Income Statement'!D13 -> 0.040385883 | E41: ='Income Statement'!E27/'Income Statement'!E13 -> 0.037880182 | F41: ='Income Statement'!F27/'Income Statement'!F13 -> 0.042623517 | G41: ='Income Statement'!G27/'Income Statement'!G13 -> 0.041607212 | H41: ='Income Statement'!H27/'Income Statement'!H13 -> 0.041231752 | I41: =D18 -> 0.041 | J41: =I41+(INDEX($E$18:$G$18,MATCH($H$18,$E$9:$G$9,0))-I41)*1/4 -> 0.04075 | K41: =I41+(INDEX($E$18:$G$18,MATCH($H$18,$E$9:$G$9,0))-I41)*2/4 -> 0.0405 | L41: =I41+(INDEX($E$18:$G$18,MATCH($H$18,$E$9:$G$9,0))-I41)*3/4 -> 0.04025 | M41: =INDEX($E$18:$G$18,MATCH($H$18,$E$9:$G$9,0)) -> 0.04 | O41: Corporate overhead as % of total revenue. Excludes anything at restaurant level
B42: Other (gains) & charges % of rev | C42: % | D42: 0.006 | E42: 0.008 | F42: 0.006 | G42: 0.01 | H42: 0.008 | I42: 0.005 | J42: 0.005 | K42: 0.005 | L42: 0.005 | M42: 0.005
B44: Debt Schedule
B45: Tranche / $M | C45: Rate | D45: =IF('Cover Page'!$C$63+0<'Cover Page'!$C$64,"FY"&TEXT(MOD('Cover Page'!$C$63+0,100),"00")&"A","FY"&TEXT(MOD('Cover Page'!$C$63+0,100),"00")&"E") -> FY21A | E45: =IF('Cover Page'!$C$63+1<'Cover Page'!$C$64,"FY"&TEXT(MOD('Cover Page'!$C$63+1,100),"00")&"A","FY"&TEXT(MOD('Cover Page'!$C$63+1,100),"00")&"E") -> FY22A | F45: =IF('Cover Page'!$C$63+2<'Cover Page'!$C$64,"FY"&TEXT(MOD('Cover Page'!$C$63+2,100),"00")&"A","FY"&TEXT(MOD('Cover Page'!$C$63+2,100),"00")&"E") -> FY23A | G45: =IF('Cover Page'!$C$63+3<'Cover Page'!$C$64,"FY"&TEXT(MOD('Cover Page'!$C$63+3,100),"00")&"A","FY"&TEXT(MOD('Cover Page'!$C$63+3,100),"00")&"E") -> FY24A | H45: =IF('Cover Page'!$C$63+4<'Cover Page'!$C$64,"FY"&TEXT(MOD('Cover Page'!$C$63+4,100),"00")&"A","FY"&TEXT(MOD('Cover Page'!$C$63+4,100),"00")&"E") -> FY25A | I45: =IF('Cover Page'!$C$63+5<'Cover Page'!$C$64,"FY"&TEXT(MOD('Cover Page'!$C$63+5,100),"00")&"A","FY"&TEXT(MOD('Cover Page'!$C$63+5,100),"00")&"E") -> FY26E | J45: =IF('Cover Page'!$C$63+6<'Cover Page'!$C$64,"FY"&TEXT(MOD('Cover Page'!$C$63+6,100),"00")&"A","FY"&TEXT(MOD('Cover Page'!$C$63+6,100),"00")&"E") -> FY27E | K45: =IF('Cover Page'!$C$63+7<'Cover Page'!$C$64,"FY"&TEXT(MOD('Cover Page'!$C$63+7,100),"00")&"A","FY"&TEXT(MOD('Cover Page'!$C$63+7,100),"00")&"E") -> FY28E | L45: =IF('Cover Page'!$C$63+8<'Cover Page'!$C$64,"FY"&TEXT(MOD('Cover Page'!$C$63+8,100),"00")&"A","FY"&TEXT(MOD('Cover Page'!$C$63+8,100),"00")&"E") -> FY29E | M45: =IF('Cover Page'!$C$63+9<'Cover Page'!$C$64,"FY"&TEXT(MOD('Cover Page'!$C$63+9,100),"00")&"A","FY"&TEXT(MOD('Cover Page'!$C$63+9,100),"00")&"E") -> FY30E
B46: Senior Notes 8.25% due 2030 | C46: 0.0825 | D46: 0 | E46: 350 | F46: 350 | G46: 350 | H46: 350 | I46: =H46 -> 350 | J46: =I46 -> 350 | K46: =J46 -> 350 | L46: =K46 -> 350 | M46: =L46 -> 350 | O46: Debt schedule = capital structure detail that flows into Interest Expense Three tranches: i) Senior Notes $350M @ 8.25% due 2030 (fixed, bullet) ii) Revolver $42M @ ~6.75% (paying down to zero by FY28) iii) Finance leases $34M @ ~5% (held flat) Rate inputs can be toggled to stress test. Excludes $1.1B op leases (ASC 842). Total debt/EBITDA ~0.5x = under-levered vs casual dining peers (2-3x). Source: FY25 10-K Notes 8 & 9.
B47: Revolving credit facility | C47: 0.0675 | D47: 300 | E47: 255 | F47: 360 | G47: 377 | H47: 42 | I47: =MAX(0,H47-25) -> 17 | J47: =MAX(0,I47-17) -> 0 | K47: =MAX(0,J47-0) -> 0 | L47: =MAX(0,K47-0) -> 0 | M47: =MAX(0,L47-0) -> 0
B48: Finance leases | C48: 0.05 | D48: 36 | E48: 34 | F48: 38 | G48: 36 | H48: 34 | I48: =H48 -> 34 | J48: =I48 -> 34 | K48: =J48 -> 34 | L48: =K48 -> 34 | M48: =L48 -> 34
B49: Total Debt (ex-op leases) | D49: =SUM(D46:D48) -> 336 | E49: =SUM(E46:E48) -> 639 | F49: =SUM(F46:F48) -> 748 | G49: =SUM(G46:G48) -> 763 | H49: =SUM(H46:H48) -> 426 | I49: =SUM(I46:I48) -> 401 | J49: =SUM(J46:J48) -> 384 | K49: =SUM(K46:K48) -> 384 | ... M49: =SUM(M46:M48) -> 384
B51: Interest Calculation (on avg BOP/EOP balance)
B52: Interest on Senior Notes | I52: =(I46+H46)/2*$C$46 -> 28.875 | J52: =(J46+I46)/2*$C$46 -> 28.875 | K52: =(K46+J46)/2*$C$46 -> 28.875 | L52: =(L46+K46)/2*$C$46 -> 28.875 | M52: =(M46+L46)/2*$C$46 -> 28.875
B53: Interest on Revolver | I53: =(I47+H47)/2*$C$47 -> 1.99125 | J53: =(J47+I47)/2*$C$47 -> 0.57375 | K53: =(K47+J47)/2*$C$47 -> 0 | L53: =(L47+K47)/2*$C$47 -> 0 | M53: =(M47+L47)/2*$C$47 -> 0
B54: Interest on Finance Leases | I54: =(I48+H48)/2*$C$48 -> 1.7 | J54: =(J48+I48)/2*$C$48 -> 1.7 | K54: =(K48+J48)/2*$C$48 -> 1.7 | L54: =(L48+K48)/2*$C$48 -> 1.7 | M54: =(M48+L48)/2*$C$48 -> 1.7
B55: Total Interest Expense | I55: =SUM(I52:I54) -> 32.56625 | J55: =SUM(J52:J54) -> 31.14875 | K55: =SUM(K52:K54) -> 30.575 | L55: =SUM(L52:L54) -> 30.575 | M55: =SUM(M52:M54) -> 30.575
B56: Weighted avg cost of debt | I56: =IF(AVERAGE(H49,I49)=0,0,I55/AVERAGE(H49,I49)) -> 0.078757557 | J56: =IF(AVERAGE(I49,J49)=0,0,J55/AVERAGE(I49,J49)) -> 0.079359873 | K56: =IF(AVERAGE(J49,K49)=0,0,K55/AVERAGE(J49,K49)) -> 0.079622396 | L56: =IF(AVERAGE(K49,L49)=0,0,L55/AVERAGE(K49,L49)) -> 0.079622396 | M56: =IF(AVERAGE(L49,M49)=0,0,M55/AVERAGE(L49,M49)) -> 0.079622396
B58: Tax & Interest
B59: Effective tax rate | C59: % | D59: 0.094 | E59: -0.021 | F59: 0.083 | G59: 0.058 | H59: 0.167 | I59: 0.17 | J59: 0.2 | K59: 0.22 | L59: 0.23 | M59: 0.23 | O59: The low tax rate in the HP was depressed by three tailwinds that will fade: huge tax deductions from stock-based comp vesting at today's elevated share price (stock up 7x since 2022), fixed FICA tip credits shrinking as a % of growing pretax income, and near-term bonus depreciation timing benefits
B60: Interest expense ($M) | C60: $M | D60: 56.2 | E60: 46.1 | F60: 54.4 | G60: 65 | H60: 53.1 | I60: =I55 -> 32.56625 | J60: =J55 -> 31.14875 | K60: =K55 -> 30.575 | L60: =L55 -> 30.575 | M60: =M55 -> 30.575
B62: Balance Sheet Drivers
B63: Capex % of revenue | C63: % | D63: =D66/'Income Statement'!D13 -> 0.028162263 | E63: =E66/'Income Statement'!E13 -> 0.039510002 | F63: =F66/'Income Statement'!F13 -> 0.04560815 | G63: =G66/'Income Statement'!G13 -> 0.045049942 | H63: =H66/'Income Statement'!H13 -> 0.049273801 | I63: =D19 -> 0.045 | J63: =I63+(INDEX($E$19:$G$19,MATCH($H$19,$E$9:$G$9,0))-I63)*1/4 -> 0.04375 | K63: =I63+(INDEX($E$19:$G$19,MATCH($H$19,$E$9:$G$9,0))-I63)*2/4 -> 0.0425 | L63: =I63+(INDEX($E$19:$G$19,MATCH($H$19,$E$9:$G$9,0))-I63)*3/4 -> 0.04125 | M63: =INDEX($E$19:$G$19,MATCH($H$19,$E$9:$G$9,0)) -> 0.04 | O63: Brinker ran lean on capex during COVID (FY21-FY22), letting assets depreciate without refresh. Now remodelling and integrating tech, Mgmt has signaled FY26-FY27 as peak investment, then moderating.
B64: SBC % of revenue | C64: % | D64: ='Income Statement'!D55/'Income Statement'!D13 -> 0.0035053029 | E64: ='Income Statement'!E55/'Income Statement'!E13 -> 0.0037853894 | F64: ='Income Statement'!F55/'Income Statement'!F13 -> 0.0035519597 | G64: ='Income Statement'!G55/'Income Statement'!G13 -> 0.0058662318 | H64: ='Income Statement'!H55/'Income Statement'!H13 -> 0.0058318785 | I64: 0.006 | J64: 0.006 | K64: 0.006 | L64: 0.006 | M64: 0.006 | O64: Modest for a large-cap company. Reflects lean corporate headcount (restaurant operators have few highly-paid options grantees vs tech
B65: Days Payable (AP / F&B costs) | C65: days | D65: =IFERROR('Balance Sheet'!D28/'Income Statement'!D17*365,0) -> 53.711109 | E65: =IFERROR('Balance Sheet'!E28/'Income Statement'!E17*365,0) -> 46.752027 | F65: =IFERROR('Balance Sheet'!F28/'Income Statement'!F17*365,0) -> 42.069045 | G65: =IFERROR('Balance Sheet'!G28/'Income Statement'!G17*365,0) -> 52.924341 | H65: =IFERROR('Balance Sheet'!H28/'Income Statement'!H17*365,0) -> 45.537169 | I65: 46 | J65: 46 | K65: 46 | L65: 46 | M65: 46 | O65: Brinker's 45-50 days is normal for casual dining
B66: Capex | C66: $M | D66: =-'Cash Flow'!D19 -> 94 | E66: =-'Cash Flow'!E19 -> 150.3 | F66: =-'Cash Flow'!F19 -> 184.9 | G66: =-'Cash Flow'!G19 -> 198.9 | H66: =-'Cash Flow'!H19 -> 265.3 | I66: =I63*'Income Statement'!I13 -> 261.20313 | J66: =J63*'Income Statement'!J13 -> 264.92114 | K66: =K63*'Income Statement'!K13 -> 264.81705 | L66: =L63*'Income Statement'!L13 -> 262.32429 | M66: =M63*'Income Statement'!M13 -> 260.5136
B68: Capital Allocation | O68: How FCF gets returned to shareholders. Flow: FCF × Buyback% = Buyback$ → retires shares at market price → reduces diluted share count → flows to CF financing.
B69: Current market share price | C69: $ | D69: 30 | E69: 30 | F69: 35 | G69: 50 | H69: 130 | I69: ='DCF & Sensitivity'!D55 -> 168 | J69: =I69 -> 168 | K69: =J69 -> 168 | L69: =K69 -> 168 | M69: =L69 -> 168
B70: Buybacks as % of FCF | C70: % | D70: =IFERROR(D71/'Cash Flow'!D38,0) -> 0.015909091 | E70: =IFERROR(E71/'Cash Flow'!E38,0) -> 1.1531429 | F70: =IFERROR(F71/'Cash Flow'!F38,0) -> 0.087719298 | G70: =IFERROR(G71/'Cash Flow'!G38,0) -> 0.13089802 | H70: =IFERROR(H71/'Cash Flow'!H38,0) -> 0.23594036 | I70: =D21 -> 0.6 | J70: =I70+(INDEX($E$21:$G$21,MATCH($H$21,$E$9:$G$9,0))-I70)*1/4 -> 0.575 | K70: =I70+(INDEX($E$21:$G$21,MATCH($H$21,$E$9:$G$9,0))-I70)*2/4 -> 0.55 | L70: =I70+(INDEX($E$21:$G$21,MATCH($H$21,$E$9:$G$9,0))-I70)*3/4 -> 0.525 | M70: =INDEX($E$21:$G$21,MATCH($H$21,$E$9:$G$9,0)) -> 0.5
B71: Share buybacks | C71: $M | D71: =-'Cash Flow'!D24 -> 4.2 | E71: =-'Cash Flow'!E24 -> 100.9 | F71: =-'Cash Flow'!F24 -> 5 | G71: =-'Cash Flow'!G24 -> 25.8 | H71: =-'Cash Flow'!H24 -> 90.2 | I71: =I70*'Cash Flow'!I38 -> 273.98295 | J71: =J70*'Cash Flow'!J38 -> 257.05336 | K71: =K70*'Cash Flow'!K38 -> 242.11995 | L71: =L70*'Cash Flow'!L38 -> 229.69541 | M71: =M70*'Cash Flow'!M38 -> 222.25936 | O71: $0 in FY21 (COVID preservation), spike to $150M FY22, near-zero FY23-24 (paying down revolver instead). Ramped buybacks dramatically in FY25-FY26 — the board authorized an additional $400M post-FY25 bringing total repurchase authority to $507M
B72: Dividends | C72: $M | D72: =-'Cash Flow'!D25 -> 1.5 | E72: =-'Cash Flow'!E25 -> 1.1 | F72: =-'Cash Flow'!F25 -> 0.6 | G72: =-'Cash Flow'!G25 -> 0.2 | H72: =-'Cash Flow'!H25 -> 0 | I72: 0 | J72: 0 | K72: 0 | L72: 0 | M72: 0 | O72: EAT does not currently pay a dividend (suspended during COVID, never reinstated). Historical FY23 $0.6M and FY24 $0.2M are just residual dividend equivalents on restricted stock unit
B73: Diluted shares | C73: M | D73: ='Income Statement'!D44 -> 46.7 | E73: ='Income Statement'!E44 -> 45.4 | F73: ='Income Statement'!F44 -> 45.3 | G73: ='Income Statement'!G44 -> 45 | H73: ='Income Statement'!H44 -> 45.5 | I73: =H73-I71/I69+'Income Statement'!I55/I69 -> 44.076453 | J73: =I73-J71/J69+'Income Statement'!J55/J69 -> 42.762636 | K73: =J73-K71/K69+'Income Statement'!K55/K69 -> 41.543981 | L73: =K73-L71/L69+'Income Statement'!L55/L69 -> 40.403867 | M73: =L73-M71/M69+'Income Statement'!M55/M69 -> 39.313496 | O73: Prior shares – (buybacks / share price) + (SBC / share price). Captures both shares retired via buybacks and shares issued via SBC vesting.
B74: Total capital return (% of FCF) | C74: % | D74: =IFERROR((D71+D72)/'Cash Flow'!D38,0) -> 0.021590909 | E74: =IFERROR((E71+E72)/'Cash Flow'!E38,0) -> 1.1657143 | F74: =IFERROR((F71+F72)/'Cash Flow'!F38,0) -> 0.098245614 | G74: =IFERROR((G71+G72)/'Cash Flow'!G38,0) -> 0.13191273 | H74: =IFERROR((H71+H72)/'Cash Flow'!H38,0) -> 0.23594036 | I74: =IFERROR((I71+I72)/'Cash Flow'!I38,0) -> 0.6 | J74: =IFERROR((J71+J72)/'Cash Flow'!J38,0) -> 0.575 | K74: =IFERROR((K71+K72)/'Cash Flow'!K38,0) -> 0.55 | ... M74: =IFERROR((M71+M72)/'Cash Flow'!M38,0) -> 0.5 | O74: Sanity check on total capital return intensity
B77: DCF ASSUMPTIONS
B78: Risk-Free Rate (10Y UST) | C78: % | D78: 0.0431
B79: Equity Risk Premium | C79: % | D79: 0.055
B80: Beta (raw, 5-yr regression) | C80: x | D80: 1.25
B81: Adjusted beta (Blume) | C81: x | D81: =D80*0.67+0.33 -> 1.1675
B82: Cost of Equity (CAPM) | C82: % | D82: =D78+D81*D79 -> 0.1073125
B83: Pre-tax Cost of Debt | C83: % | D83: =I56 -> 0.078757557
B84: Market Value of Debt ($M) | C84: $M | D84: =H49 -> 426
B85: Market Value of Equity ($M) | C85: $M | D85: ='Income Statement'!H44*'DCF & Sensitivity'!D55 -> 7644
B86: Debt / Total Cap | C86: % | D86: =D84/(D84+D85) -> 0.052788104
B87: WACC | C87: % | D87: =D82*(1-D86)+D83*(1-I59)*D86 -> 0.10509837
B88: Terminal Growth Rate | C88: % | D88: =INDEX($E$23:$G$23,MATCH($H$23,$E$9:$G$9,0)) -> 0.025
B89: Exit EV/EBITDA | C89: x | D89: =INDEX($E$24:$G$24,MATCH($H$24,$E$9:$G$9,0)) -> 11

Sheet Revenue Build
B2: Revenue Build
B3: Brinker International (EAT)
B4: All amounts in $ millions unless noted
B6: Ideally, a restaurant DCF would build revenue from unit economic drivers (avg units × AUV + new units × ramp-up AUV − closed units × partial-year AUV) to isolate new stores, existing stores, and closed stores as separate value drivers. We can't do this cleanly because the 10-K doesn't disclose: (1) unit-week counts (when during the year stores closed), (2) new-build AUV vs mature AUV (new restaurants ramp over ~2 yrs), (3) domestic vs international AUV split (international franchisees have different economics), or (4) the restaurant population used in the AUV metric. In the HP, we attempted to take AUV * # of Units to see if this bottoms-up revenue build would align close to reported revenue, but this method overshoots reported sales by 3-9% historically, confirming the current level of disclosure isn't sufficient for a precise bottoms-up build. How we forecast revenue: FY25 Reported × (1 + SSS%), compounded. This method sacrifices segment-level unit economics visibility but anchors forecast to audited revenue. Unit economics breakdown below is kept as analytical color. This is doable for Brinker specifically, because new stores expansion is immaterial (~+2 net Chili's/yr = <0.1% revenue impact). SSS toggles remain the primary value lever.
C16: Units | D16: FY21A | E16: FY22A | F16: FY23A | G16: FY24A | H16: FY25A | I16: FY26E | J16: FY27E | K16: FY28E | L16: FY29E | M16: FY30E | O16: Notes
B18: Chili's Company-Owned
B19: Units BOP | C19: # | D19: 1145 | E19: =D21 -> 1134 | F19: =E21 -> 1123 | G19: =F21 -> 1127 | H19: =G21 -> 1121 | I19: =H21 -> 1113 | J19: =I21 -> 1115 | K19: =J21 -> 1115 | L19: =K21 -> 1115 | M19: =L21 -> 1115 | O19: Proforma company-owned sales are linked here from Assumptions row 29 (FY25 Reported $4,834M × SSS, compounded). Unit counts, SSS, and AUV shown here for reference. FY21 SSS +21.5% = post-COVID rebound; FY25 SSS +17% driven by CEO Hochman's "Chili's Reimagined" turnaround (Q4 traffic +16%, unusually traffic-led growth vs. industry pricing-led norm).
B20: Net new / (closures) | C20: # | D20: =D21-D19 -> -11 | E20: =E21-E19 -> -11 | F20: =F21-F19 -> 4 | G20: =G21-G19 -> -6 | H20: =H21-H19 -> -8 | I20: =7-5 -> 2 | J20: 0 | K20: 0 | L20: 0 | M20: 0
B21: Units EOP | C21: # | D21: 1134 | E21: 1123 | F21: 1127 | G21: 1121 | H21: 1113 | I21: =I19+I20 -> 1115 | J21: =J19+J20 -> 1115 | K21: =K19+K20 -> 1115 | L21: =L19+L20 -> 1115 | M21: =M19+M20 -> 1115
B22: Same store sales YoY growth (SSS) | C22: % | D22: 0.215 | E22: 0.03 | F22: 0.074 | G22: 0.038 | H22: 0.17 | I22: =Assumptions!$D$11 -> 0.086 | J22: =Assumptions!$D$11*0.55 -> 0.0473 | K22: =Assumptions!$D$11*0.35 -> 0.0301 | L22: =(Assumptions!$D$11*0.2+INDEX(Assumptions!$E$11:$G$11,MATCH(Assumptions!$H$11,Assumptions!$E$9:$G$9,0)))/2 -> 0.0211 | M22: =INDEX(Assumptions!$E$11:$G$11,MATCH(Assumptions!$H$11,Assumptions!$E$9:$G$9,0)) -> 0.025
B23: Average unit volume (AUV) | C23: $M | D23: 2.9 | E23: 3.2 | F23: 3.4 | G23: 3.6 | H23: 4.5 | I23: =H23*(1+I22) -> 4.887 | J23: =I23*(1+J22) -> 5.1181551 | K23: =J23*(1+K22) -> 5.2722116 | L23: =K23*(1+L22) -> 5.3834552 | M23: =L23*(1+M22) -> 5.5180416
B24: Chili's company-owned sales | C24: $M | D24: =((D19+D21)/2)*D23 -> 3304.55 | E24: =((E19+E21)/2)*E23 -> 3611.2 | F24: =((F19+F21)/2)*F23 -> 3825 | G24: =((G19+G21)/2)*G23 -> 4046.4 | H24: =((H19+H21)/2)*H23 -> 5026.5 | I24: =Assumptions!I29 -> 5250.5928 | J24: =Assumptions!J29 -> 5498.9458 | K24: =Assumptions!K29 -> 5664.4641 | L24: =Assumptions!L29 -> 5783.9843 | M24: =Assumptions!M29 -> 5928.5839
B25: % of Total Revenue | C25: % | D25: =D24/D41 -> 0.90942991 | E25: =E24/E41 -> 0.87556978 | F25: =F24/F41 -> 0.8710603 | G25: =G24/G41 -> 0.8834163 | H25: =H24/H41 -> 0.90396547 | I25: =I24/I41 -> 0.9045706 | J25: =J24/J41 -> 0.90811507 | K25: =K24/K41 -> 0.9090794 | ... M25: =M24/M41 -> 0.91029164
B27: Maggiano's Company-Owned
B28: Units EOP | C28: # | D28: 51 | E28: 52 | F28: 50 | G28: 50 | H28: 49 | I28: =H28 -> 49 | J28: =I28 -> 49 | K28: =J28 -> 49 | L28: =K28 -> 49 | M28: =L28 -> 49 | O28: Proforma company-owned sales are linked here from Assumptions row 31 (FY25 Reported $500M × SSS). 49 units, 100% Company-operated (zero franchised). Italian-American polished casual; banquet-heavy (15% of sales). Highest AUV in casual dining ($9.9M vs Chili's $4.5M) from higher check size ($39/guest vs $22) and banquet volume. ~9% of total revenue. Brand contracting — FY26 Q1 comp -6.4%, Q2 -2.4%; mgmt applying "Chili's turnaround playbook."
B29: Same store sales YoY growth (SSS) | C29: % | D29: 0.15 | E29: 0.08 | F29: 0.069 | G29: 0.024 | H29: 0.008 | I29: =Assumptions!$D$12 -> -0.024 | J29: =(Assumptions!$D$12+INDEX(Assumptions!$E$12:$G$12,MATCH(Assumptions!$H$12,Assumptions!$E$9:$G$9,0)))/2 -> -0.007 | K29: =INDEX(Assumptions!$E$12:$G$12,MATCH(Assumptions!$H$12,Assumptions!$E$9:$G$9,0)) -> 0.01 | L29: =INDEX(Assumptions!$E$12:$G$12,MATCH(Assumptions!$H$12,Assumptions!$E$9:$G$9,0)) -> 0.01 | M29: =INDEX(Assumptions!$E$12:$G$12,MATCH(Assumptions!$H$12,Assumptions!$E$9:$G$9,0)) -> 0.01
B30: Average unit volume (AUV) | C30: $M | D30: 5.3 | E30: 8.1 | F30: 9.5 | G30: 9.8 | H30: 9.9 | I30: =H30*(1+I29) -> 9.6624 | J30: =I30*(1+J29) -> 9.5947632 | K30: =J30*(1+K29) -> 9.6907108 | L30: =K30*(1+L29) -> 9.7876179 | M30: =L30*(1+M29) -> 9.8854941
B31: Maggiano's company-owned sales | C31: $M | D31: =D28*D30 -> 270.3 | E31: =E28*E30 -> 421.2 | F31: =F28*F30 -> 475 | G31: =G28*G30 -> 490 | H31: =H28*H30 -> 485.1 | I31: =Assumptions!I31 -> 488.488 | J31: =Assumptions!J31 -> 485.06858 | K31: =Assumptions!K31 -> 489.91927 | L31: =Assumptions!L31 -> 494.81846 | M31: =Assumptions!M31 -> 499.76665
B32: % of Total Revenue | C32: % | D32: =D31/D41 -> 0.074388012 | E32: =E31/E41 -> 0.10212395 | F32: =F31/F41 -> 0.10817089 | G32: =G31/G41 -> 0.10697756 | H32: =H31/H41 -> 0.087240356 | I32: =I31/I41 -> 0.084156571 | J32: =J31/J41 -> 0.080105916 | K32: =K31/K41 -> 0.078626241 | ... M32: =M31/M41 -> 0.076735593
B33: Total company-owned sales | C33: $M | D33: =D24+D31 -> 3574.85 | E33: =E24+E31 -> 4032.4 | F33: =F24+F31 -> 4300 | G33: =G24+G31 -> 4536.4 | H33: =H24+H31 -> 5511.6 | I33: =I24+I31 -> 5739.0808 | J33: =J24+J31 -> 5984.0144 | K33: =K24+K31 -> 6154.3834 | ... M33: =M24+M31 -> 6428.3506
B35: Chili's Franchise
B36: Chili's franchise units | C36: # | D36: 316 | E36: 353 | F36: 398 | G36: 430 | H36: 463 | I36: =H36+26 -> 489 | J36: =I36+26 -> 515 | K36: =J36+24 -> 539 | L36: =K36+22 -> 561 | M36: =L36+20 -> 581 | O36: 463 units at FY25 (99 domestic + 364 international): Brinker collects royalties. Per-unit sales much lower than Co-owned ($2.9M vs $4.5M) due to international weighting. FY23→FY24 drop reflects ASC 606 reclassification (ad fund netted vs grossed up), not economic decline. Not a real valuation driver.
B37: Est. franchise system sales | C37: $M | D37: 850 | E37: 950 | F37: 1100 | G37: 1200 | H37: 1320 | I37: =I36*(H37/H36)*(1+I22*0.5) -> 1454.0727 | J37: =J36*(I37/I36)*(1+J22*0.5) -> 1567.6026 | K37: =K36*(J37/J36)*(1+K22*0.5) -> 1665.3478 | L37: =L36*(K37/K36)*(1+L22*0.5) -> 1751.6077 | M37: =M36*(L37/L36)*(1+M22*0.5) -> 1836.7293
B38: Effective royalty + other | C38: % | D38: =D39/D37 -> 0.069176471 | E38: =E39/E37 -> 0.096842105 | F38: =F39/F37 -> 0.082909091 | G38: =G39/G37 -> 0.036666667 | H38: =H39/H37 -> 0.037045455 | I38: =Assumptions!$D$13 -> 0.045 | J38: =(Assumptions!$D$13+INDEX(Assumptions!$E$13:$G$13,MATCH(Assumptions!$H$13,Assumptions!$E$9:$G$9,0)))/2 -> 0.0455 | K38: =INDEX(Assumptions!$E$13:$G$13,MATCH(Assumptions!$H$13,Assumptions!$E$9:$G$9,0)) -> 0.046 | L38: =INDEX(Assumptions!$E$13:$G$13,MATCH(Assumptions!$H$13,Assumptions!$E$9:$G$9,0)) -> 0.046 | M38: =INDEX(Assumptions!$E$13:$G$13,MATCH(Assumptions!$H$13,Assumptions!$E$9:$G$9,0)) -> 0.046
B39: Franchise & other revenue | C39: $M | D39: 58.8 | E39: 92 | F39: 91.2 | G39: 44 | H39: 48.9 | I39: =I37*I38 -> 65.43327 | J39: =J37*J38 -> 71.325917 | K39: =K37*K38 -> 76.605997 | L39: =L37*L38 -> 80.573954 | M39: =M37*M38 -> 84.489546
B40: % of Total Revenue | C40: % | D40: =D39/D41 -> 0.016182076 | E40: =E39/E41 -> 0.022306275 | F40: =F39/F41 -> 0.02076881 | G40: =G39/G41 -> 0.0096061479 | H40: =H39/H41 -> 0.0087941732 | I40: =I39/I41 -> 0.011272825 | J40: =J39/J41 -> 0.01177901 | K40: =K39/K41 -> 0.012294355 | ... M40: =M39/M41 -> 0.012972765
B41: Total Revenue (company-owned + franchise) | C41: $M | D41: =D33+D39 -> 3633.65 | E41: =E33+E39 -> 4124.4 | F41: =F33+F39 -> 4391.2 | G41: =G33+G39 -> 4580.4 | H41: =H33+H39 -> 5560.5 | I41: =I33+I39 -> 5804.5141 | J41: =J33+J39 -> 6055.3403 | K41: =K33+K39 -> 6230.9894 | ... M41: =M33+M39 -> 6512.8401
B42: YoY growth | C42: % | E42: =E41/D41-1 -> 0.13505704 | F42: =F41/E41-1 -> 0.064688197 | G42: =G41/F41-1 -> 0.043086172 | H42: =H41/G41-1 -> 0.21397695 | I42: =I41/H41-1 -> 0.043883476 | J42: =J41/I41-1 -> 0.043212277 | K42: =K41/J41-1 -> 0.029007294 | L42: =L41/K41-1 -> 0.020604648 | M42: =M41/L41-1 -> 0.024131828
B44: Revenue Check : Unit Economics Build vs. Reported
B45: Reported Revenue (IS Statement) | C45: $M | D45: ='Income Statement'!D13 -> 3337.8 | E45: ='Income Statement'!E13 -> 3804.1 | F45: ='Income Statement'!F13 -> 4054.1 | G45: ='Income Statement'!G13 -> 4415.1 | H45: ='Income Statement'!H13 -> 5384.2
B46: Variance (Unit Economics Build vs. IS Reported) | C46: $M | D46: =D41-D45 -> 295.85 | E46: =E41-E45 -> 320.3 | F46: =F41-F45 -> 337.1 | G46: =G41-G45 -> 165.3 | H46: =H41-H45 -> 176.3
B47: Variance % | C47: % | D47: =D46/D45 -> 0.088636227 | E47: =E46/E45 -> 0.084198628 | F47: =F46/F45 -> 0.083150391 | G47: =G46/G45 -> 0.037439696 | H47: =H46/H45 -> 0.032743955

Sheet Income Statement
B2: Income Statement
B3: Brinker International (EAT)
B4: All amounts in $ millions unless noted
C6: Units | D6: =IF('Cover Page'!$C$63+0<'Cover Page'!$C$64,"FY"&TEXT(MOD('Cover Page'!$C$63+0,100),"00")&"A","FY"&TEXT(MOD('Cover Page'!$C$63+0,100),"00")&"E") -> FY21A | E6: =IF('Cover Page'!$C$63+1<'Cover Page'!$C$64,"FY"&TEXT(MOD('Cover Page'!$C$63+1,100),"00")&"A","FY"&TEXT(MOD('Cover Page'!$C$63+1,100),"00")&"E") -> FY22A | F6: =IF('Cover Page'!$C$63+2<'Cover Page'!$C$64,"FY"&TEXT(MOD('Cover Page'!$C$63+2,100),"00")&"A","FY"&TEXT(MOD('Cover Page'!$C$63+2,100),"00")&"E") -> FY23A | G6: =IF('Cover Page'!$C$63+3<'Cover Page'!$C$64,"FY"&TEXT(MOD('Cover Page'!$C$63+3,100),"00")&"A","FY"&TEXT(MOD('Cover Page'!$C$63+3,100),"00")&"E") -> FY24A | H6: =IF('Cover Page'!$C$63+4<'Cover Page'!$C$64,"FY"&TEXT(MOD('Cover Page'!$C$63+4,100),"00")&"A","FY"&TEXT(MOD('Cover Page'!$C$63+4,100),"00")&"E") -> FY25A | I6: =IF('Cover Page'!$C$63+5<'Cover Page'!$C$64,"FY"&TEXT(MOD('Cover Page'!$C$63+5,100),"00")&"A","FY"&TEXT(MOD('Cover Page'!$C$63+5,100),"00")&"E") -> FY26E | J6: =IF('Cover Page'!$C$63+6<'Cover Page'!$C$64,"FY"&TEXT(MOD('Cover Page'!$C$63+6,100),"00")&"A","FY"&TEXT(MOD('Cover Page'!$C$63+6,100),"00")&"E") -> FY27E | K6: =IF('Cover Page'!$C$63+7<'Cover Page'!$C$64,"FY"&TEXT(MOD('Cover Page'!$C$63+7,100),"00")&"A","FY"&TEXT(MOD('Cover Page'!$C$63+7,100),"00")&"E") -> FY28E | L6: =IF('Cover Page'!$C$63+8<'Cover Page'!$C$64,"FY"&TEXT(MOD('Cover Page'!$C$63+8,100),"00")&"A","FY"&TEXT(MOD('Cover Page'!$C$63+8,100),"00")&"E") -> FY29E | M6: =IF('Cover Page'!$C$63+9<'Cover Page'!$C$64,"FY"&TEXT(MOD('Cover Page'!$C$63+9,100),"00")&"A","FY"&TEXT(MOD('Cover Page'!$C$63+9,100),"00")&"E") -> FY30E | O6: Notes
B8: Revenue
B9: Chili's company sales | C9: $M | D9: 3008.7 | E9: 3290.9 | F9: 3487.9 | G9: 3876 | H9: 4834.8 | I9: =Assumptions!I29 -> 5250.5928 | J9: =Assumptions!J29 -> 5498.9458 | K9: =Assumptions!K29 -> 5664.4641 | L9: =Assumptions!L29 -> 5783.9843 | M9: =Assumptions!M29 -> 5928.5839 | O9: Brinker revenue = Company sales (98%) + Franchise revenues (1%). Company sales = revenue from restaurants Brinker owns & operates (1,113 Chili's + 49 Maggiano's). Franchise = royalties from 463 franchised Chili's (mostly international). Forecast: FY25 reported × (1 + SSS%), compounded. SSS toggles live on Assumptions
B10: Maggiano's company sales | C10: $M | D10: 270.3 | E10: 421.2 | F10: 475 | G10: 495.1 | H10: 500.5 | I10: =Assumptions!I31 -> 488.488 | J10: =Assumptions!J31 -> 485.06858 | K10: =Assumptions!K31 -> 489.91927 | L10: =Assumptions!L31 -> 494.81846 | M10: =Assumptions!M31 -> 499.76665
B11: Total Company-Owned Sales | C11: $M | D11: =D9+D10 -> 3279 | E11: =E9+E10 -> 3712.1 | F11: =F9+F10 -> 3962.9 | G11: =G9+G10 -> 4371.1 | H11: =H9+H10 -> 5335.3 | I11: =I9+I10 -> 5739.0808 | J11: =J9+J10 -> 5984.0144 | K11: =K9+K10 -> 6154.3834 | ... M11: =M9+M10 -> 6428.3506
B12: Franchise revenues | C12: $M | D12: 58.8 | E12: 92 | F12: 91.2 | G12: 44 | H12: 48.9 | I12: =Assumptions!I32 -> 65.43327 | J12: =Assumptions!J32 -> 71.325917 | K12: =Assumptions!K32 -> 76.605997 | L12: =Assumptions!L32 -> 80.573954 | M12: =Assumptions!M32 -> 84.489546
B13: Total revenues | C13: $M | D13: =D11+D12 -> 3337.8 | E13: =E11+E12 -> 3804.1 | F13: =F11+F12 -> 4054.1 | G13: =G11+G12 -> 4415.1 | H13: =H11+H12 -> 5384.2 | I13: =I11+I12 -> 5804.5141 | J13: =J11+J12 -> 6055.3403 | K13: =K11+K12 -> 6230.9894 | ... M13: =M11+M12 -> 6512.8401
B14: YoY growth % | C14: % | E14: =E13/D13-1 -> 0.1397028 | F14: =F13/E13-1 -> 0.065718567 | G14: =G13/F13-1 -> 0.089045657 | H14: =H13/G13-1 -> 0.21949673 | I14: =I13/H13-1 -> 0.078064349 | J14: =J13/I13-1 -> 0.043212277 | K14: =K13/J13-1 -> 0.029007294 | L14: =L13/K13-1 -> 0.020604648 | M14: =M13/L13-1 -> 0.024131828
B16: Restaurant-level operating costs
B17: Food and beverage costs | C17: $M | D17: 867.8 | E17: 1048.5 | F17: 1090.6 | G17: 1107.6 | H17: 1350.6 | I17: =I11*Assumptions!I36 -> 1463.4656 | J17: =J11*Assumptions!J36 -> 1533.4037 | K17: =K11*Assumptions!K36 -> 1584.7537 | L17: =L11*Assumptions!L36 -> 1624.6402 | M17: =M11*Assumptions!M36 -> 1671.3711 | O17: Costs that happen inside the four walls of a restaurant. Three line items: i) F&B costs — ingredients; moves with commodity cycles, ii) Restaurant labor — hourly staff, managers, benefits, payroll taxes iii) Restaurant expenses — rent, utilities, R&M, credit card fees, local marketing Forecast % driven by scenario toggles on Assumptions (F&B/Labor/Rest Exp). These three sum to ~82-83% of company sales.
B18: % of Company sales | C18: % | D18: =D17/D11 -> 0.26465386 | E18: =E17/E11 -> 0.28245468 | F18: =F17/F11 -> 0.2752025 | G18: =G17/G11 -> 0.25339159 | H18: =H17/H11 -> 0.25314415 | I18: =I17/I11 -> 0.255 | J18: =J17/J11 -> 0.25625 | K18: =K17/K11 -> 0.2575 | ... M18: =M17/M11 -> 0.26
B19: Restaurant labor | C19: $M | D19: 1108.2 | E19: 1288.1 | F19: 1361.1 | G19: 1467.3 | H19: 1717.3 | I19: =I11*Assumptions!I37 -> 1847.984 | J19: =J11*Assumptions!J37 -> 1931.3407 | K19: =K11*Assumptions!K37 -> 1990.943 | L19: =L11*Assumptions!L37 -> 2035.9018 | M19: =M11*Assumptions!M37 -> 2089.2139
B20: % of Company sales | C20: % | D20: =D19/D11 -> 0.33796889 | E20: =E19/E11 -> 0.34700035 | F20: =F19/F11 -> 0.3434606 | G20: =G19/G11 -> 0.33568209 | H20: =H19/H11 -> 0.32187506 | I20: =I19/I11 -> 0.322 | J20: =J19/J11 -> 0.32275 | K20: =K19/K11 -> 0.3235 | ... M20: =M19/M11 -> 0.325
B21: Restaurant expenses | C21: $M | D21: 858.5 | E21: 968.3 | F21: 1056.4 | G21: 1212.9 | H21: 1333.9 | I21: =I11*Assumptions!I38 -> 1406.0748 | J21: =J11*Assumptions!J38 -> 1473.5636 | K21: =K11*Assumptions!K38 -> 1523.2099 | L21: =L11*Assumptions!L38 -> 1561.8522 | M21: =M11*Assumptions!M38 -> 1607.0876
B22: % of Company sales | C22: % | D22: =D21/D11 -> 0.26181763 | E22: =E21/E11 -> 0.26084965 | F22: =F21/F11 -> 0.26657246 | G22: =G21/G11 -> 0.27748164 | H22: =H21/H11 -> 0.25001406 | I22: =I21/I11 -> 0.245 | J22: =J21/J11 -> 0.24625 | K22: =K21/K11 -> 0.2475 | ... M22: =M21/M11 -> 0.25
B23: Restaurant-Level Profit | C23: $M | D23: =D11-D17-D19-D21 -> 444.5 | E23: =E11-E17-E19-E21 -> 407.2 | F23: =F11-F17-F19-F21 -> 454.8 | G23: =G11-G17-G19-G21 -> 583.3 | H23: =H11-H17-H19-H21 -> 933.5 | I23: =I11-I17-I19-I21 -> 1021.5564 | J23: =J11-J17-J19-J21 -> 1045.7065 | K23: =K11-K17-K19-K21 -> 1055.4767 | ... M23: =M11-M17-M19-M21 -> 1060.6778
B24: Restaurant-Level Margin % | C24: % | D24: =D23/D11 -> 0.13555962 | E24: =E23/E11 -> 0.10969532 | F24: =F23/F11 -> 0.11476444 | G24: =G23/G11 -> 0.13344467 | H24: =H23/H11 -> 0.17496673 | I24: =I23/I11 -> 0.178 | J24: =J23/J11 -> 0.17475 | K24: =K23/K11 -> 0.1715 | ... M24: =M23/M11 -> 0.165
B25: Corporate costs
B26: Depreciation & amortization | C26: $M | D26: 150.2 | E26: 164.4 | F26: 168.5 | G26: 170.8 | H26: 206.6 | I26: =I13*Assumptions!I40 -> 226.37605 | J26: =J13*Assumptions!J40 -> 242.21361 | K26: =K13*Assumptions!K40 -> 249.23958 | L26: =L13*Assumptions!L40 -> 260.73445 | M26: =M13*Assumptions!M40 -> 267.02644 | O26: Costs that happen above the restaurant level at HQ: i) D&A — depreciation on restaurant buildings/equipment + intangibles amortization ii) G&A — corporate HQ staff, field leadership above GM, legal/audit, IT iii) Other (gains) & charges — impairments, litigation settlements, restructuring, one-timers. Forecast driven by Assumptions scenario toggles.
B27: General & administrative | C27: $M | D27: 134.8 | E27: 144.1 | F27: 172.8 | G27: 183.7 | H27: 222 | I27: =I13*Assumptions!I41 -> 237.98508 | J27: =J13*Assumptions!J41 -> 246.75512 | K27: =K13*Assumptions!K41 -> 252.35507 | L27: =L13*Assumptions!L41 -> 255.96491 | M27: =M13*Assumptions!M41 -> 260.5136
B28: Other (gains) and charges | C28: $M | D28: 19 | E28: 31.2 | F28: 24 | G28: 43.2 | H28: 41.8 | I28: =I13*Assumptions!I42 -> 29.02257 | J28: =J13*Assumptions!J42 -> 30.276702 | K28: =K13*Assumptions!K42 -> 31.154947 | L28: =L13*Assumptions!L42 -> 31.796884 | M28: =M13*Assumptions!M42 -> 32.564201
B29: Total operating costs and expenses | C29: $M | D29: =D17+D19+D21+D26+D27+D28 -> 3138.5 | E29: =E17+E19+E21+E26+E27+E28 -> 3644.6 | F29: =F17+F19+F21+F26+F27+F28 -> 3873.4 | G29: =G17+G19+G21+G26+G27+G28 -> 4185.5 | H29: =H17+H19+H21+H26+H27+H28 -> 4872.2 | I29: =I17+I19+I21+I26+I27+I28 -> 5210.9081 | J29: =J17+J19+J21+J26+J27+J28 -> 5457.5533 | K29: =K17+K19+K21+K26+K27+K28 -> 5631.6562 | ... M29: =M17+M19+M21+M26+M27+M28 -> 5927.777
B31: Operating Income (EBIT) | C31: $M | D31: =D13-D29 -> 199.3 | E31: =E13-E29 -> 159.5 | F31: =F13-F29 -> 180.7 | G31: =G13-G29 -> 229.6 | H31: =H13-H29 -> 512 | I31: =I13-I29 -> 593.60596 | J31: =J13-J29 -> 597.787 | K31: =K13-K29 -> 599.33316 | ... M31: =M13-M29 -> 585.06314
B32: Operating margin % | C32: % | D32: =D31/D13 -> 0.059709989 | E32: =E31/E13 -> 0.041928446 | F32: =F31/F13 -> 0.044572162 | G32: =G31/G13 -> 0.052003352 | H32: =H31/H13 -> 0.09509305 | I32: =I31/I13 -> 0.10226626 | J32: =J31/J13 -> 0.098720628 | K32: =K31/K13 -> 0.096185873 | ... M32: =M31/M13 -> 0.089832259
B34: Below-the-line
B35: Interest expense | C35: $M | D35: 56.2 | E35: 46.1 | F35: 54.4 | G35: 65 | H35: 53.1 | I35: =Assumptions!I60 -> 32.56625 | J35: =Assumptions!J60 -> 31.14875 | K35: =Assumptions!K60 -> 30.575 | L35: =Assumptions!L60 -> 30.575 | M35: =Assumptions!M60 -> 30.575 | O35: Items between EBIT and Net Income: i) Interest expense — flows from debt schedule (Assumptions row 60) ii) Other income, net — FX gains/losses and misc; typically immaterial (~$1M) iii) Taxes — provision = pretax income × effective tax rate (Assumptions I43) FY25 effective rate 16.7% depressed by SBC tax benefits; normalizing to ~23% by FY30E as benefits fade.
B36: Other income, net | C36: $M | D36: -2.1 | E36: -1.8 | F36: -1.6 | G36: -0.3 | H36: -1.1 | I36: -1 | J36: -1 | K36: -1 | L36: -1 | M36: -1
B37: Pre-tax income | C37: $M | D37: =D31-D35-D36 -> 145.2 | E37: =E31-E35-E36 -> 115.2 | F37: =F31-F35-F36 -> 127.9 | G37: =G31-G35-G36 -> 164.9 | H37: =H31-H35-H36 -> 460 | I37: =I31-I35-I36 -> 562.03971 | J37: =J31-J35-J36 -> 567.63825 | K37: =K31-K35-K36 -> 569.75816 | ... M37: =M31-M35-M36 -> 555.48814
B38: Provision for income taxes | C38: $M | D38: 13.6 | E38: -2.4 | F38: 10.9 | G38: 9.6 | H38: 76.9 | I38: =I37*Assumptions!I59 -> 95.54675 | J38: =J37*Assumptions!J59 -> 113.52765 | K38: =K37*Assumptions!K59 -> 125.34679 | L38: =L37*Assumptions!L59 -> 128.54959 | M38: =M37*Assumptions!M59 -> 127.76227
B39: Effective tax rate | C39: % | D39: =D38/D37 -> 0.093663912 | E39: =E38/E37 -> -0.020833333 | F39: =F38/F37 -> 0.08522283 | G39: =G38/G37 -> 0.058217101 | H39: =H38/H37 -> 0.16717391 | I39: =I38/I37 -> 0.17 | J39: =J38/J37 -> 0.2 | K39: =K38/K37 -> 0.22 | ... M39: =M38/M37 -> 0.23
B40: NET INCOME | C40: $M | D40: =D37-D38 -> 131.6 | E40: =E37-E38 -> 117.6 | F40: =F37-F38 -> 117 | G40: =G37-G38 -> 155.3 | H40: =H37-H38 -> 383.1 | I40: =I37-I38 -> 466.49296 | J40: =J37-J38 -> 454.1106 | K40: =K37-K38 -> 444.41136 | ... M40: =M37-M38 -> 427.72587
B41: Net margin % | C41: % | D41: =D40/D13 -> 0.039427168 | E41: =E40/E13 -> 0.030914014 | F41: =F40/F13 -> 0.028859673 | G41: =G40/G13 -> 0.035174741 | H41: =H40/H13 -> 0.071152632 | I41: =I40/I13 -> 0.080367271 | J41: =J40/J13 -> 0.074993407 | K41: =K40/K13 -> 0.07132276 | ... M41: =M40/M13 -> 0.065674247
B43: EPS & Share Count
B44: Diluted shares outstanding | C44: M | D44: 46.7 | E44: 45.4 | F44: 45.3 | G44: 45 | H44: 45.5 | I44: =Assumptions!I73 -> 44.076453 | J44: =Assumptions!J73 -> 42.762636 | K44: =Assumptions!K73 -> 41.543981 | L44: =Assumptions!L73 -> 40.403867 | M44: =Assumptions!M73 -> 39.313496 | O44: Diluted EPS = Net Income / Diluted Shares. Diluted share count derived on Assumptions from buyback math (prior shares − buybacks/price + SBC/price). Current ~45.5M diluted declining to ~38.5M by FY30E reflecting aggressive buyback program
B45: Diluted EPS (GAAP) | C45: $ | D45: =D40/D44 -> 2.8179872 | E45: =E40/E44 -> 2.5903084 | F45: =F40/F44 -> 2.5827815 | G45: =G40/G44 -> 3.4511111 | H45: =H40/H44 -> 8.4197802 | I45: =I40/I44 -> 10.583723 | J45: =J40/J44 -> 10.619331 | K45: =K40/K44 -> 10.697371 | ... M45: =M40/M44 -> 10.879874
B46: Diluted EPS growth | C46: % | E46: =E45/D45-1 -> -0.080794826 | F46: =F45/E45-1 -> -0.0029057981 | G46: =G45/F45-1 -> 0.33619943 | H46: =H45/G45-1 -> 1.4397303 | I46: =I45/H45-1 -> 0.257007 | J46: =J45/I45-1 -> 0.0033644856 | K46: =K45/J45-1 -> 0.0073487842 | L46: =L45/K45-1 -> -0.0042882716 | M46: =M45/L45-1 -> 0.021440762
B48: EBITDA & SBC
B49: Operating income (EBIT) | C49: $M | D49: =D31 -> 199.3 | E49: =E31 -> 159.5 | F49: =F31 -> 180.7 | G49: =G31 -> 229.6 | H49: =H31 -> 512 | I49: =I31 -> 593.60596 | J49: =J31 -> 597.787 | K49: =K31 -> 599.33316 | ... M49: =M31 -> 585.06314 | O49: Adjusted EBITDA = EBIT + D&A + Other charges. Adds back non-cash D&A and one-time items (impairments, restructuring). Standard proxy for cash earnings
B50: (+) D&A | C50: $M | D50: =D26 -> 150.2 | E50: =E26 -> 164.4 | F50: =F26 -> 168.5 | G50: =G26 -> 170.8 | H50: =H26 -> 206.6 | I50: =I26 -> 226.37605 | J50: =J26 -> 242.21361 | K50: =K26 -> 249.23958 | ... M50: =M26 -> 267.02644
B51: (+) Other (gains) & charges | C51: $M | D51: =D28 -> 19 | E51: =E28 -> 31.2 | F51: =F28 -> 24 | G51: =G28 -> 43.2 | H51: =H28 -> 41.8 | I51: =I28 -> 29.02257 | J51: =J28 -> 30.276702 | K51: =K28 -> 31.154947 | ... M51: =M28 -> 32.564201
B52: Adjusted EBITDA | C52: $M | D52: =D49+D50+D51 -> 368.5 | E52: =E49+E50+E51 -> 355.1 | F52: =F49+F50+F51 -> 373.2 | G52: =G49+G50+G51 -> 443.6 | H52: =H49+H50+H51 -> 760.4 | I52: =I49+I50+I51 -> 849.00458 | J52: =J49+J50+J51 -> 870.27732 | K52: =K49+K50+K51 -> 879.72768 | ... M52: =M49+M50+M51 -> 884.65378
B53: EBITDA margin | C53: % | D53: =D52/D13 -> 0.11040206 | E53: =E52/E13 -> 0.093346652 | F53: =F52/F13 -> 0.092054957 | G53: =G52/G13 -> 0.10047338 | H53: =H52/H13 -> 0.14122804 | I53: =I52/I13 -> 0.14626626 | J53: =J52/J13 -> 0.14372063 | K53: =K52/K13 -> 0.14118587 | ... M53: =M52/M13 -> 0.13583226
B55: Stock-based compensation | C55: $M | D55: 11.7 | E55: 14.4 | F55: 14.4 | G55: 25.9 | H55: 31.4 | I55: =I13*Assumptions!I64 -> 34.827084 | J55: =J13*Assumptions!J64 -> 36.332042 | K55: =K13*Assumptions!K64 -> 37.385936 | L55: =L13*Assumptions!L64 -> 38.15626 | M55: =M13*Assumptions!M64 -> 39.077041
B56: SBC % of revenue | C56: % | D56: =D55/D13 -> 0.0035053029 | E56: =E55/E13 -> 0.0037853894 | F56: =F55/F13 -> 0.0035519597 | G56: =G55/G13 -> 0.0058662318 | H56: =H55/H13 -> 0.0058318785 | I56: =I55/I13 -> 0.006 | J56: =J55/J13 -> 0.006 | K56: =K55/K13 -> 0.006 | ... M56: =M55/M13 -> 0.006

Sheet Balance Sheet
B2: Balance Sheet
B3: Brinker International (EAT)
B4: All amounts in $ millions unless noted
C6: Units | D6: =IF('Cover Page'!$C$63+0<'Cover Page'!$C$64,"FY"&TEXT(MOD('Cover Page'!$C$63+0,100),"00")&"A","FY"&TEXT(MOD('Cover Page'!$C$63+0,100),"00")&"E") -> FY21A | E6: =IF('Cover Page'!$C$63+1<'Cover Page'!$C$64,"FY"&TEXT(MOD('Cover Page'!$C$63+1,100),"00")&"A","FY"&TEXT(MOD('Cover Page'!$C$63+1,100),"00")&"E") -> FY22A | F6: =IF('Cover Page'!$C$63+2<'Cover Page'!$C$64,"FY"&TEXT(MOD('Cover Page'!$C$63+2,100),"00")&"A","FY"&TEXT(MOD('Cover Page'!$C$63+2,100),"00")&"E") -> FY23A | G6: =IF('Cover Page'!$C$63+3<'Cover Page'!$C$64,"FY"&TEXT(MOD('Cover Page'!$C$63+3,100),"00")&"A","FY"&TEXT(MOD('Cover Page'!$C$63+3,100),"00")&"E") -> FY24A | H6: =IF('Cover Page'!$C$63+4<'Cover Page'!$C$64,"FY"&TEXT(MOD('Cover Page'!$C$63+4,100),"00")&"A","FY"&TEXT(MOD('Cover Page'!$C$63+4,100),"00")&"E") -> FY25A | I6: =IF('Cover Page'!$C$63+5<'Cover Page'!$C$64,"FY"&TEXT(MOD('Cover Page'!$C$63+5,100),"00")&"A","FY"&TEXT(MOD('Cover Page'!$C$63+5,100),"00")&"E") -> FY26E | J6: =IF('Cover Page'!$C$63+6<'Cover Page'!$C$64,"FY"&TEXT(MOD('Cover Page'!$C$63+6,100),"00")&"A","FY"&TEXT(MOD('Cover Page'!$C$63+6,100),"00")&"E") -> FY27E | K6: =IF('Cover Page'!$C$63+7<'Cover Page'!$C$64,"FY"&TEXT(MOD('Cover Page'!$C$63+7,100),"00")&"A","FY"&TEXT(MOD('Cover Page'!$C$63+7,100),"00")&"E") -> FY28E | L6: =IF('Cover Page'!$C$63+8<'Cover Page'!$C$64,"FY"&TEXT(MOD('Cover Page'!$C$63+8,100),"00")&"A","FY"&TEXT(MOD('Cover Page'!$C$63+8,100),"00")&"E") -> FY29E | M6: =IF('Cover Page'!$C$63+9<'Cover Page'!$C$64,"FY"&TEXT(MOD('Cover Page'!$C$63+9,100),"00")&"A","FY"&TEXT(MOD('Cover Page'!$C$63+9,100),"00")&"E") -> FY30E
B8: Assets: | O8: Notes
B9: Current assets:
B10: Cash and cash equivalents | C10: $M | D10: 23.9 | E10: 13.5 | F10: 15.1 | G10: 64.6 | H10: 18.9 | I10: ='Cash Flow'!I32 -> 243.38238 | J10: ='Cash Flow'!J32 -> 476.71039 | K10: ='Cash Flow'!K32 -> 719.19446 | L10: ='Cash Flow'!L32 -> 972.17038 | M10: ='Cash Flow'!M32 -> 1240.5068 | O10: Brinker runs very lean on cash — uses $1B revolver for liquidity and deploys excess cash into buybacks. jumps FY26E-FY30E as model doesn't fully recycle excess FCF into buybacks/dividends.
B11: Accounts receivable, net | C11: $M | D11: 65.2 | E11: 66.4 | F11: 60.9 | G11: 60.6 | H11: 73.4 | I11: =H11*'Income Statement'!I13/'Income Statement'!H13 -> 79.129923 | J11: =I11*'Income Statement'!J13/'Income Statement'!I13 -> 82.549307 | K11: =J11*'Income Statement'!K13/'Income Statement'!J13 -> 84.943839 | L11: =K11*'Income Statement'!L13/'Income Statement'!K13 -> 86.694077 | M11: =L11*'Income Statement'!M13/'Income Statement'!L13 -> 88.786164 | O11: Mostly credit card recievables, but also franchise recievables and gift card recievables
B12: Inventories | C12: $M | D12: 28.9 | E12: 35.6 | F12: 34.5 | G12: 34.5 | H12: 35.2 | I12: =H12*'Income Statement'!I11/'Income Statement'!H11 -> 37.863971 | J12: =I12*'Income Statement'!J11/'Income Statement'!I11 -> 39.479937 | K12: =J12*'Income Statement'!K11/'Income Statement'!J11 -> 40.603958 | L12: =K12*'Income Statement'!L11/'Income Statement'!K11 -> 41.424823 | M12: =L12*'Income Statement'!M11/'Income Statement'!L11 -> 42.411474 | O12: Raw food and beverages. Not a whole lot of volume because inventory turns 1-2 weeks.
B13: Restaurant supplies | C13: $M | D13: 52.6 | E13: 55.5 | F13: 55.6 | G13: 53.8 | H13: 54.9 | I13: =H13*'Income Statement'!I11/'Income Statement'!H11 -> 59.054886 | J13: =I13*'Income Statement'!J11/'Income Statement'!I11 -> 61.575243 | K13: =J13*'Income Statement'!K11/'Income Statement'!J11 -> 63.328332 | L13: =K13*'Income Statement'!L11/'Income Statement'!K11 -> 64.608602 | M13: =L13*'Income Statement'!M11/'Income Statement'!L11 -> 66.147442 | O13: Smallwares, packaging, cleaning supps, uniforms, menus. Turnover is months not weeks
B14: Prepaid expenses | C14: $M | D14: 36.6 | E14: 30.2 | F14: 17.2 | G14: 20.6 | H14: 24.6 | I14: =H14*'Income Statement'!I13/'Income Statement'!H13 -> 26.520383 | J14: =I14*'Income Statement'!J13/'Income Statement'!I13 -> 27.666389 | K14: =J14*'Income Statement'!K13/'Income Statement'!J13 -> 28.468916 | L14: =K14*'Income Statement'!L13/'Income Statement'!K13 -> 29.055508 | M14: =L14*'Income Statement'!M13/'Income Statement'!L13 -> 29.756671 | O14: Insurance premiums, rent, enterprise software SaaS, licenses & permits
B15: Current assets | C15: $M | D15: =SUM(D10:D14) -> 207.2 | E15: =SUM(E10:E14) -> 201.2 | F15: =SUM(F10:F14) -> 183.3 | G15: =SUM(G10:G14) -> 234.1 | H15: =SUM(H10:H14) -> 207 | I15: =SUM(I10:I14) -> 445.95155 | J15: =SUM(J10:J14) -> 687.98126 | K15: =SUM(K10:K14) -> 936.53951 | ... M15: =SUM(M10:M14) -> 1467.6085
B17: Non-current assets:
B18: Net property & equipment | C18: $M | D18: 774.8 | E18: 816.7 | F18: 808.3 | G18: 879.7 | H18: 952.7 | I18: =H18+Assumptions!I66-'Income Statement'!I26 -> 987.52708 | J18: =I18+Assumptions!J66-'Income Statement'!J26 -> 1010.2346 | K18: =J18+Assumptions!K66-'Income Statement'!K26 -> 1025.8121 | L18: =K18+Assumptions!L66-'Income Statement'!L26 -> 1027.4019 | M18: =L18+Assumptions!M66-'Income Statement'!M26 -> 1020.8891 | O18: Owned buildings and improvements on leased buildings mostly but also furniture and equipment
B19: Operating lease assets | C19: $M | D19: 1007.4 | E19: 1160.5 | F19: 1134.9 | G19: 1095.2 | H19: 1149.1 | I19: =H19 -> 1149.1 | J19: =I19 -> 1149.1 | K19: =J19 -> 1149.1 | L19: =K19 -> 1149.1 | M19: =L19 -> 1149.1 | O19: Right to operate leased restaurants. Brinker leases most of its 1,113 Chili's + 49 Maggiano's locations.
B20: Goodwill | C20: $M | D20: 188.2 | E20: 195.1 | F20: 195 | G20: 194.8 | H20: 194.7 | I20: =H20 -> 194.7 | J20: =I20 -> 194.7 | K20: =J20 -> 194.7 | L20: =K20 -> 194.7 | M20: =L20 -> 194.7 | O20: FY22 frachise reaquisition + maggiano's acquisition in 1995
B21: Deferred income taxes, net | C21: $M | D21: 50.9 | E21: 62.5 | F21: 93.4 | G21: 113.9 | H21: 101.4 | I21: =H21 -> 101.4 | J21: =I21 -> 101.4 | K21: =J21 -> 101.4 | L21: =K21 -> 101.4 | M21: =L21 -> 101.4 | O21: Future tax savings from timing differences between GAAP book income and IRS taxable income.
B22: Intangibles, net | C22: $M | D22: 21.1 | E22: 27.4 | F22: 23.9 | G22: 19.9 | H22: 17.4 | I22: =H22 -> 17.4 | J22: =I22 -> 17.4 | K22: =J22 -> 17.4 | L22: =K22 -> 17.4 | M22: =L22 -> 17.4 | O22: Identifiable intangible assets from past acquisitions
B23: Other non-current assets | C23: $M | D23: 25.3 | E23: 21 | F23: 48.2 | G23: 55.5 | H23: 56.3 | I23: =H23-'Cash Flow'!I20 -> 54.3 | J23: =I23-'Cash Flow'!J20 -> 52.3 | K23: =J23-'Cash Flow'!K20 -> 50.3 | L23: =K23-'Cash Flow'!L20 -> 48.3 | M23: =L23-'Cash Flow'!M20 -> 46.3 | O23: Long-term marketable securities, long-term renteres deposits, life insurance deposits
B24: Total assets | C24: $M | D24: =D15+SUM(D18:D23) -> 2274.9 | E24: =E15+SUM(E18:E23) -> 2484.4 | F24: =F15+SUM(F18:F23) -> 2487 | G24: =G15+SUM(G18:G23) -> 2593.1 | H24: =H15+SUM(H18:H23) -> 2678.6 | I24: =I15+SUM(I18:I23) -> 2950.3786 | J24: =J15+SUM(J18:J23) -> 3213.1159 | K24: =K15+SUM(K18:K23) -> 3475.2516 | ... M24: =M15+SUM(M18:M23) -> 3997.3976
B26: Liabilities + Equity:
B27: Current liabilities:
B28: Accounts payable | C28: $M | D28: 127.7 | E28: 134.3 | F28: 125.7 | G28: 160.6 | H28: 168.5 | I28: =H28*'Income Statement'!I17/'Income Statement'!H17 -> 182.58104 | J28: =I28*'Income Statement'!J17/'Income Statement'!I17 -> 191.30647 | K28: =J28*'Income Statement'!K17/'Income Statement'!J17 -> 197.71287 | L28: =K28*'Income Statement'!L17/'Income Statement'!K17 -> 202.68908 | M28: =L28*'Income Statement'!M17/'Income Statement'!L17 -> 208.5192 | O28: Mostly food & beverage distributors, smallware suppliers, utilities, maintenance/R&M vendors, marketing agencies, and third-party tech providers
B29: Gift card liability | C29: $M | D29: 106.4 | E29: 83.9 | F29: 73 | G29: 64.8 | H29: 57.2 | I29: =H29 -> 57.2 | J29: =I29 -> 57.2 | K29: =J29 -> 57.2 | L29: =K29 -> 57.2 | M29: =L29 -> 57.2 | O29: Money received from customers (via gift card sales) but for which food/drink hasn't yet been delivered. Deferred revenue.
B30: Accrued payroll | C30: $M | D30: 122.4 | E30: 111 | F30: 106.1 | G30: 130.8 | H30: 156.2 | I30: =H30*'Income Statement'!I19/'Income Statement'!H19 -> 168.08659 | J30: =I30*'Income Statement'!J19/'Income Statement'!I19 -> 175.66844 | K30: =J30*'Income Statement'!K19/'Income Statement'!J19 -> 181.08968 | L30: =K30*'Income Statement'!L19/'Income Statement'!K19 -> 185.17898 | M30: =L30*'Income Statement'!M19/'Income Statement'!L19 -> 190.02808 | O30: Labor-related obligations earned by employees but not yet paid. Big number relative to AP — reflects that labor is Brinker's single largest cost line
B31: Current operating lease liabilities | C31: $M | D31: 97.7 | E31: 112.7 | F31: 112.4 | G31: 114.1 | H31: 114.6 | I31: =H31 -> 114.6 | J31: =I31 -> 114.6 | K31: =J31 -> 114.6 | L31: =K31 -> 114.6 | M31: =L31 -> 114.6 | O31: Next year's rent payments on leased restaurants, reported at the present value of scheduled cash payments.
B32: Other accrued liabilities | C32: $M | D32: 117.4 | E32: 116.1 | F32: 116.3 | G32: 144.7 | H32: 172.6 | I32: =H32*'Income Statement'!I13/'Income Statement'!H13 -> 186.07391 | J32: =I32*'Income Statement'!J13/'Income Statement'!I13 -> 194.11458 | K32: =J32*'Income Statement'!K13/'Income Statement'!J13 -> 199.74532 | L32: =K32*'Income Statement'!L13/'Income Statement'!K13 -> 203.861 | M32: =L32*'Income Statement'!M13/'Income Statement'!L13 -> 208.78054 | O32: Utilities, property taxes, advertising & markteing, professional fees, insurance, sales payable, interest on debt
B33: Income taxes payable, net | C33: $M | D33: 0 | E33: 0 | F33: 2.4 | G33: 7.3 | H33: 6.5 | I33: =H33 -> 6.5 | J33: =I33 -> 6.5 | K33: =J33 -> 6.5 | L33: =K33 -> 6.5 | M33: =L33 -> 6.5 | O33: Taaxes owed to the IRS and state authorities but not yet remitted
B34: Current liabilities | C34: $M | D34: =SUM(D28:D33) -> 571.6 | E34: =SUM(E28:E33) -> 558 | F34: =SUM(F28:F33) -> 535.9 | G34: =SUM(G28:G33) -> 622.3 | H34: =SUM(H28:H33) -> 675.6 | I34: =SUM(I28:I33) -> 715.04154 | J34: =SUM(J28:J33) -> 739.3895 | K34: =SUM(K28:K33) -> 756.84787 | ... M34: =SUM(M28:M33) -> 785.62782
B36: Non-current liabilities:
B37: Long-term debt & finance leases | C37: $M | D37: 917.9 | E37: 989.1 | F37: 912.2 | G37: 786.3 | H37: 426 | I37: =H37 -> 426 | J37: =I37 -> 426 | K37: =J37 -> 426 | L37: =K37 -> 426 | M37: =L37 -> 426 | O37: $350M Senior Notes (8.25% due 2030) + revolver + finance leases; tied to debt schedule on Assumptions.
B38: LT operating lease liabilities | C38: $M | D38: 1006.7 | E38: 1151.1 | F38: 1125.8 | G38: 1084.5 | H38: 1135.3 | I38: =H38 -> 1135.3 | J38: =I38 -> 1135.3 | K38: =J38 -> 1135.3 | L38: =K38 -> 1135.3 | M38: =L38 -> 1135.3 | O38: PV of future rent. Not 'debt' traditionally but rating agencies treat as debt-like.
B39: Other non-current liabilities | C39: $M | D39: 82 | E39: 54.3 | F39: 57.4 | G39: 60.6 | H39: 70.8 | I39: =H39+'Cash Flow'!I27 -> 75.8 | J39: =I39+'Cash Flow'!J27 -> 80.8 | K39: =J39+'Cash Flow'!K27 -> 85.8 | L39: =K39+'Cash Flow'!L27 -> 90.8 | M39: =L39+'Cash Flow'!M27 -> 95.8 | O39: Catch-all for long-term obligations. Uncertain tax positions, deferred comp for execs, asset retirement obligations, long-term workers' comp reserves.
B40: Total liabilities | C40: $M | D40: =D34+SUM(D37:D39) -> 2578.2 | E40: =E34+SUM(E37:E39) -> 2752.5 | F40: =F34+SUM(F37:F39) -> 2631.3 | G40: =G34+SUM(G37:G39) -> 2553.7 | H40: =H34+SUM(H37:H39) -> 2307.7 | I40: =I34+SUM(I37:I39) -> 2352.1415 | J40: =J34+SUM(J37:J39) -> 2381.4895 | K40: =K34+SUM(K37:K39) -> 2403.9479 | ... M40: =M34+SUM(M37:M39) -> 2442.7278
B42: Shareholders' equity:
B43: Common stock ($0.10 par) | C43: $M | D43: 7 | E43: 7 | F43: 6 | G43: 6 | H43: 6 | I43: =H43 -> 6 | J43: =I43 -> 6 | K43: =J43 -> 6 | L43: =K43 -> 6 | M43: =L43 -> 6 | O43: Par value of issued shares ($0.10 par × 60.3M shares issued).
B44: Additional paid-in capital | C44: $M | D44: 685.4 | E44: 690.9 | F44: 690 | G44: 707.8 | H44: 714.5 | I44: =H44+'Income Statement'!I55 -> 749.32708 | J44: =I44+'Income Statement'!J55 -> 785.65913 | K44: =J44+'Income Statement'!K55 -> 823.04506 | L44: =K44+'Income Statement'!L55 -> 861.20132 | M44: =L44+'Income Statement'!M55 -> 900.27836 | O44: Amount paid above par value when shares were originally issued, plus cumulative SBC expense recognized
B45: Accumulated OCI | C45: $M | D45: -4.7 | E45: -5.3 | F45: -6 | G45: -6.3 | H45: -6.4 | I45: =H45 -> -6.4 | J45: =I45 -> -6.4 | K45: =J45 -> -6.4 | L45: =K45 -> -6.4 | M45: =L45 -> -6.4 | O45: non-P&L equity items, mostly FX translation adjustments on foreign subsidiaries
B46: Retained earnings (Accumulated deficit) | C46: $M | D46: -266.1 | E46: -148.4 | F46: -351.9 | G46: -196.6 | H46: 186.5 | I46: =H46+'Income Statement'!I40+'Cash Flow'!I25 -> 652.99296 | J46: =I46+'Income Statement'!J40+'Cash Flow'!J25 -> 1107.1036 | K46: =J46+'Income Statement'!K40+'Cash Flow'!K25 -> 1551.5149 | L46: =K46+'Income Statement'!L40+'Cash Flow'!L25 -> 1981.8766 | M46: =L46+'Income Statement'!M40+'Cash Flow'!M25 -> 2409.6025 | O46: Was negative (Accumulated Deficit) through FY24 due to historical losses + large buybacks — flipped positive in FY25 as recent profitability caught up
B47: Treasury stock | C47: $M | D47: -724.9 | E47: -812.3 | F47: -482.4 | G47: -471.5 | H47: -529.7 | I47: =H47-Assumptions!I71 -> -803.68295 | J47: =I47-Assumptions!J71 -> -1060.7363 | K47: =J47-Assumptions!K71 -> -1302.8563 | L47: =K47-Assumptions!L71 -> -1532.5517 | M47: =L47-Assumptions!M71 -> -1754.811 | O47: Cumulative cost of all shares Brinker has repurchased and retired since inception. Reflects Brinker's aggressive capital return program
B48: Total shareholders' equity | C48: $M | D48: =SUM(D43:D47) -> -303.3 | E48: =SUM(E43:E47) -> -268.1 | F48: =SUM(F43:F47) -> -144.3 | G48: =SUM(G43:G47) -> 39.4 | H48: =SUM(H43:H47) -> 370.9 | I48: =SUM(I43:I47) -> 598.23709 | J48: =SUM(J43:J47) -> 831.62638 | K48: =SUM(K43:K47) -> 1071.3037 | ... M48: =SUM(M43:M47) -> 1554.6698
B50: TOTAL LIABILITIES & EQUITY | C50: $M | D50: =D40+D48 -> 2274.9 | E50: =E40+E48 -> 2484.4 | F50: =F40+F48 -> 2487 | G50: =G40+G48 -> 2593.1 | H50: =H40+H48 -> 2678.6 | I50: =I40+I48 -> 2950.3786 | J50: =J40+J48 -> 3213.1159 | K50: =K40+K48 -> 3475.2516 | ... M50: =M40+M48 -> 3997.3976
B52: BS Check (Assets - L&E) | C52: $M | D52: =D24-D50 -> 0 | E52: =E24-E50 -> 0 | F52: =F24-F50 -> 0 | G52: =G24-G50 -> 0 | H52: =H24-H50 -> 0 | I52: =I24-I50 -> 0 | J52: =J24-J50 -> 0 | K52: =K24-K50 -> 0 | ... M52: =M24-M50 -> 0
B53: Cash Check (historical only) | C53: $M | D53: =IFERROR(D10-'Cash Flow'!D32,0) -> 5.6843419e-14 | E53: =IFERROR(E10-'Cash Flow'!E32,0) -> 8.8817842e-14 | F53: =IFERROR(F10-'Cash Flow'!F32,0) -> 7.9936058e-14 | G53: =G10-'Cash Flow'!G32 -> 1.2789769e-13 | H53: =H10-'Cash Flow'!H32 -> 4.9737992e-14

Sheet Cash Flow
B2: Cash Flow
B3: Brinker International (EAT)
B4: All amounts in $ millions unless noted
C7: Units | D7: =IF('Cover Page'!$C$63+0<'Cover Page'!$C$64,"FY"&TEXT(MOD('Cover Page'!$C$63+0,100),"00")&"A","FY"&TEXT(MOD('Cover Page'!$C$63+0,100),"00")&"E") -> FY21A | E7: =IF('Cover Page'!$C$63+1<'Cover Page'!$C$64,"FY"&TEXT(MOD('Cover Page'!$C$63+1,100),"00")&"A","FY"&TEXT(MOD('Cover Page'!$C$63+1,100),"00")&"E") -> FY22A | F7: =IF('Cover Page'!$C$63+2<'Cover Page'!$C$64,"FY"&TEXT(MOD('Cover Page'!$C$63+2,100),"00")&"A","FY"&TEXT(MOD('Cover Page'!$C$63+2,100),"00")&"E") -> FY23A | G7: =IF('Cover Page'!$C$63+3<'Cover Page'!$C$64,"FY"&TEXT(MOD('Cover Page'!$C$63+3,100),"00")&"A","FY"&TEXT(MOD('Cover Page'!$C$63+3,100),"00")&"E") -> FY24A | H7: =IF('Cover Page'!$C$63+4<'Cover Page'!$C$64,"FY"&TEXT(MOD('Cover Page'!$C$63+4,100),"00")&"A","FY"&TEXT(MOD('Cover Page'!$C$63+4,100),"00")&"E") -> FY25A | I7: =IF('Cover Page'!$C$63+5<'Cover Page'!$C$64,"FY"&TEXT(MOD('Cover Page'!$C$63+5,100),"00")&"A","FY"&TEXT(MOD('Cover Page'!$C$63+5,100),"00")&"E") -> FY26E | J7: =IF('Cover Page'!$C$63+6<'Cover Page'!$C$64,"FY"&TEXT(MOD('Cover Page'!$C$63+6,100),"00")&"A","FY"&TEXT(MOD('Cover Page'!$C$63+6,100),"00")&"E") -> FY27E | K7: =IF('Cover Page'!$C$63+7<'Cover Page'!$C$64,"FY"&TEXT(MOD('Cover Page'!$C$63+7,100),"00")&"A","FY"&TEXT(MOD('Cover Page'!$C$63+7,100),"00")&"E") -> FY28E | L7: =IF('Cover Page'!$C$63+8<'Cover Page'!$C$64,"FY"&TEXT(MOD('Cover Page'!$C$63+8,100),"00")&"A","FY"&TEXT(MOD('Cover Page'!$C$63+8,100),"00")&"E") -> FY29E | M7: =IF('Cover Page'!$C$63+9<'Cover Page'!$C$64,"FY"&TEXT(MOD('Cover Page'!$C$63+9,100),"00")&"A","FY"&TEXT(MOD('Cover Page'!$C$63+9,100),"00")&"E") -> FY30E | O7: Notes
B9: Operating Activities
B10: Net income | C10: $M | D10: ='Income Statement'!D40 -> 131.6 | E10: ='Income Statement'!E40 -> 117.6 | F10: ='Income Statement'!F40 -> 117 | G10: ='Income Statement'!G40 -> 155.3 | H10: ='Income Statement'!H40 -> 383.1 | I10: ='Income Statement'!I40 -> 466.49296 | J10: ='Income Statement'!J40 -> 454.1106 | K10: ='Income Statement'!K40 -> 444.41136 | ... M10: ='Income Statement'!M40 -> 427.72587 | O10: Starting point from IS. Links to Income Statement Net Income line.
B11: (+) Depreciation & amortization | C11: $M | D11: ='Income Statement'!D26 -> 150.2 | E11: ='Income Statement'!E26 -> 164.4 | F11: ='Income Statement'!F26 -> 168.5 | G11: ='Income Statement'!G26 -> 170.8 | H11: ='Income Statement'!H26 -> 206.6 | I11: ='Income Statement'!I26 -> 226.37605 | J11: ='Income Statement'!J26 -> 242.21361 | K11: ='Income Statement'!K26 -> 249.23958 | ... M11: ='Income Statement'!M26 -> 267.02644 | O11: Add back non-cash depreciation from IS. Biggest CFO addback.
B12: (+) Stock-based compensation | C12: $M | D12: ='Income Statement'!D55 -> 11.7 | E12: ='Income Statement'!E55 -> 14.4 | F12: ='Income Statement'!F55 -> 14.4 | G12: ='Income Statement'!G55 -> 25.9 | H12: ='Income Statement'!H55 -> 31.4 | I12: ='Income Statement'!I55 -> 34.827084 | J12: ='Income Statement'!J55 -> 36.332042 | K12: ='Income Statement'!K55 -> 37.385936 | ... M12: ='Income Statement'!M55 -> 39.077041 | O12: Add back non-cash stock comp from IS. Shares issued count against equity but don't use cash.
B13: (+) Non-cash other (gains)/charges | C13: $M | D13: 9.8 | E13: 20.3 | F13: 24 | G13: 28.7 | H13: 25.7 | I13: 0 | J13: 0 | K13: 0 | L13: 0 | M13: 0 | O13: Add back non-cash portion of Other (gains)/charges line on IS — restructuring, impairments, asset disposals.
B14: (+) Deferred income taxes | C14: $M | D14: -12.5 | E14: -11.7 | F14: -30.9 | G14: -20.6 | H14: 12.6 | I14: 0 | J14: 0 | K14: 0 | L14: 0 | M14: 0 | O14: Deferred tax expense — non-cash. Represents timing differences between book and tax income. Can be + or −.
B15: Working capital & other changes | C15: $M | D15: =369.7-SUM(D10:D14) -> 78.9 | E15: =252.2-SUM(E10:E14) -> -52.8 | F15: =256.3-SUM(F10:F14) -> -36.7 | G15: =421.9-SUM(G10:G14) -> 61.8 | H15: =679-SUM(H10:H14) -> 19.6 | I15: =-('Balance Sheet'!I11-'Balance Sheet'!H11)-('Balance Sheet'!I12-'Balance Sheet'!H12)-('Balance Sheet'!I13-'Balance Sheet'!H13)-('Balance Sheet'!I14-'Balance Sheet'!H14)+('Balance Sheet'!I28-'Balance Sheet'!H28)+('Balance Sheet'!I30-'Balance Sheet'!H30)+('Balance Sheet'!I32-'Balance Sheet'!H32)+('Balance Sheet'!I33-'Balance Sheet'!H33) -> 24.972376 | J15: =-('Balance Sheet'!J11-'Balance Sheet'!I11)-('Balance Sheet'!J12-'Balance Sheet'!I12)-('Balance Sheet'!J13-'Balance Sheet'!I13)-('Balance Sheet'!J14-'Balance Sheet'!I14)+('Balance Sheet'!J28-'Balance Sheet'!I28)+('Balance Sheet'!J30-'Balance Sheet'!I30)+('Balance Sheet'!J32-'Balance Sheet'!I32)+('Balance Sheet'!J33-'Balance Sheet'!I33) -> 15.646244 | K15: =-('Balance Sheet'!K11-'Balance Sheet'!J11)-('Balance Sheet'!K12-'Balance Sheet'!J12)-('Balance Sheet'!K13-'Balance Sheet'!J13)-('Balance Sheet'!K14-'Balance Sheet'!J14)+('Balance Sheet'!K28-'Balance Sheet'!J28)+('Balance Sheet'!K30-'Balance Sheet'!J30)+('Balance Sheet'!K32-'Balance Sheet'!J32)+('Balance Sheet'!K33-'Balance Sheet'!J33) -> 11.384203 | L15: =-('Balance Sheet'!L11-'Balance Sheet'!K11)-('Balance Sheet'!L12-'Balance Sheet'!K12)-('Balance Sheet'!L13-'Balance Sheet'!K13)-('Balance Sheet'!L14-'Balance Sheet'!K14)+('Balance Sheet'!L28-'Balance Sheet'!K28)+('Balance Sheet'!L30-'Balance Sheet'!K30)+('Balance Sheet'!L32-'Balance Sheet'!K32)+('Balance Sheet'!L33-'Balance Sheet'!K33) -> 8.743234 | M15: =-('Balance Sheet'!M11-'Balance Sheet'!L11)-('Balance Sheet'!M12-'Balance Sheet'!L12)-('Balance Sheet'!M13-'Balance Sheet'!L13)-('Balance Sheet'!M14-'Balance Sheet'!L14)+('Balance Sheet'!M28-'Balance Sheet'!L28)+('Balance Sheet'!M30-'Balance Sheet'!L30)+('Balance Sheet'!M32-'Balance Sheet'!L32)+('Balance Sheet'!M33-'Balance Sheet'!L33) -> 10.280017 | O15: Historical: plug to reported CFO per 10-K. Forecast: derived from BS working capital deltas (AR, inventory, AP, accrued liabilities, etc.).
B16: Cash from Operations (CFO) | C16: $M | D16: =SUM(D10:D15) -> 369.7 | E16: =SUM(E10:E15) -> 252.2 | F16: =SUM(F10:F15) -> 256.3 | G16: =SUM(G10:G15) -> 421.9 | H16: =SUM(H10:H15) -> 679 | I16: =SUM(I10:I15) -> 752.66846 | J16: =SUM(J10:J15) -> 748.3025 | K16: =SUM(K10:K15) -> 742.42108 | ... M16: =SUM(M10:M15) -> 744.10937
B18: Investing Activities
B19: Capital expenditures | C19: $M | D19: -94 | E19: -150.3 | F19: -184.9 | G19: -198.9 | H19: -265.3 | I19: =-Assumptions!I66 -> -261.20313 | J19: =-Assumptions!J66 -> -264.92114 | K19: =-Assumptions!K66 -> -264.81705 | L19: =-Assumptions!L66 -> -262.32429 | M19: =-Assumptions!M66 -> -260.5136 | O19: Cash spent on restaurant buildouts, equipment, remodels, tech. Links to Assumptions capex row (Capex % × Revenue).
B20: Other investing activities | C20: $M | D20: 3.1 | E20: -83.9 | F20: 10.7 | G20: 6.7 | H20: 1.9 | I20: 2 | J20: 2 | K20: 2 | L20: 2 | M20: 2 | O20: Misc investing — asset sales, insurance recoveries, note receivable collections, and FY22 $106M franchise reacquisition.
B21: Cash from Investing (CFI) | C21: $M | D21: =D19+D20 -> -90.9 | E21: =E19+E20 -> -234.2 | F21: =F19+F20 -> -174.2 | G21: =G19+G20 -> -192.2 | H21: =H19+H20 -> -263.4 | I21: =I19+I20 -> -259.20313 | J21: =J19+J20 -> -262.92114 | K21: =K19+K20 -> -262.81705 | ... M21: =M19+M20 -> -258.5136
B23: Financing Activities
B24: Share repurchases | C24: $M | D24: -4.2 | E24: -100.9 | F24: -5 | G24: -25.8 | H24: -90.2 | I24: =-Assumptions!I71 -> -273.98295 | J24: =-Assumptions!J71 -> -257.05336 | K24: =-Assumptions!K71 -> -242.11995 | L24: =-Assumptions!L71 -> -229.69541 | M24: =-Assumptions!M71 -> -222.25936 | O24: Cash spent buying back EAT shares. Links to Assumptions (Buyback % of FCF × FCF).
B25: Dividends paid | C25: $M | D25: -1.5 | E25: -1.1 | F25: -0.6 | G25: -0.2 | H25: 0 | I25: =-Assumptions!I72 -> 0 | J25: =-Assumptions!J72 -> 0 | K25: =-Assumptions!K72 -> 0 | L25: =-Assumptions!L72 -> 0 | M25: =-Assumptions!M72 -> 0 | O25: Dividend payments to shareholders. Brinker suspended dividend during COVID; model assumes $0 going forward.
B26: Debt issuance / (repayment), net | C26: $M | D26: -321.6 | E26: 76.3 | F26: -82.1 | G26: -181.4 | H26: -375.8 | I26: 0 | J26: 0 | K26: 0 | L26: 0 | M26: 0 | O26: Net of new borrowings and repayments. Revolver draws/paydowns + Senior Notes issuance/repayment. Tied to debt schedule.
B27: Other financing activities | C27: $M | D27: 28.5 | E27: -2.7 | F27: 7.2 | G27: 27.2 | H27: 4.7 | I27: 5 | J27: 5 | K27: 5 | L27: 5 | M27: 5 | O27: Misc financing — treasury stock issuance for RSU vesting, debt issuance costs, other.
B28: Cash from Financing (CFF) | C28: $M | D28: =SUM(D24:D27) -> -298.8 | E28: =SUM(E24:E27) -> -28.4 | F28: =SUM(F24:F27) -> -80.5 | G28: =SUM(G24:G27) -> -180.2 | H28: =SUM(H24:H27) -> -461.3 | I28: =SUM(I24:I27) -> -268.98295 | J28: =SUM(J24:J27) -> -252.05336 | K28: =SUM(K24:K27) -> -237.11995 | ... M28: =SUM(M24:M27) -> -217.25936
B30: Net change in cash | C30: $M | D30: =D16+D21+D28 -> -20 | E30: =E16+E21+E28 -> -10.4 | F30: =F16+F21+F28 -> 1.6 | G30: =G16+G21+G28 -> 49.5 | H30: =H16+H21+H28 -> -45.7 | I30: =I16+I21+I28 -> 224.48238 | J30: =J16+J21+J28 -> 233.328 | K30: =K16+K21+K28 -> 242.48408 | ... M30: =M16+M21+M28 -> 268.3364 | O30: CFO + CFI + CFF. Increase/decrease in cash for the period.
B31: Beginning cash | C31: $M | D31: 43.9 | E31: =D32 -> 23.9 | F31: =E32 -> 13.5 | G31: =F32 -> 15.1 | H31: 64.6 | I31: ='Balance Sheet'!H10 -> 18.9 | J31: =I32 -> 243.38238 | K31: =J32 -> 476.71039 | L31: =K32 -> 719.19446 | M31: =L32 -> 972.17038 | O31: Prior period's ending cash. Historical FY21 = FY20 ending per 10-K ($43.9M).
B32: Ending cash | C32: $M | D32: =D30+D31 -> 23.9 | E32: =E30+E31 -> 13.5 | F32: =F30+F31 -> 15.1 | G32: =G30+G31 -> 64.6 | H32: =H30+H31 -> 18.9 | I32: =I30+I31 -> 243.38238 | J32: =J30+J31 -> 476.71039 | K32: =K30+K31 -> 719.19446 | ... M32: =M30+M31 -> 1240.5068
B34: Free Cash Flow
B35: Cash from Operations | C35: $M | D35: =D16 -> 369.7 | E35: =E16 -> 252.2 | F35: =F16 -> 256.3 | G35: =G16 -> 421.9 | H35: =H16 -> 679 | I35: =I16 -> 752.66846 | J35: =J16 -> 748.3025 | K35: =K16 -> 742.42108 | ... M35: =M16 -> 744.10937 | O35: Pulls CFO from above.
B36: (-) Capital expenditures | C36: $M | D36: =D19 -> -94 | E36: =E19 -> -150.3 | F36: =F19 -> -184.9 | G36: =G19 -> -198.9 | H36: =H19 -> -265.3 | I36: =I19 -> -261.20313 | J36: =J19 -> -264.92114 | K36: =K19 -> -264.81705 | ... M36: =M19 -> -260.5136 | O36: Capital expenditures (negative here since it's a subtraction from CFO).
B37: (-) Stock-based comp | C37: $M | D37: =-'Income Statement'!D55 -> -11.7 | E37: =-'Income Statement'!E55 -> -14.4 | F37: =-'Income Statement'!F55 -> -14.4 | G37: =-'Income Statement'!G55 -> -25.9 | H37: =-'Income Statement'!H55 -> -31.4 | I37: =-'Income Statement'!I55 -> -34.827084 | J37: =-'Income Statement'!J55 -> -36.332042 | K37: =-'Income Statement'!K55 -> -37.385936 | ... M37: =-'Income Statement'!M55 -> -39.077041
B38: Free Cash Flow | C38: $M | D38: =D35+D36+D37 -> 264 | E38: =E35+E36+E37 -> 87.5 | F38: =F35+F36+F37 -> 57 | G38: =G35+G36+G37 -> 197.1 | H38: =H35+H36+H37 -> 382.3 | I38: =I35+I36+I37 -> 456.63825 | J38: =J35+J36+J37 -> 447.04932 | K38: =K35+K36+K37 -> 440.21809 | ... M38: =M35+M36+M37 -> 444.51872 | O38: FCF = CFO − Capex. The cash available to return to shareholders or reinvest. Drives DCF valuation.
B39: FCF margin | C39: % | D39: =D38/'Income Statement'!D13 -> 0.079094014 | E39: =E38/'Income Statement'!E13 -> 0.023001498 | F39: =F38/'Income Statement'!F13 -> 0.014059841 | G39: =G38/'Income Statement'!G13 -> 0.04464225 | H39: =H38/'Income Statement'!H13 -> 0.071004049 | I39: =I38/'Income Statement'!I13 -> 0.078669505 | J39: =J38/'Income Statement'!J13 -> 0.073827282 | K39: =K38/'Income Statement'!K13 -> 0.07064979 | ... M39: =M38/'Income Statement'!M13 -> 0.06825267 | O39: FCF as % of total revenue. Brinker delivers ~8-10% FCF margin — strong for casual dining.
B40: FCF per diluted share | C40: $/sh | D40: =D38/'Income Statement'!D44 -> 5.6531049 | E40: =E38/'Income Statement'!E44 -> 1.9273128 | F40: =F38/'Income Statement'!F44 -> 1.2582781 | G40: =G38/'Income Statement'!G44 -> 4.38 | H40: =H38/'Income Statement'!H44 -> 8.4021978 | I40: =I38/'Income Statement'!I44 -> 10.36014 | J40: =J38/'Income Statement'!J44 -> 10.454204 | K40: =K38/'Income Statement'!K44 -> 10.596435 | ... M40: =M38/'Income Statement'!M44 -> 11.307026 | O40: FCF divided by diluted shares. Proxy for intrinsic value creation per share.

Sheet DCF & Sensitivity
B2: DCF & Sensitivity Analysis
B3: Brinker International (EAT)
B4: All amounts in $ millions unless noted
B6: Takeaway
B7: At the current share price (~$168), EAT trades at ~11x LTM EV/EBITDA and ~9x forward FCF.
B8: Chili's sustained double-digit same-store sales growth (6 consecutive quarters) and FY26 guidance raised to $5.76-5.83B revenue and $10.45-10.85 adj. EPS. Key risk is Chili's SSS growth and to a much lesser extent Maggiano's (~9% of co sales) underperformance.
B10: WACC Calculation | C10: Units | O10: Notes
B11: Risk-Free Rate | C11: % | D11: =Assumptions!D78 -> 0.0431 | O11: WACC is driven almost entirely by cost of equity. EAT is lightly levered, so the tax shield contributes minimally and moves in beta or ERP flow directly into WACC. Excludes operating leases; capitalizing them would raise D/V (Debt/Total Capital) and lower WACC.
B12: Equity Risk Premium | C12: % | D12: =Assumptions!D79 -> 0.055
B13: Beta (Adjusted, peer-median) | C13: x | D13: =Assumptions!D81 -> 1.1675
B14: Cost of Equity | C14: % | D14: =Assumptions!D82 -> 0.1073125
B15: Cost of Debt (pre-tax) | C15: % | D15: =Assumptions!D83 -> 0.078757557
B16: Tax Rate | C16: % | D16: =Assumptions!M59 -> 0.23
B17: Cost of Debt (after-tax) | C17: % | D17: =D15*(1-D16) -> 0.060643319
B18: Debt / Total Capital | C18: % | D18: =Assumptions!D86 -> 0.052788104
B19: Equity / Total Capital | C19: % | D19: =1-D18 -> 0.9472119
B20: WACC | C20: % | D20: =Assumptions!D87 -> 0.10509837
B22: FCF Projection | C22: Units | D22: =IF('Cover Page'!$C$63+0<'Cover Page'!$C$64,"FY"&TEXT(MOD('Cover Page'!$C$63+0,100),"00")&"A","FY"&TEXT(MOD('Cover Page'!$C$63+0,100),"00")&"E") -> FY21A | E22: =IF('Cover Page'!$C$63+1<'Cover Page'!$C$64,"FY"&TEXT(MOD('Cover Page'!$C$63+1,100),"00")&"A","FY"&TEXT(MOD('Cover Page'!$C$63+1,100),"00")&"E") -> FY22A | F22: =IF('Cover Page'!$C$63+2<'Cover Page'!$C$64,"FY"&TEXT(MOD('Cover Page'!$C$63+2,100),"00")&"A","FY"&TEXT(MOD('Cover Page'!$C$63+2,100),"00")&"E") -> FY23A | G22: =IF('Cover Page'!$C$63+3<'Cover Page'!$C$64,"FY"&TEXT(MOD('Cover Page'!$C$63+3,100),"00")&"A","FY"&TEXT(MOD('Cover Page'!$C$63+3,100),"00")&"E") -> FY24A | H22: =IF('Cover Page'!$C$63+4<'Cover Page'!$C$64,"FY"&TEXT(MOD('Cover Page'!$C$63+4,100),"00")&"A","FY"&TEXT(MOD('Cover Page'!$C$63+4,100),"00")&"E") -> FY25A | I22: =IF('Cover Page'!$C$63+5<'Cover Page'!$C$64,"FY"&TEXT(MOD('Cover Page'!$C$63+5,100),"00")&"A","FY"&TEXT(MOD('Cover Page'!$C$63+5,100),"00")&"E") -> FY26E | J22: =IF('Cover Page'!$C$63+6<'Cover Page'!$C$64,"FY"&TEXT(MOD('Cover Page'!$C$63+6,100),"00")&"A","FY"&TEXT(MOD('Cover Page'!$C$63+6,100),"00")&"E") -> FY27E | K22: =IF('Cover Page'!$C$63+7<'Cover Page'!$C$64,"FY"&TEXT(MOD('Cover Page'!$C$63+7,100),"00")&"A","FY"&TEXT(MOD('Cover Page'!$C$63+7,100),"00")&"E") -> FY28E | L22: =IF('Cover Page'!$C$63+8<'Cover Page'!$C$64,"FY"&TEXT(MOD('Cover Page'!$C$63+8,100),"00")&"A","FY"&TEXT(MOD('Cover Page'!$C$63+8,100),"00")&"E") -> FY29E | M22: =IF('Cover Page'!$C$63+9<'Cover Page'!$C$64,"FY"&TEXT(MOD('Cover Page'!$C$63+9,100),"00")&"A","FY"&TEXT(MOD('Cover Page'!$C$63+9,100),"00")&"E") -> FY30E
B23: Free Cash Flow (ex-SBC) | C23: $M | I23: ='Cash Flow'!I38 -> 456.63825 | J23: ='Cash Flow'!J38 -> 447.04932 | K23: ='Cash Flow'!K38 -> 440.21809 | L23: ='Cash Flow'!L38 -> 437.51507 | M23: ='Cash Flow'!M38 -> 444.51872 | O23: FCF = CFO − Capex − SBC. SBC is deducted as a true economic cost to avoid masking dilution. Capex runs at a maintenance-level plateau while revenue growth decelerates across the projection, so FCF margin compresses modestly year-over-year.
B24: Discount Period | C24: # | I24: 1 | J24: 2 | K24: 3 | L24: 4 | M24: 5
B25: Discount Factor | C25: x | I25: =1/(1+$D$20)^I24 -> 0.90489682 | J25: =1/(1+$D$20)^J24 -> 0.81883825 | K25: =1/(1+$D$20)^K24 -> 0.74096413 | L25: =1/(1+$D$20)^L24 -> 0.67049609 | M25: =1/(1+$D$20)^M24 -> 0.60672977
B26: Present Value of FCF | C26: $M | I26: =I23*I25 -> 413.2105 | J26: =J23*J25 -> 366.06109 | K26: =K23*K25 -> 326.18582 | L26: =L23*L25 -> 293.35214 | M26: =M23*M25 -> 269.70275
B28: Terminal Value | C28: Units | D28: Value | O28: Perpetuity TV is structurally fragile because the (WACC − g) denominator is small. A 100bps move in either input swings TV by double-digit percentages. The method is most defensible when g is anchored to long-run nominal GDP and well below WACC. Sanity check: TV should not exceed ~75% of EV.
B29: Method 1: Perpetuity Growth
B30: Terminal Growth Rate | C30: % | D30: =Assumptions!D88 -> 0.025
B31: Terminal FCF (ex-SBC) | C31: $M | D31: =M23 -> 444.51872
B32: Terminal Value | C32: $M | D32: =D31*(1+D30)/(D20-D30) -> 5688.4015
B33: PV of Terminal Value | C33: $M | D33: =D32*M25 -> 3451.3226
B35: Method 2: Exit Multiple | O35: Exit multiple TV anchors on FY30E EBITDA, so it's more stable than perpetuity but depends on the credibility of the chosen multiple. Triangulate against (1) current EAT LTM multiple, (2) peer median in Comps tab, and (3) historical casual-dining M&A multiples. A defensible exit sits within that range, not above it.
B36: Terminal EBITDA | C36: $M | D36: ='Income Statement'!M52 -> 884.65378
B37: Exit EV/EBITDA Multiple | C37: x | D37: =Assumptions!D89 -> 11
B38: Terminal Value | C38: $M | D38: =D36*D37 -> 9731.1916
B39: PV of Terminal Value | C39: $M | D39: =D38*M25 -> 5904.2037
B41: Valuation Summary | C41: Units | D41: Value
B42: Sum of PV of FCFs | C42: $M | D42: =SUM(I26:M26) -> 1668.5123 | O42: Both methods put ~70-80% of EV in the terminal value, so either way this is a bet on terminal-period economics. The methods differ in WHAT assumption the TV rests on: perpetuity is fragile to the terminal growth rate (g) and WACC spread; exit-multiple is only as good as the chosen EV/EBITDA multiple. The gap between the two methods is the real information — it quantifies how much your answer depends on which terminal assumption you trust more. Cross-check both against P/E and EV/EBITDA comps in the Comps tab.
B43: PV of Terminal Value (Perpetuity) | C43: $M | D43: =D33 -> 3451.3226
B44: Enterprise Value (Perpetuity) | C44: $M | D44: =D42+D43 -> 5119.8349
B45: PV of Terminal Value (Multiple) | C45: $M | D45: =D39 -> 5904.2037
B46: Enterprise Value (Multiple) | C46: $M | D46: =D42+D45 -> 7572.716
B48: Less: Net Debt (neg = net cash) | C48: $M | D48: ='Balance Sheet'!H37-'Balance Sheet'!H10 -> 407.1
B49: Equity Value (Perpetuity) | C49: $M | D49: =D44-D48 -> 4712.7349
B50: Equity Value (Multiple) | C50: $M | D50: =D46-D48 -> 7165.616
B51: Shares Outstanding | C51: M | D51: =Assumptions!H73 -> 45.5
B53: Implied Share Price (Perpetuity) | C53: $/sh | D53: =D49/D51 -> 103.57659
B54: Implied Share Price (Multiple) | C54: $/sh | D54: =D50/D51 -> 157.48607
B55: Current Share Price | C55: $/sh | D55: 168
B56: Upside / (Downside) — Perpetuity | C56: % | D56: =D53/D55-1 -> -0.38347268
B57: Upside / (Downside) — Multiple | C57: % | D57: =D54/D55-1 -> -0.062582943
B59: TV as % of EV (Perpetuity) | C59: % | D59: =D43/D44 -> 0.67410818
B60: TV as % of EV (Multiple) | C60: % | D60: =D45/D46 -> 0.77966792
B64: Sensitivity: WACC vs. Terminal Growth Rate (Perpetuity Method) | O64: Perpetuity sensitivity shows a wide output range across WACC × g combinations which quantifies the method's fragility. Use the grid to reverse-engineer which WACC/g combination matches the current market price; if that combination looks unreasonable, the stock is mispriced.
B65: Implied Share Price ($/share)
B66: WACC \ g | C66: 0.015 | D66: 0.02 | E66: 0.025 | F66: 0.03 | G66: 0.035 | H66: 0.04 | I66: 0.045
B67: 0.09 | C67: =($I$23/(1+$B67)^1+$J$23/(1+$B67)^2+$K$23/(1+$B67)^3+$L$23/(1+$B67)^4+$M$23/(1+$B67)^5+$M$23*(1+C$66)/($B67-C$66)/(1+$B67)^5-$D$48)/$D$51 -> 115.09361 | D67: =($I$23/(1+$B67)^1+$J$23/(1+$B67)^2+$K$23/(1+$B67)^3+$L$23/(1+$B67)^4+$M$23/(1+$B67)^5+$M$23*(1+D$66)/($B67-D$66)/(1+$B67)^5-$D$48)/$D$51 -> 121.6851 | E67: =($I$23/(1+$B67)^1+$J$23/(1+$B67)^2+$K$23/(1+$B67)^3+$L$23/(1+$B67)^4+$M$23/(1+$B67)^5+$M$23*(1+E$66)/($B67-E$66)/(1+$B67)^5-$D$48)/$D$51 -> 129.29066 | F67: =($I$23/(1+$B67)^1+$J$23/(1+$B67)^2+$K$23/(1+$B67)^3+$L$23/(1+$B67)^4+$M$23/(1+$B67)^5+$M$23*(1+F$66)/($B67-F$66)/(1+$B67)^5-$D$48)/$D$51 -> 138.16382 | G67: =($I$23/(1+$B67)^1+$J$23/(1+$B67)^2+$K$23/(1+$B67)^3+$L$23/(1+$B67)^4+$M$23/(1+$B67)^5+$M$23*(1+G$66)/($B67-G$66)/(1+$B67)^5-$D$48)/$D$51 -> 148.65027 | H67: =($I$23/(1+$B67)^1+$J$23/(1+$B67)^2+$K$23/(1+$B67)^3+$L$23/(1+$B67)^4+$M$23/(1+$B67)^5+$M$23*(1+H$66)/($B67-H$66)/(1+$B67)^5-$D$48)/$D$51 -> 161.23402 | I67: =($I$23/(1+$B67)^1+$J$23/(1+$B67)^2+$K$23/(1+$B67)^3+$L$23/(1+$B67)^4+$M$23/(1+$B67)^5+$M$23*(1+I$66)/($B67-I$66)/(1+$B67)^5-$D$48)/$D$51 -> 176.61416
B68: 0.095 | C68: =($I$23/(1+$B68)^1+$J$23/(1+$B68)^2+$K$23/(1+$B68)^3+$L$23/(1+$B68)^4+$M$23/(1+$B68)^5+$M$23*(1+C$66)/($B68-C$66)/(1+$B68)^5-$D$48)/$D$51 -> 107.41386 | D68: =($I$23/(1+$B68)^1+$J$23/(1+$B68)^2+$K$23/(1+$B68)^3+$L$23/(1+$B68)^4+$M$23/(1+$B68)^5+$M$23*(1+D$66)/($B68-D$66)/(1+$B68)^5-$D$48)/$D$51 -> 113.07679 | E68: =($I$23/(1+$B68)^1+$J$23/(1+$B68)^2+$K$23/(1+$B68)^3+$L$23/(1+$B68)^4+$M$23/(1+$B68)^5+$M$23*(1+E$66)/($B68-E$66)/(1+$B68)^5-$D$48)/$D$51 -> 119.54871 | F68: =($I$23/(1+$B68)^1+$J$23/(1+$B68)^2+$K$23/(1+$B68)^3+$L$23/(1+$B68)^4+$M$23/(1+$B68)^5+$M$23*(1+F$66)/($B68-F$66)/(1+$B68)^5-$D$48)/$D$51 -> 127.0163 | G68: =($I$23/(1+$B68)^1+$J$23/(1+$B68)^2+$K$23/(1+$B68)^3+$L$23/(1+$B68)^4+$M$23/(1+$B68)^5+$M$23*(1+G$66)/($B68-G$66)/(1+$B68)^5-$D$48)/$D$51 -> 135.7285 | H68: =($I$23/(1+$B68)^1+$J$23/(1+$B68)^2+$K$23/(1+$B68)^3+$L$23/(1+$B68)^4+$M$23/(1+$B68)^5+$M$23*(1+H$66)/($B68-H$66)/(1+$B68)^5-$D$48)/$D$51 -> 146.02473 | I68: =($I$23/(1+$B68)^1+$J$23/(1+$B68)^2+$K$23/(1+$B68)^3+$L$23/(1+$B68)^4+$M$23/(1+$B68)^5+$M$23*(1+I$66)/($B68-I$66)/(1+$B68)^5-$D$48)/$D$51 -> 158.3802
B69: 0.1 | C69: =($I$23/(1+$B69)^1+$J$23/(1+$B69)^2+$K$23/(1+$B69)^3+$L$23/(1+$B69)^4+$M$23/(1+$B69)^5+$M$23*(1+C$66)/($B69-C$66)/(1+$B69)^5-$D$48)/$D$51 -> 100.63666 | D69: =($I$23/(1+$B69)^1+$J$23/(1+$B69)^2+$K$23/(1+$B69)^3+$L$23/(1+$B69)^4+$M$23/(1+$B69)^5+$M$23*(1+D$66)/($B69-D$66)/(1+$B69)^5-$D$48)/$D$51 -> 105.54313 | E69: =($I$23/(1+$B69)^1+$J$23/(1+$B69)^2+$K$23/(1+$B69)^3+$L$23/(1+$B69)^4+$M$23/(1+$B69)^5+$M$23*(1+E$66)/($B69-E$66)/(1+$B69)^5-$D$48)/$D$51 -> 111.10379 | F69: =($I$23/(1+$B69)^1+$J$23/(1+$B69)^2+$K$23/(1+$B69)^3+$L$23/(1+$B69)^4+$M$23/(1+$B69)^5+$M$23*(1+F$66)/($B69-F$66)/(1+$B69)^5-$D$48)/$D$51 -> 117.45884 | G69: =($I$23/(1+$B69)^1+$J$23/(1+$B69)^2+$K$23/(1+$B69)^3+$L$23/(1+$B69)^4+$M$23/(1+$B69)^5+$M$23*(1+G$66)/($B69-G$66)/(1+$B69)^5-$D$48)/$D$51 -> 124.79158 | H69: =($I$23/(1+$B69)^1+$J$23/(1+$B69)^2+$K$23/(1+$B69)^3+$L$23/(1+$B69)^4+$M$23/(1+$B69)^5+$M$23*(1+H$66)/($B69-H$66)/(1+$B69)^5-$D$48)/$D$51 -> 133.34645 | I69: =($I$23/(1+$B69)^1+$J$23/(1+$B69)^2+$K$23/(1+$B69)^3+$L$23/(1+$B69)^4+$M$23/(1+$B69)^5+$M$23*(1+I$66)/($B69-I$66)/(1+$B69)^5-$D$48)/$D$51 -> 143.45675
B70: 0.105 | C70: =($I$23/(1+$B70)^1+$J$23/(1+$B70)^2+$K$23/(1+$B70)^3+$L$23/(1+$B70)^4+$M$23/(1+$B70)^5+$M$23*(1+C$66)/($B70-C$66)/(1+$B70)^5-$D$48)/$D$51 -> 94.611597 | D70: =($I$23/(1+$B70)^1+$J$23/(1+$B70)^2+$K$23/(1+$B70)^3+$L$23/(1+$B70)^4+$M$23/(1+$B70)^5+$M$23*(1+D$66)/($B70-D$66)/(1+$B70)^5-$D$48)/$D$51 -> 98.894499 | E70: =($I$23/(1+$B70)^1+$J$23/(1+$B70)^2+$K$23/(1+$B70)^3+$L$23/(1+$B70)^4+$M$23/(1+$B70)^5+$M$23*(1+E$66)/($B70-E$66)/(1+$B70)^5-$D$48)/$D$51 -> 103.71276 | F70: =($I$23/(1+$B70)^1+$J$23/(1+$B70)^2+$K$23/(1+$B70)^3+$L$23/(1+$B70)^4+$M$23/(1+$B70)^5+$M$23*(1+F$66)/($B70-F$66)/(1+$B70)^5-$D$48)/$D$51 -> 109.17346 | G70: =($I$23/(1+$B70)^1+$J$23/(1+$B70)^2+$K$23/(1+$B70)^3+$L$23/(1+$B70)^4+$M$23/(1+$B70)^5+$M$23*(1+G$66)/($B70-G$66)/(1+$B70)^5-$D$48)/$D$51 -> 115.41426 | H70: =($I$23/(1+$B70)^1+$J$23/(1+$B70)^2+$K$23/(1+$B70)^3+$L$23/(1+$B70)^4+$M$23/(1+$B70)^5+$M$23*(1+H$66)/($B70-H$66)/(1+$B70)^5-$D$48)/$D$51 -> 122.61519 | I70: =($I$23/(1+$B70)^1+$J$23/(1+$B70)^2+$K$23/(1+$B70)^3+$L$23/(1+$B70)^4+$M$23/(1+$B70)^5+$M$23*(1+I$66)/($B70-I$66)/(1+$B70)^5-$D$48)/$D$51 -> 131.01626
B71: 0.11 | C71: =($I$23/(1+$B71)^1+$J$23/(1+$B71)^2+$K$23/(1+$B71)^3+$L$23/(1+$B71)^4+$M$23/(1+$B71)^5+$M$23*(1+C$66)/($B71-C$66)/(1+$B71)^5-$D$48)/$D$51 -> 89.219931 | D71: =($I$23/(1+$B71)^1+$J$23/(1+$B71)^2+$K$23/(1+$B71)^3+$L$23/(1+$B71)^4+$M$23/(1+$B71)^5+$M$23*(1+D$66)/($B71-D$66)/(1+$B71)^5-$D$48)/$D$51 -> 92.98342 | E71: =($I$23/(1+$B71)^1+$J$23/(1+$B71)^2+$K$23/(1+$B71)^3+$L$23/(1+$B71)^4+$M$23/(1+$B71)^5+$M$23*(1+E$66)/($B71-E$66)/(1+$B71)^5-$D$48)/$D$51 -> 97.189672 | F71: =($I$23/(1+$B71)^1+$J$23/(1+$B71)^2+$K$23/(1+$B71)^3+$L$23/(1+$B71)^4+$M$23/(1+$B71)^5+$M$23*(1+F$66)/($B71-F$66)/(1+$B71)^5-$D$48)/$D$51 -> 101.92171 | G71: =($I$23/(1+$B71)^1+$J$23/(1+$B71)^2+$K$23/(1+$B71)^3+$L$23/(1+$B71)^4+$M$23/(1+$B71)^5+$M$23*(1+G$66)/($B71-G$66)/(1+$B71)^5-$D$48)/$D$51 -> 107.28468 | H71: =($I$23/(1+$B71)^1+$J$23/(1+$B71)^2+$K$23/(1+$B71)^3+$L$23/(1+$B71)^4+$M$23/(1+$B71)^5+$M$23*(1+H$66)/($B71-H$66)/(1+$B71)^5-$D$48)/$D$51 -> 113.41379 | I71: =($I$23/(1+$B71)^1+$J$23/(1+$B71)^2+$K$23/(1+$B71)^3+$L$23/(1+$B71)^4+$M$23/(1+$B71)^5+$M$23*(1+I$66)/($B71-I$66)/(1+$B71)^5-$D$48)/$D$51 -> 120.48584
B72: 0.115 | C72: =($I$23/(1+$B72)^1+$J$23/(1+$B72)^2+$K$23/(1+$B72)^3+$L$23/(1+$B72)^4+$M$23/(1+$B72)^5+$M$23*(1+C$66)/($B72-C$66)/(1+$B72)^5-$D$48)/$D$51 -> 84.366667 | D72: =($I$23/(1+$B72)^1+$J$23/(1+$B72)^2+$K$23/(1+$B72)^3+$L$23/(1+$B72)^4+$M$23/(1+$B72)^5+$M$23*(1+D$66)/($B72-D$66)/(1+$B72)^5-$D$48)/$D$51 -> 87.693459 | E72: =($I$23/(1+$B72)^1+$J$23/(1+$B72)^2+$K$23/(1+$B72)^3+$L$23/(1+$B72)^4+$M$23/(1+$B72)^5+$M$23*(1+E$66)/($B72-E$66)/(1+$B72)^5-$D$48)/$D$51 -> 91.389894 | F72: =($I$23/(1+$B72)^1+$J$23/(1+$B72)^2+$K$23/(1+$B72)^3+$L$23/(1+$B72)^4+$M$23/(1+$B72)^5+$M$23*(1+F$66)/($B72-F$66)/(1+$B72)^5-$D$48)/$D$51 -> 95.521204 | G72: =($I$23/(1+$B72)^1+$J$23/(1+$B72)^2+$K$23/(1+$B72)^3+$L$23/(1+$B72)^4+$M$23/(1+$B72)^5+$M$23*(1+G$66)/($B72-G$66)/(1+$B72)^5-$D$48)/$D$51 -> 100.16893 | H72: =($I$23/(1+$B72)^1+$J$23/(1+$B72)^2+$K$23/(1+$B72)^3+$L$23/(1+$B72)^4+$M$23/(1+$B72)^5+$M$23*(1+H$66)/($B72-H$66)/(1+$B72)^5-$D$48)/$D$51 -> 105.43635 | I72: =($I$23/(1+$B72)^1+$J$23/(1+$B72)^2+$K$23/(1+$B72)^3+$L$23/(1+$B72)^4+$M$23/(1+$B72)^5+$M$23*(1+I$66)/($B72-I$66)/(1+$B72)^5-$D$48)/$D$51 -> 111.45626
B73: 0.12 | C73: =($I$23/(1+$B73)^1+$J$23/(1+$B73)^2+$K$23/(1+$B73)^3+$L$23/(1+$B73)^4+$M$23/(1+$B73)^5+$M$23*(1+C$66)/($B73-C$66)/(1+$B73)^5-$D$48)/$D$51 -> 79.974905 | D73: =($I$23/(1+$B73)^1+$J$23/(1+$B73)^2+$K$23/(1+$B73)^3+$L$23/(1+$B73)^4+$M$23/(1+$B73)^5+$M$23*(1+D$66)/($B73-D$66)/(1+$B73)^5-$D$48)/$D$51 -> 82.931469 | E73: =($I$23/(1+$B73)^1+$J$23/(1+$B73)^2+$K$23/(1+$B73)^3+$L$23/(1+$B73)^4+$M$23/(1+$B73)^5+$M$23*(1+E$66)/($B73-E$66)/(1+$B73)^5-$D$48)/$D$51 -> 86.19925 | F73: =($I$23/(1+$B73)^1+$J$23/(1+$B73)^2+$K$23/(1+$B73)^3+$L$23/(1+$B73)^4+$M$23/(1+$B73)^5+$M$23*(1+F$66)/($B73-F$66)/(1+$B73)^5-$D$48)/$D$51 -> 89.830118 | G73: =($I$23/(1+$B73)^1+$J$23/(1+$B73)^2+$K$23/(1+$B73)^3+$L$23/(1+$B73)^4+$M$23/(1+$B73)^5+$M$23*(1+G$66)/($B73-G$66)/(1+$B73)^5-$D$48)/$D$51 -> 93.888147 | H73: =($I$23/(1+$B73)^1+$J$23/(1+$B73)^2+$K$23/(1+$B73)^3+$L$23/(1+$B73)^4+$M$23/(1+$B73)^5+$M$23*(1+H$66)/($B73-H$66)/(1+$B73)^5-$D$48)/$D$51 -> 98.45343 | I73: =($I$23/(1+$B73)^1+$J$23/(1+$B73)^2+$K$23/(1+$B73)^3+$L$23/(1+$B73)^4+$M$23/(1+$B73)^5+$M$23*(1+I$66)/($B73-I$66)/(1+$B73)^5-$D$48)/$D$51 -> 103.62742
B75: Sensitivity: WACC vs. Exit EV/EBITDA Multiple | O75: Exit-multiple sensitivity has a tighter output range than perpetuity because TV is anchored to EBITDA. The method is most useful for stress-testing which exit multiple the market is implicitly paying today — compare that implied multiple against peer and historical ranges.
B76: Implied Share Price ($/share)
B77: WACC \ Mult | C77: 8 | D77: 9 | E77: 10 | F77: 11 | G77: 12 | H77: 13 | I77: 14
B78: 0.09 | C78: =($I$23/(1+$B78)^1+$J$23/(1+$B78)^2+$K$23/(1+$B78)^3+$L$23/(1+$B78)^4+$M$23/(1+$B78)^5+$D$36*C$77/(1+$B78)^5-$D$48)/$D$51 -> 130.25502 | D78: =($I$23/(1+$B78)^1+$J$23/(1+$B78)^2+$K$23/(1+$B78)^3+$L$23/(1+$B78)^4+$M$23/(1+$B78)^5+$D$36*D$77/(1+$B78)^5-$D$48)/$D$51 -> 142.89159 | E78: =($I$23/(1+$B78)^1+$J$23/(1+$B78)^2+$K$23/(1+$B78)^3+$L$23/(1+$B78)^4+$M$23/(1+$B78)^5+$D$36*E$77/(1+$B78)^5-$D$48)/$D$51 -> 155.52817 | F78: =($I$23/(1+$B78)^1+$J$23/(1+$B78)^2+$K$23/(1+$B78)^3+$L$23/(1+$B78)^4+$M$23/(1+$B78)^5+$D$36*F$77/(1+$B78)^5-$D$48)/$D$51 -> 168.16475 | G78: =($I$23/(1+$B78)^1+$J$23/(1+$B78)^2+$K$23/(1+$B78)^3+$L$23/(1+$B78)^4+$M$23/(1+$B78)^5+$D$36*G$77/(1+$B78)^5-$D$48)/$D$51 -> 180.80132 | H78: =($I$23/(1+$B78)^1+$J$23/(1+$B78)^2+$K$23/(1+$B78)^3+$L$23/(1+$B78)^4+$M$23/(1+$B78)^5+$D$36*H$77/(1+$B78)^5-$D$48)/$D$51 -> 193.4379 | I78: =($I$23/(1+$B78)^1+$J$23/(1+$B78)^2+$K$23/(1+$B78)^3+$L$23/(1+$B78)^4+$M$23/(1+$B78)^5+$D$36*I$77/(1+$B78)^5-$D$48)/$D$51 -> 206.07448
B79: 0.095 | C79: =($I$23/(1+$B79)^1+$J$23/(1+$B79)^2+$K$23/(1+$B79)^3+$L$23/(1+$B79)^4+$M$23/(1+$B79)^5+$D$36*C$77/(1+$B79)^5-$D$48)/$D$51 -> 127.48146 | D79: =($I$23/(1+$B79)^1+$J$23/(1+$B79)^2+$K$23/(1+$B79)^3+$L$23/(1+$B79)^4+$M$23/(1+$B79)^5+$D$36*D$77/(1+$B79)^5-$D$48)/$D$51 -> 139.83215 | E79: =($I$23/(1+$B79)^1+$J$23/(1+$B79)^2+$K$23/(1+$B79)^3+$L$23/(1+$B79)^4+$M$23/(1+$B79)^5+$D$36*E$77/(1+$B79)^5-$D$48)/$D$51 -> 152.18285 | F79: =($I$23/(1+$B79)^1+$J$23/(1+$B79)^2+$K$23/(1+$B79)^3+$L$23/(1+$B79)^4+$M$23/(1+$B79)^5+$D$36*F$77/(1+$B79)^5-$D$48)/$D$51 -> 164.53354 | G79: =($I$23/(1+$B79)^1+$J$23/(1+$B79)^2+$K$23/(1+$B79)^3+$L$23/(1+$B79)^4+$M$23/(1+$B79)^5+$D$36*G$77/(1+$B79)^5-$D$48)/$D$51 -> 176.88423 | H79: =($I$23/(1+$B79)^1+$J$23/(1+$B79)^2+$K$23/(1+$B79)^3+$L$23/(1+$B79)^4+$M$23/(1+$B79)^5+$D$36*H$77/(1+$B79)^5-$D$48)/$D$51 -> 189.23493 | I79: =($I$23/(1+$B79)^1+$J$23/(1+$B79)^2+$K$23/(1+$B79)^3+$L$23/(1+$B79)^4+$M$23/(1+$B79)^5+$D$36*I$77/(1+$B79)^5-$D$48)/$D$51 -> 201.58562
B80: 0.1 | C80: =($I$23/(1+$B80)^1+$J$23/(1+$B80)^2+$K$23/(1+$B80)^3+$L$23/(1+$B80)^4+$M$23/(1+$B80)^5+$D$36*C$77/(1+$B80)^5-$D$48)/$D$51 -> 124.77963 | D80: =($I$23/(1+$B80)^1+$J$23/(1+$B80)^2+$K$23/(1+$B80)^3+$L$23/(1+$B80)^4+$M$23/(1+$B80)^5+$D$36*D$77/(1+$B80)^5-$D$48)/$D$51 -> 136.85217 | E80: =($I$23/(1+$B80)^1+$J$23/(1+$B80)^2+$K$23/(1+$B80)^3+$L$23/(1+$B80)^4+$M$23/(1+$B80)^5+$D$36*E$77/(1+$B80)^5-$D$48)/$D$51 -> 148.92471 | F80: =($I$23/(1+$B80)^1+$J$23/(1+$B80)^2+$K$23/(1+$B80)^3+$L$23/(1+$B80)^4+$M$23/(1+$B80)^5+$D$36*F$77/(1+$B80)^5-$D$48)/$D$51 -> 160.99724 | G80: =($I$23/(1+$B80)^1+$J$23/(1+$B80)^2+$K$23/(1+$B80)^3+$L$23/(1+$B80)^4+$M$23/(1+$B80)^5+$D$36*G$77/(1+$B80)^5-$D$48)/$D$51 -> 173.06978 | H80: =($I$23/(1+$B80)^1+$J$23/(1+$B80)^2+$K$23/(1+$B80)^3+$L$23/(1+$B80)^4+$M$23/(1+$B80)^5+$D$36*H$77/(1+$B80)^5-$D$48)/$D$51 -> 185.14231 | I80: =($I$23/(1+$B80)^1+$J$23/(1+$B80)^2+$K$23/(1+$B80)^3+$L$23/(1+$B80)^4+$M$23/(1+$B80)^5+$D$36*I$77/(1+$B80)^5-$D$48)/$D$51 -> 197.21485
B81: 0.105 | C81: =($I$23/(1+$B81)^1+$J$23/(1+$B81)^2+$K$23/(1+$B81)^3+$L$23/(1+$B81)^4+$M$23/(1+$B81)^5+$D$36*C$77/(1+$B81)^5-$D$48)/$D$51 -> 122.14734 | D81: =($I$23/(1+$B81)^1+$J$23/(1+$B81)^2+$K$23/(1+$B81)^3+$L$23/(1+$B81)^4+$M$23/(1+$B81)^5+$D$36*D$77/(1+$B81)^5-$D$48)/$D$51 -> 133.9492 | E81: =($I$23/(1+$B81)^1+$J$23/(1+$B81)^2+$K$23/(1+$B81)^3+$L$23/(1+$B81)^4+$M$23/(1+$B81)^5+$D$36*E$77/(1+$B81)^5-$D$48)/$D$51 -> 145.75106 | F81: =($I$23/(1+$B81)^1+$J$23/(1+$B81)^2+$K$23/(1+$B81)^3+$L$23/(1+$B81)^4+$M$23/(1+$B81)^5+$D$36*F$77/(1+$B81)^5-$D$48)/$D$51 -> 157.55293 | G81: =($I$23/(1+$B81)^1+$J$23/(1+$B81)^2+$K$23/(1+$B81)^3+$L$23/(1+$B81)^4+$M$23/(1+$B81)^5+$D$36*G$77/(1+$B81)^5-$D$48)/$D$51 -> 169.35479 | H81: =($I$23/(1+$B81)^1+$J$23/(1+$B81)^2+$K$23/(1+$B81)^3+$L$23/(1+$B81)^4+$M$23/(1+$B81)^5+$D$36*H$77/(1+$B81)^5-$D$48)/$D$51 -> 181.15665 | I81: =($I$23/(1+$B81)^1+$J$23/(1+$B81)^2+$K$23/(1+$B81)^3+$L$23/(1+$B81)^4+$M$23/(1+$B81)^5+$D$36*I$77/(1+$B81)^5-$D$48)/$D$51 -> 192.95851
B82: 0.11 | C82: =($I$23/(1+$B82)^1+$J$23/(1+$B82)^2+$K$23/(1+$B82)^3+$L$23/(1+$B82)^4+$M$23/(1+$B82)^5+$D$36*C$77/(1+$B82)^5-$D$48)/$D$51 -> 119.58245 | D82: =($I$23/(1+$B82)^1+$J$23/(1+$B82)^2+$K$23/(1+$B82)^3+$L$23/(1+$B82)^4+$M$23/(1+$B82)^5+$D$36*D$77/(1+$B82)^5-$D$48)/$D$51 -> 131.12089 | E82: =($I$23/(1+$B82)^1+$J$23/(1+$B82)^2+$K$23/(1+$B82)^3+$L$23/(1+$B82)^4+$M$23/(1+$B82)^5+$D$36*E$77/(1+$B82)^5-$D$48)/$D$51 -> 142.65933 | F82: =($I$23/(1+$B82)^1+$J$23/(1+$B82)^2+$K$23/(1+$B82)^3+$L$23/(1+$B82)^4+$M$23/(1+$B82)^5+$D$36*F$77/(1+$B82)^5-$D$48)/$D$51 -> 154.19776 | G82: =($I$23/(1+$B82)^1+$J$23/(1+$B82)^2+$K$23/(1+$B82)^3+$L$23/(1+$B82)^4+$M$23/(1+$B82)^5+$D$36*G$77/(1+$B82)^5-$D$48)/$D$51 -> 165.7362 | H82: =($I$23/(1+$B82)^1+$J$23/(1+$B82)^2+$K$23/(1+$B82)^3+$L$23/(1+$B82)^4+$M$23/(1+$B82)^5+$D$36*H$77/(1+$B82)^5-$D$48)/$D$51 -> 177.27464 | I82: =($I$23/(1+$B82)^1+$J$23/(1+$B82)^2+$K$23/(1+$B82)^3+$L$23/(1+$B82)^4+$M$23/(1+$B82)^5+$D$36*I$77/(1+$B82)^5-$D$48)/$D$51 -> 188.81308
B83: 0.115 | C83: =($I$23/(1+$B83)^1+$J$23/(1+$B83)^2+$K$23/(1+$B83)^3+$L$23/(1+$B83)^4+$M$23/(1+$B83)^5+$D$36*C$77/(1+$B83)^5-$D$48)/$D$51 -> 117.08291 | D83: =($I$23/(1+$B83)^1+$J$23/(1+$B83)^2+$K$23/(1+$B83)^3+$L$23/(1+$B83)^4+$M$23/(1+$B83)^5+$D$36*D$77/(1+$B83)^5-$D$48)/$D$51 -> 128.36495 | E83: =($I$23/(1+$B83)^1+$J$23/(1+$B83)^2+$K$23/(1+$B83)^3+$L$23/(1+$B83)^4+$M$23/(1+$B83)^5+$D$36*E$77/(1+$B83)^5-$D$48)/$D$51 -> 139.64699 | F83: =($I$23/(1+$B83)^1+$J$23/(1+$B83)^2+$K$23/(1+$B83)^3+$L$23/(1+$B83)^4+$M$23/(1+$B83)^5+$D$36*F$77/(1+$B83)^5-$D$48)/$D$51 -> 150.92903 | G83: =($I$23/(1+$B83)^1+$J$23/(1+$B83)^2+$K$23/(1+$B83)^3+$L$23/(1+$B83)^4+$M$23/(1+$B83)^5+$D$36*G$77/(1+$B83)^5-$D$48)/$D$51 -> 162.21107 | H83: =($I$23/(1+$B83)^1+$J$23/(1+$B83)^2+$K$23/(1+$B83)^3+$L$23/(1+$B83)^4+$M$23/(1+$B83)^5+$D$36*H$77/(1+$B83)^5-$D$48)/$D$51 -> 173.49311 | I83: =($I$23/(1+$B83)^1+$J$23/(1+$B83)^2+$K$23/(1+$B83)^3+$L$23/(1+$B83)^4+$M$23/(1+$B83)^5+$D$36*I$77/(1+$B83)^5-$D$48)/$D$51 -> 184.77515
B84: 0.12 | C84: =($I$23/(1+$B84)^1+$J$23/(1+$B84)^2+$K$23/(1+$B84)^3+$L$23/(1+$B84)^4+$M$23/(1+$B84)^5+$D$36*C$77/(1+$B84)^5-$D$48)/$D$51 -> 114.64676 | D84: =($I$23/(1+$B84)^1+$J$23/(1+$B84)^2+$K$23/(1+$B84)^3+$L$23/(1+$B84)^4+$M$23/(1+$B84)^5+$D$36*D$77/(1+$B84)^5-$D$48)/$D$51 -> 125.6792 | E84: =($I$23/(1+$B84)^1+$J$23/(1+$B84)^2+$K$23/(1+$B84)^3+$L$23/(1+$B84)^4+$M$23/(1+$B84)^5+$D$36*E$77/(1+$B84)^5-$D$48)/$D$51 -> 136.71165 | F84: =($I$23/(1+$B84)^1+$J$23/(1+$B84)^2+$K$23/(1+$B84)^3+$L$23/(1+$B84)^4+$M$23/(1+$B84)^5+$D$36*F$77/(1+$B84)^5-$D$48)/$D$51 -> 147.74409 | G84: =($I$23/(1+$B84)^1+$J$23/(1+$B84)^2+$K$23/(1+$B84)^3+$L$23/(1+$B84)^4+$M$23/(1+$B84)^5+$D$36*G$77/(1+$B84)^5-$D$48)/$D$51 -> 158.77654 | H84: =($I$23/(1+$B84)^1+$J$23/(1+$B84)^2+$K$23/(1+$B84)^3+$L$23/(1+$B84)^4+$M$23/(1+$B84)^5+$D$36*H$77/(1+$B84)^5-$D$48)/$D$51 -> 169.80899 | I84: =($I$23/(1+$B84)^1+$J$23/(1+$B84)^2+$K$23/(1+$B84)^3+$L$23/(1+$B84)^4+$M$23/(1+$B84)^5+$D$36*I$77/(1+$B84)^5-$D$48)/$D$51 -> 180.84143

Sheet Comps
B2: Comparable Companies Analysis
B3: Brinker International (EAT)
B4: All amounts in $ millions unless noted
B6: Ticker | C6: Company | D6: Price ($) | E6: Mkt Cap ($M) | F6: Net Debt ($M) | G6: EV ($M) | H6: Revenue ($M) | I6: EBITDA ($M) | J6: EPS (NTM) | K6: Rev Growth | L6: EBITDA % | M6: EV/Rev | N6: EV/EBITDA | O6: P/E
B7: EAT | C7: Brinker International | D7: 168 | E7: =D7*'DCF & Sensitivity'!D51 -> 7644 | F7: ='DCF & Sensitivity'!D48 -> 407.1 | G7: =E7+F7 -> 8051.1 | H7: ='Income Statement'!I13 -> 5804.5141 | I7: ='Income Statement'!I52 -> 849.00458 | J7: ='Income Statement'!I45 -> 10.583723 | K7: ='Income Statement'!I14 -> 0.078064349 | L7: =I7/H7 -> 0.14626626 | M7: =G7/H7 -> 1.3870412 | N7: =G7/I7 -> 9.4829878 | O7: =D7/J7 -> 15.873432
B9: Casual Dining Peers
B10: DRI | C10: Darden Restaurants | D10: 201.66 | E10: 23220 | F10: 7880 | G10: =E10+F10 -> 31100 | H10: 13000 | I10: 1945 | J10: 10.85 | K10: 0.08 | L10: =I10/H10 -> 0.14961538 | M10: =G10/H10 -> 2.3923077 | N10: =G10/I10 -> 15.989717 | O10: =D10/J10 -> 18.586175
B11: TXRH | C11: Texas Roadhouse | D11: 160 | E11: 10570 | F11: -120 | G11: =E11+F11 -> 10450 | H11: 6280 | I11: 740 | J11: 6.85 | K11: 0.068 | L11: =I11/H11 -> 0.11783439 | M11: =G11/H11 -> 1.6640127 | N11: =G11/I11 -> 14.121622 | O11: =D11/J11 -> 23.357664
B12: CAKE | C12: Cheesecake Factory | D12: 62 | E12: 2940 | F12: 350 | G12: =E12+F12 -> 3290 | H12: 3750 | I12: 335 | J12: 4.45 | K12: 0.045 | L12: =I12/H12 -> 0.089333333 | M12: =G12/H12 -> 0.87733333 | N12: =G12/I12 -> 9.8208955 | O12: =D12/J12 -> 13.932584
B13: BLMN | C13: Bloomin' Brands | D13: 9.5 | E13: 810 | F13: 1100 | G13: =E13+F13 -> 1910 | H13: 4020 | I13: 340 | J13: 1.25 | K13: -0.02 | L13: =I13/H13 -> 0.084577114 | M13: =G13/H13 -> 0.47512438 | N13: =G13/I13 -> 5.6176471 | O13: =D13/J13 -> 7.6
B14: DIN | C14: Dine Brands (Applebee's/IHOP) | D14: 24 | E14: 365 | F14: 1080 | G14: =E14+F14 -> 1445 | H14: 800 | I14: 200 | J14: 4.85 | K14: -0.025 | L14: =I14/H14 -> 0.25 | M14: =G14/H14 -> 1.80625 | N14: =G14/I14 -> 7.225 | O14: =D14/J14 -> 4.9484536
B15: CBRL | C15: Cracker Barrel | D15: 42 | E15: 940 | F15: 540 | G15: =E15+F15 -> 1480 | H15: 3470 | I15: 205 | J15: 2.6 | K15: 0.01 | L15: =I15/H15 -> 0.05907781 | M15: =G15/H15 -> 0.42651297 | N15: =G15/I15 -> 7.2195122 | O15: =D15/J15 -> 16.153846
B16: BJRI | C16: BJ's Restaurants | D16: 37 | E16: 840 | F16: 45 | G16: =E16+F16 -> 885 | H16: 1435 | I16: 115 | J16: 1.95 | K16: 0.04 | L16: =I16/H16 -> 0.080139373 | M16: =G16/H16 -> 0.61672474 | N16: =G16/I16 -> 7.6956522 | O16: =D16/J16 -> 18.974359
B18: Summary Statistics (Peers, excl. EAT)
B19: Mean | K19: =AVERAGE(K10:K16) -> 0.028285714 | L19: =AVERAGE(L10:L16) -> 0.11865392 | M19: =AVERAGE(M10:M16) -> 1.1797523 | N19: =AVERAGE(N10:N16) -> 9.6700065 | O19: =AVERAGE(O10:O16) -> 14.793297
B20: Median | K20: =MEDIAN(K10:K16) -> 0.04 | L20: =MEDIAN(L10:L16) -> 0.089333333 | M20: =MEDIAN(M10:M16) -> 0.87733333 | N20: =MEDIAN(N10:N16) -> 7.6956522 | O20: =MEDIAN(O10:O16) -> 16.153846
B21: High | K21: =MAX(K10:K16) -> 0.08 | L21: =MAX(L10:L16) -> 0.25 | M21: =MAX(M10:M16) -> 2.3923077 | N21: =MAX(N10:N16) -> 15.989717 | O21: =MAX(O10:O16) -> 23.357664
B22: Low | K22: =MIN(K10:K16) -> -0.025 | L22: =MIN(L10:L16) -> 0.05907781 | M22: =MIN(M10:M16) -> 0.42651297 | N22: =MIN(N10:N16) -> 5.6176471 | O22: =MIN(O10:O16) -> 4.9484536
B24: Implied EAT Valuation (Peer Median)
B25: Method | D25: Peer Multiple | E25: EAT Metric | F25: Implied EV | G25: Equity Val | H25: Per Share | I25: Upside/(Downside)
B26: EV / Revenue | D26: =M20 -> 0.87733333 | E26: =H7 -> 5804.5141 | F26: =D26*E26 -> 5092.4937 | G26: =F26-F7 -> 4685.3937 | H26: =G26/'DCF & Sensitivity'!D51 -> 102.97569 | I26: =H26/D7-1 -> -0.38704949
B27: EV / EBITDA | D27: =N20 -> 7.6956522 | E27: =I7 -> 849.00458 | F27: =D27*E27 -> 6533.6439 | G27: =F27-F7 -> 6126.5439 | H27: =G27/'DCF & Sensitivity'!D51 -> 134.64932 | I27: =H27/D7-1 -> -0.19851597
B28: P/E (NTM) | D28: =O20 -> 16.153846 | E28: =J7 -> 10.583723 | F28: n/a | G28: n/a | H28: =D28*E28 -> 170.96783 | I28: =H28/D7-1 -> 0.01766564
B30: Key Takeaways
B31: i) Current operating metrics look differentiated but are cyclically inflated. FY26E's 7.8% revenue growth and 14.6% EBITDA margin sit top quartile vs. peers (4.0% and 8.9% median), but both still ride Chili's turnaround momentum. In Base they converge toward peer mean; in Bear, toward peer median. ii) Every multiple resolves to the same question: does Chili's SSS stay elevated or normalize? EV/Revenue implies $103, EV/EBITDA $135, P/E $171. The spread mirrors the DCF's Bear to Base range. Each method prices in a different degree of margin durability, so 'which comp do I trust' is just 'which scenario do I believe.' At current $168, the market is roughly pricing the Base case.
L35: `

Sheet Appendix >>>
B18: Appendix >>>

Sheet Sources
B2: Data Sources & References
B3: Brinker International, Inc. (EAT) DCF Model
B5: SEC FILINGS (PRIMARY SOURCES)
B6: FY25 10-K (fiscal year ended 6/25/2025) | C6: https://www.sec.gov/Archives/edgar/data/0000703351/000070335125000035/eat-20250625.htm
B7: FY22 10-K (for FY21/FY22 historicals) | C7: https://www.sec.gov/Archives/edgar/data/0000703351/000070335122000036/eat-20220629.htm
B8: Q1 FY26 10-Q (quarter ended 9/24/2025) | C8: https://www.sec.gov/Archives/edgar/data/0000703351/000070335125000046/eat-20250924.htm
B9: Q2 FY26 Earnings Release 8-K (Jan 2026) | C9: https://www.sec.gov/Archives/edgar/data/0000703351/000070335126000004/fy26q2ex991-earningsrelease.htm
B10: Investor Relations Hub | C10: https://investors.brinker.com
B12: FINANCIAL DATA SOURCED
B13: Income Statement | C13: FY23/FY24/FY25 from FY25 10-K; FY21/FY22 from FY22 10-K. Matches exactly to reported GAAP figures.
B14: Balance Sheet | C14: FY24/FY25 from FY25 10-K Consolidated Balance Sheets.
B15: Cash Flow | C15: FY23-FY25 from FY25 10-K; includes CFO bridge, capex, buybacks, debt activity.
B16: Unit Counts & AUV | C16: FY25 10-K Item 2 Properties table. 1,113 Chili's Co + 463 Fran + 49 Maggiano's Co + 3 Fran = 1,628 system-wide. Chili's AUV $4.5M, Maggiano's $9.9M.
B17: Comparable Restaurant Sales | C17: Q1 FY26 press release (PRNewswire): consolidated +18.8%, Chili's +21.4%, Maggiano's -6.4%. Q2 FY26: consol +7.5%, Chili's +8.6%, Maggiano's -2.4%.
B18: FY26 Guidance | C18: Q2 FY26 8-K (raised): Revenue $5.76B-$5.83B; Adj EPS $10.45-$10.85; Capex $250M-$260M; WA shares 44.7-45.2M.
B19: Management Commentary | C19: Q1/Q2 FY26 earnings calls via Seeking Alpha, Motley Fool, Insider Monkey transcripts. Key: 6 consecutive quarters DD growth; North of Six initiative; Maggiano's 'North Star' turnaround; $34M R&M favorability.
B20: Debt & Liquidity | C20: FY25 10-K Note 7 (Debt). $350M 8.25% notes due 7/15/2030 semi-annual; $1.0B revolver matures 5/1/2030, SOFR+1.25-2.00%, undrawn at 6/25/25.
B22: MARKET DATA (AS OF APR 2026)
B23: EAT Share Price: $168 | C23: Yahoo Finance / live quote. Also 44,431,215 shares outstanding at 10/23/25 per 10-Q cover page.
B24: Risk-Free Rate: 4.3% | C24: 10-Year US Treasury. treasury.gov / Apr 2026.
B25: Equity Risk Premium: 5.5% | C25: Damodaran (NYU Stern) implied ERP, current-year estimate.
B26: Beta | C26: Raw beta 1.25 (5Y monthly regression vs S&P 500). Adjusted per Blume: 0.67*raw + 0.33*1 = 1.17. See Assumptions row 60-61.
B27: Peer Data (Comps tab) | C27: Yahoo Finance, StockAnalysis.com, peer 10-K/10-Q filings. DRI Feb 2026 Q3 release; TXRH Feb 2026 Q4 release.
B29: NOTES & CAVEATS
B30: Model variance vs reported | C30: Revenue Build reconstructs total revenue from unit economics (AUV x SSS). Minor 3-5% variance vs reported in FY22-24 due to AUV/mix smoothing; FY25 closes to within $176M (3.3%).
B31: FY23 Net Income variance | C31: Model shows FY23 NI of ~$117M vs reported $102.6M. Gap reflects unmodeled special items. Acceptable for DCF valuation.
B32: Balance Sheet imbalance | C32: Minor $12-13M imbalance in FY26E (~0.4% of total assets) from working capital / accumulated OCI timing. Flagged but not material to valuation.
B33: Shadow DCF tab | C33: DEPRECATED. Was set up for QLYS (prior model). Scenario Summary has been re-routed to pull from main DCF tab only.

Sheet Shadow DCF
B2: Shadow DCF — Scenario Comparison
B3: Brinker International (EAT)
B4: Supports Scenario Summary. Each scenario re-runs the DCF using Bear/Base/Bull drivers from Assumptions. Shared WACC, shares, net debt.
B5: Note: Simplified scenario view showing Bear/Base/Bull side-by-side (independent of the Assumptions selector, by design). Uses a single blended revenue driver (Chili's SSS applied to total revenue, collapsing Maggiano's and franchise streams), FY26E EBITDA margin anchored to management's FY26E guidance and interpolated linearly to each scenario's FY30E terminal margin, D&A held flat at 30% of EBITDA, and no working capital. Expect ~1-2% variance vs. the main three-statement model on implied price when running the main model at the same scenario.
B11: Shared Constants | D11: Value
B12: WACC | C12: % | D12: =Assumptions!D87 -> 0.10509837
B13: Tax Rate | C13: % | D13: ='DCF & Sensitivity'!D16 -> 0.23
B14: Net Debt | C14: $M | D14: ='DCF & Sensitivity'!D48 -> 407.1
B15: Diluted Shares | C15: M | D15: ='DCF & Sensitivity'!D51 -> 45.5
B16: FY25A Revenue | C16: $M | D16: ='Income Statement'!H13 -> 5384.2
B17: FY25A EBITDA Margin | C17: % | D17: ='Income Statement'!H52/'Income Statement'!H13 -> 0.14122804
B18: FY25A Capex % Rev | C18: % | D18: =-'Cash Flow'!H36/'Income Statement'!H13 -> 0.049273801
B19: SBC % Rev (projected) | C19: % | D19: =Assumptions!I64 -> 0.006
B20: FY26E Revenue (mgmt guidance midpoint) | C20: $M | D20: 5795
B21: FY26E EBITDA Margin (guidance anchor) | C21: % | D21: ='Income Statement'!I52/'Income Statement'!I13 -> 0.14626626
B23: Scenario Drivers (by scenario) | D23: Bear | E23: Base | F23: Bull
B24: Revenue growth — FY26E anchor (guidance) → terminal SSS | C24: % | D24: =Assumptions!E11 -> 0.01 | E24: =Assumptions!F11 -> 0.025 | F24: =Assumptions!G11 -> 0.04
B25: Terminal EBITDA margin (100 − F&B − Labor − RestExp − G&A) | C25: % | D25: =1-(Assumptions!E15+Assumptions!E16+Assumptions!E17)*('Income Statement'!M11/'Income Statement'!M13)-Assumptions!E18 -> 0.10122144 | E25: =1-(Assumptions!F15+Assumptions!F16+Assumptions!F17)*('Income Statement'!M11/'Income Statement'!M13)-Assumptions!F18 -> 0.13583226 | F25: =1-(Assumptions!G15+Assumptions!G16+Assumptions!G17)*('Income Statement'!M11/'Income Statement'!M13)-Assumptions!G18 -> 0.17731335
B26: Terminal Capex % rev | C26: % | D26: =Assumptions!E19 -> 0.045 | E26: =Assumptions!F19 -> 0.04 | F26: =Assumptions!G19 -> 0.035
B27: Terminal Growth Rate | C27: % | D27: =Assumptions!E23 -> 0.02 | E27: =Assumptions!F23 -> 0.025 | F27: =Assumptions!G23 -> 0.03
B28: Exit EV/EBITDA Multiple | C28: x | D28: =Assumptions!E24 -> 9 | E28: =Assumptions!F24 -> 11 | F28: =Assumptions!G24 -> 13
B31: BEAR SCENARIO | D31: ="FY"&TEXT(MOD('Cover Page'!$C$64+0,100),"00")&"E" -> FY26E | E31: ="FY"&TEXT(MOD('Cover Page'!$C$64+1,100),"00")&"E" -> FY27E | F31: ="FY"&TEXT(MOD('Cover Page'!$C$64+2,100),"00")&"E" -> FY28E | G31: ="FY"&TEXT(MOD('Cover Page'!$C$64+3,100),"00")&"E" -> FY29E | H31: ="FY"&TEXT(MOD('Cover Page'!$C$64+4,100),"00")&"E" -> FY30E
B32: Revenue | C32: $M | D32: =$D$20 -> 5795 | E32: =D32*(1+$D$24) -> 5852.95 | F32: =E32*(1+$D$24) -> 5911.4795 | G32: =F32*(1+$D$24) -> 5970.5943 | H32: =G32*(1+$D$24) -> 6030.3002
B33: EBITDA margin (linear interp FY25A → terminal) | C33: % | D33: =$D$21+($D$25-$D$21)*0/4 -> 0.14626626 | E33: =$D$21+($D$25-$D$21)*1/4 -> 0.13500506 | F33: =$D$21+($D$25-$D$21)*2/4 -> 0.12374385 | G33: =$D$21+($D$25-$D$21)*3/4 -> 0.11248265 | H33: =$D$21+($D$25-$D$21)*4/4 -> 0.10122144
B34: EBITDA | C34: $M | D34: =D32*D33 -> 847.61299 | E34: =E32*E33 -> 790.17785 | F34: =F32*F33 -> 731.50924 | G34: =G32*G33 -> 671.58825 | H34: =H32*H33 -> 610.39569
B35: (-) D&A (assume ~30% of EBITDA) | C35: $M | D35: =-D34*0.3 -> -254.2839 | E35: =-E34*0.3 -> -237.05335 | F35: =-F34*0.3 -> -219.45277 | G35: =-G34*0.3 -> -201.47648 | H35: =-H34*0.3 -> -183.11871
B36: EBIT | C36: $M | D36: =D34+D35 -> 593.32909 | E36: =E34+E35 -> 553.12449 | F36: =F34+F35 -> 512.05647 | G36: =G34+G35 -> 470.11178 | H36: =H34+H35 -> 427.27698
B37: NOPAT = EBIT × (1−t) | C37: $M | D37: =D36*(1-$D$13) -> 456.8634 | E37: =E36*(1-$D$13) -> 425.90586 | F37: =F36*(1-$D$13) -> 394.28348 | G37: =G36*(1-$D$13) -> 361.98607 | H37: =H36*(1-$D$13) -> 329.00327
B38: (+) D&A | C38: $M | D38: =-D35 -> 254.2839 | E38: =-E35 -> 237.05335 | F38: =-F35 -> 219.45277 | G38: =-G35 -> 201.47648 | H38: =-H35 -> 183.11871
B39: (-) Capex (terminal %, linear interp) | C39: $M | D39: =-D32*($D$18+($D$26-$D$18)*1/5) -> -280.58834 | E39: =-E32*($D$18+($D$26-$D$18)*2/5) -> -278.39136 | F39: =-F32*($D$18+($D$26-$D$18)*3/5) -> -276.12237 | G39: =-G32*($D$18+($D$26-$D$18)*4/5) -> -273.78017 | H39: =-H32*$D$26 -> -271.36351
B40: (-) SBC | C40: $M | D40: =-D32*$D$19 -> -34.77 | E40: =-E32*$D$19 -> -35.1177 | F40: =-F32*$D$19 -> -35.468877 | G40: =-G32*$D$19 -> -35.823566 | H40: =-H32*$D$19 -> -36.181801
B41: FCF | C41: $M | D41: =D37+D38+D39+D40 -> 395.78895 | E41: =E37+E38+E39+E40 -> 349.45016 | F41: =F37+F38+F39+F40 -> 302.14501 | G41: =G37+G38+G39+G40 -> 253.85881 | H41: =H37+H38+H39+H40 -> 204.57667
B42: Discount Period | C42: # | D42: 1 | E42: 2 | F42: 3 | G42: 4 | H42: 5
B43: Discount Factor | C43: x | D43: =1/(1+$D$12)^D42 -> 0.90489682 | E43: =1/(1+$D$12)^E42 -> 0.81883825 | F43: =1/(1+$D$12)^F42 -> 0.74096413 | G43: =1/(1+$D$12)^G42 -> 0.67049609 | H43: =1/(1+$D$12)^H42 -> 0.60672977
B44: PV of FCF | C44: $M | D44: =D41*D43 -> 358.14817 | E44: =E41*E43 -> 286.14316 | F44: =F41*F43 -> 223.87861 | G44: =G41*G43 -> 170.21134 | H44: =H41*H43 -> 124.12276
B46: Sum of PV of FCFs (Bear) | C46: $M | D46: =SUM(D44:H44) -> 1162.504
B47: Terminal FCF (year 5) | C47: $M | D47: =H41 -> 204.57667
B48: Terminal Value — Perpetuity | C48: $M | D48: =H41*(1+$D$27)/($D$12-$D$27) -> 2452.0822
B49: PV of TV — Perpetuity | C49: $M | D49: =D48*H43 -> 1487.7513
B50: Terminal Value — Exit Multiple | C50: $M | D50: =H34*$D$28 -> 5493.5612
B51: PV of TV — Exit Multiple | C51: $M | D51: =D50*H43 -> 3333.1071
B52: Enterprise Value — Perpetuity | C52: $M | D52: =D46+D49 -> 2650.2553
B53: Enterprise Value — Exit Multiple | C53: $M | D53: =D46+D51 -> 4495.6112
B54: (−) Net Debt | C54: $M | D54: =-$D$14 -> -407.1
B55: Equity Value — Perpetuity | C55: $M | D55: =D52+D54 -> 2243.1553
B56: Equity Value — Exit Multiple | C56: $M | D56: =D53+D54 -> 4088.5112
B57: → Implied Price — Perpetuity | C57: $/sh | D57: =D55/$D$15 -> 49.300117
B58: → Implied Price — Exit Multiple | C58: $/sh | D58: =D56/$D$15 -> 89.857388
B61: BASE SCENARIO | D61: ="FY"&TEXT(MOD('Cover Page'!$C$64+0,100),"00")&"E" -> FY26E | E61: ="FY"&TEXT(MOD('Cover Page'!$C$64+1,100),"00")&"E" -> FY27E | F61: ="FY"&TEXT(MOD('Cover Page'!$C$64+2,100),"00")&"E" -> FY28E | G61: ="FY"&TEXT(MOD('Cover Page'!$C$64+3,100),"00")&"E" -> FY29E | H61: ="FY"&TEXT(MOD('Cover Page'!$C$64+4,100),"00")&"E" -> FY30E
B62: Revenue | C62: $M | D62: =$D$20 -> 5795 | E62: =D62*(1+$E$24) -> 5939.875 | F62: =E62*(1+$E$24) -> 6088.3719 | G62: =F62*(1+$E$24) -> 6240.5812 | H62: =G62*(1+$E$24) -> 6396.5957
B63: EBITDA margin (linear interp) | C63: % | D63: =$D$21+($E$25-$D$21)*0/4 -> 0.14626626 | E63: =$D$21+($E$25-$D$21)*1/4 -> 0.14365776 | F63: =$D$21+($E$25-$D$21)*2/4 -> 0.14104926 | G63: =$D$21+($E$25-$D$21)*3/4 -> 0.13844076 | H63: =$D$21+($E$25-$D$21)*4/4 -> 0.13583226
B64: EBITDA | C64: $M | D64: =D62*D63 -> 847.61299 | E64: =E62*E63 -> 853.30914 | F64: =F62*F63 -> 858.76035 | G64: =G62*G63 -> 863.9508 | H64: =H62*H63 -> 868.86404
B65: (-) D&A | C65: $M | D65: =-D64*0.3 -> -254.2839 | E65: =-E64*0.3 -> -255.99274 | F65: =-F64*0.3 -> -257.62811 | G65: =-G64*0.3 -> -259.18524 | H65: =-H64*0.3 -> -260.65921
B66: EBIT | C66: $M | D66: =D64+D65 -> 593.32909 | E66: =E64+E65 -> 597.3164 | F66: =F64+F65 -> 601.13225 | G66: =G64+G65 -> 604.76556 | H66: =H64+H65 -> 608.20483
B67: NOPAT | C67: $M | D67: =D66*(1-$D$13) -> 456.8634 | E67: =E66*(1-$D$13) -> 459.93363 | F67: =F66*(1-$D$13) -> 462.87183 | G67: =G66*(1-$D$13) -> 465.66948 | H67: =H66*(1-$D$13) -> 468.31772
B68: (+) D&A | C68: $M | D68: =-D65 -> 254.2839 | E68: =-E65 -> 255.99274 | F68: =-F65 -> 257.62811 | G68: =-G65 -> 259.18524 | H68: =-H65 -> 260.65921
B69: (-) Capex | C69: $M | D69: =-D62*($D$18+($E$26-$D$18)*1/5) -> -274.79334 | E69: =-E62*($D$18+($E$26-$D$18)*2/5) -> -270.64613 | F69: =-F62*($D$18+($E$26-$D$18)*3/5) -> -266.11981 | G69: =-G62*($D$18+($E$26-$D$18)*4/5) -> -261.19803 | H69: =-H62*$E$26 -> -255.86383
B70: (-) SBC | C70: $M | D70: =-D62*$D$19 -> -34.77 | E70: =-E62*$D$19 -> -35.63925 | F70: =-F62*$D$19 -> -36.530231 | G70: =-G62*$D$19 -> -37.443487 | H70: =-H62*$D$19 -> -38.379574
B71: FCF | C71: $M | D71: =D67+D68+D69+D70 -> 401.58395 | E71: =E67+E68+E69+E70 -> 409.64099 | F71: =F67+F68+F69+F70 -> 417.84989 | G71: =G67+G68+G69+G70 -> 426.2132 | H71: =H67+H68+H69+H70 -> 434.73353
B72: Discount Factor | C72: x | D72: =1/(1+$D$12)^1 -> 0.90489682 | E72: =1/(1+$D$12)^2 -> 0.81883825 | F72: =1/(1+$D$12)^3 -> 0.74096413 | G72: =1/(1+$D$12)^4 -> 0.67049609 | H72: =1/(1+$D$12)^5 -> 0.60672977
B73: PV of FCF | C73: $M | D73: =D71*D72 -> 363.39204 | E73: =E71*E72 -> 335.42971 | F73: =F71*F72 -> 309.61178 | G73: =G71*G72 -> 285.77429 | H73: =H71*H72 -> 263.76578
B75: Sum of PV of FCFs (Base) | C75: $M | D75: =SUM(D73:H73) -> 1557.9736
B76: Terminal Value — Perpetuity | C76: $M | D76: =H71*(1+$E$27)/($D$12-$E$27) -> 5563.1827
B77: PV of TV — Perpetuity | C77: $M | D77: =D76*H72 -> 3375.3486
B78: Terminal Value — Exit Multiple | C78: $M | D78: =H64*$E$28 -> 9557.5045
B79: PV of TV — Exit Multiple | C79: $M | D79: =D78*H72 -> 5798.8225
B80: Enterprise Value — Perpetuity | C80: $M | D80: =D75+D77 -> 4933.3222
B81: Enterprise Value — Exit Multiple | C81: $M | D81: =D75+D79 -> 7356.7961
B82: (−) Net Debt | C82: $M | D82: =-$D$14 -> -407.1
B83: Equity Value — Perpetuity | C83: $M | D83: =D80+D82 -> 4526.2222
B84: Equity Value — Exit Multiple | C84: $M | D84: =D81+D82 -> 6949.6961
B85: → Implied Price — Perpetuity | C85: $/sh | D85: =D83/$D$15 -> 99.477411
B86: → Implied Price — Exit Multiple | C86: $/sh | D86: =D84/$D$15 -> 152.74057
B91: BULL SCENARIO | D91: ="FY"&TEXT(MOD('Cover Page'!$C$64+0,100),"00")&"E" -> FY26E | E91: ="FY"&TEXT(MOD('Cover Page'!$C$64+1,100),"00")&"E" -> FY27E | F91: ="FY"&TEXT(MOD('Cover Page'!$C$64+2,100),"00")&"E" -> FY28E | G91: ="FY"&TEXT(MOD('Cover Page'!$C$64+3,100),"00")&"E" -> FY29E | H91: ="FY"&TEXT(MOD('Cover Page'!$C$64+4,100),"00")&"E" -> FY30E
B92: Revenue | C92: $M | D92: =$D$20 -> 5795 | E92: =D92*(1+$F$24) -> 6026.8 | F92: =E92*(1+$F$24) -> 6267.872 | G92: =F92*(1+$F$24) -> 6518.5869 | H92: =G92*(1+$F$24) -> 6779.3304
B93: EBITDA margin | C93: % | D93: =$D$21+($F$25-$D$21)*0/4 -> 0.14626626 | E93: =$D$21+($F$25-$D$21)*1/4 -> 0.15402803 | F93: =$D$21+($F$25-$D$21)*2/4 -> 0.16178981 | G93: =$D$21+($F$25-$D$21)*3/4 -> 0.16955158 | H93: =$D$21+($F$25-$D$21)*4/4 -> 0.17731335
B94: EBITDA | C94: $M | D94: =D92*D93 -> 847.61299 | E94: =E92*E93 -> 928.29615 | F94: =F92*F93 -> 1014.0778 | G94: =G92*G93 -> 1105.2367 | H94: =H92*H93 -> 1202.0658
B95: (-) D&A | C95: $M | D95: =-D94*0.3 -> -254.2839 | E95: =-E94*0.3 -> -278.48885 | F95: =-F94*0.3 -> -304.22334 | G95: =-G94*0.3 -> -331.57101 | H95: =-H94*0.3 -> -360.61973
B96: EBIT | C96: $M | D96: =D94+D95 -> 593.32909 | E96: =E94+E95 -> 649.80731 | F96: =F94+F95 -> 709.85445 | G96: =G94+G95 -> 773.66568 | H96: =H94+H95 -> 841.44604
B97: NOPAT | C97: $M | D97: =D96*(1-$D$13) -> 456.8634 | E97: =E96*(1-$D$13) -> 500.35163 | F97: =F96*(1-$D$13) -> 546.58793 | G97: =G96*(1-$D$13) -> 595.72257 | H97: =H96*(1-$D$13) -> 647.91345
B98: (+) D&A | C98: $M | D98: =-D95 -> 254.2839 | E98: =-E95 -> 278.48885 | F98: =-F95 -> 304.22334 | G98: =-G95 -> 331.57101 | H98: =-H95 -> 360.61973
B99: (-) Capex | C99: $M | D99: =-D92*($D$18+($F$26-$D$18)*1/5) -> -268.99834 | E99: =-E92*($D$18+($F$26-$D$18)*2/5) -> -262.55321 | F99: =-F92*($D$18+($F$26-$D$18)*3/5) -> -255.16206 | G99: =-G92*($D$18+($F$26-$D$18)*4/5) -> -246.75954 | H99: =-H92*$F$26 -> -237.27656
B100: (-) SBC | C100: $M | D100: =-D92*$D$19 -> -34.77 | E100: =-E92*$D$19 -> -36.1608 | F100: =-F92*$D$19 -> -37.607232 | G100: =-G92*$D$19 -> -39.111521 | H100: =-H92*$D$19 -> -40.675982
B101: FCF | C101: $M | D101: =D97+D98+D99+D100 -> 407.37895 | E101: =E97+E98+E99+E100 -> 480.12647 | F101: =F97+F98+F99+F100 -> 558.04197 | G101: =G97+G98+G99+G100 -> 641.42251 | H101: =H97+H98+H99+H100 -> 730.58063
B102: Discount Factor | C102: x | D102: =1/(1+$D$12)^1 -> 0.90489682 | E102: =1/(1+$D$12)^2 -> 0.81883825 | F102: =1/(1+$D$12)^3 -> 0.74096413 | G102: =1/(1+$D$12)^4 -> 0.67049609 | H102: =1/(1+$D$12)^5 -> 0.60672977
B103: PV of FCF | C103: $M | D103: =D101*D102 -> 368.63592 | E103: =E101*E102 -> 393.14592 | F103: =F101*F102 -> 413.48908 | G103: =G101*G102 -> 430.07128 | H103: =H101*H102 -> 443.26502
B105: Sum of PV of FCFs (Bull) | C105: $M | D105: =SUM(D103:H103) -> 2048.6072
B106: Terminal Value — Perpetuity | C106: $M | D106: =H101*(1+$F$27)/($D$12-$F$27) -> 10020.165
B107: PV of TV — Perpetuity | C107: $M | D107: =D106*H102 -> 6079.5324
B108: Terminal Value — Exit Multiple | C108: $M | D108: =H94*$F$28 -> 15626.855
B109: PV of TV — Exit Multiple | C109: $M | D109: =D108*H102 -> 9481.2782
B110: Enterprise Value — Perpetuity | C110: $M | D110: =D105+D107 -> 8128.1396
B111: Enterprise Value — Exit Multiple | C111: $M | D111: =D105+D109 -> 11529.885
B112: (−) Net Debt | C112: $M | D112: =-$D$14 -> -407.1
B113: Equity Value — Perpetuity | C113: $M | D113: =D110+D112 -> 7721.0396
B114: Equity Value — Exit Multiple | C114: $M | D114: =D111+D112 -> 11122.785
B115: → Implied Price — Perpetuity | C115: $/sh | D115: =D113/$D$15 -> 169.69318
B116: → Implied Price — Exit Multiple | C116: $/sh | D116: =D114/$D$15 -> 244.45682
B119: Summary (pulled into Scenario Summary) | D119: Bear | E119: Base | F119: Bull
B120: Revenue FY30E | C120: $M | D120: =H32 -> 6030.3002 | E120: =H62 -> 6396.5957 | F120: =H92 -> 6779.3304
...

Sheet Shadow DCF Rec
B2: Main Model Outputs — Snapshot
B3: Brinker International (EAT)
B4: Hardcoded main-model outputs for each scenario. Feeds Scenario Summary reconciliation.
B6: ⚠ REFRESH REQUIRED after any assumption change
B7: Workflow | C7: 1. Set all dropdowns on Assumptions!H11:H24 to "Bear" → copy the values from the main model tabs into column D below. 2. Repeat for "Base" (column E) and "Bull" (column F). 3. Update the refresh timestamp in C8. 4. Return the Assumptions toggles to the scenario you want the main model to display.
B9: Last Refreshed | C9: 46134
B11: Source cells | C11: Pull from these cells on the main model tabs (all show FY30E values except EV/Share Price which are the final DCF outputs).
B14: Main Model Outputs | C14: Source Cell | D14: Bear | E14: Base | F14: Bull
B15: FY30E Revenue ($M) | C15: Income Statement'!M13 | D15: 6314.44 | E15: 6512.84 | F15: 6682.2
B16: FY30E Net Income ($M) | C16: Income Statement'!M40 | D16: 245.6 | E16: 427.73 | F16: 653.24
B17: FY30E EBITDA ($M) | C17: Income Statement'!M52 | D17: 639 | E17: 884.65 | F17: 1185.32
B18: FY30E EBITDA Margin | C18: Income Statement'!M53 | D18: =IFERROR(D17/D15,"") -> 0.10119662 | E18: =IFERROR(E17/E15,"") -> 0.13583168 | F18: =IFERROR(F17/F15,"") -> 0.17738469
B19: FY30E FCF ($M) | C19: Cash Flow'!M38 | D19: 227.8 | E19: 444.52 | F19: 704.38
B20: Enterprise Value — Perpetuity ($M) | C20: DCF & Sensitivity'!D44 | D20: 2975.52 | E20: 5119.83 | F20: 7940.12
B21: Enterprise Value — Exit Multiple ($M) | C21: DCF & Sensitivity'!D46 | D21: 4808.19 | E21: 7572.72 | F21: 11427.83
B22: Share Price — Perpetuity ($/sh) | C22: DCF & Sensitivity'!D53 | D22: 56.45 | E22: 103.58 | F22: 165.56
B23: Share Price — Exit Multiple ($/sh) | C23: DCF & Sensitivity'!D54 | D23: 96.73 | E23: 157.49 | F23: 242.21
B24: Share Price — Blended ($/sh) | C24: avg of perp + mult | D24: =IFERROR(AVERAGE(D22:D23),"") -> 76.59 | E24: =IFERROR(AVERAGE(E22:E23),"") -> 130.535 | F24: =IFERROR(AVERAGE(F22:F23),"") -> 203.885
B26: Scenario Summary Reconciliation | D26: Bear | E26: Base | F26: Bull
B27: Blended Share Price — Shadow | C27: Shadow DCF'!D123 / E123 / F123 | D27: =IFERROR('Shadow DCF'!D128,"") -> 69.578753 | E27: =IFERROR('Shadow DCF'!E128,"") -> 126.10899 | F27: =IFERROR('Shadow DCF'!F128,"") -> 207.075
B28: Blended Share Price — Main Model (snapshot above) | D28: =IFERROR(D24,"") -> 76.59 | E28: =IFERROR(E24,"") -> 130.535 | F28: =IFERROR(F24,"") -> 203.885
B29: Variance (Shadow − Main) | D29: =IFERROR(IF(AND(ISNUMBER(D27),ISNUMBER(D28)),D27/D28-1,""),"") -> -0.091542596 | E29: =IFERROR(IF(AND(ISNUMBER(E27),ISNUMBER(E28)),E27/E28-1,""),"") -> -0.033906671 | F29: =IFERROR(IF(AND(ISNUMBER(F27),ISNUMBER(F28)),F27/F28-1,""),"") -> 0.015646076

Sheet FootballField Data
A1: Football Field Chart — Source Data
A3: This sheet feeds the 'Football Field — Implied Price by Method ($/sh)' chart on Scenario Summary. Do not delete.
A5: Method | B5: Low | C5: Width | D5: High | E5: Description | G5: Current Price Line
A6: DCF — Perpetuity Growth | B6: ='Scenario Summary'!D8 -> 49.300117 | C6: =D6-B6 -> 120.39306 | D6: ='Scenario Summary'!F8 -> 169.69318 | E6: Bear → Bull scenario range | G6: X (Price) | H6: Y (Position)
A7: DCF — Exit Multiple | B7: ='Scenario Summary'!D9 -> 89.857388 | C7: =D7-B7 -> 154.59943 | D7: ='Scenario Summary'!F9 -> 244.45682 | E7: Bear → Bull scenario range | G7: =B12 -> 168 | H7: 0.5
A8: Comps — EV/EBITDA | B8: =(PERCENTILE(Comps!N10:N16,0.25)*'Income Statement'!I52-'DCF & Sensitivity'!D48)/'DCF & Sensitivity'!D51 -> 125.81601 | C8: =D8-B8 -> 88.613732 | D8: =(PERCENTILE(Comps!N10:N16,0.75)*'Income Statement'!I52-'DCF & Sensitivity'!D48)/'DCF & Sensitivity'!D51 -> 214.42974 | E8: Peer 25th–75th pctile × EAT FY26E EBITDA | G8: =B12 -> 168 | H8: 5.5
A9: Comps — P/E | B9: =PERCENTILE(Comps!O10:O16,0.25)*'Income Statement'!I45 -> 113.94745 | C9: =D9-B9 -> 84.817688 | D9: =PERCENTILE(Comps!O10:O16,0.75)*'Income Statement'!I45 -> 198.76514 | E9: Peer 25th–75th pctile × EAT FY26E EPS
A10: 52-Week Trading Range | B10: 100.3 | C10: =D10-B10 -> 86.82 | D10: 187.12 | E10: Market trading context
A12: Current Price | B12: ='DCF & Sensitivity'!D55 -> 168
