Workbook
Name BaseYear: 'Cover Page'!$C$63
Name CompanyName: 'Cover Page'!$B$2
Name CurrentPrice: 'DCF & Sensitivity'!$D$51
Name ExitMultiple: Assumptions!$D$106
Name FirstForecastYear: 'Cover Page'!$C$64
Name NetDebt: 'DCF & Sensitivity'!$D$44
Name ScenarioRange: Assumptions!$E$9:$G$9
Name SharesOut: 'DCF & Sensitivity'!$D$47
Name TaxRate: 'DCF & Sensitivity'!$D$12
Name TerminalGrowth: Assumptions!$D$105
Name Ticker: 'Cover Page'!$B$3
Name WACC: Assumptions!$D$104

Sheet Cover Page
B2: GRACO INC.
B3: NYSE: GGG
B4: Industrial — Specialty Fluid Handling Equipment & Coatings
B6: Company Overview
B7: Sector | C7: Industrials: Specialty Industrial Machinery
B8: Brands | C8: Three segments: Contractor (paint sprayers ~48% of rev), Industrial (manufacturing/finishing ~45%), Expansion Markets (semis, oil & gas, environmental ~7%)
B9: Footprint | C9: Global manufacturing: HQ Minneapolis MN; major facilities in OH, MI, plus international (Italy, Switzerland, India, China). Sells in 60+ countries via distributor network. ~4,400 employees.
B10: Revenue Model | C10: Equipment & systems sales (point-of-shipment recognition); some service & contract revenue. Americas ~60%, EMEA ~24%, APAC ~16%.
B11: Capital Structure | C11: Essentially debt-free: $25M total debt (FY25), $624M cash = $600M+ net cash position. $750M revolver undrawn. $507M buyback authority outstanding.
B13: Valuation Snapshot
B14: Current Share Price | C14: ='DCF & Sensitivity'!D51 -> 80.76
B15: Base Case (Perpetuity Growth) | C15: ='DCF & Sensitivity'!D49 -> 61.712738
B16: Base Case (Exit Multiple, 15x) | C16: ='DCF & Sensitivity'!D50 -> 70.737056
B17: Upside/(Downside) vs Market (Blended) | C17: =AVERAGE(C15:C16)/C14-1 -> -0.17997899
B19: Key Assumptions
B20: WACC | C20: =Assumptions!D104 -> 0.08
B21: Terminal Growth Rate | C21: =Assumptions!D105 -> 0.025
B22: Exit EV/EBITDA Multiple | C22: =Assumptions!D106 -> 15
B23: Terminal EBITDA Margin | C23: =Assumptions!M57 -> 0.274
B24: Net Debt ($M) | C24: ='DCF & Sensitivity'!D44 -> -624.083
B25: Diluted Shares Outstanding (M) | C25: ='DCF & Sensitivity'!D47 -> 169.219
B27: Table of Contents
B28: › Summary
B29: Scenario Summary
B30: SWOT
B31: › Valuation
B32: Assumptions
B33: Revenue Build
B34: Income Statement
B35: Balance Sheet
B36: Cash Flow
B37: DCF & Sensitivity
B38: Comps
... B45: › Color Coding
B46: Blue text | C46: Hardcoded inputs and assumptions. Scenario drivers, historical data, WACC components.
B47: Black text | C47: Formulas and calculations that reference cells within the same sheet.
B48: Green text | C48: Cross-sheet links. Formulas pulling values from other tabs.
B49: › Number Conventions
B50: Amounts | C50: All $ values in millions ($M) unless labeled per-share ($/sh). Units column on each sheet confirms.
B51: Percentages | C51: Stored as decimals (0.125 = 12.5%) and displayed with 0.0% format
B52: Fiscal year | C52: Brinker fiscal year ends late June. FY25 = July 2024 through June 2025.
B53: Negatives | C53: Shown as (123) in parentheses via number format, not as -123.
B54: › Scenario Toggle
B55: Selector cells | C55: "Assumptions" tab with dropdown of "Bear" / "Base" / "Bull" options. Each row's selector independently drives one scenario dimension.
B56: Interpolation | C56: Revenue and Margin drivers interpolate YoY from the FY26E anchor to the scenario-selected FY30E terminal value.
B57: › How to Run the Model
B58: 1. Set Scenario | C58: Use dropdowns on top of "Assumptions" tab to select Bear/Base/Bull per driver.
B59: 2. Flex DCF Inputs | C59: Flex any of the DCF inputs including WACC or Terminal Value in the DCF section on the bottom of the "Assumptions" tab
B60: 3. Update Market Data | C60: Update current share price on "DCF & SensitivityD55". Flows through to upside calcs on DCF tab and Cover Page.
B62: Fiscal Year Inputs
B63: Base Year (first historical) | C63: 2021
B64: First Forecast Year | C64: 2026
Z100: =WACC -> 0.08
Z101: =CompanyName & " (" & Ticker & ")" -> GRACO INC. (NYSE: GGG)

Sheet Scenario Summary
B2: Scenario Summary
B3: Graco Inc. (NYSE: GGG)
B4: Bear / Base / Bull scenarios side-by-side. Valuation from Shadow DCF tab (simplified model, scenario-specific drivers). Current market: $168/sh.
B5: The valuation outputs (share price & FY30E) values are simplified views of bear, base, and bull that reconcile within a material percentage of main model
B7: Valuation Summary | C7: Units | D7: Bear | E7: Base | F7: Bull | G7: Range (Bull − Bear)
B8: Implied Price — Perpetuity | C8: $/sh | D8: ='Shadow DCF'!D126 -> 23.995326 | E8: ='Shadow DCF'!E126 -> 45.166975 | F8: ='Shadow DCF'!F126 -> 102.87723 | G8: =F8-D8 -> 78.881899
B9: Implied Price — Exit Multiple | C9: $/sh | D9: ='Shadow DCF'!D127 -> 35.617127 | E9: ='Shadow DCF'!E127 -> 63.167838 | F9: ='Shadow DCF'!F127 -> 112.74784 | G9: =F9-D9 -> 77.130717
B10: Blended (avg of two methods) | C10: $/sh | D10: ='Shadow DCF'!D128 -> 29.806226 | E10: ='Shadow DCF'!E128 -> 54.167406 | F10: ='Shadow DCF'!F128 -> 107.81253 | G10: =F10-D10 -> 78.006308
B11: Current Share Price | C11: $/sh | D11: ='DCF & Sensitivity'!$D$51 -> 80.76 | E11: ='DCF & Sensitivity'!$D$51 -> 80.76 | F11: ='DCF & Sensitivity'!$D$51 -> 80.76 | G11: —
B12: Upside / (Downside) vs. market | C12: % | D12: =D10/D11-1 -> -0.63092835 | E12: =E10/E11-1 -> -0.32927927 | F12: =F10/F11-1 -> 0.33497442 | G12: =F12-D12 -> 0.96590277
B14: Scenario Drivers | C14: Units | D14: Bear | E14: Base | F14: Bull | G14: ="FY"&TEXT(MOD('Cover Page'!$C$64-1,100),"00")&"A" -> FY25A
B15: REVENUE
B16: Contractor
B17: Contractor Organic Growth | C17: % | D17: =Assumptions!E12 -> -0.02 | E17: =Assumptions!F12 -> 0.01 | F17: =Assumptions!G12 -> 0.04 | G17: 0.084
B18: Contractor Acquisitions | C18: % | D18: =Assumptions!E13 -> 0.01 | E18: =Assumptions!F13 -> 0.03 | F18: =Assumptions!G13 -> 0.06 | G18: 0
B19: Industrial
B20: Industrial Organic Growth | C20: % | D20: =Assumptions!E15 -> -0.02 | E20: =Assumptions!F15 -> 0.03 | F20: =Assumptions!G15 -> 0.05 | G20: 0.039
B21: Industrial Acquisitions | C21: % | D21: =Assumptions!E16 -> 0.01 | E21: =Assumptions!F16 -> 0.02 | F21: =Assumptions!G16 -> 0.04 | G21: 0
B22: Expansion
B23: Expansion Organic Growth | C23: % | D23: =Assumptions!E18 -> -0.05 | E23: =Assumptions!F18 -> 0.03 | F23: =Assumptions!G18 -> 0.08 | G23: 0.009
B24: Expansion Acquisitions | C24: % | D24: =Assumptions!E19 -> 0.01 | E24: =Assumptions!F19 -> 0.03 | F24: =Assumptions!G19 -> 0.08 | G24: 0
B25: FX Impact | C25: % | D25: =Assumptions!E20 -> -0.01 | E25: =Assumptions!F20 -> 0.01 | F25: =Assumptions!G20 -> 0.02 | G25: 0.005
B26: COST (As a % of Revenue)
B27: Cost of Products Sold | C27: % | D27: =Assumptions!E22 -> 0.5 | E27: =Assumptions!F22 -> 0.475 | F27: =Assumptions!G22 -> 0.45 | G27: =Assumptions!H52 -> 0.47545381
B28: Product Development | C28: % | D28: =Assumptions!E23 -> 0.042 | E28: =Assumptions!F23 -> 0.038 | F28: =Assumptions!G23 -> 0.035 | G28: =Assumptions!H54 -> 0.036796924
B29: Selling, Marketing, & Dist | C29: % | D29: =Assumptions!E24 -> 0.135 | E29: =Assumptions!F24 -> 0.125 | F29: =Assumptions!G24 -> 0.115 | G29: =Assumptions!H55 -> 0.12246267
B30: G&A | C30: % | D30: =Assumptions!E25 -> 0.095 | E30: =Assumptions!F25 -> 0.088 | F30: =Assumptions!G25 -> 0.08 | G30: =Assumptions!H56 -> 0.092193508
B31: CASH CONVERSION CYCLE
B32: Days Inventory Outstanding (DIO) | C32: days | D32: =Assumptions!E27 -> 145 | E32: =Assumptions!F27 -> 138 | F32: =Assumptions!G27 -> 130 | G32: =Assumptions!H77 -> 137.68607
B33: Days Sales Outstanding (DSO) | C33: days | D33: =Assumptions!E28 -> 60 | E33: =Assumptions!F28 -> 62 | F33: =Assumptions!G28 -> 58 | G33: =Assumptions!H76 -> 64.25818
B34: Days Payables Outstanding (DPO) | C34: days | D34: =Assumptions!E29 -> 30 | E34: =Assumptions!F29 -> 27 | F34: =Assumptions!G29 -> 32 | G34: =Assumptions!H78 -> 26.969292
B35: CAPITAL ALLOCATION
B36: CapEx % (as a % of revenue) | C36: % | D36: =Assumptions!E31 -> 0.038 | E36: =Assumptions!F31 -> 0.042 | F36: =Assumptions!G31 -> 0.05 | G36: =Assumptions!H80 -> 0.020418939
B37: Buybacks % (as a % of FCF) | C37: % | D37: =Assumptions!E32 -> 0.3 | E37: =Assumptions!F32 -> 0.5 | F37: =Assumptions!G32 -> 0.7 | G37: =Assumptions!D32 -> 0.6
B38: Acquisition Spend ($M/year) | C38: $M | D38: =Assumptions!E33 -> 50 | E38: =Assumptions!F33 -> 100 | F38: =Assumptions!G33 -> 200 | G38: =Assumptions!D33 -> 135
B39: VALUATION
B40: Terminal Growth Rate | C40: % | D40: =Assumptions!E35 -> 0.02 | E40: =Assumptions!F35 -> 0.025 | F40: =Assumptions!G35 -> 0.03 | G40: n/a
B41: Exit EV / EBITDA Multiple | C41: x | D41: =Assumptions!E36 -> 13 | E41: =Assumptions!F36 -> 15 | F41: =Assumptions!G36 -> 18 | G41: =Assumptions!D36 -> 17.6
B42: WACC | C42: % | D42: =Assumptions!E37 -> 0.1 | E42: =Assumptions!F37 -> 0.08 | F42: =Assumptions!G37 -> 0.06 | G42: =Assumptions!D37 -> 0.107
B44: FY30E Model Outputs | C44: Units | D44: Bear | E44: Base | F44: Bull
B45: Revenue FY30E | C45: $M | D45: ='Shadow DCF'!D120 -> 2152.0787 | E45: ='Shadow DCF'!E120 -> 2981.9706 | F45: ='Shadow DCF'!F120 -> 3851.1787
B46: EBITDA FY30E | C46: $M | D46: ='Shadow DCF'!D121 -> 490.67394 | E46: ='Shadow DCF'!E121 -> 817.05994 | F46: ='Shadow DCF'!F121 -> 1232.3772
B47: EBITDA Margin FY30E | C47: % | D47: ='Shadow DCF'!D122 -> 0.228 | E47: ='Shadow DCF'!E122 -> 0.274 | F47: ='Shadow DCF'!F122 -> 0.32
B48: FCF FY30E | C48: $M | D48: ='Shadow DCF'!D123 -> 251.88117 | E48: ='Shadow DCF'!E123 -> 417.47395 | F48: ='Shadow DCF'!F123 -> 580.99678
B49: Enterprise Value — Perpetuity | C49: $M | D49: ='Shadow DCF'!D124 -> 3436.3821 | E49: ='Shadow DCF'!E124 -> 7019.0273 | F49: ='Shadow DCF'!F124 -> 16784.698
B50: Enterprise Value — Exit Multiple | C50: $M | D50: ='Shadow DCF'!D125 -> 5403.0115 | E50: ='Shadow DCF'!E125 -> 10065.115 | F50: ='Shadow DCF'!F125 -> 18454.994
B52: Investment Thesis
B53: Graco is a high-quality industrial compounder with industry-leading margins (33% EBITDA, 28.5% FCF), a 100-year brand, and a $600M cash position. As a mature business with organic growth structurally capped at 1-3%, Graco's growth engine is acquisitions (~$100M/yr to deliver mid-single-digit total growth), making M&A execution the single biggest swing factor in the implied price. At ~$81, the stock trades roughly in line with peer multiples but above conventional DCF fair value. This gap reflects the market paying for moat durability and capital return discipline that a DCF valuation mechanically undersells. The bull case is owning a steady compounder where 89% of FCF returns to shareholders annually; the bear case is paying full price for a business showing early cracks (Q1 FY26 organic -6%, 60bps tariff GM drag) without much room for multiple expansion. Over the next 12-24 months, watch organic growth recovery, tariff/pricing dynamics, acquisition cadence and multiples paid, and whether mgmt remains buyback-disciplined at premium prices. Overall, this is a quality mature business that trades near its fair value. It isn't undervalued where it must be bought, but is a stable compounder where the downside is contained by margins and cash, and the upside depends on M&A success.
B62: Check: Rec to Three Statement DCF | C62: Units | D62: Bear | E62: Base | F62: Bull
B63: Blended Share Price - Scenario Summary | C63: $/sh | D63: ='Shadow DCF'!D128 -> 29.806226 | E63: ='Shadow DCF'!E128 -> 54.167406 | F63: ='Shadow DCF'!F128 -> 107.81253
B64: Blended Share Price - Main Model | C64: $/sh | D64: ='Shadow DCF Rec'!D24 -> 38.39 | E64: ='Shadow DCF Rec'!E24 -> 60.07 | F64: ='Shadow DCF Rec'!F24 -> 105.57
B65: Variance (Shadow − Main) | C65: % | D65: =IFERROR(D63/D64-1,"") -> -0.223594 | E65: =IFERROR(E63/E64-1,"") -> -0.098261923 | F65: =IFERROR(F63/F64-1,"") -> 0.021242154

Sheet SWOT
B2: SWOT Analysis
B3: Graco Inc. (NYSE: GGG)
C5: Helpful (to achieving objectives) | H5: Harmful (to achieving objectives)
B6: INTERNAL | C6: STRENGTHS | H6: WEAKNESSES
C7: • Strong margins: 33% EBITDA margin, 28.5% FCF margin (peer-leading ex-Roper); ROIC ~24% sustained over 5 years | H7: • Cyclical end-market exposure: Contractor segment tied to U.S. residential/commercial construction; Industrial tied to manufacturing capex
C8: • Niche pricing power: 52-53% gross margin reflects specialty fluid-handling moat in difficult-to-handle materials. Peer median ~38% but Nordson - most direct compeitior - is around the same GM. | H8: • US construction soft in recent periods; FY25 Contractor organic growth muted, masked by acquisitions and FX tailwind
C9: • Strong balance sheet: $624M cash, ~$25M debt = $600M+ net cash; 100-year operating history with consistent dividend increases for 25+ years | H9: • Heavy reliance on a few large channel partners in Contractor segment (Sherwin-Williams, Home Depot/Sam's Club)
C10: • Diversified end markets: Contractor (paint sprayers ~48%), Industrial (manufacturing/automotive/finishing ~45%), Expansion (semis, oil & gas ~7%) | H10: • Mature business in mature end markets, there is a ceiling to growth and most likely the company will stay within low-single digits
C11: • Capital return engine: $423M buybacks + $183M dividends in FY25 = $606M returned (~89% of FCF) | H11: • R&D intensity below specialty peers: Graco spends ~3.7% of revenue on Product Development vs. Nordson at ~5%+
C12: • Geographic balance: Americas ~60%, EMEA ~24%, APAC ~16% — reduces single-region exposure
B15: EXTERNAL | C15: OPPORTUNITIES | H15: THREATS
C16: • M&A pipeline: 100+ name pipeline per mgmt; FY24-25 closed Corob (€230M), Color Service (€63M), Radia ($69M); $190M run-rate revenue from acquisitions | H16: • Tariff exposure: $4M Q4 FY25 hit to gross margin (70bps) from increased product costs; ongoing tariff and supply chain risk
C17: • ETM electric pump licensing: high-torque motor IP being licensed to OEMs/motor manufacturers; royalties not in current guidance — incremental upside | H17: • Industrial production weakness: end markets remain soft; macroeconomic uncertainty cited by mgmt as biggest near-term headwind
C18: • One Graco operating model launch (2025) — organizational leverage from consolidation | H18: • Valuation premium: trades at 17x EV/EBITDA, ~5% premium to closest comps (NDSN, IEX); limited multiple expansion room
C19: • Capex normalization: FY25 capex spiked low ($46M) post heavy FY21-23 buildout cycle; sustained low maintenance capex would lift FCF | H19: • Currency translation risk: 40% of revenue outside USA; EUR/CNY/GBP fluctuations swing reported results materially
H20: • Acquisition integration risk: 3 acquisitions in 18 months (Corob/Color Service/Radia); execution risk if integration falters or earnouts trigger

Sheet Valuation >>>
B18: Valuation >>>

Sheet Assumptions
B2: Assumptions
B3: Graco Inc. (NYSE: GGG)
B4: All $ in millions unless noted. Fiscal year ends last Wednesday in June.
B7: SCENARIO SELECTOR
B8: FY26E anchored to mgmt's guidance where given. FY27-FY30 interpolate linearly between FY26 start and scenario terminal values. Each driver toggles independently via column H dropdown.
B9: Metric | C9: Units | D9: FY26E Start | E9: Bear | F9: Base | G9: Bull | H9: Scenario
B10: REVENUE
B11: Contractor
B12: Contractor Organic Growth | C12: % | D12: 0.01 | E12: -0.02 | F12: 0.01 | G12: 0.04 | H12: Base
B13: Contractor Acquisitions | C13: % | D13: 0.03 | E13: 0.01 | F13: 0.03 | G13: 0.06 | H13: Base
B14: Industrial
B15: Industrial Organic Growth | C15: % | D15: 0.03 | E15: -0.02 | F15: 0.03 | G15: 0.05 | H15: Base
B16: Industrial Acquisitions | C16: % | D16: 0.02 | E16: 0.01 | F16: 0.02 | G16: 0.04 | H16: Base
B17: Expansion
B18: Expansion Organic Growth | C18: % | D18: 0.03 | E18: -0.05 | F18: 0.03 | G18: 0.08 | H18: Base
B19: Expansion Acquisitions | C19: % | D19: 0.03 | E19: 0.01 | F19: 0.03 | G19: 0.08 | H19: Base
B20: FX Impact | C20: % | D20: 0.01 | E20: -0.01 | F20: 0.01 | G20: 0.02 | H20: Base
B21: COST (As a % of Revenue)
B22: Cost of Products Sold | C22: % | D22: 0.475 | E22: 0.5 | F22: 0.475 | G22: 0.45 | H22: Base
B23: Product Development | C23: % | D23: 0.038 | E23: 0.042 | F23: 0.038 | G23: 0.035 | H23: Base
B24: Selling, Marketing, & Dist | C24: % | D24: 0.125 | E24: 0.135 | F24: 0.125 | G24: 0.115 | H24: Base
B25: G&A | C25: % | D25: 0.088 | E25: 0.095 | F25: 0.088 | G25: 0.08 | H25: Base
B26: CASH CONVERSION CYCLE
B27: Days Inventory Outstanding (DIO) | C27: days | D27: 137.5 | E27: 145 | F27: 138 | G27: 130 | H27: Base
B28: Days Sales Outstanding (DSO) | C28: days | D28: 65 | E28: 60 | F28: 62 | G28: 58 | H28: Base
B29: Days Payables Outstanding (DPO) | C29: days | D29: 25 | E29: 30 | F29: 27 | G29: 32 | H29: Base
B30: CAPITAL ALLOCATION
B31: CapEx % (as a % of revenue) | C31: % | D31: 0.062 | E31: 0.038 | F31: 0.042 | G31: 0.05 | H31: Base
B32: Buybacks % (as a % of FCF) | C32: % | D32: 0.6 | E32: 0.3 | F32: 0.5 | G32: 0.7 | H32: Base
B33: Acquisition Spend ($M/year) | C33: $M | D33: 135 | E33: 50 | F33: 100 | G33: 200 | H33: Base
B34: VALUATION
B35: Terminal Growth Rate | C35: % | D35: 0.025 | E35: 0.02 | F35: 0.025 | G35: 0.03 | H35: Base
B36: Exit EV / EBITDA Multiple | C36: x | D36: 17.6 | E36: 13 | F36: 15 | G36: 18 | H36: Base
B37: WACC | C37: % | D37: 0.107 | E37: 0.1 | F37: 0.08 | G37: 0.06 | H37: Base
B39: Revenue Drivers | C39: Units | D39: =IF('Cover Page'!$C$63+0<'Cover Page'!$C$64,"FY"&TEXT(MOD('Cover Page'!$C$63+0,100),"00")&"A","FY"&TEXT(MOD('Cover Page'!$C$63+0,100),"00")&"E") -> FY21A | E39: =IF('Cover Page'!$C$63+1<'Cover Page'!$C$64,"FY"&TEXT(MOD('Cover Page'!$C$63+1,100),"00")&"A","FY"&TEXT(MOD('Cover Page'!$C$63+1,100),"00")&"E") -> FY22A | F39: =IF('Cover Page'!$C$63+2<'Cover Page'!$C$64,"FY"&TEXT(MOD('Cover Page'!$C$63+2,100),"00")&"A","FY"&TEXT(MOD('Cover Page'!$C$63+2,100),"00")&"E") -> FY23A | G39: =IF('Cover Page'!$C$63+3<'Cover Page'!$C$64,"FY"&TEXT(MOD('Cover Page'!$C$63+3,100),"00")&"A","FY"&TEXT(MOD('Cover Page'!$C$63+3,100),"00")&"E") -> FY24A | H39: =IF('Cover Page'!$C$63+4<'Cover Page'!$C$64,"FY"&TEXT(MOD('Cover Page'!$C$63+4,100),"00")&"A","FY"&TEXT(MOD('Cover Page'!$C$63+4,100),"00")&"E") -> FY25A | I39: =IF('Cover Page'!$C$63+5<'Cover Page'!$C$64,"FY"&TEXT(MOD('Cover Page'!$C$63+5,100),"00")&"A","FY"&TEXT(MOD('Cover Page'!$C$63+5,100),"00")&"E") -> FY26E | J39: =IF('Cover Page'!$C$63+6<'Cover Page'!$C$64,"FY"&TEXT(MOD('Cover Page'!$C$63+6,100),"00")&"A","FY"&TEXT(MOD('Cover Page'!$C$63+6,100),"00")&"E") -> FY27E | K39: =IF('Cover Page'!$C$63+7<'Cover Page'!$C$64,"FY"&TEXT(MOD('Cover Page'!$C$63+7,100),"00")&"A","FY"&TEXT(MOD('Cover Page'!$C$63+7,100),"00")&"E") -> FY28E | L39: =IF('Cover Page'!$C$63+8<'Cover Page'!$C$64,"FY"&TEXT(MOD('Cover Page'!$C$63+8,100),"00")&"A","FY"&TEXT(MOD('Cover Page'!$C$63+8,100),"00")&"E") -> FY29E | M39: =IF('Cover Page'!$C$63+9<'Cover Page'!$C$64,"FY"&TEXT(MOD('Cover Page'!$C$63+9,100),"00")&"A","FY"&TEXT(MOD('Cover Page'!$C$63+9,100),"00")&"E") -> FY30E | O39: Notes
B40: Contractor | C40: $M | D40: ='Revenue Build'!D43 -> 987.6 | E40: ='Revenue Build'!E43 -> 999.1 | F40: ='Revenue Build'!F43 -> 985.7 | G40: ='Revenue Build'!G43 -> 988.9 | H40: ='Revenue Build'!H43 -> 1071.9 | I40: ='Revenue Build'!I43 -> 1125.495 | J40: ='Revenue Build'!J43 -> 1181.7698 | K40: ='Revenue Build'!K43 -> 1240.8582 | ... M40: ='Revenue Build'!M43 -> 1368.0462 | O40: Revenue build by segment (Contractor, Industrial, Expansion). Drives top-line forecast off scenario-selected growth rates. Contractor (~48% of revenue) is the largest segment and most cyclical; Industrial is the highest-margin business; Expansion Markets is the smallest but fastest-growing.
B41: Industrial | C41: $M | D41: ='Revenue Build'!D51 -> 864.6 | E41: ='Revenue Build'!E51 -> 972.7 | F41: ='Revenue Build'!F51 -> 1018.2 | G41: ='Revenue Build'!G51 -> 958 | H41: ='Revenue Build'!H51 -> 996.8 | I41: ='Revenue Build'!I51 -> 1056.608 | J41: ='Revenue Build'!J51 -> 1120.0045 | K41: ='Revenue Build'!K51 -> 1187.2047 | ... M41: ='Revenue Build'!M51 -> 1333.9433
B42: Expansion | C42: $M | D42: ='Revenue Build'!D59 -> 135.4 | E42: ='Revenue Build'!E59 -> 171.7 | F42: ='Revenue Build'!F59 -> 191.7 | G42: ='Revenue Build'!G59 -> 166.4 | H42: ='Revenue Build'!H59 -> 167.9 | I42: ='Revenue Build'!I59 -> 179.653 | J42: ='Revenue Build'!J59 -> 192.22871 | K42: ='Revenue Build'!K59 -> 205.68472 | ... M42: ='Revenue Build'!M59 -> 235.48844
B43: Total Revenue | C43: $M | D43: ='Revenue Build'!D61 -> 1987.6 | E43: ='Revenue Build'!E61 -> 2143.5 | F43: ='Revenue Build'!F61 -> 2195.6 | G43: ='Revenue Build'!G61 -> 2113.3 | H43: ='Revenue Build'!H61 -> 2236.6 | I43: ='Revenue Build'!I61 -> 2361.756 | J43: ='Revenue Build'!J61 -> 2494.0029 | K43: ='Revenue Build'!K61 -> 2633.7477 | ... M43: ='Revenue Build'!M61 -> 2937.4779
B44: YoY Growth % | E44: =(E43-D43)/D43 -> 0.078436305 | F44: =(F43-E43)/E43 -> 0.024306042 | G44: =(G43-F43)/F43 -> -0.037484059 | H44: =(H43-G43)/G43 -> 0.058344769 | I44: =(I43-H43)/H43 -> 0.055958151 | J44: =(J43-I43)/I43 -> 0.055995175 | K44: =(K43-J43)/J43 -> 0.056032318 | L44: =(L43-K43)/K43 -> 0.05606958 | M44: =(M43-L43)/L43 -> 0.056106959
B46: As a % of Total of Revenue
B47: Contractor | D47: =D40/D$43 -> 0.49688066 | E47: =E40/E$43 -> 0.46610683 | F47: =F40/F$43 -> 0.44894334 | G47: =G40/G$43 -> 0.46794113 | H47: =H40/H$43 -> 0.47925423 | I47: =I40/I$43 -> 0.47655008 | J47: =J40/J$43 -> 0.47384457 | K47: =K40/K$43 -> 0.47113785 | ... M47: =M40/M$43 -> 0.46572136
B48: Industrial | D48: =D41/D$43 -> 0.43499698 | E48: =E41/E$43 -> 0.45379053 | F48: =F41/F$43 -> 0.46374567 | G48: =G41/G$43 -> 0.45331945 | H48: =H41/H$43 -> 0.44567647 | I48: =I41/I$43 -> 0.44738237 | J48: =J41/J$43 -> 0.44907905 | K48: =K41/K$43 -> 0.45076632 | ... M48: =M41/M$43 -> 0.45411176
B49: Expansion | D49: =D42/D$43 -> 0.068122359 | E49: =E42/E$43 -> 0.080102636 | F49: =F42/F$43 -> 0.087310986 | G49: =G42/G$43 -> 0.078739412 | H49: =H42/H$43 -> 0.075069302 | I49: =I42/I$43 -> 0.076067553 | J49: =J42/J$43 -> 0.077076377 | K49: =K42/K$43 -> 0.078095833 | ... M49: =M42/M$43 -> 0.080166879
B51: Margin Drivers
B52: Cost of Products Sold | C52: % | D52: ='Income Statement'!D16/'Income Statement'!D12 -> 0.47982491 | E52: ='Income Statement'!E16/'Income Statement'!E12 -> 0.50669466 | F52: ='Income Statement'!F16/'Income Statement'!F12 -> 0.47121516 | G52: ='Income Statement'!G16/'Income Statement'!G12 -> 0.46888752 | H52: ='Income Statement'!H16/'Income Statement'!H12 -> 0.47545381 | I52: =H52 -> 0.47545381 | J52: =H52+(INDEX($E$22:$G$22,MATCH($H$22,$E$9:$G$9,0))-H52)*1/4 -> 0.47534036 | K52: =H52+(INDEX($E$22:$G$22,MATCH($H$22,$E$9:$G$9,0))-H52)*2/4 -> 0.47522691 | L52: =H52+(INDEX($E$22:$G$22,MATCH($H$22,$E$9:$G$9,0))-H52)*3/4 -> 0.47511345 | M52: =INDEX($E$22:$G$22,MATCH($H$22,$E$9:$G$9,0)) -> 0.475 | O52: P&L cost structure as % of revenue. COGS drives gross margin (~52-53% historically); Product Development, S&M, and G&A combine for total operating expenses. Forecast normalizes toward scenario-selected terminal margins via linear ramp from FY25A.
B53: Gross Margin % | D53: =1-D52 -> 0.52017509 | E53: =1-E52 -> 0.49330534 | F53: =1-F52 -> 0.52878484 | G53: =1-G52 -> 0.53111248 | H53: =1-H52 -> 0.52454619 | I53: =1-I52 -> 0.52454619 | J53: =1-J52 -> 0.52465964 | K53: =1-K52 -> 0.52477309 | ... M53: =1-M52 -> 0.525
B54: Product Development | C54: % | D54: ='Income Statement'!D21/'Income Statement'!D12 -> 0.040098611 | E54: ='Income Statement'!E21/'Income Statement'!E12 -> 0.037322137 | F54: ='Income Statement'!F21/'Income Statement'!F12 -> 0.037711787 | G54: ='Income Statement'!G21/'Income Statement'!G12 -> 0.04126248 | H54: ='Income Statement'!H21/'Income Statement'!H12 -> 0.036796924 | I54: =D23 -> 0.038 | J54: =H54+(INDEX($E$23:$G$23,MATCH($H$23,$E$9:$G$9,0))-H54)*1/4 -> 0.037097693 | K54: =H54+(INDEX($E$23:$G$23,MATCH($H$23,$E$9:$G$9,0))-H54)*2/4 -> 0.037398462 | L54: =H54+(INDEX($E$23:$G$23,MATCH($H$23,$E$9:$G$9,0))-H54)*3/4 -> 0.037699231 | M54: =INDEX($E$23:$G$23,MATCH($H$23,$E$9:$G$9,0)) -> 0.038
B55: Selling, Marketing, & Dist | C55: % | D55: ='Income Statement'!D23/'Income Statement'!D12 -> 0.1365969 | E55: ='Income Statement'!E23/'Income Statement'!E12 -> 0.11705155 | F55: ='Income Statement'!F23/'Income Statement'!F12 -> 0.11873747 | G55: ='Income Statement'!G23/'Income Statement'!G12 -> 0.12951308 | H55: ='Income Statement'!H23/'Income Statement'!H12 -> 0.12246267 | I55: =D24 -> 0.125 | J55: =H55+(INDEX($E$24:$G$24,MATCH($H$24,$E$9:$G$9,0))-H55)*1/4 -> 0.123097 | K55: =H55+(INDEX($E$24:$G$24,MATCH($H$24,$E$9:$G$9,0))-H55)*2/4 -> 0.12373133 | L55: =H55+(INDEX($E$24:$G$24,MATCH($H$24,$E$9:$G$9,0))-H55)*3/4 -> 0.12436567 | M55: =INDEX($E$24:$G$24,MATCH($H$24,$E$9:$G$9,0)) -> 0.125
B56: G&A | C56: % | D56: ='Income Statement'!D25/'Income Statement'!D12 -> 0.076172268 | E56: ='Income Statement'!E25/'Income Statement'!E12 -> 0.071751808 | F56: ='Income Statement'!F25/'Income Statement'!F12 -> 0.078065221 | G56: ='Income Statement'!G25/'Income Statement'!G12 -> 0.090569252 | H56: ='Income Statement'!H25/'Income Statement'!H12 -> 0.092193508 | I56: =D25 -> 0.088 | J56: =H56+(INDEX($E$25:$G$25,MATCH($H$25,$E$9:$G$9,0))-H56)*1/4 -> 0.091145131 | K56: =H56+(INDEX($E$25:$G$25,MATCH($H$25,$E$9:$G$9,0))-H56)*2/4 -> 0.090096754 | L56: =H56+(INDEX($E$25:$G$25,MATCH($H$25,$E$9:$G$9,0))-H56)*3/4 -> 0.089048377 | M56: =INDEX($E$25:$G$25,MATCH($H$25,$E$9:$G$9,0)) -> 0.088
B57: Operating Margin % | C57: % | D57: ='Income Statement'!D29/'Income Statement'!D12 -> 0.26730731 | E57: ='Income Statement'!E29/'Income Statement'!E12 -> 0.26717985 | F57: ='Income Statement'!F29/'Income Statement'!F12 -> 0.29463472 | G57: ='Income Statement'!G29/'Income Statement'!G12 -> 0.26976766 | H57: ='Income Statement'!H29/'Income Statement'!H12 -> 0.2793973 | I57: =1-I52-I54-I55-I56 -> 0.27354619 | J57: =1-J52-J54-J55-J56 -> 0.27331982 | K57: =1-K52-K54-K55-K56 -> 0.27354654 | L57: =1-L52-L54-L55-L56 -> 0.27377327 | M57: =1-M52-M54-M55-M56 -> 0.274
B59: Debt Schedule
B60: Tranche / $M | C60: Rate | D60: =D39 -> FY21A | E60: =E39 -> FY22A | F60: =F39 -> FY23A | G60: =G39 -> FY24A | H60: =H39 -> FY25A | I60: =I39 -> FY26E | J60: =J39 -> FY27E | K60: =K39 -> FY28E | ... M60: =M39 -> FY30E
B61: Long-term debt | C61: 0.022 | D61: 150 | E61: 75 | F61: 0 | G61: 0 | H61: 1.6 | I61: =H61 -> 1.6 | J61: =I61 -> 1.6 | K61: =J61 -> 1.6 | L61: =K61 -> 1.6 | M61: =L61 -> 1.6 | O61: Debt schedule: tracks Graco's three debt tranches (LT debt, ST notes payable, undrawn revolver). FY25 total debt ~$25M, essentially debt-free. Used to calculate weighted-avg pre-tax cost of debt for WACC.
B62: Notes payable to banks (short-term) | C62: 0.0274 | D62: 28 | E62: 28 | F62: 28 | G62: 28.5 | H62: 23.1 | I62: =H62 -> 23.1 | J62: =I62 -> 23.1 | K62: =J62 -> 23.1 | L62: =K62 -> 23.1 | M62: =L62 -> 23.1
B63: Revolver (US$750M facility, undrawn) | C63: 0.06 | D63: 0 | E63: 0 | F63: 0 | G63: 0 | H63: 0 | I63: =H63 -> 0 | J63: =I63 -> 0 | K63: =J63 -> 0 | L63: =K63 -> 0 | M63: =L63 -> 0
B64: Total Debt | D64: =SUM(D61:D63) -> 178 | E64: =SUM(E61:E63) -> 103 | F64: =SUM(F61:F63) -> 28 | G64: =SUM(G61:G63) -> 28.5 | H64: =SUM(H61:H63) -> 24.7 | I64: =SUM(I61:I63) -> 24.7 | J64: =SUM(J61:J63) -> 24.7 | K64: =SUM(K61:K63) -> 24.7 | ... M64: =SUM(M61:M63) -> 24.7
B66: Interest Expense
B67: Historical (actual, per 10-K) | D67: ='Income Statement'!D33 -> 10.2 | E67: ='Income Statement'!E33 -> 9.9 | F67: ='Income Statement'!F33 -> 5.2 | G67: ='Income Statement'!G33 -> 2.8 | H67: ='Income Statement'!H33 -> 2.9
B68: Forecast (avg balance × blended rate) | I68: =AVERAGE(H64,I64)*((I61*$C$61+I62*$C$62+I63*$C$63)/SUM(I61:I63)) -> 0.66814 | J68: =AVERAGE(I64,J64)*((J61*$C$61+J62*$C$62+J63*$C$63)/SUM(J61:J63)) -> 0.66814 | K68: =AVERAGE(J64,K64)*((K61*$C$61+K62*$C$62+K63*$C$63)/SUM(K61:K63)) -> 0.66814 | L68: =AVERAGE(K64,L64)*((L61*$C$61+L62*$C$62+L63*$C$63)/SUM(L61:L63)) -> 0.66814 | M68: =AVERAGE(L64,M64)*((M61*$C$61+M62*$C$62+M63*$C$63)/SUM(M61:M63)) -> 0.66814
B69: Total Interest Expense | D69: =D67 -> 10.2 | E69: =E67 -> 9.9 | F69: =F67 -> 5.2 | G69: =G67 -> 2.8 | H69: =H67 -> 2.9 | I69: =I68 -> 0.66814 | J69: =J68 -> 0.66814 | K69: =K68 -> 0.66814 | L69: =L68 -> 0.66814 | M69: =M68 -> 0.66814
B71: Tax & Interest
B72: Effective tax rate | C72: % | D72: ='Income Statement'!D37 -> 0.13490659 | E72: ='Income Statement'!E37 -> 0.18578752 | F72: ='Income Statement'!F37 -> 0.16803548 | G72: ='Income Statement'!G37 -> 0.17512303 | H72: ='Income Statement'!H37 -> 0.18618431 | I72: ='Income Statement'!I37 -> 0.19 | J72: ='Income Statement'!J37 -> 0.19 | K72: ='Income Statement'!K37 -> 0.19 | ... M72: ='Income Statement'!M37 -> 0.19 | O72: Effective tax rate and interest expense. Tax rate runs below statutory (~22-24%) due to OBBBA bonus depreciation and excess SBC tax benefits, both of which lower ETR. Interest expense is minimal given Graco's near-zero debt balance.
B73: Interest expense ($M) | C73: $M | D73: =D69 -> 10.2 | E73: =E69 -> 9.9 | F73: =F69 -> 5.2 | G73: =G69 -> 2.8 | H73: =H69 -> 2.9 | I73: =I69 -> 0.66814 | J73: =J69 -> 0.66814 | K73: =K69 -> 0.66814 | ... M73: =M69 -> 0.66814
B75: Balance Sheet Drivers
B76: Days sales outstanding (DSO) | C76: days | D76: =('Balance Sheet'!D11/'Income Statement'!D12)*365 -> 59.706772 | E76: =('Balance Sheet'!E11/'Income Statement'!E12)*365 -> 58.919361 | F76: =('Balance Sheet'!F11/'Income Statement'!F12)*365 -> 58.922497 | G76: =('Balance Sheet'!G11/'Income Statement'!G12)*365 -> 62.615126 | H76: =('Balance Sheet'!H11/'Income Statement'!H12)*365 -> 64.25818 | I76: =H76+(INDEX($E$28:$G$28,MATCH($H$28,$E$9:$G$9,0))-H76)*1/5 -> 63.806544 | J76: =H76+(INDEX($E$28:$G$28,MATCH($H$28,$E$9:$G$9,0))-H76)*2/5 -> 63.354908 | K76: =H76+(INDEX($E$28:$G$28,MATCH($H$28,$E$9:$G$9,0))-H76)*3/5 -> 62.903272 | L76: =H76+(INDEX($E$28:$G$28,MATCH($H$28,$E$9:$G$9,0))-H76)*4/5 -> 62.451636 | M76: =INDEX($E$28:$G$28,MATCH($H$28,$E$9:$G$9,0)) -> 62 | O76: Working capital drivers: DSO, DIO, DPO, and CCC. Drive forecasted AR, Inventory, and AP via days × volume / 365. Capex % of revenue and SBC % of revenue drive capex spend and stock comp expense respectively.
B77: Days inventory outstanding (DIO) | C77: days | D77: =('Balance Sheet'!D12/'Income Statement'!D16)*365 -> 146.31421 | E77: =('Balance Sheet'!E12/'Income Statement'!E16)*365 -> 160.23235 | F77: =('Balance Sheet'!F12/'Income Statement'!F16)*365 -> 154.64661 | G77: =('Balance Sheet'!G12/'Income Statement'!G16)*365 -> 149.06322 | H77: =('Balance Sheet'!H12/'Income Statement'!H16)*365 -> 137.68607 | I77: =H77+(INDEX($E$27:$G$27,MATCH($H$27,$E$9:$G$9,0))-H77)*1/5 -> 137.74886 | J77: =H77+(INDEX($E$27:$G$27,MATCH($H$27,$E$9:$G$9,0))-H77)*2/5 -> 137.81164 | K77: =H77+(INDEX($E$27:$G$27,MATCH($H$27,$E$9:$G$9,0))-H77)*3/5 -> 137.87443 | L77: =H77+(INDEX($E$27:$G$27,MATCH($H$27,$E$9:$G$9,0))-H77)*4/5 -> 137.93721 | M77: =INDEX($E$27:$G$27,MATCH($H$27,$E$9:$G$9,0)) -> 138
B78: Days payables outstanding (DPO) | C78: days | D78: =('Balance Sheet'!D29/'Income Statement'!D16)*365 -> 30.01749 | E78: =('Balance Sheet'!E29/'Income Statement'!E16)*365 -> 28.302707 | F78: =('Balance Sheet'!F29/'Income Statement'!F16)*365 -> 25.476619 | G78: =('Balance Sheet'!G29/'Income Statement'!G16)*365 -> 22.401695 | H78: =('Balance Sheet'!H29/'Income Statement'!H16)*365 -> 26.969292 | I78: =H78+(INDEX($E$29:$G$29,MATCH($H$29,$E$9:$G$9,0))-H78)*1/5 -> 26.975434 | J78: =H78+(INDEX($E$29:$G$29,MATCH($H$29,$E$9:$G$9,0))-H78)*2/5 -> 26.981575 | K78: =H78+(INDEX($E$29:$G$29,MATCH($H$29,$E$9:$G$9,0))-H78)*3/5 -> 26.987717 | L78: =H78+(INDEX($E$29:$G$29,MATCH($H$29,$E$9:$G$9,0))-H78)*4/5 -> 26.993858 | M78: =INDEX($E$29:$G$29,MATCH($H$29,$E$9:$G$9,0)) -> 27
B79: Cash conversion cycle (CCC) | C79: days | D79: =D76+D77-D78 -> 176.0035 | E79: =E76+E77-E78 -> 190.849 | F79: =F76+F77-F78 -> 188.09249 | G79: =G76+G77-G78 -> 189.27665 | H79: =H76+H77-H78 -> 174.97496 | I79: =I76+I77-I78 -> 174.57997 | J79: =J76+J77-J78 -> 174.18498 | K79: =K76+K77-K78 -> 173.78998 | ... M79: =M76+M77-M78 -> 173
B80: Capex % of revenue | C80: % | D80: =D81/'Income Statement'!D12 -> 0.067199638 | E80: =E81/'Income Statement'!E12 -> 0.093846979 | F80: =F81/'Income Statement'!F12 -> 0.08415695 | G80: =G81/'Income Statement'!G12 -> 0.050507264 | H80: =H81/'Income Statement'!H12 -> 0.020418939 | I80: 0.062 | J80: =I80+(INDEX($E$31:$G$31,MATCH($H$31,$E$9:$G$9,0))-I80)*1/4 -> 0.057 | K80: =I80+(INDEX($E$31:$G$31,MATCH($H$31,$E$9:$G$9,0))-I80)*2/4 -> 0.052 | L80: =I80+(INDEX($E$31:$G$31,MATCH($H$31,$E$9:$G$9,0))-I80)*3/4 -> 0.047 | M80: =INDEX($E$31:$G$31,MATCH($H$31,$E$9:$G$9,0)) -> 0.042
B81: Capex $ | C81: $M | D81: =-'Cash Flow'!D27 -> 133.566 | E81: =-'Cash Flow'!E27 -> 201.161 | F81: =-'Cash Flow'!F27 -> 184.775 | G81: =-'Cash Flow'!G27 -> 106.737 | H81: =-'Cash Flow'!H27 -> 45.669 | I81: =I80*'Income Statement'!I12 -> 146.42887 | J81: =J80*'Income Statement'!J12 -> 142.15817 | K81: =K80*'Income Statement'!K12 -> 136.95488 | L81: =L80*'Income Statement'!L12 -> 130.72678 | M81: =M80*'Income Statement'!M12 -> 123.37407
B82: SBC % of revenue | C82: % | D82: ='Income Statement'!D54/'Income Statement'!D12 -> 0.012527672 | E82: ='Income Statement'!E54/'Income Statement'!E12 -> 0.01152321 | F82: ='Income Statement'!F54/'Income Statement'!F12 -> 0.013754782 | G82: ='Income Statement'!G54/'Income Statement'!G12 -> 0.015094875 | H82: ='Income Statement'!H54/'Income Statement'!H12 -> 0.015335778 | I82: =H82 -> 0.015335778 | J82: =H82 -> 0.015335778 | K82: =H82 -> 0.015335778 | L82: =H82 -> 0.015335778 | M82: =H82 -> 0.015335778
B84: Capital Allocation
B85: Current market share price | C85: $ | D85: 30 | E85: 30 | F85: 35 | G85: 50 | H85: 130 | I85: ='DCF & Sensitivity'!D51 -> 80.76 | J85: =I85 -> 80.76 | K85: =J85 -> 80.76 | L85: =K85 -> 80.76 | M85: =L85 -> 80.76 | O85: Capital allocation block: drives buyback dollars (% of FCF) and dividend growth. Share count rolls forward dynamically using buyback dollars / share price net of SBC issuance / share price. Updates tie to IS row 42 (diluted shares) for EPS calc.
B86: Buybacks (as % of FCF) | C86: % | D86: =IFERROR(D87/'Cash Flow'!D52,0) -> 0 | E86: =IFERROR(E87/'Cash Flow'!E52,0) -> 1.5408064 | F86: =IFERROR(F87/'Cash Flow'!F52,0) -> 0.23474417 | G86: =IFERROR(G87/'Cash Flow'!G52,0) -> 0.064738753 | H86: =IFERROR(H87/'Cash Flow'!H52,0) -> 0.70143085 | I86: =D32 -> 0.6 | J86: =I86+(INDEX($E$32:$G$32,MATCH($H$32,$E$9:$G$9,0))-I86)*1/4 -> 0.575 | K86: =I86+(INDEX($E$32:$G$32,MATCH($H$32,$E$9:$G$9,0))-I86)*2/4 -> 0.55 | L86: =I86+(INDEX($E$32:$G$32,MATCH($H$32,$E$9:$G$9,0))-I86)*3/4 -> 0.525 | M86: =INDEX($E$32:$G$32,MATCH($H$32,$E$9:$G$9,0)) -> 0.5
B87: Share buybacks | C87: $M | D87: =-'Cash Flow'!D37 -> 0 | E87: =-'Cash Flow'!E37 -> 233.426 | F87: =-'Cash Flow'!F37 -> 102.344 | G87: =-'Cash Flow'!G37 -> 31.35 | H87: =-'Cash Flow'!H37 -> 423.108 | I87: =I86*'Cash Flow'!I52 -> 285.76832 | J87: =J86*'Cash Flow'!J52 -> 288.55536 | K87: =K86*'Cash Flow'!K52 -> 293.54024 | L87: =L86*'Cash Flow'!L52 -> 298.48571 | M87: =M86*'Cash Flow'!M52 -> 303.27596
B88: Dividends | C88: $M | D88: =-'Cash Flow'!D39 -> 127.11 | E88: =-'Cash Flow'!E39 -> 142.125 | F88: =-'Cash Flow'!F39 -> 158.323 | G88: =-'Cash Flow'!G39 -> 172.088 | H88: =-'Cash Flow'!H39 -> 183.352 | I88: =H88*1.05 -> 192.5196 | J88: =I88*1.05 -> 202.14558 | K88: =J88*1.05 -> 212.25286 | L88: =K88*1.05 -> 222.8655 | M88: =L88*1.05 -> 234.00878
B89: Diluted shares | C89: M | D89: ='Income Statement'!D42 -> 174.526 | E89: ='Income Statement'!E42 -> 172.893 | F89: ='Income Statement'!F42 -> 172.199 | G89: ='Income Statement'!G42 -> 172.405 | H89: ='Income Statement'!H42 -> 169.219 | I89: =H89-I87/I85+'Income Statement'!I54/I85 -> 166.12899 | J89: =I89-J87/J85+'Income Statement'!J54/J85 -> 163.02959 | K89: =J89-K87/K85+'Income Statement'!K54/K85 -> 159.895 | L89: =K89-L87/L85+'Income Statement'!L54/L85 -> 156.72721 | M89: =L89-M87/M85+'Income Statement'!M54/M85 -> 153.52974
B90: Total capital return (% of FCF) | C90: % | D90: =IFERROR((D87+D88)/'Cash Flow'!D52,0) -> 0.42596043 | E90: =IFERROR((E87+E88)/'Cash Flow'!E52,0) -> 2.4789499 | F90: =IFERROR((F87+F88)/'Cash Flow'!F52,0) -> 0.59788615 | G90: =IFERROR((G87+G88)/'Cash Flow'!G52,0) -> 0.42010598 | H90: =IFERROR((H87+H88)/'Cash Flow'!H52,0) -> 1.0053928 | I90: =IFERROR((I87+I88)/'Cash Flow'!I52,0) -> 1.0042147 | J90: =IFERROR((J87+J88)/'Cash Flow'!J52,0) -> 0.97781251 | K90: =IFERROR((K87+K88)/'Cash Flow'!K52,0) -> 0.9476936 | ... M90: =IFERROR((M87+M88)/'Cash Flow'!M52,0) -> 0.88580173
O92: DCF inputs: cost of equity (CAPM), pre-tax cost of debt (weighted from debt schedule), market values of debt and equity, and resulting WACC. Terminal growth rate and exit multiple drive perpetuity vs. multiple terminal value calculations.
B93: DCF ASSUMPTIONS
B94: Risk-Free Rate (10Y UST) | C94: % | D94: 0.0431
B95: Equity Risk Premium | C95: % | D95: 0.055
B96: Beta (raw, 5-yr regression) | C96: x | D96: 1.25
B97: Adjusted beta (Blume) | C97: x | D97: =D96*0.67+0.33 -> 1.1675
B98: Cost of Equity (CAPM) | C98: % | D98: =D94+D97*D95 -> 0.1073125
B99: Pre-tax Cost of Debt | C99: % | D99: =IFERROR(SUMPRODUCT($C$61:$C$63,H61:H63)/H64,0) -> 0.027050202
B100: Market Value of Debt ($M) | C100: $M | D100: =H64 -> 24.7
B101: Market Value of Equity ($M) | C101: $M | D101: ='Income Statement'!H42*'DCF & Sensitivity'!D51 -> 13666.126
B102: Debt / Total Cap | C102: % | D102: =D100/(D100+D101) -> 0.0018041278
B103: Equity / Total Cap | C103: % | D103: =D101/(D101+D100) -> 0.99819587
B104: WACC | C104: % | D104: =INDEX($E$37:$G$37,MATCH($H$37,$E$9:$G$9,0)) -> 0.08
B105: Terminal Growth Rate | C105: % | D105: =INDEX($E$35:$G$35,MATCH($H$35,$E$9:$G$9,0)) -> 0.025
B106: Exit EV/EBITDA | C106: x | D106: =INDEX($E$36:$G$36,MATCH($H$36,$E$9:$G$9,0)) -> 15

Sheet Revenue Build
B2: Revenue Build
B3: Graco Inc. (NYSE: GGG)
B4: All amounts in $ millions unless noted
B6: Revenue Build Overview
B7: This tab is a high-level segment-level revenue bridge: BoP Revenue × (1 + Organic % + Acquisitions % + FX %) = EoP Revenue, applied separately to each segment (Contractor, Industrial, Expansion) and rolled to consolidated. Historicals tie to filed numbers; forecasts pull growth assumptions from the Assumptions tab via a scenario switch. This enables an easier understanding of the model and quick scenario analysis - flex one growth rate and watch the total roll forward. Graco's investor matierials only break out metrics at the business unit level. What this build cannot do is explain the drivers behind growth — price vs. volume, which tier, which sales channel, which geography, aftermarket vs. new equipment, or how M&A integrates into the revenue base. The growth rate is the assumption; there is no underlying logic within this model supporting the growth rates at a more granular level. An ideal revenue decomposition is illustrated on the orange-colored tabs (Rev Build - PF1 - Airless Spray, Rev Build - PF2 - Powder Coat, Rev Build - BU 1 - Contractor). Those derive segment growth from Units × ASP by tier, Installed Base × Attach Rate for aftermarket, Service & Integration contracts, deal-by-deal M&A, and FX on a weighted currency-exposure base. Inputs are real business mechanics, not top-line growth rates. Those tabs demonstrate that we would have a build for each product family feeding into business segment tabs, which would roll up to a consolidated company-level view like the one presented below. In that architecture, the growth rates on this tab stop being standalone inputs and become outputs of the bottoms-up work — this tab becomes the presentation layer, the bottoms-up tabs become the justification layer.
C13: Units | D13: FY21A | E13: FY22A | F13: FY23A | G13: FY24A | H13: FY25A | I13: FY26E | J13: FY27E | K13: FY28E | L13: FY29E | M13: FY30E
B15: Consolidated Revenue Bridge
B16: BOP Revenue | C16: $M | D16: 1842 | E16: =D21 -> 1989.36 | F16: =E21 -> 2148.5088 | G16: =F21 -> 2191.479 | H16: =G21 -> 2103.8198
B17: Organic Growth % | C17: % | D17: 0.11 | E17: 0.11 | F17: 0.02 | G17: -0.04 | H17: 0
B18: Acquisitions Growth % | C18: % | D18: 0.01 | E18: 0.01 | F18: 0 | G18: 0.01 | H18: 0.05
B19: Currency % | C19: % | D19: -0.04 | E19: -0.04 | F19: 0 | G19: -0.01 | H19: 0.01
B20: Total Growth % | C20: % | D20: =SUM(D17:D19) -> 0.08 | E20: =SUM(E17:E19) -> 0.08 | F20: =SUM(F17:F19) -> 0.02 | G20: =SUM(G17:G19) -> -0.04 | H20: =SUM(H17:H19) -> 0.06
B21: Total Revenue (Growth %) | C21: $M | D21: =D16*(D20+1) -> 1989.36 | E21: =E16*(E20+1) -> 2148.5088 | F21: =F16*(F20+1) -> 2191.479 | G21: =G16*(G20+1) -> 2103.8198 | H21: =H16*(H20+1) -> 2230.049
B23: Revenue by Geography
B24: USA | C24: $M | E24: 1116 | F24: 1162 | G24: 1329.3 | H24: 1353
B25: EMEA | C25: $M | E25: 451.8 | F25: 463.9 | G25: 454.2 | H25: 527.5
B26: Asia Pacific | C26: $M | E26: 409.8 | F26: 393.7 | G26: 329.8 | H26: 356.1
B27: Other Americas | C27: $M | E27: 165.9 | F27: 176 | G27: 0 | H27: 0
B28: Total Revenue (Geo) | C28: $M | E28: =SUM(E24:E27) -> 2143.5 | F28: =SUM(F24:F27) -> 2195.6 | G28: =SUM(G24:G27) -> 2113.3
B30: Segment Revenue (Old Naming)
B31: Contractor | C31: $M | E31: 999.1 | F31: 985.7 | G31: 988.9
B32: Industrial | C32: $M | E32: 649.3 | F32: 662.8 | G32: 619.6
B33: Process | C33: $M | E33: 495.1 | F33: 547.1 | G33: 504.8
B34: Total Revenue (Old Segments) | C34: $M | E34: =SUM(E31:E33) -> 2143.5 | F34: =SUM(F31:F33) -> 2195.6 | G34: =SUM(G31:G33) -> 2113.3
B36: Segment Revenue
B37: › Contractor
B38: BoP Revenue | E38: =D43 -> 987.6 | F38: =E43 -> 999.1 | G38: =F43 -> 985.7 | H38: =G43 -> 988.9 | I38: =H43 -> 1071.9 | J38: =I43 -> 1125.495 | K38: =J43 -> 1181.7698 | L38: =K43 -> 1240.8582 | M38: =L43 -> 1302.9011
B39: Organic Growth % | E39: 0.04 | F39: -0.01 | G39: -0.01 | H39: -0.02 | I39: =Assumptions!$D$12 -> 0.01 | J39: =$I39+(INDEX(Assumptions!$E$12:$G$12,MATCH(Assumptions!$H$12,Assumptions!$E$9:$G$9,0))-$I39)*(COLUMN()-COLUMN($I39))/4 -> 0.01 | K39: =$I39+(INDEX(Assumptions!$E$12:$G$12,MATCH(Assumptions!$H$12,Assumptions!$E$9:$G$9,0))-$I39)*(COLUMN()-COLUMN($I39))/4 -> 0.01 | L39: =$I39+(INDEX(Assumptions!$E$12:$G$12,MATCH(Assumptions!$H$12,Assumptions!$E$9:$G$9,0))-$I39)*(COLUMN()-COLUMN($I39))/4 -> 0.01 | M39: =$I39+(INDEX(Assumptions!$E$12:$G$12,MATCH(Assumptions!$H$12,Assumptions!$E$9:$G$9,0))-$I39)*(COLUMN()-COLUMN($I39))/4 -> 0.01
B40: Acquisitions % | E40: 0 | F40: 0 | G40: 0.02 | H40: 0.1 | I40: =Assumptions!$D$13 -> 0.03 | J40: =$I40+(INDEX(Assumptions!$E$13:$G$13,MATCH(Assumptions!$H$13,Assumptions!$E$9:$G$9,0))-$I40)*(COLUMN()-COLUMN($I40))/4 -> 0.03 | K40: =$I40+(INDEX(Assumptions!$E$13:$G$13,MATCH(Assumptions!$H$13,Assumptions!$E$9:$G$9,0))-$I40)*(COLUMN()-COLUMN($I40))/4 -> 0.03 | L40: =$I40+(INDEX(Assumptions!$E$13:$G$13,MATCH(Assumptions!$H$13,Assumptions!$E$9:$G$9,0))-$I40)*(COLUMN()-COLUMN($I40))/4 -> 0.03 | M40: =$I40+(INDEX(Assumptions!$E$13:$G$13,MATCH(Assumptions!$H$13,Assumptions!$E$9:$G$9,0))-$I40)*(COLUMN()-COLUMN($I40))/4 -> 0.03
B41: Currency % | E41: -0.03 | F41: 0 | G41: -0.01 | H41: 0 | I41: =Assumptions!$D$20 -> 0.01 | J41: =$I41+(INDEX(Assumptions!$E$20:$G$20,MATCH(Assumptions!$H$20,Assumptions!$E$9:$G$9,0))-$I41)*(COLUMN()-COLUMN($I41))/4 -> 0.01 | K41: =$I41+(INDEX(Assumptions!$E$20:$G$20,MATCH(Assumptions!$H$20,Assumptions!$E$9:$G$9,0))-$I41)*(COLUMN()-COLUMN($I41))/4 -> 0.01 | L41: =$I41+(INDEX(Assumptions!$E$20:$G$20,MATCH(Assumptions!$H$20,Assumptions!$E$9:$G$9,0))-$I41)*(COLUMN()-COLUMN($I41))/4 -> 0.01 | M41: =$I41+(INDEX(Assumptions!$E$20:$G$20,MATCH(Assumptions!$H$20,Assumptions!$E$9:$G$9,0))-$I41)*(COLUMN()-COLUMN($I41))/4 -> 0.01
B42: Total Growth % | E42: =SUM(E39:E41) -> 0.01 | F42: =SUM(F39:F41) -> -0.01 | G42: =SUM(G39:G41) -> 0 | H42: =SUM(H39:H41) -> 0.08 | I42: =SUM(I39:I41) -> 0.05 | J42: =SUM(J39:J41) -> 0.05 | K42: =SUM(K39:K41) -> 0.05 | L42: =SUM(L39:L41) -> 0.05 | M42: =SUM(M39:M41) -> 0.05
B43: EOP Revenue | D43: 987.6 | E43: 999.1 | F43: 985.7 | G43: 988.9 | H43: 1071.9 | I43: =I38*(1+I42) -> 1125.495 | J43: =J38*(1+J42) -> 1181.7698 | K43: =K38*(1+K42) -> 1240.8582 | L43: =L38*(1+L42) -> 1302.9011 | M43: =M38*(1+M42) -> 1368.0462
B44: Check | E44: =(E38*(E42+1))-E43 -> -1.624 | F44: =(F38*(F42+1))-F43 -> 3.409 | G44: =(G38*(G42+1))-G43 -> -3.2 | H44: =(H38*(H42+1))-H43 -> -3.888
B45: › Industrial
B46: BoP Revenue | E46: =D51 -> 864.6 | F46: =E51 -> 972.7 | G46: =F51 -> 1018.2 | H46: =G51 -> 958 | I46: =H51 -> 996.8 | J46: =I51 -> 1056.608 | K46: =J51 -> 1120.0045 | L46: =K51 -> 1187.2047 | M46: =L51 -> 1258.437
B47: Organic Growth % | E47: 0.18 | F47: 0.05 | G47: -0.05 | H47: 0.02 | I47: =Assumptions!$D$15 -> 0.03 | J47: =$I47+(INDEX(Assumptions!$E$15:$G$15,MATCH(Assumptions!$H$15,Assumptions!$E$9:$G$9,0))-$I47)*(COLUMN()-COLUMN($I47))/4 -> 0.03 | K47: =$I47+(INDEX(Assumptions!$E$15:$G$15,MATCH(Assumptions!$H$15,Assumptions!$E$9:$G$9,0))-$I47)*(COLUMN()-COLUMN($I47))/4 -> 0.03 | L47: =$I47+(INDEX(Assumptions!$E$15:$G$15,MATCH(Assumptions!$H$15,Assumptions!$E$9:$G$9,0))-$I47)*(COLUMN()-COLUMN($I47))/4 -> 0.03 | M47: =$I47+(INDEX(Assumptions!$E$15:$G$15,MATCH(Assumptions!$H$15,Assumptions!$E$9:$G$9,0))-$I47)*(COLUMN()-COLUMN($I47))/4 -> 0.03
B48: Acquisitions % | E48: 0 | F48: 0 | G48: 0 | H48: 0.01 | I48: =Assumptions!$D$16 -> 0.02 | J48: =$I48+(INDEX(Assumptions!$E$16:$G$16,MATCH(Assumptions!$H$16,Assumptions!$E$9:$G$9,0))-$I48)*(COLUMN()-COLUMN($I48))/4 -> 0.02 | K48: =$I48+(INDEX(Assumptions!$E$16:$G$16,MATCH(Assumptions!$H$16,Assumptions!$E$9:$G$9,0))-$I48)*(COLUMN()-COLUMN($I48))/4 -> 0.02 | L48: =$I48+(INDEX(Assumptions!$E$16:$G$16,MATCH(Assumptions!$H$16,Assumptions!$E$9:$G$9,0))-$I48)*(COLUMN()-COLUMN($I48))/4 -> 0.02 | M48: =$I48+(INDEX(Assumptions!$E$16:$G$16,MATCH(Assumptions!$H$16,Assumptions!$E$9:$G$9,0))-$I48)*(COLUMN()-COLUMN($I48))/4 -> 0.02
B49: Currency % | E49: -0.05 | F49: 0 | G49: 0 | H49: 0.01 | I49: =Assumptions!$D$20 -> 0.01 | J49: =$I49+(INDEX(Assumptions!$E$20:$G$20,MATCH(Assumptions!$H$20,Assumptions!$E$9:$G$9,0))-$I49)*(COLUMN()-COLUMN($I49))/4 -> 0.01 | K49: =$I49+(INDEX(Assumptions!$E$20:$G$20,MATCH(Assumptions!$H$20,Assumptions!$E$9:$G$9,0))-$I49)*(COLUMN()-COLUMN($I49))/4 -> 0.01 | L49: =$I49+(INDEX(Assumptions!$E$20:$G$20,MATCH(Assumptions!$H$20,Assumptions!$E$9:$G$9,0))-$I49)*(COLUMN()-COLUMN($I49))/4 -> 0.01 | M49: =$I49+(INDEX(Assumptions!$E$20:$G$20,MATCH(Assumptions!$H$20,Assumptions!$E$9:$G$9,0))-$I49)*(COLUMN()-COLUMN($I49))/4 -> 0.01
B50: Total Growth % | E50: =SUM(E47:E49) -> 0.13 | F50: =SUM(F47:F49) -> 0.05 | G50: =SUM(G47:G49) -> -0.05 | H50: =SUM(H47:H49) -> 0.04 | I50: =SUM(I47:I49) -> 0.06 | J50: =SUM(J47:J49) -> 0.06 | K50: =SUM(K47:K49) -> 0.06 | L50: =SUM(L47:L49) -> 0.06 | M50: =SUM(M47:M49) -> 0.06
B51: EOP Revenue | D51: 864.6 | E51: 972.7 | F51: 1018.2 | G51: 958 | H51: 996.8 | I51: =I46*(1+I50) -> 1056.608 | J51: =J46*(1+J50) -> 1120.0045 | K51: =K46*(1+K50) -> 1187.2047 | L51: =L46*(1+L50) -> 1258.437 | M51: =M46*(1+M50) -> 1333.9433
B52: Check | E52: =(E46*(E50+1))-E51 -> 4.298 | F52: =(F46*(F50+1))-F51 -> 3.135 | G52: =(G46*(G50+1))-G51 -> 9.29 | H52: =(H46*(H50+1))-H51 -> -0.48 | I52: =0 -> 0 | J52: 0 | K52: 0 | L52: 0 | M52: 0
B53: › Expansion
B54: BoP Revenue | E54: =D59 -> 135.4 | F54: =E59 -> 171.7 | G54: =F59 -> 191.7 | H54: =G59 -> 166.4 | I54: =H59 -> 167.9 | J54: =I59 -> 179.653 | K54: =J59 -> 192.22871 | L54: =K59 -> 205.68472 | M54: =L59 -> 220.08265
B55: Organic Growth % | E55: 0.22 | F55: 0.11 | G55: -0.13 | H55: 0 | I55: =Assumptions!$D$18 -> 0.03 | J55: =$I55+(INDEX(Assumptions!$E$18:$G$18,MATCH(Assumptions!$H$18,Assumptions!$E$9:$G$9,0))-$I55)*(COLUMN()-COLUMN($I55))/4 -> 0.03 | K55: =$I55+(INDEX(Assumptions!$E$18:$G$18,MATCH(Assumptions!$H$18,Assumptions!$E$9:$G$9,0))-$I55)*(COLUMN()-COLUMN($I55))/4 -> 0.03 | L55: =$I55+(INDEX(Assumptions!$E$18:$G$18,MATCH(Assumptions!$H$18,Assumptions!$E$9:$G$9,0))-$I55)*(COLUMN()-COLUMN($I55))/4 -> 0.03 | M55: =$I55+(INDEX(Assumptions!$E$18:$G$18,MATCH(Assumptions!$H$18,Assumptions!$E$9:$G$9,0))-$I55)*(COLUMN()-COLUMN($I55))/4 -> 0.03
B56: Acquisitions % | E56: 0.07 | F56: 0.01 | G56: 0 | H56: 0.01 | I56: =Assumptions!$D$19 -> 0.03 | J56: =$I56+(INDEX(Assumptions!$E$19:$G$19,MATCH(Assumptions!$H$19,Assumptions!$E$9:$G$9,0))-$I56)*(COLUMN()-COLUMN($I56))/4 -> 0.03 | K56: =$I56+(INDEX(Assumptions!$E$19:$G$19,MATCH(Assumptions!$H$19,Assumptions!$E$9:$G$9,0))-$I56)*(COLUMN()-COLUMN($I56))/4 -> 0.03 | L56: =$I56+(INDEX(Assumptions!$E$19:$G$19,MATCH(Assumptions!$H$19,Assumptions!$E$9:$G$9,0))-$I56)*(COLUMN()-COLUMN($I56))/4 -> 0.03 | M56: =$I56+(INDEX(Assumptions!$E$19:$G$19,MATCH(Assumptions!$H$19,Assumptions!$E$9:$G$9,0))-$I56)*(COLUMN()-COLUMN($I56))/4 -> 0.03
B57: Currency % | E57: -0.02 | F57: 0 | G57: 0 | H57: 0 | I57: =Assumptions!$D$20 -> 0.01 | J57: =$I57+(INDEX(Assumptions!$E$20:$G$20,MATCH(Assumptions!$H$20,Assumptions!$E$9:$G$9,0))-$I57)*(COLUMN()-COLUMN($I57))/4 -> 0.01 | K57: =$I57+(INDEX(Assumptions!$E$20:$G$20,MATCH(Assumptions!$H$20,Assumptions!$E$9:$G$9,0))-$I57)*(COLUMN()-COLUMN($I57))/4 -> 0.01 | L57: =$I57+(INDEX(Assumptions!$E$20:$G$20,MATCH(Assumptions!$H$20,Assumptions!$E$9:$G$9,0))-$I57)*(COLUMN()-COLUMN($I57))/4 -> 0.01 | M57: =$I57+(INDEX(Assumptions!$E$20:$G$20,MATCH(Assumptions!$H$20,Assumptions!$E$9:$G$9,0))-$I57)*(COLUMN()-COLUMN($I57))/4 -> 0.01
B58: Total Growth % | E58: =SUM(E55:E57) -> 0.27 | F58: =SUM(F55:F57) -> 0.12 | G58: =SUM(G55:G57) -> -0.13 | H58: =SUM(H55:H57) -> 0.01 | I58: =SUM(I55:I57) -> 0.07 | J58: =SUM(J55:J57) -> 0.07 | K58: =SUM(K55:K57) -> 0.07 | L58: =SUM(L55:L57) -> 0.07 | M58: =SUM(M55:M57) -> 0.07
B59: EOP Revenue | D59: 135.4 | E59: 171.7 | F59: 191.7 | G59: 166.4 | H59: 167.9 | I59: =I54*(1+I58) -> 179.653 | J59: =J54*(1+J58) -> 192.22871 | K59: =K54*(1+K58) -> 205.68472 | L59: =L54*(1+L58) -> 220.08265 | M59: =M54*(1+M58) -> 235.48844
B60: Check | E60: =(E54*(E58+1))-E59 -> 0.258 | F60: =(F54*(F58+1))-F59 -> 0.604 | G60: =(G54*(G58+1))-G59 -> 0.379 | H60: =(H54*(H58+1))-H59 -> 0.164 | I60: 0 | J60: 0 | K60: 0 | L60: 0 | M60: 0
B61: Total Revenue | C61: $M | D61: =SUM(D43,D51,D59) -> 1987.6 | E61: =SUM(E43,E51,E59) -> 2143.5 | F61: =SUM(F43,F51,F59) -> 2195.6 | G61: =SUM(G43,G51,G59) -> 2113.3 | H61: =SUM(H43,H51,H59) -> 2236.6 | I61: =SUM(I43,I51,I59) -> 2361.756 | J61: =SUM(J43,J51,J59) -> 2494.0029 | K61: =SUM(K43,K51,K59) -> 2633.7477 | ... M61: =SUM(M43,M51,M59) -> 2937.4779
B62: YoY growth | C62: % | E62: =IFERROR(E61/D61-1,0) -> 0.078436305 | F62: =IFERROR(F61/E61-1,0) -> 0.024306042 | G62: =IFERROR(G61/F61-1,0) -> -0.037484059 | H62: =IFERROR(H61/G61-1,0) -> 0.058344769 | I62: =IFERROR(I61/H61-1,0) -> 0.055958151 | J62: =IFERROR(J61/I61-1,0) -> 0.055995175 | K62: =IFERROR(K61/J61-1,0) -> 0.056032318 | L62: =IFERROR(L61/K61-1,0) -> 0.05606958 | M62: =IFERROR(M61/L61-1,0) -> 0.056106959

Sheet Income Statement
B2: Income Statement
B3: Graco Inc. (NYSE: GGG)
B4: All amounts in $ millions unless noted
C6: Units | D6: =IF('Cover Page'!$C$63+0<'Cover Page'!$C$64,"FY"&TEXT(MOD('Cover Page'!$C$63+0,100),"00")&"A","FY"&TEXT(MOD('Cover Page'!$C$63+0,100),"00")&"E") -> FY21A | E6: =IF('Cover Page'!$C$63+1<'Cover Page'!$C$64,"FY"&TEXT(MOD('Cover Page'!$C$63+1,100),"00")&"A","FY"&TEXT(MOD('Cover Page'!$C$63+1,100),"00")&"E") -> FY22A | F6: =IF('Cover Page'!$C$63+2<'Cover Page'!$C$64,"FY"&TEXT(MOD('Cover Page'!$C$63+2,100),"00")&"A","FY"&TEXT(MOD('Cover Page'!$C$63+2,100),"00")&"E") -> FY23A | G6: =IF('Cover Page'!$C$63+3<'Cover Page'!$C$64,"FY"&TEXT(MOD('Cover Page'!$C$63+3,100),"00")&"A","FY"&TEXT(MOD('Cover Page'!$C$63+3,100),"00")&"E") -> FY24A | H6: =IF('Cover Page'!$C$63+4<'Cover Page'!$C$64,"FY"&TEXT(MOD('Cover Page'!$C$63+4,100),"00")&"A","FY"&TEXT(MOD('Cover Page'!$C$63+4,100),"00")&"E") -> FY25A | I6: =IF('Cover Page'!$C$63+5<'Cover Page'!$C$64,"FY"&TEXT(MOD('Cover Page'!$C$63+5,100),"00")&"A","FY"&TEXT(MOD('Cover Page'!$C$63+5,100),"00")&"E") -> FY26E | J6: =IF('Cover Page'!$C$63+6<'Cover Page'!$C$64,"FY"&TEXT(MOD('Cover Page'!$C$63+6,100),"00")&"A","FY"&TEXT(MOD('Cover Page'!$C$63+6,100),"00")&"E") -> FY27E | K6: =IF('Cover Page'!$C$63+7<'Cover Page'!$C$64,"FY"&TEXT(MOD('Cover Page'!$C$63+7,100),"00")&"A","FY"&TEXT(MOD('Cover Page'!$C$63+7,100),"00")&"E") -> FY28E | L6: =IF('Cover Page'!$C$63+8<'Cover Page'!$C$64,"FY"&TEXT(MOD('Cover Page'!$C$63+8,100),"00")&"A","FY"&TEXT(MOD('Cover Page'!$C$63+8,100),"00")&"E") -> FY29E | M6: =IF('Cover Page'!$C$63+9<'Cover Page'!$C$64,"FY"&TEXT(MOD('Cover Page'!$C$63+9,100),"00")&"A","FY"&TEXT(MOD('Cover Page'!$C$63+9,100),"00")&"E") -> FY30E | O6: Notes
B8: Revenue
B9: Contractor | C9: $M | D9: ='Revenue Build'!D43 -> 987.6 | E9: ='Revenue Build'!E43 -> 999.1 | F9: ='Revenue Build'!F43 -> 985.7 | G9: ='Revenue Build'!G43 -> 988.9 | H9: ='Revenue Build'!H43 -> 1071.9 | I9: ='Revenue Build'!I43 -> 1125.495 | J9: ='Revenue Build'!J43 -> 1181.7698 | K9: ='Revenue Build'!K43 -> 1240.8582 | ... M9: ='Revenue Build'!M43 -> 1368.0462 | O9: Graco's three reporting segments. Contractor (~48% of sales) sells paint sprayers and dispensing equipment to professional contractors. Industrial (~45%) supplies fluid handling and finishing systems for manufacturing and process applications. Expansion Markets (~7%) covers semiconductor pumps, oil & gas valves, and environmental remediation. Forecast pulls segment-level revenue from the Revenue Build tab, which scenarios growth rates by segment.
B10: Industrial | C10: $M | D10: ='Revenue Build'!D51 -> 864.6 | E10: ='Revenue Build'!E51 -> 972.7 | F10: ='Revenue Build'!F51 -> 1018.2 | G10: ='Revenue Build'!G51 -> 958 | H10: ='Revenue Build'!H51 -> 996.8 | I10: ='Revenue Build'!I51 -> 1056.608 | J10: ='Revenue Build'!J51 -> 1120.0045 | K10: ='Revenue Build'!K51 -> 1187.2047 | ... M10: ='Revenue Build'!M51 -> 1333.9433
B11: Expansion | C11: $M | D11: ='Revenue Build'!D59 -> 135.4 | E11: ='Revenue Build'!E59 -> 171.7 | F11: ='Revenue Build'!F59 -> 191.7 | G11: ='Revenue Build'!G59 -> 166.4 | H11: ='Revenue Build'!H59 -> 167.9 | I11: ='Revenue Build'!I59 -> 179.653 | J11: ='Revenue Build'!J59 -> 192.22871 | K11: ='Revenue Build'!K59 -> 205.68472 | ... M11: ='Revenue Build'!M59 -> 235.48844
B12: Total revenues | C12: $M | D12: =SUM(D9:D11) -> 1987.6 | E12: =SUM(E9:E11) -> 2143.5 | F12: =SUM(F9:F11) -> 2195.6 | G12: =SUM(G9:G11) -> 2113.3 | H12: =SUM(H9:H11) -> 2236.6 | I12: =SUM(I9:I11) -> 2361.756 | J12: =SUM(J9:J11) -> 2494.0029 | K12: =SUM(K9:K11) -> 2633.7477 | ... M12: =SUM(M9:M11) -> 2937.4779
B13: YoY growth % | C13: % | D13: ="-" -> - | E13: =E12/D12-1 -> 0.078436305 | F13: =F12/E12-1 -> 0.024306042 | G13: =G12/F12-1 -> -0.037484059 | H13: =H12/G12-1 -> 0.058344769 | I13: =I12/H12-1 -> 0.055958151 | J13: =J12/I12-1 -> 0.055995175 | K13: =K12/J12-1 -> 0.056032318 | L13: =L12/K12-1 -> 0.05606958 | M13: =M12/L12-1 -> 0.056106959
B15: Gross Profit
B16: Cost of products sold | C16: $M | D16: 953.7 | E16: 1086.1 | F16: 1034.6 | G16: 990.9 | H16: 1063.4 | I16: =Assumptions!I52*I12 -> 1122.9059 | J16: =Assumptions!J52*J12 -> 1185.5003 | K16: =Assumptions!K52*K12 -> 1251.6278 | L16: =Assumptions!L52*L12 -> 1321.4905 | M16: =Assumptions!M52*M12 -> 1395.302 | O16: Cost of Products Sold includes raw materials, direct labor, manufacturing overhead, freight. Graco's gross margin runs historically at ~52-53%, well above peers like IDEX (~44-45%), Watts Water (~37-38%), and Lincoln Electric (~35%) and roughly in line with Nordson (~55%)
B17: Gross Margin % | C17: % | D17: =D18/D12 -> 0.52017509 | E17: =E18/E12 -> 0.49330534 | F17: =F18/F12 -> 0.52878484 | G17: =G18/G12 -> 0.53111248 | H17: =H18/H12 -> 0.52454619 | I17: =I18/I12 -> 0.52454619 | J17: =J18/J12 -> 0.52465964 | K17: =K18/K12 -> 0.52477309 | ... M17: =M18/M12 -> 0.525
B18: Gross Profit | C18: $M | D18: =D12-D16 -> 1033.9 | E18: =E12-E16 -> 1057.4 | F18: =F12-F16 -> 1161 | G18: =G12-G16 -> 1122.4 | H18: =H12-H16 -> 1173.2 | I18: =I12-I16 -> 1238.8501 | J18: =J12-J16 -> 1308.5027 | K18: =K12-K16 -> 1382.1199 | ... M18: =M12-M16 -> 1542.1759
B20: Operating Expenses
B21: Product development | C21: $M | D21: 79.7 | E21: 80 | F21: 82.8 | G21: 87.2 | H21: 82.3 | I21: =Assumptions!I54*I12 -> 89.746728 | J21: =Assumptions!J54*J12 -> 92.521755 | K21: =Assumptions!K54*K12 -> 98.498113 | L21: =Assumptions!L54*L12 -> 104.85743 | M21: =Assumptions!M54*M12 -> 111.62416 | O21: Three main buckets: Product Development (~3.7-4.1% of revenue) is R&D for new equipment platforms. Selling, Marketing & Distribution (~12-13% of revenue) covers the global sales force, channel partners, and distribution. G&A (~7-9% of revenue) is corporate overhead. 'Other Operating Items' captures contingent consideration adjustments, impairments, and one-time charges. FY25 operating margin was 27.9%, expanding from 26.7% in FY21 as the business scaled.
B22: % of revenue | C22: % | D22: =D21/D$12 -> 0.040098611 | E22: =E21/E$12 -> 0.037322137 | F22: =F21/F$12 -> 0.037711787 | G22: =G21/G$12 -> 0.04126248 | H22: =H21/H$12 -> 0.036796924 | I22: =I21/I12 -> 0.038 | J22: =J21/J12 -> 0.037097693 | K22: =K21/K12 -> 0.037398462 | L22: =L21/L12 -> 0.037699231 | M22: =M21/M12 -> 0.038
B23: Selling, marketing, & distribution | C23: $M | D23: 271.5 | E23: 250.9 | F23: 260.7 | G23: 273.7 | H23: 273.9 | I23: =Assumptions!I55*I12 -> 295.2195 | J23: =Assumptions!J55*J12 -> 307.00428 | K23: =Assumptions!K55*K12 -> 325.87712 | L23: =Assumptions!L55*L12 -> 345.91326 | M23: =Assumptions!M55*M12 -> 367.18474
B24: % of revenue | C24: % | D24: =D23/D$12 -> 0.1365969 | E24: =E23/E$12 -> 0.11705155 | F24: =F23/F$12 -> 0.11873747 | G24: =G23/G$12 -> 0.12951308 | H24: =H23/H$12 -> 0.12246267 | I24: =I23/I12 -> 0.125 | J24: =J23/J12 -> 0.123097 | K24: =K23/K12 -> 0.12373133 | L24: =L23/L12 -> 0.12436567 | M24: =M23/M12 -> 0.125
B25: General & admin | C25: $M | D25: 151.4 | E25: 153.8 | F25: 171.4 | G25: 191.4 | H25: 206.2 | I25: =Assumptions!I56*I12 -> 207.83453 | J25: =Assumptions!J56*J12 -> 227.31622 | K25: =Assumptions!K56*K12 -> 237.29212 | L25: =Assumptions!L56*L12 -> 247.68101 | M25: =Assumptions!M56*M12 -> 258.49806
B26: % of revenue | C26: % | D26: =D25/D$12 -> 0.076172268 | E26: =E25/E$12 -> 0.071751808 | F26: =F25/F$12 -> 0.078065221 | G26: =G25/G$12 -> 0.090569252 | H26: =H25/H$12 -> 0.092193508 | I26: =I25/I12 -> 0.088 | J26: =J25/J12 -> 0.091145131 | K26: =K25/K12 -> 0.090096754 | L26: =L25/L12 -> 0.089048377 | M26: =M25/M12 -> 0.088
B27: Other Op. items / contingent considerations | C27: $M | D27: 0 | E27: 0 | F27: -0.8 | G27: 0 | H27: -14.1 | I27: 0 | J27: 0 | K27: 0 | L27: 0 | M27: 0
B28: Total Operating Expenses | C28: $M | D28: =SUM(D21,D23,D25,D27) -> 502.6 | E28: =SUM(E21,E23,E25,E27) -> 484.7 | F28: =SUM(F21,F23,F25,F27) -> 514.1 | G28: =SUM(G21,G23,G25,G27) -> 552.3 | H28: =SUM(H21,H23,H25,H27) -> 548.3 | I28: =SUM(I21,I23,I25,I27) -> 592.80076 | J28: =SUM(J21,J23,J25,J27) -> 626.84226 | K28: =SUM(K21,K23,K25,K27) -> 661.66735 | ... M28: =SUM(M21,M23,M25,M27) -> 737.30695
B29: Operating Income (EBIT) | C29: $M | D29: =D18-D28 -> 531.3 | E29: =E18-E28 -> 572.7 | F29: =F18-F28 -> 646.9 | G29: =G18-G28 -> 570.1 | H29: =H18-H28 -> 624.9 | I29: =I18-I28 -> 646.04935 | J29: =J18-J28 -> 681.66042 | K29: =K18-K28 -> 720.45258 | ... M29: =M18-M28 -> 804.86894
B30: Operating margin % | C30: % | D30: =D29/D12 -> 0.26730731 | E30: =E29/E12 -> 0.26717985 | F30: =F29/F12 -> 0.29463472 | G30: =G29/G12 -> 0.26976766 | H30: =H29/H12 -> 0.2793973 | I30: =I29/I12 -> 0.27354619 | J30: =J29/J12 -> 0.27331982 | K30: =K29/K12 -> 0.27354654 | ... M30: =M29/M12 -> 0.274
B32: Below-the-line
B33: Interest expense | C33: $M | D33: 10.2 | E33: 9.9 | F33: 5.2 | G33: 2.8 | H33: 2.9 | I33: =Assumptions!I69 -> 0.66814 | J33: =Assumptions!J69 -> 0.66814 | K33: =Assumptions!K69 -> 0.66814 | L33: =Assumptions!L69 -> 0.66814 | M33: =Assumptions!M69 -> 0.66814 | O33: Two separate items between EBIT and pretax income. (1) Interest expense: cost of carrying Graco's small debt load (2) Other (income) / expense, non operating costs including pension/retirement plan returns, FX gains/losses, equity method investment income, gains on sale of buildings. This line is volatile: FY23 had a $42M pension settlement charge; FY24-FY25 had $19-22M of net gains. Therefore, we took 5 yr avg. for forecast. Effective tax rate has run 13-19%, held BELOW the ~21-23% statutory rate by OBBBA bonus depreciation and SBC excess tax benefits.
B34: Other (income) / expense, net | C34: $M | D34: 12.6 | E34: -2.9 | F34: 32.9 | G34: -22 | H34: -19.3 | I34: =AVERAGE($D$34:$H$34) -> 0.26 | J34: =AVERAGE($D$34:$H$34) -> 0.26 | K34: =AVERAGE($D$34:$H$34) -> 0.26 | L34: =AVERAGE($D$34:$H$34) -> 0.26 | M34: =AVERAGE($D$34:$H$34) -> 0.26
B35: Pre-tax income | C35: $M | D35: =D29-D33-D34 -> 508.5 | E35: =E29-E33-E34 -> 565.7 | F35: =F29-F33-F34 -> 608.8 | G35: =G29-G33-G34 -> 589.3 | H35: =H29-H33-H34 -> 641.3 | I35: =I29-I33-I34 -> 645.12121 | J35: =J29-J33-J34 -> 680.73228 | K35: =K29-K33-K34 -> 719.52444 | ... M35: =M29-M33-M34 -> 803.9408
B36: Income Tax Expense | C36: $M | D36: 68.6 | E36: 105.1 | F36: 102.3 | G36: 103.2 | H36: 119.4 | I36: =I35*$I$37 -> 122.57303 | J36: =J35*$I$37 -> 129.33913 | K36: =K35*$I$37 -> 136.70964 | L36: =L35*$I$37 -> 144.5046 | M36: =M35*$I$37 -> 152.74875
B37: Effective tax rate | C37: % | D37: =D36/D35 -> 0.13490659 | E37: =E36/E35 -> 0.18578752 | F37: =F36/F35 -> 0.16803548 | G37: =G36/G35 -> 0.17512303 | H37: =H36/H35 -> 0.18618431 | I37: 0.19 | J37: 0.19 | K37: 0.19 | L37: 0.19 | M37: 0.19
B38: Net Income | C38: $M | D38: =D35-D36 -> 439.9 | E38: =E35-E36 -> 460.6 | F38: =F35-F36 -> 506.5 | G38: =G35-G36 -> 486.1 | H38: =H35-H36 -> 521.9 | I38: =I35-I36 -> 522.54818 | J38: =J35-J36 -> 551.39315 | K38: =K35-K36 -> 582.8148 | ... M38: =M35-M36 -> 651.19205
B39: Net margin % | C39: % | D39: =D38/D12 -> 0.2213222 | E39: =E38/E12 -> 0.2148822 | F39: =F38/F12 -> 0.23068865 | G39: =G38/G12 -> 0.2300194 | H39: =H38/H12 -> 0.23334526 | I39: =I38/I12 -> 0.22125409 | J39: =J38/J12 -> 0.22108761 | K39: =K38/K12 -> 0.22128725 | ... M39: =M38/M12 -> 0.22168407
B41: EPS & Share Count
B42: Diluted shares outstanding | C42: M | D42: 174.526 | E42: 172.893 | F42: 172.199 | G42: 172.405 | H42: 169.219 | I42: =Assumptions!I89 -> 166.12899 | J42: =Assumptions!J89 -> 163.02959 | K42: =Assumptions!K89 -> 159.895 | L42: =Assumptions!L89 -> 156.72721 | M42: =Assumptions!M89 -> 153.52974 | O42: Diluted shares = basic shares + dilutive impact of stock options and RSUs. Graco's share count drifts down ~2% per year (buybacks > RSUs). Forecast assumes 2% annual share count reduction and EPS reaches ~$3.93 by FY30. Adjusted EPS strips out one-time items in historicals; in the forecast we don't model discrete charges so Adjusted = GAAP.
B43: Diluted EPS (GAAP) | C43: $ | D43: =D38/D42 -> 2.5205414 | E43: =E38/E42 -> 2.6640755 | F43: =F38/F42 -> 2.9413644 | G43: =G38/G42 -> 2.8195238 | H43: =H38/H42 -> 3.084169 | I43: =I38/I42 -> 3.1454364 | J43: =J38/J42 -> 3.3821661 | K43: =K38/K42 -> 3.6449846 | ... M43: =M38/M42 -> 4.2414716
B44: Diluted EPS growth | C44: % | D44: 0 | E44: =E43/D43-1 -> 0.05694575 | F44: =F43/E43-1 -> 0.10408447 | G44: =G43/F43-1 -> -0.041423143 | H44: =H43/G43-1 -> 0.09386168 | I44: =I43/H43-1 -> 0.019865103 | J44: =J43/I43-1 -> 0.075261334 | K44: =K43/J43-1 -> 0.077707147 | L44: =L43/K43-1 -> 0.07838292 | M44: =M43/L43-1 -> 0.07906566
B45: Adjusted Diluted EPS | C45: $ | D45: 2.44 | E45: 2.63 | F45: 3.04 | G45: 2.77 | H45: 3 | I45: =I43 -> 3.1454364 | J45: =J43 -> 3.3821661 | K45: =K43 -> 3.6449846 | L45: =L43 -> 3.9306891 | M45: =M43 -> 4.2414716
B47: EBITDA & SBC
B48: Operating income (EBIT) | C48: $M | D48: =D29 -> 531.3 | E48: =E29 -> 572.7 | F48: =F29 -> 646.9 | G48: =G29 -> 570.1 | H48: =H29 -> 624.9 | I48: =I29 -> 646.04935 | J48: =J29 -> 681.66042 | K48: =K29 -> 720.45258 | ... M48: =M29 -> 804.86894 | O48: EBITDA margin has expanded from 29.7% (FY21) to 33.4% (FY25) as fixed-cost leverage and acquisition-driven amortization both grew. Forecast EBITDA margin compresses slightly to ~31% by FY30 as amortization runs off (intangibles burn down without new M&A modeled). Stock-based compensation runs ~1.2-1.5% of revenue.
B49: (+) D&A | C49: $M | D49: 59.3 | E49: 66 | F49: 74.3 | G49: 86.7 | H49: 107.4 | I49: =I58+I59 -> 110.76741 | J49: =J58+J59 -> 107.33808 | K49: =K58+K59 -> 104.11119 | L49: =L58+L59 -> 101.09836 | M49: =M58+M59 -> 98.311903
B50: (+) Other (gains) & charges | C50: $M | D50: =-D27 -> 0 | E50: =-E27 -> 0 | F50: =-F27 -> 0.8 | G50: =-G27 -> 0 | H50: =-H27 -> 14.1 | I50: =-I27 -> 0 | J50: =-J27 -> 0 | K50: =-K27 -> 0 | ... M50: =-M27 -> 0
B51: Adjusted EBITDA | C51: $M | D51: =D48+D49+D50 -> 590.6 | E51: =E48+E49+E50 -> 638.7 | F51: =F48+F49+F50 -> 722 | G51: =G48+G49+G50 -> 656.8 | H51: =H48+H49+H50 -> 746.4 | I51: =I48+I49+I50 -> 756.81676 | J51: =J48+J49+J50 -> 788.9985 | K51: =K48+K49+K50 -> 824.56377 | ... M51: =M48+M49+M50 -> 903.18085
B52: EBITDA margin | C52: % | D52: =D51/D12 -> 0.29714228 | E52: =E51/E12 -> 0.29797061 | F52: =F51/F12 -> 0.3288395 | G52: =G51/G12 -> 0.31079355 | H52: =H51/H12 -> 0.33372083 | I52: =I51/I12 -> 0.32044663 | J52: =J51/J12 -> 0.31635829 | K52: =K51/K12 -> 0.31307622 | ... M52: =M51/M12 -> 0.30746813
B54: Stock-based compensation | C54: $M | D54: 24.9 | E54: 24.7 | F54: 30.2 | G54: 31.9 | H54: 34.3 | I54: =I12*Assumptions!I82 -> 36.219365 | J54: =J12*Assumptions!J82 -> 38.247474 | K54: =K12*Assumptions!K82 -> 40.390569 | L54: =L12*Assumptions!L82 -> 42.655251 | M54: =M12*Assumptions!M82 -> 45.048508
B55: SBC % of revenue | C55: % | D55: =D54/D12 -> 0.012527672 | E55: =E54/E12 -> 0.01152321 | F55: =F54/F12 -> 0.013754782 | G55: =G54/G12 -> 0.015094875 | H55: =H54/H12 -> 0.015335778 | I55: =I54/I12 -> 0.015335778 | J55: =J54/J12 -> 0.015335778 | K55: =K54/K12 -> 0.015335778 | ... M55: =M54/M12 -> 0.015335778
B57: D&A Detail
B58: Depreciation | C58: $M | D58: 50.3 | E58: 54.5 | F58: 56 | G58: 56 | H58: 60 | I58: =I12*0.027 -> 63.767412 | J58: =J12*0.027 -> 67.338079 | K58: =K12*0.027 -> 71.111188 | L58: =L12*0.027 -> 75.098362 | M58: =M12*0.027 -> 79.311903
B59: Amortization of intangibles | C59: $M | D59: 9 | E59: 11.5 | F59: 18.3 | G59: 30.7 | H59: 47.4 | I59: 47 | J59: =I59-7 -> 40 | K59: =J59-7 -> 33 | L59: =K59-7 -> 26 | M59: =L59-7 -> 19
B60: Total D&A (check) | C60: $M | D60: =(D58+D59)-D49 -> 0 | E60: =(E58+E59)-E49 -> 0 | F60: =(F58+F59)-F49 -> 0 | G60: =(G58+G59)-G49 -> 0 | H60: =(H58+H59)-H49 -> 0 | I60: =(I58+I59)-I49 -> 0 | J60: =(J58+J59)-J49 -> 0 | K60: =(K58+K59)-K49 -> 0 | ... M60: =(M58+M59)-M49 -> 0

Sheet Balance Sheet
B2: Balance Sheet
B3: Graco Inc. (NYSE: GGG)
B4: All amounts in $ millions unless noted
C6: Units | D6: =IF('Cover Page'!$C$63+0<'Cover Page'!$C$64,"FY"&TEXT(MOD('Cover Page'!$C$63+0,100),"00")&"A","FY"&TEXT(MOD('Cover Page'!$C$63+0,100),"00")&"E") -> FY21A | E6: =IF('Cover Page'!$C$63+1<'Cover Page'!$C$64,"FY"&TEXT(MOD('Cover Page'!$C$63+1,100),"00")&"A","FY"&TEXT(MOD('Cover Page'!$C$63+1,100),"00")&"E") -> FY22A | F6: =IF('Cover Page'!$C$63+2<'Cover Page'!$C$64,"FY"&TEXT(MOD('Cover Page'!$C$63+2,100),"00")&"A","FY"&TEXT(MOD('Cover Page'!$C$63+2,100),"00")&"E") -> FY23A | G6: =IF('Cover Page'!$C$63+3<'Cover Page'!$C$64,"FY"&TEXT(MOD('Cover Page'!$C$63+3,100),"00")&"A","FY"&TEXT(MOD('Cover Page'!$C$63+3,100),"00")&"E") -> FY24A | H6: =IF('Cover Page'!$C$63+4<'Cover Page'!$C$64,"FY"&TEXT(MOD('Cover Page'!$C$63+4,100),"00")&"A","FY"&TEXT(MOD('Cover Page'!$C$63+4,100),"00")&"E") -> FY25A | I6: =IF('Cover Page'!$C$63+5<'Cover Page'!$C$64,"FY"&TEXT(MOD('Cover Page'!$C$63+5,100),"00")&"A","FY"&TEXT(MOD('Cover Page'!$C$63+5,100),"00")&"E") -> FY26E | J6: =IF('Cover Page'!$C$63+6<'Cover Page'!$C$64,"FY"&TEXT(MOD('Cover Page'!$C$63+6,100),"00")&"A","FY"&TEXT(MOD('Cover Page'!$C$63+6,100),"00")&"E") -> FY27E | K6: =IF('Cover Page'!$C$63+7<'Cover Page'!$C$64,"FY"&TEXT(MOD('Cover Page'!$C$63+7,100),"00")&"A","FY"&TEXT(MOD('Cover Page'!$C$63+7,100),"00")&"E") -> FY28E | L6: =IF('Cover Page'!$C$63+8<'Cover Page'!$C$64,"FY"&TEXT(MOD('Cover Page'!$C$63+8,100),"00")&"A","FY"&TEXT(MOD('Cover Page'!$C$63+8,100),"00")&"E") -> FY29E | M6: =IF('Cover Page'!$C$63+9<'Cover Page'!$C$64,"FY"&TEXT(MOD('Cover Page'!$C$63+9,100),"00")&"A","FY"&TEXT(MOD('Cover Page'!$C$63+9,100),"00")&"E") -> FY30E
B8: Assets: | O8: Notes
B9: Current assets:
B10: Cash and cash equivalents | C10: $M | D10: 624.302 | E10: 339.196 | F10: 537.951 | G10: 675.336 | H10: 624.083 | I10: ='Cash Flow'!I46 -> 712.38418 | J10: ='Cash Flow'!J46 -> 813.85532 | K10: ='Cash Flow'!K46 -> 934.25151 | L10: ='Cash Flow'!L46 -> 1076.189 | M10: ='Cash Flow'!M46 -> 1242.5938 | O10: Cash on hand. Graco runs a large cash balance (~$600-700M). No marketable securities.
B11: Accounts receivable, net | C11: $M | D11: 325.132 | E11: 346.01 | F11: 354.439 | G11: 362.533 | H11: 393.753 | I11: =(Assumptions!I76*'Income Statement'!I12)/365 -> 412.86435 | J11: =(I11*'Income Statement'!J12)/'Income Statement'!I12 -> 435.98276 | K11: =(J11*'Income Statement'!K12)/'Income Statement'!J12 -> 460.41189 | L11: =(K11*'Income Statement'!L12)/'Income Statement'!K12 -> 486.22699 | M11: =(L11*'Income Statement'!M12)/'Income Statement'!L12 -> 513.50771 | O11: Mostly comprised from channel resellers - distributors, OEMs
B12: Inventories, net | C12: $M | D12: 382.301 | E12: 476.79 | F12: 438.349 | G12: 404.676 | H12: 401.138 | I12: =(Assumptions!I77*'Income Statement'!I16)/365 -> 423.7781 | J12: =(Assumptions!J77*'Income Statement'!J16)/365 -> 447.60476 | K12: =(Assumptions!K77*'Income Statement'!K16)/365 -> 472.78758 | L12: =(Assumptions!L77*'Income Statement'!L16)/365 -> 499.40469 | M12: =(Assumptions!M77*'Income Statement'!M16)/365 -> 527.53884 | O12: Raw materials, WIP, and finished goods. Inventory has been declining since FY22 peak as supply chain normalizes.
B13: Other current assets | C13: $M | D13: 31.886 | E13: 43.624 | F13: 35.07 | G13: 54.896 | H13: 52.907 | I13: =(H13/'Income Statement'!H12)*'Income Statement'!I12 -> 55.867578 | J13: =(H13/'Income Statement'!H12)*'Income Statement'!J12 -> 58.995893 | K13: =(H13/'Income Statement'!H12)*'Income Statement'!K12 -> 62.301569 | L13: =(H13/'Income Statement'!H12)*'Income Statement'!L12 -> 65.794792 | M13: =(H13/'Income Statement'!H12)*'Income Statement'!M12 -> 69.486338 | O13: Prepaid expenses, refundable income taxes, and miscellaneous short-term receivables. Forecast as % of revenue (scales with operating activity).
B14: Current assets | C14: $M | D14: =SUM(D10:D13) -> 1363.621 | E14: =SUM(E10:E13) -> 1205.62 | F14: =SUM(F10:F13) -> 1365.809 | G14: =SUM(G10:G13) -> 1497.441 | H14: =SUM(H10:H13) -> 1471.881 | I14: =SUM(I10:I13) -> 1604.8942 | J14: =SUM(J10:J13) -> 1756.4387 | K14: =SUM(K10:K13) -> 1929.7525 | ... M14: =SUM(M10:M13) -> 2353.1267
B16: Non-current assets:
B17: PP&E, net | C17: $M | D17: 451.061 | E17: 607.609 | F17: 741.713 | G17: 771.656 | H17: 755.064 | I17: =H17+Assumptions!I81-'Income Statement'!I58 -> 837.72546 | J17: =I17+Assumptions!J81-'Income Statement'!J58 -> 912.54555 | K17: =J17+Assumptions!K81-'Income Statement'!K58 -> 978.38924 | L17: =K17+Assumptions!L81-'Income Statement'!L58 -> 1034.0177 | M17: =L17+Assumptions!M81-'Income Statement'!M58 -> 1078.0798 | O17: Forecast roll-forward: prior + Capex - Depreciation. Reflects manufacturing facilities in MN, OH, MI, plus international sites. PPE is cumulative total CapEx spend - Acc. Dep
B18: Goodwill | C18: $M | D18: 356.255 | E18: 368.171 | F18: 370.228 | G18: 487.468 | H18: 585.304 | I18: =H18+(Assumptions!I33*0.55) -> 585.304 | J18: =I18+(Assumptions!J33*0.55) -> 585.304 | K18: =J18+(Assumptions!K33*0.55) -> 585.304 | L18: =K18+(Assumptions!L33*0.55) -> 585.304 | M18: =L18+(Assumptions!M33*0.55) -> 585.304 | O18: Excess of acquisition cost over fair value of net assets acquired. Held flat in forecast (no future M&A modeled). Step-ups from FY24 Corob ($230M) and FY25 Color Service / Radia acquisitions.
B19: Intangibles, net | C19: $M | D19: 149.74 | E19: 137.507 | F19: 126.258 | G19: 233.306 | H19: 303.851 | I19: =H19-'Income Statement'!I59+(Assumptions!I33*0.45) -> 256.851 | J19: =I19-'Income Statement'!J59+(Assumptions!J33*0.45) -> 216.851 | K19: =J19-'Income Statement'!K59+(Assumptions!K33*0.45) -> 183.851 | L19: =K19-'Income Statement'!L59+(Assumptions!L33*0.45) -> 157.851 | M19: =L19-'Income Statement'!M59+(Assumptions!M33*0.45) -> 138.851 | O19: Acquired customer relationships, technology, trademarks. Forecast roll-forward: prior - Amortization (assumes no new M&A). Runs off ~$7M/yr as ~7-yr useful life intangibles age.
B20: Operating lease assets | C20: $M | D20: 30.046 | E20: 29.785 | F20: 18.768 | G20: 19.678 | H20: 26.073 | I20: =H20 -> 26.073 | J20: =I20 -> 26.073 | K20: =J20 -> 26.073 | L20: =K20 -> 26.073 | M20: =L20 -> 26.073 | O20: Right-of-use asset for operating leases (ASC 842). Held flat in forecast — small (~$26M) and minimal impact.
B21: Deferred income taxes, net | C21: $M | D21: 55.786 | E21: 57.09 | F21: 61.381 | G21: 46.91 | H21: 35.975 | I21: =H21 -> 35.975 | J21: =I21 -> 35.975 | K21: =J21 -> 35.975 | L21: =K21 -> 35.975 | M21: =L21 -> 35.975 | O21: Net deferred tax asset position from temporary differences (mostly U.S. pension, SBC, inventory reserves). Held flat in forecast because its based on discrete events.
B22: Other non-current assets | C22: $M | D22: 36.689 | E22: 33.118 | F22: 37.85 | G22: 82.753 | H22: 96.122 | I22: =H22+((AVERAGE($D$22:$F$22)-H22)*1/5) -> 84.074733 | J22: =H22+((AVERAGE($D$22:$F$22)-H22)*2/5) -> 72.027467 | K22: =H22+((AVERAGE($D$22:$F$22)-H22)*3/5) -> 59.9802 | L22: =H22+((AVERAGE($D$22:$F$22)-H22)*4/5) -> 47.932933 | M22: =AVERAGE($D$22:$F$22) -> 35.885667 | O22: Catch-all: long-term notes receivable, minority equity investments in companies, indemnification escrow assets from acquisitions, and deferred long-term costs. Inflated FY24-25 likely high M&A activity tied escrow holdbacks and minority stakes from those deals. Forecast linear runoff to ~$36M baseline over 5 years as escrows release and items roll off.
B23: Total assets | C23: $M | D23: =D14+SUM(D17:D22) -> 2443.198 | E23: =E14+SUM(E17:E22) -> 2438.9 | F23: =F14+SUM(F17:F22) -> 2722.007 | G23: =G14+SUM(G17:G22) -> 3139.212 | H23: =H14+SUM(H17:H22) -> 3274.27 | I23: =I14+SUM(I17:I22) -> 3430.8974 | J23: =J14+SUM(J17:J22) -> 3605.2148 | K23: =K14+SUM(K17:K22) -> 3799.325 | ... M23: =M14+SUM(M17:M22) -> 4253.2952
B25: Liabilities + Equity:
B26: Current liabilities:
B27: Notes payable | C27: $M | D27: 43.489 | E27: 20.974 | F27: 30.036 | G27: 28.537 | H27: 23.072 | I27: =H27 -> 23.072 | J27: =I27 -> 23.072 | K27: =J27 -> 23.072 | L27: =K27 -> 23.072 | M27: =L27 -> 23.072 | O27: Short-term borrowings on bank lines of credit, primarily used to fund foreign subsidiary operations in local currency. A treasury / financing decision, not an operating one. Historically stable at $21-44M range with no clear trend; held flat at FY25 level (~$23M) since there is no clean economic driver.
B28: Current portion of LTD | C28: $M | D28: 75 | E28: 0 | F28: 0 | G28: 0 | H28: 1.624 | I28: =H28 -> 1.624 | J28: =I28 -> 1.624 | K28: =J28 -> 1.624 | L28: =K28 -> 1.624 | M28: =L28 -> 1.624 | O28: All LTD is maturing in NTM
B29: Trade accounts payable | C29: $M | D29: 78.432 | E29: 84.218 | F29: 72.214 | G29: 60.816 | H29: 78.573 | I29: =(Assumptions!I78*'Income Statement'!I16)/365 -> 82.988694 | J29: =(Assumptions!J78*'Income Statement'!J16)/365 -> 87.634697 | K29: =(Assumptions!K78*'Income Statement'!K16)/365 -> 92.544044 | L29: =(Assumptions!L78*'Income Statement'!L16)/365 -> 97.731853 | M29: =(Assumptions!M78*'Income Statement'!M16)/365 -> 103.21412 | O29: DPO well below industry norms (~50-60 days), suggesting it doesn't use suppliers as a cheap financing source, but gains discounts and strengthens relationship by paying fast. They can do this because consistent they got stockpile of cash.
B30: Salaries and incentives | C30: $M | D30: 82.941 | E30: 63.969 | F30: 64.802 | G30: 58.169 | H30: 73.42 | I30: =(H30/'Income Statement'!H12)*'Income Statement'!I12 -> 77.528447 | J30: =(H30/'Income Statement'!H12)*'Income Statement'!J12 -> 81.869666 | K30: =(H30/'Income Statement'!H12)*'Income Statement'!K12 -> 86.457014 | L30: =(H30/'Income Statement'!H12)*'Income Statement'!L12 -> 91.304622 | M30: =(H30/'Income Statement'!H12)*'Income Statement'!M12 -> 96.427447 | O30: Accrued bonus, commissions, and incentive comp. Forecast as % of revenue (scales with headcount and revenue base).
B31: Dividends payable | C31: $M | D31: 35.771 | E31: 39.963 | F31: 42.789 | G31: 46.558 | H31: 48.705 | I31: =H31 -> 48.705 | J31: =I31 -> 48.705 | K31: =J31 -> 48.705 | L31: =K31 -> 48.705 | M31: =L31 -> 48.705 | O31: Quarterly cash dividend declared but not yet paid. Held flat at FY25 level (≈ quarterly dividend run-rate × shares outstanding).
B32: Operating lease liability | C32: $M | D32: 23.527 | E32: 21.057 | F32: 11.785 | G32: 12.278 | H32: 18.131 | I32: =H32 -> 18.131 | J32: =I32 -> 18.131 | K32: =J32 -> 18.131 | L32: =K32 -> 18.131 | M32: =L32 -> 18.131 | O32: Held flat in forecast - small total (~$18M)
B33: Other current liabilities | C33: $M | D33: 191.159 | E33: 190.793 | F33: 185.359 | G33: 211.728 | H33: 241.867 | I33: =(H33/'Income Statement'!H12)*'Income Statement'!I12 -> 255.40143 | J33: =(H33/'Income Statement'!H12)*'Income Statement'!J12 -> 269.70268 | K33: =(H33/'Income Statement'!H12)*'Income Statement'!K12 -> 284.81474 | L33: =(H33/'Income Statement'!H12)*'Income Statement'!L12 -> 300.78419 | M33: =(H33/'Income Statement'!H12)*'Income Statement'!M12 -> 317.66027 | O33: Accrued warranties, customer rebates, deferred revenue, accrued professional fees, and miscellaneous accruals. Forecast as % of revenue.
B34: Current liabilities | C34: $M | D34: =SUM(D27:D33) -> 530.319 | E34: =SUM(E27:E33) -> 420.974 | F34: =SUM(F27:F33) -> 406.985 | G34: =SUM(G27:G33) -> 418.086 | H34: =SUM(H27:H33) -> 485.392 | I34: =SUM(I27:I33) -> 507.45057 | J34: =SUM(J27:J33) -> 530.73904 | K34: =SUM(K27:K33) -> 555.3478 | ... M34: =SUM(M27:M33) -> 608.83384
B36: Non-current liabilities:
B37: Long-term debt & finance leases | C37: $M | D37: 75 | E37: 75 | F37: 0 | G37: 0 | H37: 0 | I37: =H37 -> 0 | J37: =I37 -> 0 | K37: =J37 -> 0 | L37: =K37 -> 0 | M37: =L37 -> 0 | O37: Graco operates with minimal LT debt (mostly paid off after FY22); held at $0 in forecast (no new debt assumed).
B38: Retirement benefits and deferred comp | C38: $M | D38: 106.897 | E38: 61.672 | F38: 80.347 | G38: 80.381 | H38: 87.179 | I38: =H38 -> 87.179 | J38: =I38 -> 87.179 | K38: =J38 -> 87.179 | L38: =K38 -> 87.179 | M38: =L38 -> 87.179 | O38: Pension obligation + deferred compensation liability for executives. Held flat in forecast (assumes minimal pension contribution changes).
B39: Deferred income taxes | C39: $M | D39: 10.661 | E39: 9.443 | F39: 8.215 | G39: 37.822 | H39: 36.708 | I39: =H39 -> 36.708 | J39: =I39 -> 36.708 | K39: =J39 -> 36.708 | L39: =K39 -> 36.708 | M39: =L39 -> 36.708 | O39: Net deferred tax liability from temporary differences (intangible amortization, accelerated tax depreciation). Volatile, hard to forecast so held flat .
B40: Other non-current liabilities | C40: $M | D40: 10.978 | E40: 12.159 | F40: 2.235 | G40: 18.788 | H40: 11.06 | I40: =H40 -> 11.06 | J40: =I40 -> 11.06 | K40: =J40 -> 11.06 | L40: =K40 -> 11.06 | M40: =L40 -> 11.06 | O40: Uncertain tax positions, contingent consideration earnouts from acquisitions, miscellaneous LT obligations. Held flat in forecast.
B41: Total liabilities | C41: $M | D41: =D34+SUM(D37:D40) -> 733.855 | E41: =E34+SUM(E37:E40) -> 579.248 | F41: =F34+SUM(F37:F40) -> 497.782 | G41: =G34+SUM(G37:G40) -> 555.077 | H41: =H34+SUM(H37:H40) -> 620.339 | I41: =I34+SUM(I37:I40) -> 642.39757 | J41: =J34+SUM(J37:J40) -> 665.68604 | K41: =K34+SUM(K37:K40) -> 690.2948 | ... M41: =M34+SUM(M37:M40) -> 743.78084
B43: Shareholders' equity:
B44: Common stock ($1.00 stated value) | C44: $M | D44: 170.308 | E44: 167.702 | F44: 167.946 | G44: 169.394 | H44: 165.15 | I44: =H44 -> 165.15 | J44: =I44 -> 165.15 | K44: =J44 -> 165.15 | L44: =K44 -> 165.15 | M44: =L44 -> 165.15 | O44: Shares Outs. x 1.00 (bookeeping number, no insights here)
B45: Additional paid-in capital | C45: $M | D45: 742.288 | E45: 784.477 | F45: 863.336 | G45: 955.051 | H45: 994.566 | I45: =MAX(0, H45+'Income Statement'!I54+'Cash Flow'!I36+'Cash Flow'!I37+'Cash Flow'!I38) -> 797.10625 | J45: =MAX(0, I45+'Income Statement'!J54+'Cash Flow'!J36+'Cash Flow'!J37+'Cash Flow'!J38) -> 598.88756 | K45: =MAX(0, J45+'Income Statement'!K54+'Cash Flow'!K36+'Cash Flow'!K37+'Cash Flow'!K38) -> 397.8271 | L45: =MAX(0, K45+'Income Statement'!L54+'Cash Flow'!L36+'Cash Flow'!L37+'Cash Flow'!L38) -> 194.08584 | M45: =MAX(0, L45+'Income Statement'!M54+'Cash Flow'!M36+'Cash Flow'!M37+'Cash Flow'!M38) -> 0 | O45: Capital paid in above par. Drivers: SBC (+~$15M/yr), stock issued (small), buybacks (-~$300M+/yr). Floored at zero cuz GAAP doesn't allow negative APIC. Exhausts by FY29; overflow flows to RE.
B46: Retained earnings (Accumulated deficit) | C46: $M | D46: 876.916 | E46: 976.851 | F46: 1227.938 | G46: 1509.264 | H46: 1456.71 | I46: =H46+'Income Statement'!I38+'Cash Flow'!I39+MIN(0, H45+'Income Statement'!I54+'Cash Flow'!I36+'Cash Flow'!I37+'Cash Flow'!I38) -> 1786.7386 | J46: =I46+'Income Statement'!J38+'Cash Flow'!J39+MIN(0, I45+'Income Statement'!J54+'Cash Flow'!J36+'Cash Flow'!J37+'Cash Flow'!J38) -> 2135.9861 | K46: =J46+'Income Statement'!K38+'Cash Flow'!K39+MIN(0, J45+'Income Statement'!K54+'Cash Flow'!K36+'Cash Flow'!K37+'Cash Flow'!K38) -> 2506.5481 | L46: =K46+'Income Statement'!L38+'Cash Flow'!L39+MIN(0, K45+'Income Statement'!L54+'Cash Flow'!L36+'Cash Flow'!L37+'Cash Flow'!L38) -> 2899.7285 | M46: =L46+'Income Statement'!M38+'Cash Flow'!M39+MIN(0, L45+'Income Statement'!M54+'Cash Flow'!M36+'Cash Flow'!M37+'Cash Flow'!M38) -> 3304.8594 | O46: Cumulative NI less cumulative dividends, plus buyback overflow once APIC hits zero. Grows ~$340M/yr from retained earnings; dampens FY29+ as overflow charges here.
B47: Accumulated other comprehensive loss | C47: $M | D47: -80.169 | E47: -69.378 | F47: -34.995 | G47: -49.574 | H47: 37.505 | I47: =H47 -> 37.505 | J47: =I47 -> 37.505 | K47: =J47 -> 37.505 | L47: =K47 -> 37.505 | M47: =L47 -> 37.505 | O47: Cumulative FX translation + pension OCI. Held flat at FY25 ($37.5M). Historically volatile (-$80M to +$38M) driven by USD strength and pension discount rates.
B48: Total shareholders' equity | C48: $M | D48: =SUM(D44:D47) -> 1709.343 | E48: =SUM(E44:E47) -> 1859.652 | F48: =SUM(F44:F47) -> 2224.225 | G48: =SUM(G44:G47) -> 2584.135 | H48: =SUM(H44:H47) -> 2653.931 | I48: =SUM(I44:I47) -> 2786.4998 | J48: =SUM(J44:J47) -> 2937.5287 | K48: =SUM(K44:K47) -> 3107.0302 | ... M48: =SUM(M44:M47) -> 3507.5144
B50: TOTAL LIABILITIES & EQUITY | C50: $M | D50: =D41+D48 -> 2443.198 | E50: =E41+E48 -> 2438.9 | F50: =F41+F48 -> 2722.007 | G50: =G41+G48 -> 3139.212 | H50: =H41+H48 -> 3274.27 | I50: =I41+I48 -> 3428.8974 | J50: =J41+J48 -> 3603.2148 | K50: =K41+K48 -> 3797.325 | ... M50: =M41+M48 -> 4251.2952
B52: BS Check (Assets - L&E) | C52: $M | D52: =D23-D50 -> 0 | E52: =E23-E50 -> 0 | F52: =F23-F50 -> 0 | G52: =G23-G50 -> 0 | H52: =H23-H50 -> 0 | I52: =I23-I50 -> 2 | J52: =J23-J50 -> 2 | K52: =K23-K50 -> 2 | ... M52: =M23-M50 -> 2
B53: Cash Check (historical only) | C53: $M | D53: =IFERROR(D10-'Cash Flow'!D46,0) -> 0.022 | E53: =IFERROR(E10-'Cash Flow'!E46,0) -> 0.059 | F53: =IFERROR(F10-'Cash Flow'!F46,0) -> -0.878 | G53: =G10-'Cash Flow'!G46 -> 3.679 | H53: =H10-'Cash Flow'!H46 -> -2

Sheet Cash Flow
B2: Cash Flow
B3: Graco Inc. (NYSE: GGG)
B4: All amounts in $ millions unless noted
C7: Units | D7: =IF('Cover Page'!$C$63+0<'Cover Page'!$C$64,"FY"&TEXT(MOD('Cover Page'!$C$63+0,100),"00")&"A","FY"&TEXT(MOD('Cover Page'!$C$63+0,100),"00")&"E") -> FY21A | E7: =IF('Cover Page'!$C$63+1<'Cover Page'!$C$64,"FY"&TEXT(MOD('Cover Page'!$C$63+1,100),"00")&"A","FY"&TEXT(MOD('Cover Page'!$C$63+1,100),"00")&"E") -> FY22A | F7: =IF('Cover Page'!$C$63+2<'Cover Page'!$C$64,"FY"&TEXT(MOD('Cover Page'!$C$63+2,100),"00")&"A","FY"&TEXT(MOD('Cover Page'!$C$63+2,100),"00")&"E") -> FY23A | G7: =IF('Cover Page'!$C$63+3<'Cover Page'!$C$64,"FY"&TEXT(MOD('Cover Page'!$C$63+3,100),"00")&"A","FY"&TEXT(MOD('Cover Page'!$C$63+3,100),"00")&"E") -> FY24A | H7: =IF('Cover Page'!$C$63+4<'Cover Page'!$C$64,"FY"&TEXT(MOD('Cover Page'!$C$63+4,100),"00")&"A","FY"&TEXT(MOD('Cover Page'!$C$63+4,100),"00")&"E") -> FY25A | I7: =IF('Cover Page'!$C$63+5<'Cover Page'!$C$64,"FY"&TEXT(MOD('Cover Page'!$C$63+5,100),"00")&"A","FY"&TEXT(MOD('Cover Page'!$C$63+5,100),"00")&"E") -> FY26E | J7: =IF('Cover Page'!$C$63+6<'Cover Page'!$C$64,"FY"&TEXT(MOD('Cover Page'!$C$63+6,100),"00")&"A","FY"&TEXT(MOD('Cover Page'!$C$63+6,100),"00")&"E") -> FY27E | K7: =IF('Cover Page'!$C$63+7<'Cover Page'!$C$64,"FY"&TEXT(MOD('Cover Page'!$C$63+7,100),"00")&"A","FY"&TEXT(MOD('Cover Page'!$C$63+7,100),"00")&"E") -> FY28E | L7: =IF('Cover Page'!$C$63+8<'Cover Page'!$C$64,"FY"&TEXT(MOD('Cover Page'!$C$63+8,100),"00")&"A","FY"&TEXT(MOD('Cover Page'!$C$63+8,100),"00")&"E") -> FY29E | M7: =IF('Cover Page'!$C$63+9<'Cover Page'!$C$64,"FY"&TEXT(MOD('Cover Page'!$C$63+9,100),"00")&"A","FY"&TEXT(MOD('Cover Page'!$C$63+9,100),"00")&"E") -> FY30E | O7: Notes
B9: Operating Activities
B10: Net income | C10: $M | D10: ='Income Statement'!D38 -> 439.9 | E10: ='Income Statement'!E38 -> 460.6 | F10: ='Income Statement'!F38 -> 506.5 | G10: ='Income Statement'!G38 -> 486.1 | H10: ='Income Statement'!H38 -> 521.9 | I10: ='Income Statement'!I38 -> 522.54818 | J10: ='Income Statement'!J38 -> 551.39315 | K10: ='Income Statement'!K38 -> 582.8148 | ... M10: ='Income Statement'!M38 -> 651.19205 | O10: Net Income from IS row 38. Starting point for indirect-method CFO.
B11: Depreciation | C11: $M | D11: ='Income Statement'!D58 -> 50.3 | E11: ='Income Statement'!E58 -> 54.5 | F11: ='Income Statement'!F58 -> 56 | G11: ='Income Statement'!G58 -> 56 | H11: ='Income Statement'!H58 -> 60 | I11: ='Income Statement'!I58 -> 63.767412 | J11: ='Income Statement'!J58 -> 67.338079 | K11: ='Income Statement'!K58 -> 71.111188 | ... M11: ='Income Statement'!M58 -> 79.311903 | O11: Depreciation addback (non-cash). Drives from IS row 58.
B12: Amortization of intangibles | D12: ='Income Statement'!D59 -> 9 | E12: ='Income Statement'!E59 -> 11.5 | F12: ='Income Statement'!F59 -> 18.3 | G12: ='Income Statement'!G59 -> 30.7 | H12: ='Income Statement'!H59 -> 47.4 | I12: ='Income Statement'!I59 -> 47 | J12: ='Income Statement'!J59 -> 40 | K12: ='Income Statement'!K59 -> 33 | ... M12: ='Income Statement'!M59 -> 19 | O12: Amortization of intangibles addback (non-cash). Drives from IS row 59. Declines as acquired intangibles roll off.
B13: Stock-based compensation | C13: $M | D13: ='Income Statement'!D54 -> 24.9 | E13: ='Income Statement'!E54 -> 24.7 | F13: ='Income Statement'!F54 -> 30.2 | G13: ='Income Statement'!G54 -> 31.9 | H13: ='Income Statement'!H54 -> 34.3 | I13: ='Income Statement'!I54 -> 36.219365 | J13: ='Income Statement'!J54 -> 38.247474 | K13: ='Income Statement'!K54 -> 40.390569 | ... M13: ='Income Statement'!M54 -> 45.048508 | O13: Stock-based comp addback (non-cash) as it sits hidden in OpEx. Drives from IS row 54.
B14: Non-cash other (gains)/charges | C14: $M | D14: 0 | E14: 0 | F14: 41.329 | G14: 1.216 | H14: -18.798 | I14: 0 | J14: 0 | K14: 0 | L14: 0 | M14: 0 | O14: Catch-all for non-cash items: pension settlement losses, impairments, contingent consideration adjustments, gains on building sale. Forecast = 0 (assumes no discrete events; override if M&A or impairments expected).
B15: Deferred income taxes | C15: $M | D15: -46.572 | E15: -9.997 | F15: -8.502 | G15: 6.06 | H15: -8.673 | I15: 0 | J15: 0 | K15: 0 | L15: 0 | M15: 0 | O15: Deferred tax movements. Forecast = 0 (timing-driven; averages to ~zero over multi-year periods).
B16: Working capital changes
B17: Accounts receivable | C17: $M | D17: -13.801 | E17: -29.944 | F17: -3.245 | G17: 10.251 | H17: -7.383 | I17: =-('Balance Sheet'!I11-'Balance Sheet'!H11) -> -19.11135 | J17: =-('Balance Sheet'!J11-'Balance Sheet'!I11) -> -23.118411 | K17: =-('Balance Sheet'!K11-'Balance Sheet'!J11) -> -24.429125 | L17: =-('Balance Sheet'!L11-'Balance Sheet'!K11) -> -25.815101 | M17: =-('Balance Sheet'!M11-'Balance Sheet'!L11) -> -27.280718 | O17: AR change: prior - current. Decrease in AR = cash source. Driven by DSO assumption.
B18: Inventory | C18: $M | D18: -97.78 | E18: -95.691 | F18: 42.716 | G18: 55.836 | H18: 55.206 | I18: =-('Balance Sheet'!I12-'Balance Sheet'!H12) -> -22.640097 | J18: =-('Balance Sheet'!J12-'Balance Sheet'!I12) -> -23.826667 | K18: =-('Balance Sheet'!K12-'Balance Sheet'!J12) -> -25.182811 | L18: =-('Balance Sheet'!L12-'Balance Sheet'!K12) -> -26.617117 | M18: =-('Balance Sheet'!M12-'Balance Sheet'!L12) -> -28.134146 | O18: Inventory change: prior - current. Decrease in Inv = cash source. Driven by DIO assumption.
B19: Trade accounts payable | C19: $M | D19: 12.397 | E19: 4.195 | F19: -12.348 | G19: -13.298 | H19: -7.712 | I19: ='Balance Sheet'!I29-'Balance Sheet'!H29 -> 4.4156942 | J19: ='Balance Sheet'!J29-'Balance Sheet'!I29 -> 4.6460023 | K19: ='Balance Sheet'!K29-'Balance Sheet'!J29 -> 4.909347 | L19: ='Balance Sheet'!L29-'Balance Sheet'!K29 -> 5.1878092 | M19: ='Balance Sheet'!M29-'Balance Sheet'!L29 -> 5.4822679 | O19: AP change: current - prior. Increase in AP = cash source. Driven by DPO assumption.
B20: Salaries and incentives | C20: $M | D20: 29.089 | E20: -18.442 | F20: -2.158 | G20: -12.187 | H20: -6.632 | I20: ='Balance Sheet'!I30-'Balance Sheet'!H30 -> 4.1084474 | J20: ='Balance Sheet'!J30-'Balance Sheet'!I30 -> 4.341219 | K20: ='Balance Sheet'!K30-'Balance Sheet'!J30 -> 4.5873472 | L20: ='Balance Sheet'!L30-'Balance Sheet'!K30 -> 4.8476084 | M20: ='Balance Sheet'!M30-'Balance Sheet'!L30 -> 5.1228247 | O20: Salaries & incentives change: tracks BS row 30 (% of revenue).
B21: Retirement benefits | C21: $M | D21: 1.219 | E21: -18.674 | F21: -13.661 | G21: -14.171 | H21: -0.571 | I21: 0 | J21: 0 | K21: 0 | L21: 0 | M21: 0 | O21: Retirement benefits change. Forecast = 0 (assumes routine pension contributions = expense; minor).
B22: Other assets and liabilities | C22: $M | D22: 48.222 | E22: -5.39 | F22: -4.175 | G22: -15.516 | H22: 14.139 | I22: =('Balance Sheet'!I33-'Balance Sheet'!H33)-('Balance Sheet'!I13-'Balance Sheet'!H13)+('Balance Sheet'!H22-'Balance Sheet'!I22) -> 22.621119 | J22: =('Balance Sheet'!J33-'Balance Sheet'!I33)-('Balance Sheet'!J13-'Balance Sheet'!I13)+('Balance Sheet'!I22-'Balance Sheet'!J22) -> 23.2202 | K22: =('Balance Sheet'!K33-'Balance Sheet'!J33)-('Balance Sheet'!K13-'Balance Sheet'!J13)+('Balance Sheet'!J22-'Balance Sheet'!K22) -> 23.853656 | L22: =('Balance Sheet'!L33-'Balance Sheet'!K33)-('Balance Sheet'!L13-'Balance Sheet'!K13)+('Balance Sheet'!K22-'Balance Sheet'!L22) -> 24.523487 | M22: =('Balance Sheet'!M33-'Balance Sheet'!L33)-('Balance Sheet'!M13-'Balance Sheet'!L13)+('Balance Sheet'!L22-'Balance Sheet'!M22) -> 25.231807 | O22: Captures: change in Other CL + change in Other CA + Other NC asset runoff. Positive in forecast as acquisition indemnifications convert to cash.
B23: Cash from Operations (CFO) | C23: $M | D23: =SUM(D10:D15)+SUM(D17:D22) -> 456.874 | E23: =SUM(E10:E15)+SUM(E17:E22) -> 377.357 | F23: =SUM(F10:F15)+SUM(F17:F22) -> 650.956 | G23: =SUM(G10:G15)+SUM(G17:G22) -> 622.891 | H23: =SUM(H10:H15)+SUM(H17:H22) -> 683.176 | I23: =SUM(I10:I15)+SUM(I17:I22) -> 658.92877 | J23: =SUM(J10:J15)+SUM(J17:J22) -> 682.24105 | K23: =SUM(K10:K15)+SUM(K17:K22) -> 711.05497 | ... M23: =SUM(M10:M15)+SUM(M17:M22) -> 774.9745
B25: Investing Activities
B26: Acquisitions | C26: $M | D26: -19.386 | E26: -25.296 | F26: 0 | G26: -241.767 | H26: -135.262 | I26: =-Assumptions!I33 -> 0 | J26: =-Assumptions!J33 -> 0 | K26: =-Assumptions!K33 -> 0 | L26: =-Assumptions!L33 -> 0 | M26: =-Assumptions!M33 -> 0 | O26: M&A spend. Forecast = 0 (no future M&A modeled). Historical FY24-25 reflects Corob/Color Service/Radia.
B27: Capital expenditures | C27: $M | D27: -133.566 | E27: -201.161 | F27: -184.775 | G27: -106.737 | H27: -45.669 | I27: =-Assumptions!I81 -> -146.42887 | J27: =-Assumptions!J81 -> -142.15817 | K27: =-Assumptions!K81 -> -136.95488 | L27: =-Assumptions!L81 -> -130.72678 | M27: =-Assumptions!M81 -> -123.37407 | O27: Maintennce + Growth Capex. Drives from Assumptions (Capex % × Revenue). Maintenance ~$40-50M/yr per mgmt.
B28: PP&E sales | C28: $M | D28: 0 | E28: 0 | F28: 0 | G28: 5.63 | H28: 11.182 | I28: 0 | J28: 0 | K28: 0 | L28: 0 | M28: 0 | O28: PP&E sale proceeds. Forecast = 0 (building sales are discretionary and lumpy). Historical FY24-25 from divested facilities.
B29: Other investing activities | C29: $M | D29: -0.347 | E29: -0.362 | F29: 0.499 | G29: -5.689 | H29: 3.047 | I29: 0 | J29: 0 | K29: 0 | L29: 0 | M29: 0 | O29: Other investing (small; equity investments, intangible additions).
B30: Cash from Investing (CFI) | C30: $M | D30: =SUM(D26:D29) -> -153.299 | E30: =SUM(E26:E29) -> -226.819 | F30: =SUM(F26:F29) -> -184.276 | G30: =SUM(G26:G29) -> -348.563 | H30: =SUM(H26:H29) -> -166.702 | I30: =SUM(I26:I29) -> -146.42887 | J30: =SUM(J26:J29) -> -142.15817 | K30: =SUM(K26:K29) -> -136.95488 | ... M30: =SUM(M26:M29) -> -123.37407
B32: Financing Activities
B33: Borrowings (repayments) on notes payable | C33: $M | D33: 20.497 | E33: -18.252 | F33: 9.725 | G33: -0.766 | H33: -6.588 | I33: 0 | J33: 0 | K33: 0 | L33: 0 | M33: 0 | O33: Net change in short-term notes payable. Forecast = 0 (BS notes payable held constant)
B34: Borrowings on LTD | C34: $M | D34: 0 | E34: 0 | F34: 0 | G34: 0 | H34: 0.025 | I34: 0 | J34: 0 | K34: 0 | L34: 0 | M34: 0
B35: Payments on LTD | C35: $M | D35: -1.492 | E35: -75 | F35: -76.025 | G35: -1.707 | H35: 0 | I35: 0 | J35: 0 | K35: 0 | L35: 0 | M35: 0
B36: Common stock issued | C36: $M | D36: 50.963 | E36: 35.619 | F36: 60.182 | G36: 70.659 | H36: 43.023 | I36: =AVERAGE($D$36:$H$36) -> 52.0892 | J36: =AVERAGE($D$36:$H$36) -> 52.0892 | K36: =AVERAGE($D$36:$H$36) -> 52.0892 | L36: =AVERAGE($D$36:$H$36) -> 52.0892 | M36: =AVERAGE($D$36:$H$36) -> 52.0892 | O36: Cash from option being exercised + ESPP. Forecast at 5-yr historical average (~$52M/yr). Real cash inflow when employees pay strike price to exercise vested options.
B37: Common stock buybacks | C37: $M | D37: 0 | E37: -233.426 | F37: -102.344 | G37: -31.35 | H37: -423.108 | I37: =-Assumptions!I87 -> -285.76832 | J37: =-Assumptions!J87 -> -288.55536 | K37: =-Assumptions!K87 -> -293.54024 | L37: =-Assumptions!L87 -> -298.48571 | M37: =-Assumptions!M87 -> -303.27596 | O37: Share buybacks
B38: Taxes paid related to net share settlement | C38: $M | D38: 0 | E38: -1.219 | F38: -1.225 | G38: -4.611 | H38: -6.055 | I38: 0 | J38: 0 | K38: 0 | L38: 0 | M38: 0 | O38: Tax withholding on RSU/option vesting
B39: Dividends | C39: $M | D39: -127.11 | E39: -142.125 | F39: -158.323 | G39: -172.088 | H39: -183.352 | I39: =-Assumptions!I88 -> -192.5196 | J39: =-Assumptions!J88 -> -202.14558 | K39: =-Assumptions!K88 -> -212.25286 | L39: =-Assumptions!L88 -> -222.8655 | M39: =-Assumptions!M88 -> -234.00878 | O39: Cash dividends paid. (FY25 base × 5% growth/yr) — 25-yr track record of annual dividend hikes.
B40: Other financing activities | C40: $M | D40: 0 | E40: 0 | F40: 0 | G40: 0 | H40: 0 | I40: 0 | J40: 0 | K40: 0 | L40: 0 | M40: 0
B41: Cash from Financing (CFF) | C41: $M | D41: =SUM(D33:D40) -> -57.142 | E41: =SUM(E33:E40) -> -434.403 | F41: =SUM(F33:F40) -> -268.01 | G41: =SUM(G33:G40) -> -139.863 | H41: =SUM(H33:H40) -> -576.055 | I41: =SUM(I33:I40) -> -426.19872 | J41: =SUM(J33:J40) -> -438.61174 | K41: =SUM(K33:K40) -> -453.7039 | ... M41: =SUM(M33:M40) -> -485.19554
B43: Exchange rate changes | C43: $M | D43: -1.062 | E43: -1.278 | F43: 1.022 | G43: -1.637 | H43: 14.007 | I43: 0 | J43: 0 | K43: 0 | L43: 0 | M43: 0 | O43: FX impact on USD cash balances. Forecast = 0 (FX moves average to ~zero over multi-year periods).
B44: Net change in cash | C44: $M | D44: =D23+D30+D41+D43 -> 245.371 | E44: =E23+E30+E41+E43 -> -285.143 | F44: =F23+F30+F41+F43 -> 199.692 | G44: =G23+G30+G41+G43 -> 132.828 | H44: =H23+H30+H41+H43 -> -45.574 | I44: =I23+I30+I41+I43 -> 86.301177 | J44: =J23+J30+J41+J43 -> 101.47114 | K44: =K23+K30+K41+K43 -> 120.39619 | ... M44: =M23+M30+M41+M43 -> 166.40489 | O44: Net change in cash = CFO + CFI + CFF + FX.
B45: Cash BOP | C45: $M | D45: 378.909 | E45: =D46 -> 624.28 | F45: =E46 -> 339.137 | G45: =F46 -> 538.829 | H45: =G46 -> 671.657 | I45: =H46 -> 626.083 | J45: =I46 -> 712.38418 | K45: =J46 -> 813.85532 | L45: =K46 -> 934.25151 | M45: =L46 -> 1076.189 | O45: Cash beginning of period (= prior period EoP cash).
B46: Cash EOP | C46: $M | D46: =D44+D45 -> 624.28 | E46: =E44+E45 -> 339.137 | F46: =F44+F45 -> 538.829 | G46: =G44+G45 -> 671.657 | H46: =H44+H45 -> 626.083 | I46: =I44+I45 -> 712.38418 | J46: =J44+J45 -> 813.85532 | K46: =K44+K45 -> 934.25151 | ... M46: =M44+M45 -> 1242.5938 | O46: Cash end of period. Flows to BS row 10 next period.
B48: Free Cash Flow
B49: Cash from Operations | C49: $M | D49: =D23 -> 456.874 | E49: =E23 -> 377.357 | F49: =F23 -> 650.956 | G49: =G23 -> 622.891 | H49: =H23 -> 683.176 | I49: =I23 -> 658.92877 | J49: =J23 -> 682.24105 | K49: =K23 -> 711.05497 | ... M49: =M23 -> 774.9745
B50: Capital expenditures | C50: $M | D50: =D27 -> -133.566 | E50: =E27 -> -201.161 | F50: =F27 -> -184.775 | G50: =G27 -> -106.737 | H50: =H27 -> -45.669 | I50: =I27 -> -146.42887 | J50: =J27 -> -142.15817 | K50: =K27 -> -136.95488 | ... M50: =M27 -> -123.37407
B51: Stock-based comp | C51: $M | D51: =-D13 -> -24.9 | E51: =-E13 -> -24.7 | F51: =-F13 -> -30.2 | G51: =-G13 -> -31.9 | H51: =-H13 -> -34.3 | I51: =-I13 -> -36.219365 | J51: =-J13 -> -38.247474 | K51: =-K13 -> -40.390569 | ... M51: =-M13 -> -45.048508
B52: Free Cash Flow | C52: $M | D52: =D49+D50+D51 -> 298.408 | E52: =E49+E50+E51 -> 151.496 | F52: =F49+F50+F51 -> 435.981 | G52: =G49+G50+G51 -> 484.254 | H52: =H49+H50+H51 -> 603.207 | I52: =I49+I50+I51 -> 476.28053 | J52: =J49+J50+J51 -> 501.8354 | K52: =K49+K50+K51 -> 533.70952 | ... M52: =M49+M50+M51 -> 606.55192
B53: FCF margin | C53: % | D53: =D52/'Income Statement'!D12 -> 0.15013484 | E53: =E52/'Income Statement'!E12 -> 0.07067693 | F53: =F52/'Income Statement'!F12 -> 0.19857032 | G53: =G52/'Income Statement'!G12 -> 0.22914589 | H53: =H52/'Income Statement'!H12 -> 0.2696982 | I53: =I52/'Income Statement'!I12 -> 0.20166373 | J53: =J52/'Income Statement'!J12 -> 0.20121685 | K53: =K52/'Income Statement'!K12 -> 0.20264261 | ... M53: =M52/'Income Statement'!M12 -> 0.20648731 | O53: FCF margin = FCF / Revenue. Graco runs ~21-25% - best-in-class for industrials.
B54: FCF per diluted share | C54: $/sh | D54: =D52/'Income Statement'!D42 -> 1.7098197 | E54: =E52/'Income Statement'!E42 -> 0.87624137 | F54: =F52/'Income Statement'!F42 -> 2.531844 | G54: =G52/'Income Statement'!G42 -> 2.8088164 | H54: =H52/'Income Statement'!H42 -> 3.5646529 | I54: =I52/'Income Statement'!I42 -> 2.866932 | J54: =J52/'Income Statement'!J42 -> 3.078186 | K54: =K52/'Income Statement'!K42 -> 3.337875 | ... M54: =M52/'Income Statement'!M42 -> 3.9507128

Sheet DCF & Sensitivity
B2: DCF & Sensitivity Analysis
B3: Graco Inc. (NYSE: GGG)
B4: All amounts in $ millions unless noted
B6: WACC Calculation | C6: Units | O6: Notes
B7: Risk-Free Rate | C7: % | D7: =Assumptions!D94 -> 0.0431 | O7: WACC = cost of equity × equity weight + after-tax cost of debt × debt weight. Graco is essentially debt-free (~0.1% of cap), so WACC ≈ cost of equity. Excludes operating leases.
B8: Equity Risk Premium | C8: % | D8: =Assumptions!D95 -> 0.055
B9: Beta (Adjusted, peer-median) | C9: x | D9: =Assumptions!D97 -> 1.1675
B10: Cost of Equity | C10: % | D10: =Assumptions!D98 -> 0.1073125
B11: Cost of Debt (pre-tax) | C11: % | D11: =Assumptions!D99 -> 0.027050202
B12: Tax Rate | C12: % | D12: =Assumptions!M72 -> 0.19
B13: Cost of Debt (after-tax) | C13: % | D13: =D11*(1-D12) -> 0.021910664
B14: Debt / Total Capital | C14: % | D14: =Assumptions!D102 -> 0.0018041278
B15: Equity / Total Capital | C15: % | D15: =1-D14 -> 0.99819587
B16: WACC | C16: % | D16: =Assumptions!D104 -> 0.08
B18: FCF Projection | C18: Units | D18: =IF('Cover Page'!$C$63+0<'Cover Page'!$C$64,"FY"&TEXT(MOD('Cover Page'!$C$63+0,100),"00")&"A","FY"&TEXT(MOD('Cover Page'!$C$63+0,100),"00")&"E") -> FY21A | E18: =IF('Cover Page'!$C$63+1<'Cover Page'!$C$64,"FY"&TEXT(MOD('Cover Page'!$C$63+1,100),"00")&"A","FY"&TEXT(MOD('Cover Page'!$C$63+1,100),"00")&"E") -> FY22A | F18: =IF('Cover Page'!$C$63+2<'Cover Page'!$C$64,"FY"&TEXT(MOD('Cover Page'!$C$63+2,100),"00")&"A","FY"&TEXT(MOD('Cover Page'!$C$63+2,100),"00")&"E") -> FY23A | G18: =IF('Cover Page'!$C$63+3<'Cover Page'!$C$64,"FY"&TEXT(MOD('Cover Page'!$C$63+3,100),"00")&"A","FY"&TEXT(MOD('Cover Page'!$C$63+3,100),"00")&"E") -> FY24A | H18: =IF('Cover Page'!$C$63+4<'Cover Page'!$C$64,"FY"&TEXT(MOD('Cover Page'!$C$63+4,100),"00")&"A","FY"&TEXT(MOD('Cover Page'!$C$63+4,100),"00")&"E") -> FY25A | I18: =IF('Cover Page'!$C$63+5<'Cover Page'!$C$64,"FY"&TEXT(MOD('Cover Page'!$C$63+5,100),"00")&"A","FY"&TEXT(MOD('Cover Page'!$C$63+5,100),"00")&"E") -> FY26E | J18: =IF('Cover Page'!$C$63+6<'Cover Page'!$C$64,"FY"&TEXT(MOD('Cover Page'!$C$63+6,100),"00")&"A","FY"&TEXT(MOD('Cover Page'!$C$63+6,100),"00")&"E") -> FY27E | K18: =IF('Cover Page'!$C$63+7<'Cover Page'!$C$64,"FY"&TEXT(MOD('Cover Page'!$C$63+7,100),"00")&"A","FY"&TEXT(MOD('Cover Page'!$C$63+7,100),"00")&"E") -> FY28E | L18: =IF('Cover Page'!$C$63+8<'Cover Page'!$C$64,"FY"&TEXT(MOD('Cover Page'!$C$63+8,100),"00")&"A","FY"&TEXT(MOD('Cover Page'!$C$63+8,100),"00")&"E") -> FY29E | M18: =IF('Cover Page'!$C$63+9<'Cover Page'!$C$64,"FY"&TEXT(MOD('Cover Page'!$C$63+9,100),"00")&"A","FY"&TEXT(MOD('Cover Page'!$C$63+9,100),"00")&"E") -> FY30E
B19: Free Cash Flow (ex-SBC) | C19: $M | I19: ='Cash Flow'!I52+'Cash Flow'!I26 -> 476.28053 | J19: ='Cash Flow'!J52+'Cash Flow'!J26 -> 501.8354 | K19: ='Cash Flow'!K52+'Cash Flow'!K26 -> 533.70952 | L19: ='Cash Flow'!L52+'Cash Flow'!L26 -> 568.54421 | M19: ='Cash Flow'!M52+'Cash Flow'!M26 -> 606.55192 | O19: FCF = CFO − Capex − SBC. SBC deducted as a true economic cost (dilution is real). Capex runs at the assumed % of revenue from the scenario selector.
B20: Discount Period | C20: # | I20: 1 | J20: 2 | K20: 3 | L20: 4 | M20: 5
B21: Discount Factor | C21: x | I21: =1/(1+$D$16)^I20 -> 0.92592593 | J21: =1/(1+$D$16)^J20 -> 0.85733882 | K21: =1/(1+$D$16)^K20 -> 0.79383224 | L21: =1/(1+$D$16)^L20 -> 0.73502985 | M21: =1/(1+$D$16)^M20 -> 0.6805832
B22: Present Value of FCF | C22: $M | I22: =I19*I21 -> 441.00049 | J22: =J19*J21 -> 430.24297 | K22: =K19*K21 -> 423.67582 | L22: =L19*L21 -> 417.89697 | M22: =M19*M21 -> 412.80904
B24: Terminal Value | C24: Units | D24: Value | O24: Perpetuity TV = FY30E Terminal FCF × (1+g) / (WACC − g). Fragile to small changes in (WACC − g) spread. Most defensible when g anchors to long-run nominal GDP (~2.5-3%).
B25: Method 1: Perpetuity Growth
B26: Terminal Growth Rate | C26: % | D26: =Assumptions!D105 -> 0.025
B27: Terminal FCF (ex-SBC) | C27: $M | D27: =M19 -> 606.55192
B28: Terminal Value | C28: $M | D28: =D27*(1+D26)/(D16-D26) -> 11303.922
B29: PV of Terminal Value | C29: $M | D29: =D28*M21 -> 7693.2595
B31: Method 2: Exit Multiple | O31: Exit multiple TV = FY30E EBITDA × exit multiple. More stable than perpetuity but only as good as the chosen multiple. Triangulate against current LTM multiple, peer median (Comps tab), and historical M&A precedents.
B32: Terminal EBITDA | C32: $M | D32: ='Income Statement'!M51 -> 903.18085
B33: Exit EV/EBITDA Multiple | C33: x | D33: =Assumptions!D106 -> 15
B34: Terminal Value | C34: $M | D34: =D32*D33 -> 13547.713
B35: PV of Terminal Value | C35: $M | D35: =D34*M21 -> 9220.3456
B37: Valuation Summary | C37: Units | D37: Value
B38: Sum of PV of FCFs | C38: $M | D38: =SUM(I22:M22) -> 2125.6253 | O38: Both methods place ~70-80% of EV in terminal value — either way this is largely a bet on terminal-period economics. The gap between the two methods quantifies how much the answer depends on your terminal assumption choice.
B39: PV of Terminal Value (Perpetuity) | C39: $M | D39: =D29 -> 7693.2595
B40: Enterprise Value (Perpetuity) | C40: $M | D40: =D38+D39 -> 9818.8848
B41: PV of Terminal Value (Multiple) | C41: $M | D41: =D35 -> 9220.3456
B42: Enterprise Value (Multiple) | C42: $M | D42: =D38+D41 -> 11345.971
B44: Less: Net Debt (neg = net cash) | C44: $M | D44: ='Balance Sheet'!H37-'Balance Sheet'!H10 -> -624.083
B45: Equity Value (Perpetuity) | C45: $M | D45: =D40-D44 -> 10442.968
B46: Equity Value (Multiple) | C46: $M | D46: =D42-D44 -> 11970.054
B47: Shares Outstanding | C47: M | D47: =Assumptions!H89 -> 169.219
B49: Implied Share Price (Perpetuity) | C49: $/sh | D49: =D45/D47 -> 61.712738
B50: Implied Share Price (Multiple) | C50: $/sh | D50: =D46/D47 -> 70.737056
B51: Current Share Price | C51: $/sh | D51: 80.76
B52: Upside / (Downside) — Perpetuity | C52: % | D52: =D49/D51-1 -> -0.2358502
B53: Upside / (Downside) — Multiple | C53: % | D53: =D50/D51-1 -> -0.12410777
B55: TV as % of EV (Perpetuity) | C55: % | D55: =D39/D40 -> 0.78351663
B56: TV as % of EV (Multiple) | C56: % | D56: =D41/D42 -> 0.81265373
B60: Sensitivity: WACC vs. Terminal Growth Rate (Perpetuity Method) | O60: Perpetuity sensitivity quantifies fragility to WACC vs. g. Use this grid to reverse-engineer which WACC/g combo matches the current market price; if that combo looks unreasonable, the stock may be mispriced.
B61: Implied Share Price ($/share)
B62: WACC \ g | C62: 0.015 | D62: 0.02 | E62: 0.025 | F62: 0.03 | G62: 0.035 | H62: 0.04 | I62: 0.045
B63: 0.07 | C63: =($I$19/(1+$B63)^1+$J$19/(1+$B63)^2+$K$19/(1+$B63)^3+$L$19/(1+$B63)^4+$M$19/(1+$B63)^5+$M$19*(1+C$62)/($B63-C$62)/(1+$B63)^5-$D$44)/$D$47 -> 63.765338 | D63: =($I$19/(1+$B63)^1+$J$19/(1+$B63)^2+$K$19/(1+$B63)^3+$L$19/(1+$B63)^4+$M$19/(1+$B63)^5+$M$19*(1+D$62)/($B63-D$62)/(1+$B63)^5-$D$44)/$D$47 -> 68.737223 | E63: =($I$19/(1+$B63)^1+$J$19/(1+$B63)^2+$K$19/(1+$B63)^3+$L$19/(1+$B63)^4+$M$19/(1+$B63)^5+$M$19*(1+E$62)/($B63-E$62)/(1+$B63)^5-$D$44)/$D$47 -> 74.813971 | F63: =($I$19/(1+$B63)^1+$J$19/(1+$B63)^2+$K$19/(1+$B63)^3+$L$19/(1+$B63)^4+$M$19/(1+$B63)^5+$M$19*(1+F$62)/($B63-F$62)/(1+$B63)^5-$D$44)/$D$47 -> 82.409906 | G63: =($I$19/(1+$B63)^1+$J$19/(1+$B63)^2+$K$19/(1+$B63)^3+$L$19/(1+$B63)^4+$M$19/(1+$B63)^5+$M$19*(1+G$62)/($B63-G$62)/(1+$B63)^5-$D$44)/$D$47 -> 92.176109 | H63: =($I$19/(1+$B63)^1+$J$19/(1+$B63)^2+$K$19/(1+$B63)^3+$L$19/(1+$B63)^4+$M$19/(1+$B63)^5+$M$19*(1+H$62)/($B63-H$62)/(1+$B63)^5-$D$44)/$D$47 -> 105.19771 | I63: =($I$19/(1+$B63)^1+$J$19/(1+$B63)^2+$K$19/(1+$B63)^3+$L$19/(1+$B63)^4+$M$19/(1+$B63)^5+$M$19*(1+I$62)/($B63-I$62)/(1+$B63)^5-$D$44)/$D$47 -> 123.42796
B64: 0.08 | C64: =($I$19/(1+$B64)^1+$J$19/(1+$B64)^2+$K$19/(1+$B64)^3+$L$19/(1+$B64)^4+$M$19/(1+$B64)^5+$M$19*(1+C$62)/($B64-C$62)/(1+$B64)^5-$D$44)/$D$47 -> 54.343072 | D64: =($I$19/(1+$B64)^1+$J$19/(1+$B64)^2+$K$19/(1+$B64)^3+$L$19/(1+$B64)^4+$M$19/(1+$B64)^5+$M$19*(1+D$62)/($B64-D$62)/(1+$B64)^5-$D$44)/$D$47 -> 57.720835 | E64: =($I$19/(1+$B64)^1+$J$19/(1+$B64)^2+$K$19/(1+$B64)^3+$L$19/(1+$B64)^4+$M$19/(1+$B64)^5+$M$19*(1+E$62)/($B64-E$62)/(1+$B64)^5-$D$44)/$D$47 -> 61.712738 | F64: =($I$19/(1+$B64)^1+$J$19/(1+$B64)^2+$K$19/(1+$B64)^3+$L$19/(1+$B64)^4+$M$19/(1+$B64)^5+$M$19*(1+F$62)/($B64-F$62)/(1+$B64)^5-$D$44)/$D$47 -> 66.50302 | G64: =($I$19/(1+$B64)^1+$J$19/(1+$B64)^2+$K$19/(1+$B64)^3+$L$19/(1+$B64)^4+$M$19/(1+$B64)^5+$M$19*(1+G$62)/($B64-G$62)/(1+$B64)^5-$D$44)/$D$47 -> 72.35781 | H64: =($I$19/(1+$B64)^1+$J$19/(1+$B64)^2+$K$19/(1+$B64)^3+$L$19/(1+$B64)^4+$M$19/(1+$B64)^5+$M$19*(1+H$62)/($B64-H$62)/(1+$B64)^5-$D$44)/$D$47 -> 79.676298 | I64: =($I$19/(1+$B64)^1+$J$19/(1+$B64)^2+$K$19/(1+$B64)^3+$L$19/(1+$B64)^4+$M$19/(1+$B64)^5+$M$19*(1+I$62)/($B64-I$62)/(1+$B64)^5-$D$44)/$D$47 -> 89.085782
B65: 0.09 | C65: =($I$19/(1+$B65)^1+$J$19/(1+$B65)^2+$K$19/(1+$B65)^3+$L$19/(1+$B65)^4+$M$19/(1+$B65)^5+$M$19*(1+C$62)/($B65-C$62)/(1+$B65)^5-$D$44)/$D$47 -> 47.439142 | D65: =($I$19/(1+$B65)^1+$J$19/(1+$B65)^2+$K$19/(1+$B65)^3+$L$19/(1+$B65)^4+$M$19/(1+$B65)^5+$M$19*(1+D$62)/($B65-D$62)/(1+$B65)^5-$D$44)/$D$47 -> 49.857516 | E65: =($I$19/(1+$B65)^1+$J$19/(1+$B65)^2+$K$19/(1+$B65)^3+$L$19/(1+$B65)^4+$M$19/(1+$B65)^5+$M$19*(1+E$62)/($B65-E$62)/(1+$B65)^5-$D$44)/$D$47 -> 52.647948 | F65: =($I$19/(1+$B65)^1+$J$19/(1+$B65)^2+$K$19/(1+$B65)^3+$L$19/(1+$B65)^4+$M$19/(1+$B65)^5+$M$19*(1+F$62)/($B65-F$62)/(1+$B65)^5-$D$44)/$D$47 -> 55.903453 | G65: =($I$19/(1+$B65)^1+$J$19/(1+$B65)^2+$K$19/(1+$B65)^3+$L$19/(1+$B65)^4+$M$19/(1+$B65)^5+$M$19*(1+G$62)/($B65-G$62)/(1+$B65)^5-$D$44)/$D$47 -> 59.750867 | H65: =($I$19/(1+$B65)^1+$J$19/(1+$B65)^2+$K$19/(1+$B65)^3+$L$19/(1+$B65)^4+$M$19/(1+$B65)^5+$M$19*(1+H$62)/($B65-H$62)/(1+$B65)^5-$D$44)/$D$47 -> 64.367764 | I65: =($I$19/(1+$B65)^1+$J$19/(1+$B65)^2+$K$19/(1+$B65)^3+$L$19/(1+$B65)^4+$M$19/(1+$B65)^5+$M$19*(1+I$62)/($B65-I$62)/(1+$B65)^5-$D$44)/$D$47 -> 70.010638
B66: 0.1 | C66: =($I$19/(1+$B66)^1+$J$19/(1+$B66)^2+$K$19/(1+$B66)^3+$L$19/(1+$B66)^4+$M$19/(1+$B66)^5+$M$19*(1+C$62)/($B66-C$62)/(1+$B66)^5-$D$44)/$D$47 -> 42.164483 | D66: =($I$19/(1+$B66)^1+$J$19/(1+$B66)^2+$K$19/(1+$B66)^3+$L$19/(1+$B66)^4+$M$19/(1+$B66)^5+$M$19*(1+D$62)/($B66-D$62)/(1+$B66)^5-$D$44)/$D$47 -> 43.964635 | E66: =($I$19/(1+$B66)^1+$J$19/(1+$B66)^2+$K$19/(1+$B66)^3+$L$19/(1+$B66)^4+$M$19/(1+$B66)^5+$M$19*(1+E$62)/($B66-E$62)/(1+$B66)^5-$D$44)/$D$47 -> 46.004807 | F66: =($I$19/(1+$B66)^1+$J$19/(1+$B66)^2+$K$19/(1+$B66)^3+$L$19/(1+$B66)^4+$M$19/(1+$B66)^5+$M$19*(1+F$62)/($B66-F$62)/(1+$B66)^5-$D$44)/$D$47 -> 48.336433 | G66: =($I$19/(1+$B66)^1+$J$19/(1+$B66)^2+$K$19/(1+$B66)^3+$L$19/(1+$B66)^4+$M$19/(1+$B66)^5+$M$19*(1+G$62)/($B66-G$62)/(1+$B66)^5-$D$44)/$D$47 -> 51.02677 | H66: =($I$19/(1+$B66)^1+$J$19/(1+$B66)^2+$K$19/(1+$B66)^3+$L$19/(1+$B66)^4+$M$19/(1+$B66)^5+$M$19*(1+H$62)/($B66-H$62)/(1+$B66)^5-$D$44)/$D$47 -> 54.165497 | I66: =($I$19/(1+$B66)^1+$J$19/(1+$B66)^2+$K$19/(1+$B66)^3+$L$19/(1+$B66)^4+$M$19/(1+$B66)^5+$M$19*(1+I$62)/($B66-I$62)/(1+$B66)^5-$D$44)/$D$47 -> 57.874901
B67: 0.11 | C67: =($I$19/(1+$B67)^1+$J$19/(1+$B67)^2+$K$19/(1+$B67)^3+$L$19/(1+$B67)^4+$M$19/(1+$B67)^5+$M$19*(1+C$62)/($B67-C$62)/(1+$B67)^5-$D$44)/$D$47 -> 38.004386 | D67: =($I$19/(1+$B67)^1+$J$19/(1+$B67)^2+$K$19/(1+$B67)^3+$L$19/(1+$B67)^4+$M$19/(1+$B67)^5+$M$19*(1+D$62)/($B67-D$62)/(1+$B67)^5-$D$44)/$D$47 -> 39.385186 | E67: =($I$19/(1+$B67)^1+$J$19/(1+$B67)^2+$K$19/(1+$B67)^3+$L$19/(1+$B67)^4+$M$19/(1+$B67)^5+$M$19*(1+E$62)/($B67-E$62)/(1+$B67)^5-$D$44)/$D$47 -> 40.928433 | F67: =($I$19/(1+$B67)^1+$J$19/(1+$B67)^2+$K$19/(1+$B67)^3+$L$19/(1+$B67)^4+$M$19/(1+$B67)^5+$M$19*(1+F$62)/($B67-F$62)/(1+$B67)^5-$D$44)/$D$47 -> 42.664586 | G67: =($I$19/(1+$B67)^1+$J$19/(1+$B67)^2+$K$19/(1+$B67)^3+$L$19/(1+$B67)^4+$M$19/(1+$B67)^5+$M$19*(1+G$62)/($B67-G$62)/(1+$B67)^5-$D$44)/$D$47 -> 44.632226 | H67: =($I$19/(1+$B67)^1+$J$19/(1+$B67)^2+$K$19/(1+$B67)^3+$L$19/(1+$B67)^4+$M$19/(1+$B67)^5+$M$19*(1+H$62)/($B67-H$62)/(1+$B67)^5-$D$44)/$D$47 -> 46.880958 | I67: =($I$19/(1+$B67)^1+$J$19/(1+$B67)^2+$K$19/(1+$B67)^3+$L$19/(1+$B67)^4+$M$19/(1+$B67)^5+$M$19*(1+I$62)/($B67-I$62)/(1+$B67)^5-$D$44)/$D$47 -> 49.475649
B68: 0.12 | C68: =($I$19/(1+$B68)^1+$J$19/(1+$B68)^2+$K$19/(1+$B68)^3+$L$19/(1+$B68)^4+$M$19/(1+$B68)^5+$M$19*(1+C$62)/($B68-C$62)/(1+$B68)^5-$D$44)/$D$47 -> 34.640231 | D68: =($I$19/(1+$B68)^1+$J$19/(1+$B68)^2+$K$19/(1+$B68)^3+$L$19/(1+$B68)^4+$M$19/(1+$B68)^5+$M$19*(1+D$62)/($B68-D$62)/(1+$B68)^5-$D$44)/$D$47 -> 35.724976 | E68: =($I$19/(1+$B68)^1+$J$19/(1+$B68)^2+$K$19/(1+$B68)^3+$L$19/(1+$B68)^4+$M$19/(1+$B68)^5+$M$19*(1+E$62)/($B68-E$62)/(1+$B68)^5-$D$44)/$D$47 -> 36.923904 | F68: =($I$19/(1+$B68)^1+$J$19/(1+$B68)^2+$K$19/(1+$B68)^3+$L$19/(1+$B68)^4+$M$19/(1+$B68)^5+$M$19*(1+F$62)/($B68-F$62)/(1+$B68)^5-$D$44)/$D$47 -> 38.256047 | G68: =($I$19/(1+$B68)^1+$J$19/(1+$B68)^2+$K$19/(1+$B68)^3+$L$19/(1+$B68)^4+$M$19/(1+$B68)^5+$M$19*(1+G$62)/($B68-G$62)/(1+$B68)^5-$D$44)/$D$47 -> 39.744912 | H68: =($I$19/(1+$B68)^1+$J$19/(1+$B68)^2+$K$19/(1+$B68)^3+$L$19/(1+$B68)^4+$M$19/(1+$B68)^5+$M$19*(1+H$62)/($B68-H$62)/(1+$B68)^5-$D$44)/$D$47 -> 41.419885 | I68: =($I$19/(1+$B68)^1+$J$19/(1+$B68)^2+$K$19/(1+$B68)^3+$L$19/(1+$B68)^4+$M$19/(1+$B68)^5+$M$19*(1+I$62)/($B68-I$62)/(1+$B68)^5-$D$44)/$D$47 -> 43.318188
B69: 0.12 | C69: =($I$19/(1+$B69)^1+$J$19/(1+$B69)^2+$K$19/(1+$B69)^3+$L$19/(1+$B69)^4+$M$19/(1+$B69)^5+$M$19*(1+C$62)/($B69-C$62)/(1+$B69)^5-$D$44)/$D$47 -> 34.640231 | D69: =($I$19/(1+$B69)^1+$J$19/(1+$B69)^2+$K$19/(1+$B69)^3+$L$19/(1+$B69)^4+$M$19/(1+$B69)^5+$M$19*(1+D$62)/($B69-D$62)/(1+$B69)^5-$D$44)/$D$47 -> 35.724976 | E69: =($I$19/(1+$B69)^1+$J$19/(1+$B69)^2+$K$19/(1+$B69)^3+$L$19/(1+$B69)^4+$M$19/(1+$B69)^5+$M$19*(1+E$62)/($B69-E$62)/(1+$B69)^5-$D$44)/$D$47 -> 36.923904 | F69: =($I$19/(1+$B69)^1+$J$19/(1+$B69)^2+$K$19/(1+$B69)^3+$L$19/(1+$B69)^4+$M$19/(1+$B69)^5+$M$19*(1+F$62)/($B69-F$62)/(1+$B69)^5-$D$44)/$D$47 -> 38.256047 | G69: =($I$19/(1+$B69)^1+$J$19/(1+$B69)^2+$K$19/(1+$B69)^3+$L$19/(1+$B69)^4+$M$19/(1+$B69)^5+$M$19*(1+G$62)/($B69-G$62)/(1+$B69)^5-$D$44)/$D$47 -> 39.744912 | H69: =($I$19/(1+$B69)^1+$J$19/(1+$B69)^2+$K$19/(1+$B69)^3+$L$19/(1+$B69)^4+$M$19/(1+$B69)^5+$M$19*(1+H$62)/($B69-H$62)/(1+$B69)^5-$D$44)/$D$47 -> 41.419885 | I69: =($I$19/(1+$B69)^1+$J$19/(1+$B69)^2+$K$19/(1+$B69)^3+$L$19/(1+$B69)^4+$M$19/(1+$B69)^5+$M$19*(1+I$62)/($B69-I$62)/(1+$B69)^5-$D$44)/$D$47 -> 43.318188
B71: Sensitivity: WACC vs. Exit EV/EBITDA Multiple | O71: Exit-multiple sensitivity is tighter than perpetuity since TV anchors to EBITDA. Useful for stress-testing the implied exit multiple the market is pricing today vs. peer and historical ranges.
B72: Implied Share Price ($/share)
B73: WACC \ Mult | C73: 12 | D73: 13 | E73: 14 | F73: 15 | G73: 16 | H73: 17 | I73: 18
B74: 0.07 | C74: =($I$19/(1+$B74)^1+$J$19/(1+$B74)^2+$K$19/(1+$B74)^3+$L$19/(1+$B74)^4+$M$19/(1+$B74)^5+$D$32*C$73/(1+$B74)^5-$D$44)/$D$47 -> 62.267604 | D74: =($I$19/(1+$B74)^1+$J$19/(1+$B74)^2+$K$19/(1+$B74)^3+$L$19/(1+$B74)^4+$M$19/(1+$B74)^5+$D$32*D$73/(1+$B74)^5-$D$44)/$D$47 -> 66.07306 | E74: =($I$19/(1+$B74)^1+$J$19/(1+$B74)^2+$K$19/(1+$B74)^3+$L$19/(1+$B74)^4+$M$19/(1+$B74)^5+$D$32*E$73/(1+$B74)^5-$D$44)/$D$47 -> 69.878516 | F74: =($I$19/(1+$B74)^1+$J$19/(1+$B74)^2+$K$19/(1+$B74)^3+$L$19/(1+$B74)^4+$M$19/(1+$B74)^5+$D$32*F$73/(1+$B74)^5-$D$44)/$D$47 -> 73.683972 | G74: =($I$19/(1+$B74)^1+$J$19/(1+$B74)^2+$K$19/(1+$B74)^3+$L$19/(1+$B74)^4+$M$19/(1+$B74)^5+$D$32*G$73/(1+$B74)^5-$D$44)/$D$47 -> 77.489428 | H74: =($I$19/(1+$B74)^1+$J$19/(1+$B74)^2+$K$19/(1+$B74)^3+$L$19/(1+$B74)^4+$M$19/(1+$B74)^5+$D$32*H$73/(1+$B74)^5-$D$44)/$D$47 -> 81.294884 | I74: =($I$19/(1+$B74)^1+$J$19/(1+$B74)^2+$K$19/(1+$B74)^3+$L$19/(1+$B74)^4+$M$19/(1+$B74)^5+$D$32*I$73/(1+$B74)^5-$D$44)/$D$47 -> 85.10034
B75: 0.08 | C75: =($I$19/(1+$B75)^1+$J$19/(1+$B75)^2+$K$19/(1+$B75)^3+$L$19/(1+$B75)^4+$M$19/(1+$B75)^5+$D$32*C$73/(1+$B75)^5-$D$44)/$D$47 -> 59.839526 | D75: =($I$19/(1+$B75)^1+$J$19/(1+$B75)^2+$K$19/(1+$B75)^3+$L$19/(1+$B75)^4+$M$19/(1+$B75)^5+$D$32*D$73/(1+$B75)^5-$D$44)/$D$47 -> 63.472036 | E75: =($I$19/(1+$B75)^1+$J$19/(1+$B75)^2+$K$19/(1+$B75)^3+$L$19/(1+$B75)^4+$M$19/(1+$B75)^5+$D$32*E$73/(1+$B75)^5-$D$44)/$D$47 -> 67.104546 | F75: =($I$19/(1+$B75)^1+$J$19/(1+$B75)^2+$K$19/(1+$B75)^3+$L$19/(1+$B75)^4+$M$19/(1+$B75)^5+$D$32*F$73/(1+$B75)^5-$D$44)/$D$47 -> 70.737056 | G75: =($I$19/(1+$B75)^1+$J$19/(1+$B75)^2+$K$19/(1+$B75)^3+$L$19/(1+$B75)^4+$M$19/(1+$B75)^5+$D$32*G$73/(1+$B75)^5-$D$44)/$D$47 -> 74.369566 | H75: =($I$19/(1+$B75)^1+$J$19/(1+$B75)^2+$K$19/(1+$B75)^3+$L$19/(1+$B75)^4+$M$19/(1+$B75)^5+$D$32*H$73/(1+$B75)^5-$D$44)/$D$47 -> 78.002076 | I75: =($I$19/(1+$B75)^1+$J$19/(1+$B75)^2+$K$19/(1+$B75)^3+$L$19/(1+$B75)^4+$M$19/(1+$B75)^5+$D$32*I$73/(1+$B75)^5-$D$44)/$D$47 -> 81.634586
B76: 0.09 | C76: =($I$19/(1+$B76)^1+$J$19/(1+$B76)^2+$K$19/(1+$B76)^3+$L$19/(1+$B76)^4+$M$19/(1+$B76)^5+$D$32*C$73/(1+$B76)^5-$D$44)/$D$47 -> 57.538452 | D76: =($I$19/(1+$B76)^1+$J$19/(1+$B76)^2+$K$19/(1+$B76)^3+$L$19/(1+$B76)^4+$M$19/(1+$B76)^5+$D$32*D$73/(1+$B76)^5-$D$44)/$D$47 -> 61.007362 | E76: =($I$19/(1+$B76)^1+$J$19/(1+$B76)^2+$K$19/(1+$B76)^3+$L$19/(1+$B76)^4+$M$19/(1+$B76)^5+$D$32*E$73/(1+$B76)^5-$D$44)/$D$47 -> 64.476273 | F76: =($I$19/(1+$B76)^1+$J$19/(1+$B76)^2+$K$19/(1+$B76)^3+$L$19/(1+$B76)^4+$M$19/(1+$B76)^5+$D$32*F$73/(1+$B76)^5-$D$44)/$D$47 -> 67.945183 | G76: =($I$19/(1+$B76)^1+$J$19/(1+$B76)^2+$K$19/(1+$B76)^3+$L$19/(1+$B76)^4+$M$19/(1+$B76)^5+$D$32*G$73/(1+$B76)^5-$D$44)/$D$47 -> 71.414094 | H76: =($I$19/(1+$B76)^1+$J$19/(1+$B76)^2+$K$19/(1+$B76)^3+$L$19/(1+$B76)^4+$M$19/(1+$B76)^5+$D$32*H$73/(1+$B76)^5-$D$44)/$D$47 -> 74.883005 | I76: =($I$19/(1+$B76)^1+$J$19/(1+$B76)^2+$K$19/(1+$B76)^3+$L$19/(1+$B76)^4+$M$19/(1+$B76)^5+$D$32*I$73/(1+$B76)^5-$D$44)/$D$47 -> 78.351915
B77: 0.1 | C77: =($I$19/(1+$B77)^1+$J$19/(1+$B77)^2+$K$19/(1+$B77)^3+$L$19/(1+$B77)^4+$M$19/(1+$B77)^5+$D$32*C$73/(1+$B77)^5-$D$44)/$D$47 -> 55.356576 | D77: =($I$19/(1+$B77)^1+$J$19/(1+$B77)^2+$K$19/(1+$B77)^3+$L$19/(1+$B77)^4+$M$19/(1+$B77)^5+$D$32*D$73/(1+$B77)^5-$D$44)/$D$47 -> 58.67065 | E77: =($I$19/(1+$B77)^1+$J$19/(1+$B77)^2+$K$19/(1+$B77)^3+$L$19/(1+$B77)^4+$M$19/(1+$B77)^5+$D$32*E$73/(1+$B77)^5-$D$44)/$D$47 -> 61.984724 | F77: =($I$19/(1+$B77)^1+$J$19/(1+$B77)^2+$K$19/(1+$B77)^3+$L$19/(1+$B77)^4+$M$19/(1+$B77)^5+$D$32*F$73/(1+$B77)^5-$D$44)/$D$47 -> 65.298798 | G77: =($I$19/(1+$B77)^1+$J$19/(1+$B77)^2+$K$19/(1+$B77)^3+$L$19/(1+$B77)^4+$M$19/(1+$B77)^5+$D$32*G$73/(1+$B77)^5-$D$44)/$D$47 -> 68.612871 | H77: =($I$19/(1+$B77)^1+$J$19/(1+$B77)^2+$K$19/(1+$B77)^3+$L$19/(1+$B77)^4+$M$19/(1+$B77)^5+$D$32*H$73/(1+$B77)^5-$D$44)/$D$47 -> 71.926945 | I77: =($I$19/(1+$B77)^1+$J$19/(1+$B77)^2+$K$19/(1+$B77)^3+$L$19/(1+$B77)^4+$M$19/(1+$B77)^5+$D$32*I$73/(1+$B77)^5-$D$44)/$D$47 -> 75.241019
B78: 0.11 | C78: =($I$19/(1+$B78)^1+$J$19/(1+$B78)^2+$K$19/(1+$B78)^3+$L$19/(1+$B78)^4+$M$19/(1+$B78)^5+$D$32*C$73/(1+$B78)^5-$D$44)/$D$47 -> 53.286643 | D78: =($I$19/(1+$B78)^1+$J$19/(1+$B78)^2+$K$19/(1+$B78)^3+$L$19/(1+$B78)^4+$M$19/(1+$B78)^5+$D$32*D$73/(1+$B78)^5-$D$44)/$D$47 -> 56.4541 | E78: =($I$19/(1+$B78)^1+$J$19/(1+$B78)^2+$K$19/(1+$B78)^3+$L$19/(1+$B78)^4+$M$19/(1+$B78)^5+$D$32*E$73/(1+$B78)^5-$D$44)/$D$47 -> 59.621557 | F78: =($I$19/(1+$B78)^1+$J$19/(1+$B78)^2+$K$19/(1+$B78)^3+$L$19/(1+$B78)^4+$M$19/(1+$B78)^5+$D$32*F$73/(1+$B78)^5-$D$44)/$D$47 -> 62.789013 | G78: =($I$19/(1+$B78)^1+$J$19/(1+$B78)^2+$K$19/(1+$B78)^3+$L$19/(1+$B78)^4+$M$19/(1+$B78)^5+$D$32*G$73/(1+$B78)^5-$D$44)/$D$47 -> 65.95647 | H78: =($I$19/(1+$B78)^1+$J$19/(1+$B78)^2+$K$19/(1+$B78)^3+$L$19/(1+$B78)^4+$M$19/(1+$B78)^5+$D$32*H$73/(1+$B78)^5-$D$44)/$D$47 -> 69.123927 | I78: =($I$19/(1+$B78)^1+$J$19/(1+$B78)^2+$K$19/(1+$B78)^3+$L$19/(1+$B78)^4+$M$19/(1+$B78)^5+$D$32*I$73/(1+$B78)^5-$D$44)/$D$47 -> 72.291384
B79: 0.12 | C79: =($I$19/(1+$B79)^1+$J$19/(1+$B79)^2+$K$19/(1+$B79)^3+$L$19/(1+$B79)^4+$M$19/(1+$B79)^5+$D$32*C$73/(1+$B79)^5-$D$44)/$D$47 -> 51.321898 | D79: =($I$19/(1+$B79)^1+$J$19/(1+$B79)^2+$K$19/(1+$B79)^3+$L$19/(1+$B79)^4+$M$19/(1+$B79)^5+$D$32*D$73/(1+$B79)^5-$D$44)/$D$47 -> 54.350453 | E79: =($I$19/(1+$B79)^1+$J$19/(1+$B79)^2+$K$19/(1+$B79)^3+$L$19/(1+$B79)^4+$M$19/(1+$B79)^5+$D$32*E$73/(1+$B79)^5-$D$44)/$D$47 -> 57.379008 | F79: =($I$19/(1+$B79)^1+$J$19/(1+$B79)^2+$K$19/(1+$B79)^3+$L$19/(1+$B79)^4+$M$19/(1+$B79)^5+$D$32*F$73/(1+$B79)^5-$D$44)/$D$47 -> 60.407563 | G79: =($I$19/(1+$B79)^1+$J$19/(1+$B79)^2+$K$19/(1+$B79)^3+$L$19/(1+$B79)^4+$M$19/(1+$B79)^5+$D$32*G$73/(1+$B79)^5-$D$44)/$D$47 -> 63.436119 | H79: =($I$19/(1+$B79)^1+$J$19/(1+$B79)^2+$K$19/(1+$B79)^3+$L$19/(1+$B79)^4+$M$19/(1+$B79)^5+$D$32*H$73/(1+$B79)^5-$D$44)/$D$47 -> 66.464674 | I79: =($I$19/(1+$B79)^1+$J$19/(1+$B79)^2+$K$19/(1+$B79)^3+$L$19/(1+$B79)^4+$M$19/(1+$B79)^5+$D$32*I$73/(1+$B79)^5-$D$44)/$D$47 -> 69.493229
B80: 0.13 | C80: =($I$19/(1+$B80)^1+$J$19/(1+$B80)^2+$K$19/(1+$B80)^3+$L$19/(1+$B80)^4+$M$19/(1+$B80)^5+$D$32*C$73/(1+$B80)^5-$D$44)/$D$47 -> 49.456053 | D80: =($I$19/(1+$B80)^1+$J$19/(1+$B80)^2+$K$19/(1+$B80)^3+$L$19/(1+$B80)^4+$M$19/(1+$B80)^5+$D$32*D$73/(1+$B80)^5-$D$44)/$D$47 -> 52.352952 | E80: =($I$19/(1+$B80)^1+$J$19/(1+$B80)^2+$K$19/(1+$B80)^3+$L$19/(1+$B80)^4+$M$19/(1+$B80)^5+$D$32*E$73/(1+$B80)^5-$D$44)/$D$47 -> 55.249851 | F80: =($I$19/(1+$B80)^1+$J$19/(1+$B80)^2+$K$19/(1+$B80)^3+$L$19/(1+$B80)^4+$M$19/(1+$B80)^5+$D$32*F$73/(1+$B80)^5-$D$44)/$D$47 -> 58.14675 | G80: =($I$19/(1+$B80)^1+$J$19/(1+$B80)^2+$K$19/(1+$B80)^3+$L$19/(1+$B80)^4+$M$19/(1+$B80)^5+$D$32*G$73/(1+$B80)^5-$D$44)/$D$47 -> 61.04365 | H80: =($I$19/(1+$B80)^1+$J$19/(1+$B80)^2+$K$19/(1+$B80)^3+$L$19/(1+$B80)^4+$M$19/(1+$B80)^5+$D$32*H$73/(1+$B80)^5-$D$44)/$D$47 -> 63.940549 | I80: =($I$19/(1+$B80)^1+$J$19/(1+$B80)^2+$K$19/(1+$B80)^3+$L$19/(1+$B80)^4+$M$19/(1+$B80)^5+$D$32*I$73/(1+$B80)^5-$D$44)/$D$47 -> 66.837448

Sheet Comps
B2: Comparable Companies Analysis
B3: Graco Inc. (NYSE: GGG)
B4: All amounts in $ millions unless noted | EPS = GAAP diluted | FCF = CFO - Capex - SBC
B6: Company | C6: Ticker | D6: Price ($) | E6: Mkt Cap ($M) | F6: Net Debt ($M) | G6: EV ($M) | H6: Revenue ($M) | I6: EBITDA ($M) | J6: FCF ($M) | K6: SBC ($M) | L6: EBITDA-SBC ($M) | M6: FCF-SBC ($M) | N6: EPS | O6: FCF/Sh | P6: EBITDA Mgn | Q6: FCF Margin | R6: EV/Rev | S6: EV/EBITDA | T6: EV/EBITDA-SBC | U6: P/E | V6: P/FCF
B7: Graco Inc. | C7: GGG | D7: ='DCF & Sensitivity'!D51 -> 80.76 | E7: =Assumptions!D101 -> 13666.126 | F7: ='DCF & Sensitivity'!D44 -> -624.083 | G7: =E7+F7 -> 13042.043 | H7: ='Income Statement'!H12 -> 2236.6 | I7: ='Income Statement'!H51 -> 746.4 | J7: ='Cash Flow'!H49+'Cash Flow'!H50 -> 637.507 | K7: ='Income Statement'!H54 -> 34.3 | L7: =I7-K7 -> 712.1 | M7: =J7-K7 -> 603.207 | N7: ='Income Statement'!H43 -> 3.084169 | O7: =M7/'Income Statement'!H42 -> 3.5646529 | P7: =L7/H7 -> 0.31838505 | Q7: =M7/H7 -> 0.2696982 | R7: =G7/H7 -> 5.8311917 | S7: =G7/I7 -> 17.473263 | T7: =G7/L7 -> 18.314904 | U7: =D7/N7 -> 26.185335 | V7: =D7/O7 -> 22.655782
B9: Competitors
B10: Tier 1 — Niche Industrial Specialists (Closest)
B11: Nordson Corp | C11: NDSN | D11: 215 | E11: 12200 | F11: 1200 | G11: =E11+F11 -> 13400 | H11: 2850 | I11: 916 | J11: 600 | K11: 30 | L11: =I11-K11 -> 886 | M11: =J11-K11 -> 570 | N11: 9.34 | O11: =M11*(D11/E11) -> 10.045082 | P11: =L11/H11 -> 0.31087719 | Q11: =M11/H11 -> 0.2 | R11: =G11/H11 -> 4.7017544 | S11: =G11/I11 -> 14.628821 | T11: =G11/L11 -> 15.124153 | U11: =D11/N11 -> 23.019272 | V11: =D11/O11 -> 21.403509
B12: IDEX Corp | C12: IEX | D12: 200 | E12: 15000 | F12: 1000 | G12: =E12+F12 -> 16000 | H12: 3266 | I12: 875 | J12: 590 | K12: 25 | L12: =I12-K12 -> 850 | M12: =J12-K12 -> 565 | N12: 7.85 | O12: =M12*(D12/E12) -> 7.5333333 | P12: =L12/H12 -> 0.2602572 | Q12: =M12/H12 -> 0.17299449 | R12: =G12/H12 -> 4.898959 | S12: =G12/I12 -> 18.285714 | T12: =G12/L12 -> 18.823529 | U12: =D12/N12 -> 25.477707 | V12: =D12/O12 -> 26.548673
B13: Tier 2 — Specialty Industrial (Similar Moat)
B14: Roper Technologies | C14: ROP | D14: 555 | E14: 60000 | F14: 5800 | G14: =E14+F14 -> 65800 | H14: 7000 | I14: 2950 | J14: 2400 | K14: 130 | L14: =I14-K14 -> 2820 | M14: =J14-K14 -> 2270 | N14: 18.5 | O14: =M14*(D14/E14) -> 20.9975 | P14: =L14/H14 -> 0.40285714 | Q14: =M14/H14 -> 0.32428571 | R14: =G14/H14 -> 9.4 | S14: =G14/I14 -> 22.305085 | T14: =G14/L14 -> 23.333333 | U14: =D14/N14 -> 30 | V14: =D14/O14 -> 26.431718
B15: Watts Water Tech | C15: WTS | D15: 215 | E15: 7000 | F15: 100 | G15: =E15+F15 -> 7100 | H15: 2150 | I15: 470 | J15: 320 | K15: 18 | L15: =I15-K15 -> 452 | M15: =J15-K15 -> 302 | N15: 8.27 | O15: =M15*(D15/E15) -> 9.2757143 | P15: =L15/H15 -> 0.21023256 | Q15: =M15/H15 -> 0.14046512 | R15: =G15/H15 -> 3.3023256 | S15: =G15/I15 -> 15.106383 | T15: =G15/L15 -> 15.707965 | U15: =D15/N15 -> 25.997582 | V15: =D15/O15 -> 23.178808
B16: Tier 3 — Diversified Industrial (Directional)
B17: Lincoln Electric | C17: LECO | D17: 220 | E17: 12500 | F17: 1400 | G17: =E17+F17 -> 13900 | H17: 4000 | I17: 750 | J17: 530 | K17: 25 | L17: =I17-K17 -> 725 | M17: =J17-K17 -> 505 | N17: 9.41 | O17: =M17*(D17/E17) -> 8.888 | P17: =L17/H17 -> 0.18125 | Q17: =M17/H17 -> 0.12625 | R17: =G17/H17 -> 3.475 | S17: =G17/I17 -> 18.533333 | T17: =G17/L17 -> 19.172414 | U17: =D17/N17 -> 23.379384 | V17: =D17/O17 -> 24.752475
B18: Donaldson Co | C18: DCI | D18: 70 | E18: 8500 | F18: 600 | G18: =E18+F18 -> 9100 | H18: 3580 | I18: 700 | J18: 470 | K18: 22 | L18: =I18-K18 -> 678 | M18: =J18-K18 -> 448 | N18: 3.4 | O18: =M18*(D18/E18) -> 3.6894118 | P18: =L18/H18 -> 0.18938547 | Q18: =M18/H18 -> 0.12513966 | R18: =G18/H18 -> 2.5418994 | S18: =G18/I18 -> 13 | T18: =G18/L18 -> 13.421829 | U18: =D18/N18 -> 20.588235 | V18: =D18/O18 -> 18.973214
B19: A.O. Smith | C19: AOS | D19: 70 | E19: 10000 | F19: 0 | G19: =E19+F19 -> 10000 | H19: 3820 | I19: 800 | J19: 540 | K19: 22 | L19: =I19-K19 -> 778 | M19: =J19-K19 -> 518 | N19: 3.75 | O19: =M19*(D19/E19) -> 3.626 | P19: =L19/H19 -> 0.20366492 | Q19: =M19/H19 -> 0.13560209 | R19: =G19/H19 -> 2.617801 | S19: =G19/I19 -> 12.5 | T19: =G19/L19 -> 12.85347 | U19: =D19/N19 -> 18.666667 | V19: =D19/O19 -> 19.305019
B21: Summary Statistics (Peers, excl. GGG)
B22: Tier 1 Mean (NDSN, IEX) | P22: =AVERAGE(P11:P12) -> 0.28556719 | Q22: =AVERAGE(Q11:Q12) -> 0.18649724 | R22: =AVERAGE(R11:R12) -> 4.8003567 | S22: =AVERAGE(S11:S12) -> 16.457268 | T22: =AVERAGE(T11:T12) -> 16.973841 | U22: =AVERAGE(U11:U12) -> 24.248489 | V22: =AVERAGE(V11:V12) -> 23.976091
B23: Tier 1+2 Median | P23: =MEDIAN(P11:P12,P14:P15) -> 0.28556719 | Q23: =MEDIAN(Q11:Q12,Q14:Q15) -> 0.18649724 | R23: =MEDIAN(R11:R12,R14:R15) -> 4.8003567 | S23: =MEDIAN(S11:S12,S14:S15) -> 16.696049 | T23: =MEDIAN(T11:T12,T14:T15) -> 17.265747 | U23: =MEDIAN(U11:U12,U14:U15) -> 25.737644 | V23: =MEDIAN(V11:V12,V14:V15) -> 24.805263
B24: All Peers Mean | P24: =AVERAGE(P11:P12,P14:P15,P17:P19) -> 0.25121778 | Q24: =AVERAGE(Q11:Q12,Q14:Q15,Q17:Q19) -> 0.17496244 | R24: =AVERAGE(R11:R12,R14:R15,R17:R19) -> 4.4196771 | S24: =AVERAGE(S11:S12,S14:S15,S17:S19) -> 16.337048 | T24: =AVERAGE(T11:T12,T14:T15,T17:T19) -> 16.919528 | U24: =AVERAGE(U11:U12,U14:U15,U17:U19) -> 23.875549 | V24: =AVERAGE(V11:V12,V14:V15,V17:V19) -> 22.941917
B25: All Peers Median | P25: =MEDIAN(P11:P12,P14:P15,P17:P19) -> 0.21023256 | Q25: =MEDIAN(Q11:Q12,Q14:Q15,Q17:Q19) -> 0.14046512 | R25: =MEDIAN(R11:R12,R14:R15,R17:R19) -> 3.475 | S25: =MEDIAN(S11:S12,S14:S15,S17:S19) -> 15.106383 | T25: =MEDIAN(T11:T12,T14:T15,T17:T19) -> 15.707965 | U25: =MEDIAN(U11:U12,U14:U15,U17:U19) -> 23.379384 | V25: =MEDIAN(V11:V12,V14:V15,V17:V19) -> 23.178808
B26: High | P26: =MAX(P11:P12,P14:P15,P17:P19) -> 0.40285714 | Q26: =MAX(Q11:Q12,Q14:Q15,Q17:Q19) -> 0.32428571 | R26: =MAX(R11:R12,R14:R15,R17:R19) -> 9.4 | S26: =MAX(S11:S12,S14:S15,S17:S19) -> 22.305085 | T26: =MAX(T11:T12,T14:T15,T17:T19) -> 23.333333 | U26: =MAX(U11:U12,U14:U15,U17:U19) -> 30 | V26: =MAX(V11:V12,V14:V15,V17:V19) -> 26.548673
B27: Low | P27: =MIN(P11:P12,P14:P15,P17:P19) -> 0.18125 | Q27: =MIN(Q11:Q12,Q14:Q15,Q17:Q19) -> 0.12513966 | R27: =MIN(R11:R12,R14:R15,R17:R19) -> 2.5418994 | S27: =MIN(S11:S12,S14:S15,S17:S19) -> 12.5 | T27: =MIN(T11:T12,T14:T15,T17:T19) -> 12.85347 | U27: =MIN(U11:U12,U14:U15,U17:U19) -> 18.666667 | V27: =MIN(V11:V12,V14:V15,V17:V19) -> 18.973214
B29: Implied GGG Valuation (Tier 1+2 Median)
B30: Multiple | C30: Median | D30: GGG Metric | E30: Implied EV | F30: Less Net Debt ($M) | G30: Calc. Mkt Cap ($M) | H30: Shares (M) | I30: Implied Price | J30: vs. Current GGG
B31: EV / Revenue | C31: =R23 -> 4.8003567 | D31: =H7 -> 2236.6 | E31: =C31*D31 -> 10736.478 | F31: =F7 -> -624.083 | G31: =E31-F31 -> 11360.561 | H31: =Assumptions!$H$89 -> 169.219 | I31: =G31/H31 -> 67.135255 | J31: =I31/D7-1 -> -0.1687066
B32: EV / EBITDA | C32: =S23 -> 16.696049 | D32: =I7 -> 746.4 | E32: =C32*D32 -> 12461.931 | F32: =F7 -> -624.083 | G32: =E32-F32 -> 13086.014 | H32: =Assumptions!H89 -> 169.219 | I32: =G32/H32 -> 77.331823 | J32: =I32/D7-1 -> -0.042448952
B33: EV / EBITDA-SBC | C33: =T23 -> 17.265747 | D33: =L7 -> 712.1 | E33: =C33*D33 -> 12294.938 | F33: =F7 -> -624.083 | G33: =E33-F33 -> 12919.021 | H33: =Assumptions!H89 -> 169.219 | I33: =G33/H33 -> 76.344982 | J33: =I33/D7-1 -> -0.05466838
B34: P / E (no EV/net debt) | C34: =U23 -> 25.737644 | D34: =N7 -> 3.084169 | G34: =C34*D34*H34 -> 13432.477 | H34: =Assumptions!H89 -> 169.219 | I34: =C34*D34 -> 79.379246 | J34: =I34/D7-1 -> -0.017097008
B35: P / FCF (no EV/net debt) | C35: =V23 -> 24.805263 | D35: =O7 -> 3.5646529 | G35: =C35*D35*H35 -> 14962.708 | H35: =Assumptions!H89 -> 169.219 | I35: =C35*D35 -> 88.422153 | J35: =I35/D7-1 -> 0.094875592
B37: Key Takeaways
B38: Using peer exit multiples, the implied share price of Graco is close to the current $80.76. EV-based multiples suggest a slight premium (~5%), while P/FCF suggests modest undervaluation (~9%). The premium on EV/EBITDA reflects the higher premium investors are willing to pay on Graco's margin durability and growth. However, the P/FCF implied price is +9% above current, suggesting investors aren't fully rewarding Graco's current FCF conversion. Is Graco's current FCF margin on aligned with historcals? ---> No, Graco's FY25 FCF was elevated by anomalously low capex ($46M vs $130-200M historical) — as capex normalizes toward 4-5% of revenue, FCF and the implied multiple will compress.

Sheet Ideal Revenue Build >>>
B18: Ideal Revenue Build >>>

Sheet Rev Build - BU 1 - Contractor
B2: Revenue Build - BU 1: Contractor
B4: Sums product family tabs into segment totals. This demo only includes two families (Airless Sprayers, Powder Coating); a full build would include ~5-7 families under Contractor. We would engage in the same exercise across every product family and their respective business unit. Each of the three business segment tabs, would feed into a Consolidated Revenue Build. Structure: i) Revenue by Product Family - each family's total rolled up from its own tab ii) Revenue by Driver - same totals re-cut by economic driver (Equipment, Aftermarket, Service, FX) to show segment composition iii) Segment-Level M&A - deals that don't cleanly map to one family (e.g. Corob tinting, Color Service) are modeled here iv) Total Contractor Segment Revenue
C13: FY25A | D13: FY26E | E13: FY27E | F13: FY28E | G13: FY29E | H13: FY30E
B15: Revenue by Product Family | J15: Notes
B16: Airless Sprayers ($M) | C16: ='Rev Build - PF1 - Airless Spray'!C58 -> 725.38512 | D16: ='Rev Build - PF1 - Airless Spray'!D58 -> 754.34309 | E16: ='Rev Build - PF1 - Airless Spray'!E58 -> 788.3064 | F16: ='Rev Build - PF1 - Airless Spray'!F58 -> 827.32613 | G16: ='Rev Build - PF1 - Airless Spray'!G58 -> 848.20263 | H16: ='Rev Build - PF1 - Airless Spray'!H58 -> 892.09989 | J16: Rolled up from 'Rev Build - Airless Spray' tab
B17: YoY Growth % | D17: =D16/C16-1 -> 0.039920815 | E17: =E16/D16-1 -> 0.045023698 | F17: =F16/E16-1 -> 0.049498178 | G17: =G16/F16-1 -> 0.025233694 | H17: =H16/G16-1 -> 0.051753276
B18: Powder Coating ($M) | C18: ='Rev Build - PF2 - Powder Coat'!C70 -> 187.27496 | D18: ='Rev Build - PF2 - Powder Coat'!D70 -> 201.01988 | E18: ='Rev Build - PF2 - Powder Coat'!E70 -> 215.99537 | F18: ='Rev Build - PF2 - Powder Coat'!F70 -> 234.21449 | G18: ='Rev Build - PF2 - Powder Coat'!G70 -> 248.27635 | H18: ='Rev Build - PF2 - Powder Coat'!H70 -> 266.40343 | J18: Rolled up from 'Rev Build - Powder Coat' tab
B19: YoY Growth % | D19: =D18/C18-1 -> 0.073394333 | E19: =E18/D18-1 -> 0.074497577 | F19: =F18/E18-1 -> 0.084349551 | G19: =G18/F18-1 -> 0.06003842 | H19: =H18/G18-1 -> 0.073011695
B20: [OPEN] - Add other product families
B21: Total Product Family Revenue ($M) | C21: =C16+C18 -> 912.66008 | D21: =D16+D18 -> 955.36297 | E21: =E16+E18 -> 1004.3018 | F21: =F16+F18 -> 1061.5406 | G21: =G16+G18 -> 1096.479 | H21: =H16+H18 -> 1158.5033
B23: Revenue by Driver
B24: New Equipment Revenue ($M) | C24: ='Rev Build - PF1 - Airless Spray'!C55+'Rev Build - PF2 - Powder Coat'!C66 -> 648.65 | D24: ='Rev Build - PF1 - Airless Spray'!D55+'Rev Build - PF2 - Powder Coat'!D66 -> 676.81879 | E24: ='Rev Build - PF1 - Airless Spray'!E55+'Rev Build - PF2 - Powder Coat'!E66 -> 710.92178 | F24: ='Rev Build - PF1 - Airless Spray'!F55+'Rev Build - PF2 - Powder Coat'!F66 -> 746.43502 | G24: ='Rev Build - PF1 - Airless Spray'!G55+'Rev Build - PF2 - Powder Coat'!G66 -> 778.21273 | H24: ='Rev Build - PF1 - Airless Spray'!H55+'Rev Build - PF2 - Powder Coat'!H66 -> 806.9346
B25: Aftermarket & Consumables ($M) | C25: ='Rev Build - PF1 - Airless Spray'!C56+'Rev Build - PF2 - Powder Coat'!C67 -> 223.65 | D25: ='Rev Build - PF1 - Airless Spray'!D56+'Rev Build - PF2 - Powder Coat'!D67 -> 236.34612 | E25: ='Rev Build - PF1 - Airless Spray'!E56+'Rev Build - PF2 - Powder Coat'!E67 -> 249.03445 | F25: ='Rev Build - PF1 - Airless Spray'!F56+'Rev Build - PF2 - Powder Coat'!F67 -> 262.1542 | G25: ='Rev Build - PF1 - Airless Spray'!G56+'Rev Build - PF2 - Powder Coat'!G67 -> 273.55927 | H25: ='Rev Build - PF1 - Airless Spray'!H56+'Rev Build - PF2 - Powder Coat'!H67 -> 284.89661
B26: Service & Integration ($M) | C26: ='Rev Build - PF2 - Powder Coat'!C68 -> 32.174 | D26: ='Rev Build - PF2 - Powder Coat'!D68 -> 36.688908 | E26: ='Rev Build - PF2 - Powder Coat'!E68 -> 42.215735 | F26: ='Rev Build - PF2 - Powder Coat'!F68 -> 47.835663 | G26: ='Rev Build - PF2 - Powder Coat'!G68 -> 54.179024 | H26: ='Rev Build - PF2 - Powder Coat'!H68 -> 60.32577 | J26: Only Powder has this line (Airless — 0). If other Contractor families had service, it would roll up here too.
B27: FX Impact ($M) | C27: ='Rev Build - PF1 - Airless Spray'!C57+'Rev Build - PF2 - Powder Coat'!C69 -> 8.1860792 | D27: ='Rev Build - PF1 - Airless Spray'!D57+'Rev Build - PF2 - Powder Coat'!D69 -> 5.5091521 | E27: ='Rev Build - PF1 - Airless Spray'!E57+'Rev Build - PF2 - Powder Coat'!E69 -> 2.129818 | F27: ='Rev Build - PF1 - Airless Spray'!F57+'Rev Build - PF2 - Powder Coat'!F69 -> 5.1157302 | G27: ='Rev Build - PF1 - Airless Spray'!G57+'Rev Build - PF2 - Powder Coat'!G69 -> -9.472051 | H27: ='Rev Build - PF1 - Airless Spray'!H57+'Rev Build - PF2 - Powder Coat'!H69 -> 6.3463407
B28: [OPEN] - Add other product families
B29: Pre-M&A Segment Revenue ($M) | C29: =SUM(C24:C27) -> 912.66008 | D29: =SUM(D24:D27) -> 955.36297 | E29: =SUM(E24:E27) -> 1004.3018 | F29: =SUM(F24:F27) -> 1061.5406 | G29: =SUM(G24:G27) -> 1096.479 | H29: =SUM(H24:H27) -> 1158.5033
B31: Segment Level M&A
B32: Corob (tinting equipment, acquired Aug 2024) | C32: 32 | D32: 48 | E32: 52 | F32: 56 | G32: 60 | H32: 63 | J32: Annualized in FY26; ~8% organic thereafter.
B33: Color Service (tinting, acquired Aug 2025) | C33: 8 | D33: 22 | E33: 24 | F33: 26 | G33: 28 | H33: 30 | J33: Partial-year FY25; full year FY26 onward.
B34: Pipeline (unnamed future bolt-ons) | C34: 0 | D34: 0 | E34: 15 | F34: 35 | G34: 45 | H34: 55 | J34: Placeholder for bolt-ons at ~1/yr run-rate.
B35: [OPEN] - Add other product families
B36: Segment M&A Revenue ($M) | C36: =SUM(C32:C34) -> 40 | D36: =SUM(D32:D34) -> 70 | E36: =SUM(E32:E34) -> 91 | F36: =SUM(F32:F34) -> 117 | G36: =SUM(G32:G34) -> 133 | H36: =SUM(H32:H34) -> 148
B38: Business Unit Revenue
B39: Pre-M&A Segment Revenue | C39: =C29 -> 912.66008 | D39: =D29 -> 955.36297 | E39: =E29 -> 1004.3018 | F39: =F29 -> 1061.5406 | G39: =G29 -> 1096.479 | H39: =H29 -> 1158.5033
B40: Segment M&A | C40: =C36 -> 40 | D40: =D36 -> 70 | E40: =E36 -> 91 | F40: =F36 -> 117 | G40: =G36 -> 133 | H40: =H36 -> 148
B41: [OPEN] - Add other product families
B42: Contractor Segment Revenue | C42: =C39+C40 -> 952.66008 | D42: =D39+D40 -> 1025.363 | E42: =E39+E40 -> 1095.3018 | F42: =F39+F40 -> 1178.5406 | G42: =G39+G40 -> 1229.479 | H42: =H39+H40 -> 1306.5033
B43: YoY Growth % | D43: =D42/C42-1 -> 0.076315663 | E43: =E42/D42-1 -> 0.068208831 | F43: =F42/E42-1 -> 0.075996265 | G43: =G42/F42-1 -> 0.043221558 | H43: =H42/G42-1 -> 0.062647953
B45: Additional Enhancements to Revenue Build
B46: This units × ASP build by product family still doesn't incorporate a breakout by (i) Region or (ii) Sales Channel. When constructing a revenue forecast, we must choose which factors are worth being able to flex as drivers of future performance vs. the complexity and input count they add. Adding a regional breakout for each product family tier (Pro, Prosumer, DIY on Airless Sprayers) is the higher-priority enhancement as demand for each tier is tied to the economic cycle of its region (NA ties to US housing, Europe to repaint cycles, APAC to industrial capex), and regional revenue mix also replaces the standalone FX weights section, since regional mix is currency exposure. Sales Channel, on the other hand, has a much bigger impact on gross margin than on revenue, so the right place to introduce it is in the GM build — not as another axis on top of the revenue model.

Sheet Rev Build - PF1 - Airless Spray
B2: Contractor Revenue Build - Product Family 1: Airless Sprayer
B4: Presented below is a bottoms-up revenue build for the Airless Sprayers Product Family within the Contractor Business Unit. The revenue forecast has three parts: i) New Equipment Sales - derived from price x volume x margin mix assumptions ii) Consumable Cross-sell - Additional revenue from smaller SKUs w/n this Product Family that are used to maintain and upgrade a previously sold airless sprayer iii) FX Impact - Adjusting for the change in foreign currencies against the USD
C10: FY25A | D10: FY26E | E10: FY27E | F10: FY28E | G10: FY29E | H10: FY30E
B12: Step 1 - New Equipment Sales (Units × ASP) | J12: Notes
B13: › Pro Tier (Commercial Contractors)
B14: Units sold (000s) | C14: 125 | D14: =C14*(1+D15) -> 127.5 | E14: =D14*(1+E15) -> 131.325 | F14: =E14*(1+F15) -> 135.26475 | G14: =F14*(1+G15) -> 138.64637 | H14: =G14*(1+H15) -> 141.4193
B15: Unit growth % | D15: 0.02 | E15: 0.03 | F15: 0.03 | G15: 0.025 | H15: 0.02
B16: ASP ($, per unit) | C16: 2400 | D16: =C16*(1+D17) -> 2472 | E16: =D16*(1+E17) -> 2533.8 | F16: =E16*(1+F17) -> 2597.145 | G16: =F16*(1+G17) -> 2649.0879 | H16: =G16*(1+H17) -> 2702.0697
B17: Price/mix % | D17: 0.03 | E17: 0.025 | F17: 0.025 | G17: 0.02 | H17: 0.02
B18: Pro Revenue ($M) | C18: =C14*C16/1000 -> 300 | D18: =D14*D16/1000 -> 315.18 | E18: =E14*E16/1000 -> 332.75129 | F18: =F14*F16/1000 -> 351.30217 | G18: =G14*G16/1000 -> 367.28642 | H18: =H14*H16/1000 -> 382.12479
B19: › Prosumer Tier (Small Contractors)
B20: Units sold (000s) | C20: 195 | D20: =C20*(1+D21) -> 196.95 | E20: =D20*(1+E21) -> 200.889 | F20: =E20*(1+F21) -> 204.90678 | G20: =F20*(1+G21) -> 209.00492 | H20: =G20*(1+H21) -> 212.13999
B21: Unit growth % | D21: 0.01 | E21: 0.02 | F21: 0.02 | G21: 0.02 | H21: 0.015
B22: ASP ($, per unit) | C22: 750 | D22: =C22*(1+D23) -> 768.75 | E22: =D22*(1+E23) -> 784.125 | F22: =E22*(1+F23) -> 799.8075 | G22: =F22*(1+G23) -> 811.80461 | H22: =G22*(1+H23) -> 823.98168
B23: Price/mix % | D23: 0.025 | E23: 0.02 | F23: 0.02 | G23: 0.015 | H23: 0.015
B24: Prosumer Revenue ($M) | C24: =C20*C22/1000 -> 146.25 | D24: =D20*D22/1000 -> 151.40531 | E24: =E20*E22/1000 -> 157.52209 | F24: =F20*F22/1000 -> 163.88598 | G24: =G20*G22/1000 -> 169.67115 | H24: =H20*H22/1000 -> 174.79947
B25: › DIY Tier (home centers)
B26: Units sold (000s) | C26: 340 | D26: =C26*(1+D27) -> 336.6 | E26: =D26*(1+E27) -> 339.966 | F26: =E26*(1+F27) -> 345.06549 | G26: =F26*(1+G27) -> 350.24147 | H26: =G26*(1+H27) -> 353.74389
B27: Unit growth % | D27: -0.01 | E27: 0.01 | F27: 0.015 | G27: 0.015 | H27: 0.01
B28: ASP ($, per unit) | C28: 275 | D28: =C28*(1+D29) -> 279.125 | E28: =D28*(1+E29) -> 283.31187 | F28: =E28*(1+F29) -> 287.56155 | G28: =F28*(1+G29) -> 290.43717 | H28: =G28*(1+H29) -> 293.34154
B29: Price/mix % | D29: 0.015 | E29: 0.015 | F29: 0.015 | G29: 0.01 | H29: 0.01
B30: DIY Revenue ($M) | C30: =C26*C28/1000 -> 93.5 | D30: =D26*D28/1000 -> 93.953475 | E30: =E26*E28/1000 -> 96.316405 | F30: =F26*F28/1000 -> 99.227568 | G30: =G26*G28/1000 -> 101.72314 | H30: =H26*H28/1000 -> 103.76778
B31: Total New Equipment Revenue | C31: =C18+C24+C30 -> 539.75 | D31: =D18+D24+D30 -> 560.53879 | E31: =E18+E24+E30 -> 586.58978 | F31: =F18+F24+F30 -> 614.41572 | G31: =G18+G24+G30 -> 638.68071 | H31: =H18+H24+H30 -> 660.69203 | J31: Revenue's levers to grow are either price, volume, or selling higher margin products.
B33: Step 2 - Aftermarket & Consumables (Installed Base × Attach Rate)
B34: Installed base (M units, active) | C34: 1.85 | D34: =C34*(1+D35) -> 1.89625 | E34: =D34*(1+E35) -> 1.9436562 | F34: =E34*(1+F35) -> 1.9922477 | G34: =F34*(1+G35) -> 2.0320926 | H34: =G34*(1+H35) -> 2.0727345 | J34: New units - retirements (ppl getting rid of old equipment) - Comes from # of units sold in Step 1
B35: IB growth % | D35: 0.025 | E35: 0.025 | F35: 0.025 | G35: 0.02 | H35: 0.02
B36: Attach rate ($/unit/yr) | C36: 97 | D36: =C36*(1+D37) -> 99.91 | E36: =D36*(1+E37) -> 102.40775 | F36: =E36*(1+F37) -> 104.96794 | G36: =F36*(1+G37) -> 107.0673 | H36: =G36*(1+H37) -> 109.20865 | J36: Consumables: hoses, tips, fluid sections, parts.
B37: Aftermarket price % | D37: 0.03 | E37: 0.025 | F37: 0.025 | G37: 0.02 | H37: 0.02
B38: Aftermarket Revenue ($M) | C38: =C34*C36 -> 179.45 | D38: =D34*D36 -> 189.45434 | E38: =E34*E36 -> 199.04546 | F38: =F34*F36 -> 209.12214 | G38: =G34*G36 -> 217.57067 | H38: =H34*H36 -> 226.36053 | J38: Aftermarket revenue = Installed Base x Attach Rate
B40: Step 3 - FX Impact (Weighted Currency Exposure × Spot Rate Movement)
B41: › % Change vs. USD
B42: EUR | C42: 0.05 | D42: 0.02 | E42: =-5% -> -0.05 | F42: 0.07 | G42: =-3% -> -0.03 | H42: 0.0005
B43: CNY | C43: -0.02 | D43: 0.02 | E43: 0.08 | F43: -0.04 | G43: -0.02 | H43: 0.04
B44: Other | C44: 0.01 | D44: 0.005 | E44: 0.05 | F44: -0.04 | G44: -0.02 | H44: 0.02
B45: FX impact % | C45: =SUMPRODUCT(C41:C44,C48:C51) -> 0.0086 | D45: =SUMPRODUCT(D41:D44,D48:D51) -> 0.0058 | E45: =SUMPRODUCT(E41:E44,E48:E51) -> 0.0034 | F45: =SUMPRODUCT(F41:F44,F48:F51) -> 0.0046 | G45: =SUMPRODUCT(G41:G44,G48:G51) -> -0.0094 | H45: =SUMPRODUCT(H41:H44,H48:H51) -> 0.00569
B46: FX Revenue ($M) | C46: =(C31+C38)*C45 -> 6.18512 | D46: =(D31+D38)*D45 -> 4.3499601 | E46: =(E31+E38)*E45 -> 2.6711598 | F46: =(F31+F38)*F45 -> 3.7882741 | G46: =(G31+G38)*G45 -> -8.0487631 | H46: =(H31+H38)*H45 -> 5.0473291 | J46: How much excess/(reduction) is obtained from FX movements?
B47: FX as a % of Revenue
B48: USD | C48: 0.62 | D48: 0.62 | E48: 0.62 | F48: 0.62 | G48: 0.62 | H48: 0.62
B49: EUR | C49: 0.18 | D49: 0.18 | E49: 0.18 | F49: 0.18 | G49: 0.18 | H49: 0.18
B50: CNY | C50: 0.08 | D50: 0.08 | E50: 0.08 | F50: 0.08 | G50: 0.08 | H50: 0.08
B51: Other | C51: 0.12 | D51: 0.12 | E51: 0.12 | F51: 0.12 | G51: 0.12 | H51: 0.12
B52: Total | C52: =SUM(C48:C51) -> 1 | D52: =SUM(D48:D51) -> 1 | E52: =SUM(E48:E51) -> 1 | F52: =SUM(F48:F51) -> 1 | G52: =SUM(G48:G51) -> 1 | H52: =SUM(H48:H51) -> 1
B54: Product Family Revenue
B55: New Equipment Revenue ($M) | C55: =C31 -> 539.75 | D55: =D31 -> 560.53879 | E55: =E31 -> 586.58978 | F55: =F31 -> 614.41572 | G55: =G31 -> 638.68071 | H55: =H31 -> 660.69203
B56: Aftermarket & Consumables ($M) | C56: =C38 -> 179.45 | D56: =D38 -> 189.45434 | E56: =E38 -> 199.04546 | F56: =F38 -> 209.12214 | G56: =G38 -> 217.57067 | H56: =H38 -> 226.36053
B57: FX Impact ($M) | C57: =C46 -> 6.18512 | D57: =D46 -> 4.3499601 | E57: =E46 -> 2.6711598 | F57: =F46 -> 3.7882741 | G57: =G46 -> -8.0487631 | H57: =H46 -> 5.0473291
B58: Airless Sprayers Revenue | C58: =SUM(C55:C57) -> 725.38512 | D58: =SUM(D55:D57) -> 754.34309 | E58: =SUM(E55:E57) -> 788.3064 | F58: =SUM(F55:F57) -> 827.32613 | G58: =SUM(G55:G57) -> 848.20263 | H58: =SUM(H55:H57) -> 892.09989
B59: YoY Growth % | D59: =D58/C58-1 -> 0.039920815 | E59: =E58/D58-1 -> 0.045023698 | F59: =F58/E58-1 -> 0.049498178 | G59: =G58/F58-1 -> 0.025233694 | H59: =H58/G58-1 -> 0.051753276

Sheet Rev Build - PF2  - Powder Coat
B2: Contractor Revenue Build - Product Family 2: Powder Coating Equipment
B4: Presented below is a bottoms-up revenue build for the Powder Coating Equipment Product Family within the Contractor Business Unit. The revenue forecast has four parts: i) New Equipment Sales - derived from systems/guns price x volume x mix assumptions ii) Aftermarket & Consumables - Powder, filters, wear parts tied to installed base iii) Service & Systems Integration - Install revenue on new systems + recurring service contracts on installed base iv) FX Impact - Adjusting for the change in foreign currencies against the USD
C11: FY25A | D11: FY26E | E11: FY27E | F11: FY28E | G11: FY29E | H11: FY30E
B13: Step 1 - New Equipment Sales (Units × ASP) | J13: Notes
B14: › Complete Systems (full booths, ovens, reclaim)
B15: Units sold | C15: 180 | D15: =C15*(1+D16) -> 187.2 | E15: =D15*(1+E16) -> 196.56 | F15: =E15*(1+F16) -> 204.4224 | G15: =F15*(1+G16) -> 211.57718 | H15: =G15*(1+H16) -> 217.9245 | J15: Complete systems: $100K-$500K. Custom-engineered, long sales cycles.
B16: Unit growth % | D16: 0.04 | E16: 0.05 | F16: 0.04 | G16: 0.035 | H16: 0.03
B17: ASP ($, per system) | C17: 185000 | D17: =C17*(1+D18) -> 189625 | E17: =D17*(1+E18) -> 193417.5 | F17: =E17*(1+F18) -> 197285.85 | G17: =F17*(1+G18) -> 201231.57 | H17: =G17*(1+H18) -> 204250.04 | J17: ASP drifts up as reclaim/automation content increases.
B18: Price/mix % | D18: 0.025 | E18: 0.02 | F18: 0.02 | G18: 0.02 | H18: 0.015
B19: Complete Systems Revenue ($M) | C19: =C15*C17/1000000 -> 33.3 | D19: =D15*D17/1000000 -> 35.4978 | E19: =E15*E17/1000000 -> 38.018144 | F19: =F15*F17/1000000 -> 40.329647 | G19: =G15*G17/1000000 -> 42.576008 | H19: =H15*H17/1000000 -> 44.511088
B20: › Automatic Guns (robotic / inline booth integration)
B21: Units sold | C21: 2200 | D21: =C21*(1+D22) -> 2310 | E21: =D21*(1+E22) -> 2448.6 | F21: =E21*(1+F22) -> 2571.03 | G21: =F21*(1+G22) -> 2699.5815 | H21: =G21*(1+H22) -> 2807.5648 | J21: Automatic guns: $15-30K. Standard for medium/large production lines.
B22: Unit growth % | D22: 0.05 | E22: 0.06 | F22: 0.05 | G22: 0.05 | H22: 0.04
B23: ASP ($, per unit) | C23: 22000 | D23: =C23*(1+D24) -> 22660 | E23: =D23*(1+E24) -> 23226.5 | F23: =E23*(1+F24) -> 23807.162 | G23: =F23*(1+G24) -> 24283.306 | H23: =G23*(1+H24) -> 24768.972
B24: Price/mix % | D24: 0.03 | E24: 0.025 | F24: 0.025 | G24: 0.02 | H24: 0.02
B25: Automatic Guns Revenue ($M) | C25: =C21*C23/1000000 -> 48.4 | D25: =D21*D23/1000000 -> 52.3446 | E25: =E21*E23/1000000 -> 56.872408 | F25: =F21*F23/1000000 -> 61.208929 | G25: =G21*G23/1000000 -> 65.554763 | H25: =H21*H23/1000000 -> 69.540493
B26: › Manual Guns (handheld, small shop)
B27: Units sold | C27: 8500 | D27: =C27*(1+D28) -> 8670 | E27: =D27*(1+E28) -> 8800.05 | F27: =E27*(1+F28) -> 8932.0507 | G27: =F27*(1+G28) -> 9021.3713 | H27: =G27*(1+H28) -> 9111.585 | J27: Manual guns: $2-5K. Higher volume, replaced every 5-7 years.
B28: Unit growth % | D28: 0.02 | E28: 0.015 | F28: 0.015 | G28: 0.01 | H28: 0.01
B29: ASP ($, per unit) | C29: 3200 | D29: =C29*(1+D30) -> 3280 | E29: =D29*(1+E30) -> 3345.6 | F29: =E29*(1+F30) -> 3412.512 | G29: =F29*(1+G30) -> 3480.7622 | H29: =G29*(1+H30) -> 3532.9737
B30: Price/mix % | D30: 0.025 | E30: 0.02 | F30: 0.02 | G30: 0.02 | H30: 0.015
B31: Manual Guns Revenue ($M) | C31: =C27*C29/1000000 -> 27.2 | D31: =D27*D29/1000000 -> 28.4376 | E31: =E27*E29/1000000 -> 29.441447 | F31: =F27*F29/1000000 -> 30.48073 | G31: =G27*G29/1000000 -> 31.401248 | H31: =H27*H29/1000000 -> 32.19099
B32: Total New Equipment Revenue | C32: =C19+C25+C31 -> 108.9 | D32: =D19+D25+D31 -> 116.28 | E32: =E19+E25+E31 -> 124.332 | F32: =F19+F25+F31 -> 132.01931 | G32: =G19+G25+G31 -> 139.53202 | H32: =H19+H25+H31 -> 146.24257
B34: Step 2 - Aftermarket & Consumables (Installed Base × Attach Rate)
B35: Installed base (K units, active guns + systems) | C35: 85 | D35: =C35*(1+D36) -> 87.55 | E35: =D35*(1+E36) -> 90.61425 | F35: =E35*(1+F36) -> 93.785749 | G35: =F35*(1+G36) -> 96.599321 | H35: =G35*(1+H36) -> 99.014304 | J35: Smaller installed base than sprayers - longer replacement cycle (10-15 yrs).
B36: IB growth % | D36: 0.03 | E36: 0.035 | F36: 0.035 | G36: 0.03 | H36: 0.025
B37: Attach rate ($/unit/yr) | C37: 520 | D37: =C37*(1+D38) -> 535.6 | E37: =D37*(1+E38) -> 551.668 | F37: =E37*(1+F38) -> 565.4597 | G37: =F37*(1+G38) -> 579.59619 | H37: =G37*(1+H38) -> 591.18812 | J37: Higher $/unit/yr: powder + wear parts + booth filters.
B38: Aftermarket price % | D38: 0.03 | E38: 0.03 | F38: 0.025 | G38: 0.025 | H38: 0.02
B39: Aftermarket Revenue ($M) | C39: =C35*C37/1000 -> 44.2 | D39: =D35*D37/1000 -> 46.89178 | E39: =E35*E37/1000 -> 49.988982 | F39: =F35*F37/1000 -> 53.032061 | G39: =G35*G37/1000 -> 55.988599 | H39: =H35*H37/1000 -> 58.53608 | J39: Aftermarket revenue = Installed Base × Attach Rate
B41: Step 3 - Service & Systems Integration (Install Revenue + Service Contracts)
B42: › Installation Revenue (tied to new Complete Systems sold) | J42: New booth installs: 15-20% of system ASP for engineering, commissioning, training.
B43: Install attach rate (% of new system revenue) | C43: 0.18 | D43: 0.18 | E43: 0.19 | F43: 0.19 | G43: 0.2 | H43: 0.2
B44: Installation Revenue ($M) | C44: =C19*C43 -> 5.994 | D44: =D19*D43 -> 6.389604 | E44: =E19*E43 -> 7.2234473 | F44: =F19*F43 -> 7.6626329 | G44: =G19*G43 -> 8.5152017 | H44: =H19*H43 -> 8.9022176
B45: › Service Contracts (recurring, tied to installed base) | J45: Recurring annual service plans on installed base — preventative maintenance, parts, uptime SLAs.
B46: Contract attach % (share of IB on a service plan) | C46: 0.22 | D46: 0.24 | E46: 0.26 | F46: 0.28 | G46: 0.3 | H46: 0.32
B47: Annual contract value ($K / unit) | C47: 1.4 | D47: =C47*(1+0.03) -> 1.442 | E47: =D47*(1+0.03) -> 1.48526 | F47: =E47*(1+0.03) -> 1.5298178 | G47: =F47*(1+0.03) -> 1.5757123 | H47: =G47*(1+0.03) -> 1.6229837
B48: Service Contract Revenue ($M) | C48: =C35*C46*C47 -> 26.18 | D48: =D35*D46*D47 -> 30.299304 | E48: =E35*E46*E47 -> 34.992287 | F48: =F35*F46*F47 -> 40.17303 | G48: =G35*G46*G47 -> 45.663823 | H48: =H35*H46*H47 -> 51.423553 | J48: Service revenue = IB × contract attach % × ACV
B49: Total Service & Integration Revenue ($M) | C49: =C44+C48 -> 32.174 | D49: =D44+D48 -> 36.688908 | E49: =E44+E48 -> 42.215735 | F49: =F44+F48 -> 47.835663 | G49: =G44+G48 -> 54.179024 | H49: =H44+H48 -> 60.32577
B51: Step 4 - FX Impact (Weighted Currency Exposure × Spot Rate Movement)
B52: › % Change vs. USD
B53: EUR | C53: 0.05 | D53: 0.02 | E53: -0.03 | F53: 0.04 | G53: -0.02 | H53: 0.01
B54: CNY | C54: -0.02 | D54: 0.02 | E54: 0.05 | F54: -0.03 | G54: -0.01 | H54: 0.03
B55: Other | C55: 0.01 | D55: 0.005 | E55: 0.02 | F55: -0.02 | G55: -0.01 | H55: 0.015
B56: FX impact % | C56: =SUMPRODUCT(C52:C55,C59:C62) -> 0.0108 | D56: =SUMPRODUCT(D52:D55,D59:D62) -> 0.0058 | E56: =SUMPRODUCT(E52:E55,E59:E62) -> -0.0025 | F56: =SUMPRODUCT(F52:F55,F59:F62) -> 0.0057 | G56: =SUMPRODUCT(G52:G55,G59:G62) -> -0.0057 | H56: =SUMPRODUCT(H52:H55,H59:H62) -> 0.0049
B57: FX Revenue ($M) | C57: =(C32+C39+C49)*C56 -> 2.0009592 | D57: =(D32+D39+D49)*D56 -> 1.159192 | E57: =(E32+E39+E49)*E56 -> -0.54134179 | F57: =(F32+F39+F49)*F56 -> 1.3274561 | G57: =(G32+G39+G49)*G56 -> -1.423288 | H57: =(H32+H39+H49)*H56 -> 1.2990117 | J57: FX applied to pre-FX subtotal (Equipment + Aftermarket + Service)
B58: FX as a % of Revenue
B59: USD | C59: 0.65 | D59: 0.65 | E59: 0.65 | F59: 0.65 | G59: 0.65 | H59: 0.65
B60: EUR | C60: 0.22 | D60: 0.22 | E60: 0.22 | F60: 0.22 | G60: 0.22 | H60: 0.22
B61: CNY | C61: 0.05 | D61: 0.05 | E61: 0.05 | F61: 0.05 | G61: 0.05 | H61: 0.05
B62: Other | C62: 0.08 | D62: 0.08 | E62: 0.08 | F62: 0.08 | G62: 0.08 | H62: 0.08
B63: Total | C63: =SUM(C59:C62) -> 1 | D63: =SUM(D59:D62) -> 1 | E63: =SUM(E59:E62) -> 1 | F63: =SUM(F59:F62) -> 1 | G63: =SUM(G59:G62) -> 1 | H63: =SUM(H59:H62) -> 1
B65: Product Family Revenue
B66: New Equipment Revenue ($M) | C66: =C32 -> 108.9 | D66: =D32 -> 116.28 | E66: =E32 -> 124.332 | F66: =F32 -> 132.01931 | G66: =G32 -> 139.53202 | H66: =H32 -> 146.24257
B67: Aftermarket & Consumables ($M) | C67: =C39 -> 44.2 | D67: =D39 -> 46.89178 | E67: =E39 -> 49.988982 | F67: =F39 -> 53.032061 | G67: =G39 -> 55.988599 | H67: =H39 -> 58.53608
B68: Service & Integration ($M) | C68: =C49 -> 32.174 | D68: =D49 -> 36.688908 | E68: =E49 -> 42.215735 | F68: =F49 -> 47.835663 | G68: =G49 -> 54.179024 | H68: =H49 -> 60.32577
B69: FX Impact ($M) | C69: =C57 -> 2.0009592 | D69: =D57 -> 1.159192 | E69: =E57 -> -0.54134179 | F69: =F57 -> 1.3274561 | G69: =G57 -> -1.423288 | H69: =H57 -> 1.2990117
B70: Powder Coating Revenue | C70: =SUM(C66:C69) -> 187.27496 | D70: =SUM(D66:D69) -> 201.01988 | E70: =SUM(E66:E69) -> 215.99537 | F70: =SUM(F66:F69) -> 234.21449 | G70: =SUM(G66:G69) -> 248.27635 | H70: =SUM(H66:H69) -> 266.40343
B71: YoY Growth % | D71: =D70/C70-1 -> 0.073394333 | E71: =E70/D70-1 -> 0.074497577 | F71: =F70/E70-1 -> 0.084349551 | G71: =G70/F70-1 -> 0.06003842 | H71: =H70/G70-1 -> 0.073011695

Sheet Appendix >>>
B18: Appendix >>>

Sheet Sources
B2: Data Sources & References
B3: Brinker International, Inc. (EAT) DCF Model
B5: SEC FILINGS (PRIMARY SOURCES)
B6: FY25 10-K (fiscal year ended 6/25/2025) | C6: https://www.sec.gov/Archives/edgar/data/0000703351/000070335125000035/eat-20250625.htm
B7: FY22 10-K (for FY21/FY22 historicals) | C7: https://www.sec.gov/Archives/edgar/data/0000703351/000070335122000036/eat-20220629.htm
B8: Q1 FY26 10-Q (quarter ended 9/24/2025) | C8: https://www.sec.gov/Archives/edgar/data/0000703351/000070335125000046/eat-20250924.htm
B9: Q2 FY26 Earnings Release 8-K (Jan 2026) | C9: https://www.sec.gov/Archives/edgar/data/0000703351/000070335126000004/fy26q2ex991-earningsrelease.htm
B10: Investor Relations Hub | C10: https://investors.brinker.com
B12: FINANCIAL DATA SOURCED
B13: Income Statement | C13: FY23/FY24/FY25 from FY25 10-K; FY21/FY22 from FY22 10-K. Matches exactly to reported GAAP figures.
B14: Balance Sheet | C14: FY24/FY25 from FY25 10-K Consolidated Balance Sheets.
B15: Cash Flow | C15: FY23-FY25 from FY25 10-K; includes CFO bridge, capex, buybacks, debt activity.
B16: Unit Counts & AUV | C16: FY25 10-K Item 2 Properties table. 1,113 Chili's Co + 463 Fran + 49 Maggiano's Co + 3 Fran = 1,628 system-wide. Chili's AUV $4.5M, Maggiano's $9.9M.
B17: Comparable Restaurant Sales | C17: Q1 FY26 press release (PRNewswire): consolidated +18.8%, Chili's +21.4%, Maggiano's -6.4%. Q2 FY26: consol +7.5%, Chili's +8.6%, Maggiano's -2.4%.
B18: FY26 Guidance | C18: Q2 FY26 8-K (raised): Revenue $5.76B-$5.83B; Adj EPS $10.45-$10.85; Capex $250M-$260M; WA shares 44.7-45.2M.
B19: Management Commentary | C19: Q1/Q2 FY26 earnings calls via Seeking Alpha, Motley Fool, Insider Monkey transcripts. Key: 6 consecutive quarters DD growth; North of Six initiative; Maggiano's 'North Star' turnaround; $34M R&M favorability.
B20: Debt & Liquidity | C20: FY25 10-K Note 7 (Debt). $350M 8.25% notes due 7/15/2030 semi-annual; $1.0B revolver matures 5/1/2030, SOFR+1.25-2.00%, undrawn at 6/25/25.
B22: MARKET DATA (AS OF APR 2026)
B23: EAT Share Price: $168 | C23: Yahoo Finance / live quote. Also 44,431,215 shares outstanding at 10/23/25 per 10-Q cover page.
B24: Risk-Free Rate: 4.3% | C24: 10-Year US Treasury. treasury.gov / Apr 2026.
B25: Equity Risk Premium: 5.5% | C25: Damodaran (NYU Stern) implied ERP, current-year estimate.
B26: Beta | C26: Raw beta 1.25 (5Y monthly regression vs S&P 500). Adjusted per Blume: 0.67*raw + 0.33*1 = 1.17. See Assumptions row 60-61.
B27: Peer Data (Comps tab) | C27: Yahoo Finance, StockAnalysis.com, peer 10-K/10-Q filings. DRI Feb 2026 Q3 release; TXRH Feb 2026 Q4 release.
B29: NOTES & CAVEATS
B30: Model variance vs reported | C30: Revenue Build reconstructs total revenue from unit economics (AUV x SSS). Minor 3-5% variance vs reported in FY22-24 due to AUV/mix smoothing; FY25 closes to within $176M (3.3%).
B31: FY23 Net Income variance | C31: Model shows FY23 NI of ~$117M vs reported $102.6M. Gap reflects unmodeled special items. Acceptable for DCF valuation.
B32: Balance Sheet imbalance | C32: Minor $12-13M imbalance in FY26E (~0.4% of total assets) from working capital / accumulated OCI timing. Flagged but not material to valuation.
B33: Shadow DCF tab | C33: DEPRECATED. Was set up for QLYS (prior model). Scenario Summary has been re-routed to pull from main DCF tab only.

Sheet Shadow DCF
B2: Shadow DCF — Scenario Comparison
B3: Graco Inc. (NYSE: GGG)
B4: Supports Scenario Summary. Each scenario re-runs a simplified DCF using Bear/Base/Bull drivers from Assumptions. Shared WACC, shares, net debt.
B5: Note: Simplified scenario view showing Bear/Base/Bull side-by-side (independent of the main Assumptions toggle, by design). Uses a single blended revenue growth (organic + acquisitions + FX collapsed to a single rate), FY26E EBITDA margin anchored to management's guidance and interpolated linearly to each scenario's terminal margin, D&A held flat at 14% of EBITDA (~Graco run-rate), and no working capital.
B11: Shared Constants | D11: Value
B12: WACC | C12: % | D12: =Assumptions!D104 -> 0.08
B13: Tax Rate | C13: % | D13: ='DCF & Sensitivity'!D12 -> 0.19
B14: Net Debt | C14: $M | D14: ='DCF & Sensitivity'!D44 -> -624.083
B15: Diluted Shares | C15: M | D15: ='DCF & Sensitivity'!D47 -> 169.219
B16: FY25A Revenue | C16: $M | D16: ='Income Statement'!H12 -> 2236.6
B17: FY25A EBITDA Margin | C17: % | D17: ='Income Statement'!H51/'Income Statement'!H12 -> 0.33372083
B18: FY25A Capex % Rev | C18: % | D18: =-'Cash Flow'!H50/'Income Statement'!H12 -> 0.020418939
B19: SBC % Rev (projected) | C19: % | D19: =Assumptions!I82 -> 0.015335778
B20: FY26E Revenue (mgmt guidance midpoint) | C20: $M | D20: 2362
B21: FY26E EBITDA Margin (guidance anchor) | C21: % | D21: ='Income Statement'!I51/'Income Statement'!I12 -> 0.32044663
B23: Scenario Drivers (by scenario) | D23: Bear | E23: Base | F23: Bull
B24: Revenue growth — FY26E anchor (guidance) → terminal SSS | C24: % | D24: =-0.023 -> -0.023 | E24: =0.06 -> 0.06 | F24: =0.13 -> 0.13
B25: Terminal EBITDA margin | C25: % | D25: =1-Assumptions!E22-Assumptions!E23-Assumptions!E24-Assumptions!E25 -> 0.228 | E25: =1-Assumptions!F22-Assumptions!F23-Assumptions!F24-Assumptions!F25 -> 0.274 | F25: =1-Assumptions!G22-Assumptions!G23-Assumptions!G24-Assumptions!G25 -> 0.32
B26: Terminal Capex % rev | C26: % | D26: =Assumptions!E31 -> 0.038 | E26: =Assumptions!F31 -> 0.042 | F26: =Assumptions!G31 -> 0.05
B27: Terminal Growth Rate | C27: % | D27: =Assumptions!E35 -> 0.02 | E27: =Assumptions!F35 -> 0.025 | F27: =Assumptions!G35 -> 0.03
B28: Exit EV/EBITDA Multiple | C28: x | D28: =Assumptions!E36 -> 13 | E28: =Assumptions!F36 -> 15 | F28: =Assumptions!G36 -> 18
B31: BEAR SCENARIO | D31: ="FY"&TEXT(MOD('Cover Page'!$C$64+0,100),"00")&"E" -> FY26E | E31: ="FY"&TEXT(MOD('Cover Page'!$C$64+1,100),"00")&"E" -> FY27E | F31: ="FY"&TEXT(MOD('Cover Page'!$C$64+2,100),"00")&"E" -> FY28E | G31: ="FY"&TEXT(MOD('Cover Page'!$C$64+3,100),"00")&"E" -> FY29E | H31: ="FY"&TEXT(MOD('Cover Page'!$C$64+4,100),"00")&"E" -> FY30E
B32: Revenue | C32: $M | D32: =$D$20 -> 2362 | E32: =D32*(1+$D$24) -> 2307.674 | F32: =E32*(1+$D$24) -> 2254.5975 | G32: =F32*(1+$D$24) -> 2202.7418 | H32: =G32*(1+$D$24) -> 2152.0787
B33: EBITDA margin (linear interp FY25A → terminal) | C33: % | D33: =$D$21+($D$25-$D$21)*0/4 -> 0.32044663 | E33: =$D$21+($D$25-$D$21)*1/4 -> 0.29733497 | F33: =$D$21+($D$25-$D$21)*2/4 -> 0.27422332 | G33: =$D$21+($D$25-$D$21)*3/4 -> 0.25111166 | H33: =$D$21+($D$25-$D$21)*4/4 -> 0.228
B34: EBITDA | C34: $M | D34: =D32*D33 -> 756.89495 | E34: =E32*E33 -> 686.15219 | F34: =F32*F33 -> 618.2632 | G34: =G32*G33 -> 553.13414 | H34: =H32*H33 -> 490.67394
B35: (-) D&A (~4.7% of revenue, Graco actual) | C35: $M | D35: =-D32*0.047 -> -111.014 | E35: =-E32*0.047 -> -108.46068 | F35: =-F32*0.047 -> -105.96608 | G35: =-G32*0.047 -> -103.52886 | H35: =-H32*0.047 -> -101.1477
B36: EBIT | C36: $M | D36: =D34+D35 -> 645.88095 | E36: =E34+E35 -> 577.69151 | F36: =F34+F35 -> 512.29712 | G36: =G34+G35 -> 449.60527 | H36: =H34+H35 -> 389.52624
B37: NOPAT = EBIT × (1−t) | C37: $M | D37: =D36*(1-$D$13) -> 523.16357 | E37: =E36*(1-$D$13) -> 467.93013 | F37: =F36*(1-$D$13) -> 414.96067 | G37: =G36*(1-$D$13) -> 364.18027 | H37: =H36*(1-$D$13) -> 315.51626
B38: (+) D&A | C38: $M | D38: =-D35 -> 111.014 | E38: =-E35 -> 108.46068 | F38: =-F35 -> 105.96608 | G38: =-G35 -> 103.52886 | H38: =-H35 -> 101.1477
B39: (-) Capex (terminal %, linear interp) | C39: $M | D39: =-D32*($D$18+($D$26-$D$18)*1/5) -> -56.534828 | E39: =-E32*($D$18+($D$26-$D$18)*2/5) -> -63.348798 | F39: =-F32*($D$18+($D$26-$D$18)*3/5) -> -69.819419 | G39: =-G32*($D$18+($D$26-$D$18)*4/5) -> -75.958879 | H39: =-H32*$D$26 -> -81.77899
B40: (-) SBC | C40: $M | D40: =-D32*$D$19 -> -36.223107 | E40: =-E32*$D$19 -> -35.389975 | F40: =-F32*$D$19 -> -34.576006 | G40: =-G32*$D$19 -> -33.780757 | H40: =-H32*$D$19 -> -33.0038
B41: FCF | C41: $M | D41: =D37+D38+D39+D40-Assumptions!$E$33 -> 491.41963 | E41: =E37+E38+E39+E40-Assumptions!$E$33 -> 427.65203 | F41: =F37+F38+F39+F40-Assumptions!$E$33 -> 366.53133 | G41: =G37+G38+G39+G40-Assumptions!$E$33 -> 307.9695 | H41: =H37+H38+H39+H40-Assumptions!$E$33 -> 251.88117
B42: Discount Period | C42: # | D42: 1 | E42: 2 | F42: 3 | G42: 4 | H42: 5
B43: Discount Factor | C43: x | D43: =1/(1+Assumptions!$E$37)^D42 -> 0.90909091 | E43: =1/(1+Assumptions!$E$37)^E42 -> 0.82644628 | F43: =1/(1+Assumptions!$E$37)^F42 -> 0.7513148 | G43: =1/(1+Assumptions!$E$37)^G42 -> 0.68301346 | H43: =1/(1+Assumptions!$E$37)^H42 -> 0.62092132
B44: PV of FCF | C44: $M | D44: =D41*D43 -> 446.74512 | E44: =E41*E43 -> 353.43143 | F44: =F41*F43 -> 275.38041 | G44: =G41*G43 -> 210.34731 | H44: =H41*H43 -> 156.39839
B46: Sum of PV of FCFs (Bear) | C46: $M | D46: =SUM(D44:H44) -> 1442.3027
B47: Terminal FCF (year 5) | C47: $M | D47: =H41 -> 251.88117
B48: Terminal Value — Perpetuity | C48: $M | D48: =H41*(1+$D$27)/(Assumptions!$E$37-$D$27) -> 3211.4849
B49: PV of TV — Perpetuity | C49: $M | D49: =D48*H43 -> 1994.0794
B50: Terminal Value — Exit Multiple | C50: $M | D50: =H34*$D$28 -> 6378.7613
B51: PV of TV — Exit Multiple | C51: $M | D51: =D50*H43 -> 3960.7089
B52: Enterprise Value — Perpetuity | C52: $M | D52: =D46+D49 -> 3436.3821
B53: Enterprise Value — Exit Multiple | C53: $M | D53: =D46+D51 -> 5403.0115
B54: (−) Net Debt | C54: $M | D54: =-$D$14 -> 624.083
B55: Equity Value — Perpetuity | C55: $M | D55: =D52+D54 -> 4060.4651
B56: Equity Value — Exit Multiple | C56: $M | D56: =D53+D54 -> 6027.0945
B57: → Implied Price — Perpetuity | C57: $/sh | D57: =D55/$D$15 -> 23.995326
B58: → Implied Price — Exit Multiple | C58: $/sh | D58: =D56/$D$15 -> 35.617127
B61: BASE SCENARIO | D61: ="FY"&TEXT(MOD('Cover Page'!$C$64+0,100),"00")&"E" -> FY26E | E61: ="FY"&TEXT(MOD('Cover Page'!$C$64+1,100),"00")&"E" -> FY27E | F61: ="FY"&TEXT(MOD('Cover Page'!$C$64+2,100),"00")&"E" -> FY28E | G61: ="FY"&TEXT(MOD('Cover Page'!$C$64+3,100),"00")&"E" -> FY29E | H61: ="FY"&TEXT(MOD('Cover Page'!$C$64+4,100),"00")&"E" -> FY30E
B62: Revenue | C62: $M | D62: =$D$20 -> 2362 | E62: =D62*(1+$E$24) -> 2503.72 | F62: =E62*(1+$E$24) -> 2653.9432 | G62: =F62*(1+$E$24) -> 2813.1798 | H62: =G62*(1+$E$24) -> 2981.9706
B63: EBITDA margin (linear interp) | C63: % | D63: =$D$21+($E$25-$D$21)*0/4 -> 0.32044663 | E63: =$D$21+($E$25-$D$21)*1/4 -> 0.30883497 | F63: =$D$21+($E$25-$D$21)*2/4 -> 0.29722332 | G63: =$D$21+($E$25-$D$21)*3/4 -> 0.28561166 | H63: =$D$21+($E$25-$D$21)*4/4 -> 0.274
B64: EBITDA | C64: $M | D64: =D62*D63 -> 756.89495 | E64: =E62*E63 -> 773.2363 | F64: =F62*F63 -> 788.8138 | G64: =G62*G63 -> 803.47695 | H64: =H62*H63 -> 817.05994
B65: (-) D&A (~4.7% of revenue) | C65: $M | D65: =-D62*0.047 -> -111.014 | E65: =-E62*0.047 -> -117.67484 | F65: =-F62*0.047 -> -124.73533 | G65: =-G62*0.047 -> -132.21945 | H65: =-H62*0.047 -> -140.15262
B66: EBIT | C66: $M | D66: =D64+D65 -> 645.88095 | E66: =E64+E65 -> 655.56146 | F66: =F64+F65 -> 664.07847 | G66: =G64+G65 -> 671.2575 | H66: =H64+H65 -> 676.90732
B67: NOPAT | C67: $M | D67: =D66*(1-$D$13) -> 523.16357 | E67: =E66*(1-$D$13) -> 531.00479 | F67: =F66*(1-$D$13) -> 537.90356 | G67: =G66*(1-$D$13) -> 543.71857 | H67: =H66*(1-$D$13) -> 548.29493
B68: (+) D&A | C68: $M | D68: =-D65 -> 111.014 | E68: =-E65 -> 117.67484 | F68: =-F65 -> 124.73533 | G68: =-G65 -> 132.21945 | H68: =-H65 -> 140.15262
B69: (-) Capex | C69: $M | D69: =-D62*($D$18+($E$26-$D$18)*1/5) -> -58.424428 | E69: =-E62*($D$18+($E$26-$D$18)*2/5) -> -72.73648 | F69: =-F62*($D$18+($E$26-$D$18)*3/5) -> -88.555651 | G69: =-G62*($D$18+($E$26-$D$18)*4/5) -> -106.01127 | H69: =-H62*$E$26 -> -125.24276
B70: (-) SBC | C70: $M | D70: =-D62*$D$19 -> -36.223107 | E70: =-E62*$D$19 -> -38.396493 | F70: =-F62*$D$19 -> -40.700282 | G70: =-G62*$D$19 -> -43.142299 | H70: =-H62*$D$19 -> -45.730837
B71: FCF | C71: $M | D71: =D67+D68+D69+D70-Assumptions!$F$33 -> 439.53003 | E71: =E67+E68+E69+E70-Assumptions!$F$33 -> 437.54665 | F71: =F67+F68+F69+F70-Assumptions!$F$33 -> 433.38296 | G71: =G67+G68+G69+G70-Assumptions!$F$33 -> 426.78445 | H71: =H67+H68+H69+H70-Assumptions!$F$33 -> 417.47395
B72: Discount Factor | C72: x | D72: =1/(1+Assumptions!$F$37)^1 -> 0.92592593 | E72: =1/(1+Assumptions!$F$37)^2 -> 0.85733882 | F72: =1/(1+Assumptions!$F$37)^3 -> 0.79383224 | G72: =1/(1+Assumptions!$F$37)^4 -> 0.73502985 | H72: =1/(1+Assumptions!$F$37)^5 -> 0.6805832
B73: PV of FCF | C73: $M | D73: =D71*D72 -> 406.97225 | E73: =E71*E72 -> 375.12573 | F73: =F71*F72 -> 344.03336 | G73: =G71*G72 -> 313.69931 | H73: =H71*H72 -> 284.12575
B75: Sum of PV of FCFs (Base) | C75: $M | D75: =SUM(D73:H73) -> 1723.9564
B76: Terminal Value — Perpetuity | C76: $M | D76: =H71*(1+$E$27)/(Assumptions!$F$37-$E$27) -> 7780.1963
B77: PV of TV — Perpetuity | C77: $M | D77: =D76*H72 -> 5295.0708
B78: Terminal Value — Exit Multiple | C78: $M | D78: =H64*$E$28 -> 12255.899
B79: PV of TV — Exit Multiple | C79: $M | D79: =D78*H72 -> 8341.159
B80: Enterprise Value — Perpetuity | C80: $M | D80: =D75+D77 -> 7019.0273
B81: Enterprise Value — Exit Multiple | C81: $M | D81: =D75+D79 -> 10065.115
B82: (−) Net Debt | C82: $M | D82: =-$D$14 -> 624.083
B83: Equity Value — Perpetuity | C83: $M | D83: =D80+D82 -> 7643.1103
B84: Equity Value — Exit Multiple | C84: $M | D84: =D81+D82 -> 10689.198
B85: → Implied Price — Perpetuity | C85: $/sh | D85: =D83/$D$15 -> 45.166975
B86: → Implied Price — Exit Multiple | C86: $/sh | D86: =D84/$D$15 -> 63.167838
B91: BULL SCENARIO | D91: ="FY"&TEXT(MOD('Cover Page'!$C$64+0,100),"00")&"E" -> FY26E | E91: ="FY"&TEXT(MOD('Cover Page'!$C$64+1,100),"00")&"E" -> FY27E | F91: ="FY"&TEXT(MOD('Cover Page'!$C$64+2,100),"00")&"E" -> FY28E | G91: ="FY"&TEXT(MOD('Cover Page'!$C$64+3,100),"00")&"E" -> FY29E | H91: ="FY"&TEXT(MOD('Cover Page'!$C$64+4,100),"00")&"E" -> FY30E
B92: Revenue | C92: $M | D92: =$D$20 -> 2362 | E92: =D92*(1+$F$24) -> 2669.06 | F92: =E92*(1+$F$24) -> 3016.0378 | G92: =F92*(1+$F$24) -> 3408.1227 | H92: =G92*(1+$F$24) -> 3851.1787
B93: EBITDA margin | C93: % | D93: =$D$21+($F$25-$D$21)*0/4 -> 0.32044663 | E93: =$D$21+($F$25-$D$21)*1/4 -> 0.32033497 | F93: =$D$21+($F$25-$D$21)*2/4 -> 0.32022332 | G93: =$D$21+($F$25-$D$21)*3/4 -> 0.32011166 | H93: =$D$21+($F$25-$D$21)*4/4 -> 0.32
B94: EBITDA | C94: $M | D94: =D92*D93 -> 756.89495 | E94: =E92*E93 -> 854.99327 | F94: =F92*F93 -> 965.80563 | G94: =G92*G93 -> 1090.9798 | H94: =H92*H93 -> 1232.3772
B95: (-) D&A (~4.7% of revenue) | C95: $M | D95: =-D92*0.047 -> -111.014 | E95: =-E92*0.047 -> -125.44582 | F95: =-F92*0.047 -> -141.75378 | G95: =-G92*0.047 -> -160.18177 | H95: =-H92*0.047 -> -181.0054
B96: EBIT | C96: $M | D96: =D94+D95 -> 645.88095 | E96: =E94+E95 -> 729.54745 | F96: =F94+F95 -> 824.05185 | G96: =G94+G95 -> 930.79805 | H96: =H94+H95 -> 1051.3718
B97: NOPAT | C97: $M | D97: =D96*(1-$D$13) -> 523.16357 | E97: =E96*(1-$D$13) -> 590.93343 | F97: =F96*(1-$D$13) -> 667.482 | G97: =G96*(1-$D$13) -> 753.94642 | H97: =H96*(1-$D$13) -> 851.61114
B98: (+) D&A | C98: $M | D98: =-D95 -> 111.014 | E98: =-E95 -> 125.44582 | F98: =-F95 -> 141.75378 | G98: =-G95 -> 160.18177 | H98: =-H95 -> 181.0054
B99: (-) Capex | C99: $M | D99: =-D92*($D$18+($F$26-$D$18)*1/5) -> -62.203628 | E99: =-E92*($D$18+($F$26-$D$18)*2/5) -> -86.080825 | F99: =-F92*($D$18+($F$26-$D$18)*3/5) -> -115.11485 | G99: =-G92*($D$18+($F$26-$D$18)*4/5) -> -150.24296 | H99: =-H92*$F$26 -> -192.55893
B100: (-) SBC | C100: $M | D100: =-D92*$D$19 -> -36.223107 | E100: =-E92*$D$19 -> -40.93211 | F100: =-F92*$D$19 -> -46.253285 | G100: =-G92*$D$19 -> -52.266212 | H100: =-H92*$D$19 -> -59.060819
B101: FCF | C101: $M | D101: =D97+D98+D99+D100-Assumptions!$G$33 -> 335.75083 | E101: =E97+E98+E99+E100-Assumptions!$G$33 -> 389.36632 | F101: =F97+F98+F99+F100-Assumptions!$G$33 -> 447.86764 | G101: =G97+G98+G99+G100-Assumptions!$G$33 -> 511.61901 | H101: =H97+H98+H99+H100-Assumptions!$G$33 -> 580.99678
B102: Discount Factor | C102: x | D102: =1/(1+Assumptions!$G$37)^1 -> 0.94339623 | E102: =1/(1+Assumptions!$G$37)^2 -> 0.88999644 | F102: =1/(1+Assumptions!$G$37)^3 -> 0.83961928 | G102: =1/(1+Assumptions!$G$37)^4 -> 0.79209366 | H102: =1/(1+Assumptions!$G$37)^5 -> 0.74725817
B103: PV of FCF | C103: $M | D103: =D101*D102 -> 316.74607 | E103: =E101*E102 -> 346.53464 | F103: =F101*F102 -> 376.03831 | G103: =G101*G102 -> 405.25018 | H103: =H101*H102 -> 434.15459
B105: Sum of PV of FCFs (Bull) | C105: $M | D105: =SUM(D103:H103) -> 1878.7238
B106: Terminal Value — Perpetuity | C106: $M | D106: =H101*(1+$F$27)/(Assumptions!$G$37-$F$27) -> 19947.556
B107: PV of TV — Perpetuity | C107: $M | D107: =D106*H102 -> 14905.974
B108: Terminal Value — Exit Multiple | C108: $M | D108: =H94*$F$28 -> 22182.789
B109: PV of TV — Exit Multiple | C109: $M | D109: =D108*H102 -> 16576.27
B110: Enterprise Value — Perpetuity | C110: $M | D110: =D105+D107 -> 16784.698
B111: Enterprise Value — Exit Multiple | C111: $M | D111: =D105+D109 -> 18454.994
B112: (−) Net Debt | C112: $M | D112: =-$D$14 -> 624.083
B113: Equity Value — Perpetuity | C113: $M | D113: =D110+D112 -> 17408.781
B114: Equity Value — Exit Multiple | C114: $M | D114: =D111+D112 -> 19079.077
B115: → Implied Price — Perpetuity | C115: $/sh | D115: =D113/$D$15 -> 102.87723
B116: → Implied Price — Exit Multiple | C116: $/sh | D116: =D114/$D$15 -> 112.74784
B119: Summary (pulled into Scenario Summary) | D119: Bear | E119: Base | F119: Bull
B120: Revenue FY30E | C120: $M | D120: =H32 -> 2152.0787 | E120: =H62 -> 2981.9706 | F120: =H92 -> 3851.1787
...

Sheet Shadow DCF Rec
B2: Main Model Outputs — Snapshot
B3: Graco Inc. (NYSE: GGG)
B4: Hardcoded main-model outputs for each scenario. Feeds Scenario Summary reconciliation.
B6: Snapshot taken via scenario toggle sweep on Assumptions!H11:H35. Main model returned to Base after capture.
B7: Workflow | C7: 1. Set all dropdowns on Assumptions!H11:H37 to "Bear" → copy values from main model into column D below. 2. Repeat for "Base" (column E) and "Bull" (column F). 3. Update timestamp in C9. 4. Return Assumptions toggles to your preferred scenario for the main model display.
B9: Last Refreshed | C9: Refreshed after M&A and WACC scenario logic added
B11: Source cells | C11: Pull from these cells on the main model tabs (all show FY30E values except EV/Share Price which are the final DCF outputs).
B14: Main Model Outputs | C14: Source Cell | D14: Bear | E14: Base | F14: Bull
B15: FY30E Revenue ($M) | C15: Income Statement'!M12 | D15: 2427.14 | E15: 2937.48 | F15: 3409.18
B16: FY30E Net Income ($M) | C16: Income Statement'!M38 | D16: 447.49 | E16: 651.19 | F16: 882.91
B17: FY30E EBITDA ($M) | C17: Income Statement'!M51 | D17: 637.92 | E17: 903.18 | F17: 1201.99
B18: FY30E EBITDA Margin | C18: Income Statement'!M52 | D18: =IFERROR(D17/D15,"") -> 0.26282786 | E18: =IFERROR(E17/E15,"") -> 0.30746763 | F18: =IFERROR(F17/F15,"") -> 0.35257452
B19: FY30E FCF ($M) | C19: Cash Flow'!M52 | D19: 455.89 | E19: 595.33 | F19: 774.09
B20: Enterprise Value — Perpetuity ($M) | C20: DCF & Sensitivity'!D44 | D20: 4904.45 | E20: 8072.31 | F20: 16521.25
B21: Enterprise Value — Exit Multiple ($M) | C21: DCF & Sensitivity'!D46 | D21: 6840.45 | E21: 11010.07 | F21: 17960.02
B22: Share Price — Perpetuity ($/sh) | C22: DCF & Sensitivity'!D53 | D22: 32.67 | E22: 51.39 | F22: 101.32
B23: Share Price — Exit Multiple ($/sh) | C23: DCF & Sensitivity'!D54 | D23: 44.11 | E23: 68.75 | F23: 109.82
B24: Share Price — Blended ($/sh) | C24: avg of perp + mult | D24: =IFERROR(AVERAGE(D22:D23),"") -> 38.39 | E24: =IFERROR(AVERAGE(E22:E23),"") -> 60.07 | F24: =IFERROR(AVERAGE(F22:F23),"") -> 105.57
B26: Scenario Summary Reconciliation | D26: Bear | E26: Base | F26: Bull
B27: Blended Share Price — Shadow | C27: Shadow DCF'!D123 / E123 / F123 | D27: =IFERROR('Shadow DCF'!D128,"") -> 29.806226 | E27: =IFERROR('Shadow DCF'!E128,"") -> 54.167406 | F27: =IFERROR('Shadow DCF'!F128,"") -> 107.81253
B28: Blended Share Price — Main Model (snapshot above) | D28: =IFERROR(D24,"") -> 38.39 | E28: =IFERROR(E24,"") -> 60.07 | F28: =IFERROR(F24,"") -> 105.57
B29: Variance (Shadow − Main) | D29: =IFERROR(IF(AND(ISNUMBER(D27),ISNUMBER(D28)),D27/D28-1,""),"") -> -0.223594 | E29: =IFERROR(IF(AND(ISNUMBER(E27),ISNUMBER(E28)),E27/E28-1,""),"") -> -0.098261923 | F29: =IFERROR(IF(AND(ISNUMBER(F27),ISNUMBER(F28)),F27/F28-1,""),"") -> 0.021242154

Sheet FootballField Data
A1: Football Field Chart — Source Data (Graco)
A3: This sheet feeds the 'Football Field — Implied Price by Method ($/sh)' chart on Scenario Summary. Do not delete.
A5: Method | B5: Low | C5: Width | D5: High | E5: Description | G5: Current Price Line
A6: DCF — Perpetuity Growth | B6: ='Scenario Summary'!D8 -> 23.995326 | C6: =D6-B6 -> 78.881899 | D6: ='Scenario Summary'!F8 -> 102.87723 | E6: Bear → Bull scenario range | G6: X (Price) | H6: Y (Position)
A7: DCF — Exit Multiple | B7: ='Scenario Summary'!D9 -> 35.617127 | C7: =D7-B7 -> 77.130717 | D7: ='Scenario Summary'!F9 -> 112.74784 | E7: Bear → Bull scenario range | G7: =B12 -> 80.76 | H7: 0.5
A8: Comps — EV/EBITDA | B8: =(PERCENTILE(Comps!S11:S15,0.25)*'Income Statement'!I51-'DCF & Sensitivity'!D44)/'DCF & Sensitivity'!D47 -> 70.715996 | C8: =D8-B8 -> 19.247305 | D8: =(PERCENTILE(Comps!S11:S15,0.75)*'Income Statement'!I51-'DCF & Sensitivity'!D44)/'DCF & Sensitivity'!D47 -> 89.9633 | E8: Peer 25th–75th pctile × GGG FY26E EBITDA | G8: =B12 -> 80.76 | H8: 5.5
A9: Comps — P/E | B9: =PERCENTILE(Comps!U11:U15,0.25)*'Income Statement'!I43 -> 78.205293 | C9: =D9-B9 -> 6.7157834 | D9: =PERCENTILE(Comps!U11:U15,0.75)*'Income Statement'!I43 -> 84.921077 | E9: Peer 25th–75th pctile × GGG FY26E EPS
A10: 52-Week Trading Range | B10: 78.87 | C10: =D10-B10 -> 16.82 | D10: 95.69 | E10: Market trading context
A12: Current Price | B12: ='DCF & Sensitivity'!D51 -> 80.76
